Workbook

Sheet README
A1: 📊 STOCK PORTFOLIO TRACKER & ANALYTICS ENGINE
A2: A comprehensive Excel-based financial analytics platform for multi-asset portfolio management
A4: 🎯 PROJECT OVERVIEW
A5: Objective | B5: Build a real-world stock portfolio tracking system with advanced analytics, risk metrics, and sector diversification analysis — designed to demonstrate proficiency in financial modelling, data transformation, and dashboard design.
A6: Scope | B6: 16 stocks across 10 GICS industries, tracked over 7 years (2019-2025) with Buy/Sell transactions, live market data integration via Excel Stocks data type, and automated P&L calculations.
A7: Investment Strategy | B7: $10,000 annual investment allocated with 35% Technology, 20% Finance, 45% Other sectors. 70/30 Buy/Sell split per stock with systematic rebalancing.
A8: Data Sources | B8: Excel Linked Data Types (Stocks), STOCKHISTORY function for price series, historical closing prices from Nasdaq/Yahoo Finance for transaction pricing.
A10: WORKBOOK STRUCTURE
A11: Sheet Name | B11: Description
A12: Dashboard | B12: Main portfolio view with live stock prices, market values, daily P&L, unrealised gains/losses, sparkline charts, and KPI summary cards.
A13: Analytics | B13: Advanced metrics: per-stock returns and IRR, realised P&L, sector concentration (HHI Index), risk assessment, allocation charts.
A14: Ledger | B14: Transaction history: 112 records, 16 stocks, 7 years. Date, Stock, Type, Price, Units, Transaction Amount.
A15: Watchlist | B15: Competitor analysis: 10 rival stocks with live data, 52-week ranges, beta, P/E, market cap.
A16: Risk Analytics | B16: CAPM analysis, parametric and historical VaR, realised volatility, drawdown and tracking error from 12 months of daily prices, beta decomposition, CML positioning, individual stock risk attribution.
A17: WL Dashboard | B17: Watchlist scoring model: multi-factor evaluation (P/E, Beta, 52-week range, margin of safety) with composite rankings and entry-point signals.
A18: Validation | B18: Automated integrity tests: weight summation, P&L identity, net-of-sales units, HHI consistency, risk metric reasonableness and cross-sheet checks, real-time pass/fail.
A19: Price History | B19: Price history data feeding Dashboard sparkline trend visualizations.
A20: Stock Sheets | B20: Individual stock deep-dives with STOCKHISTORY price series and charts.
A21: Portfolio Series | B21: 12-month back-cast of the current holdings: daily value, returns, volatility, drawdown, VaR and tracking error vs SPY.
A22: KEY FORMULAS & TECHNIQUES
A23: Technique | B23: Implementation
A24: Dynamic Arrays | B24: SORT, UNIQUE, FILTER, SORTBY with spill ranges for automatic data propagation
A25: Linked Data Types | B25: Excel Stocks data type with dot notation for real-time market data integration
A26: STOCKHISTORY | B26: Historical price series retrieval for sparklines and stock analysis sheets
A27: SUMIF / COUNTIF | B27: Cross-sheet aggregation for transaction totals and sector-level rollups from Ledger
A28: INDEX / MATCH | B28: Best and worst performer identification with dynamic lookups across spill ranges
A29: IRR (XIRR) | B29: Money-weighted annual return over the dated purchase and sale cash flows, with today's market value as the final flow
A30: HHI Index | B30: Sum of squared sector weights to quantify portfolio concentration risk
A31: Conditional Formatting | B31: Automated color coding for negative/positive values with emoji risk indicators
A32: Allocation Model | B32: Weighted allocation with sector caps (Tech max 35%) and systematic Buy/Sell rules
A34: SKILLS DEMONSTRATED
A35: Category | B35: Skills
A36: Financial Modelling | B36: Portfolio construction, P&L tracking, CAGR analysis, risk-adjusted metrics, sector allocation
A37: Data Engineering | B37: Dynamic arrays, linked data types, structured references, cross-sheet data pipelines
A38: Risk Analysis | B38: HHI concentration index, 12-month drawdown and volatility, position sizing, diversification metrics
A39: Dashboard Design | B39: KPI cards, conditional formatting, sparklines, interactive charts, professional color themes
A40: Data Visualisation | B40: Pie charts, bar charts, sparklines, color-coded tables, trend analysis
A41: Domain Knowledge | B41: GICS sector classification, stock market mechanics, Buy/Sell transaction modelling
A43: HOW TO USE
A44: 1. Enable Data Types | B44: Ensure Excel is connected to the internet. The Stocks linked data types in the Ledger and Dashboard require a Microsoft 365 subscription.
A45: 2. Review Dashboard | B45: The Dashboard auto-updates with live prices. Check KPI cards at top for portfolio summary, stock table for details, and sector breakdown below.
A46: 3. Explore Analytics | B46: The Analytics sheet provides deeper metrics: per-stock returns, sector HHI, risk flags, and allocation charts.
A47: 4. Monitor Watchlist | B47: Track competitor stocks with live data. Use this for benchmarking and identifying new investment opportunities.
A48: 5. Add Transactions | B48: Add new rows to the Ledger table. All Dashboard and Analytics formulas auto-update via structured references.
A50: Built with Microsoft Excel 365 | Dynamic Arrays | Stocks Data Type | Advanced Formulas

Sheet Validation
A1: PORTFOLIO VALIDATION TESTS
A2: Automated integrity checks · Real-time validation
A4: DATA INTEGRITY CHECKS
A5: Test | B5: Expected | C5: Actual | D5: Status | E5: Notes
A6: Portfolio weights sum to 100% | B6: 1 | C6: =SUM(Dashboard!L7:L22) -> 1 | D6: =IF(ABS(C6-1)<0.001,"✅ PASS","❌ FAIL") -> ✅ PASS | E6: Sum of all portfolio weights must equal 100%
A7: Total MV = Sum of holdings MV | B7: =Dashboard!B3 -> 211334.92 | C7: =SUM(Dashboard!F7:F22) -> 211334.92 | D7: =IF(ABS(B7-C7)<1,"✅ PASS","❌ FAIL") -> ✅ PASS | E7: Portfolio value KPI matches sum of individual market values
A8: Cost basis consistency | B8: =Dashboard!D3 -> 42915.801 | C8: =SUM(Dashboard!N7:N22) -> 42915.801 | D8: =IF(ABS(B8-C8)<1,"✅ PASS","❌ FAIL") -> ✅ PASS | E8: Portfolio cost basis KPI matches sum of per-stock cost bases
A9: P&L identity: MV - CB = Unrealised P&L | B9: =Dashboard!E3 -> 168419.12 | C9: =Dashboard!B3-Dashboard!D3 -> 168419.12 | D9: =IF(ABS(B9-C9)<1,"✅ PASS","❌ FAIL") -> ✅ PASS | E9: Accounting identity: Unrealised P&L = Market Value − Cost Basis
A10: Unique stock count matches | B10: 16 | C10: =COUNTA(Dashboard!B7:B22) -> 16 | D10: =IF(B10=C10,"✅ PASS","❌ FAIL") -> ✅ PASS | E10: Dashboard shows all 16 unique stocks from Ledger
A11: Sector allocation weights sum to 100% | B11: 1 | C11: =SUM(Dashboard!D30:D39) -> 1 | D11: =IF(ABS(C11-1)<0.001,"✅ PASS","❌ FAIL") -> ✅ PASS | E11: Sector allocation must sum to 100%
A12: HHI consistency (Dashboard vs Analytics) | B12: =Dashboard!J3 -> 0.40936259 | C12: =Dashboard!K25 -> 0.40936259 | D12: =IF(ABS(B12-C12)<0.001,"✅ PASS","❌ FAIL") -> ✅ PASS | E12: HHI Index must be identical between KPI strip and bottom KPIs
A13: HHI = sum of sector squared weights | B13: =Dashboard!J3 -> 0.40936259 | C13: =SUM(Dashboard!E30:E39) -> 0.40936259 | D13: =IF(ABS(B13-C13)<0.001,"✅ PASS","❌ FAIL") -> ✅ PASS | E13: HHI = Σ(wi²) from sector allocation table
A14: Win rate consistency | B14: =Dashboard!O3 -> 0.9375 | C14: =COUNTIF(Dashboard!I7:I22,">0")/COUNTA(Dashboard!I7:I22) -> 0.9375 | D14: =IF(ABS(B14-C14)<0.001,"✅ PASS","❌ FAIL") -> ✅ PASS | E14: Win rate KPI matches manual count of profitable holdings
A15: Rebalancing equal weights = 1/N | B15: =1/16 -> 0.0625 | C15: =Dashboard!I30 -> 0.0625 | D15: =IF(ABS(B15-C15)<0.001,"✅ PASS","❌ FAIL") -> ✅ PASS | E15: Equal weight target = 1/N = 6.25% for 16 stocks
A16: Sector MV = sum of stock MVs per sector | B16: =Dashboard!B3 -> 211334.92 | C16: =SUM(Dashboard!C30:C39) -> 211334.92 | D16: =IF(ABS(B16-C16)<1,"✅ PASS","❌ FAIL") -> ✅ PASS | E16: Sum of sector market values equals total portfolio market value
A17: Units = bought − sold (ledger) | B17: =SUMIFS(Ledger[Units],Ledger[Transaction Type],"Buy")-SUMIFS(Ledger[Units],Ledger[Transaction Type],"Sell") -> 1008.21 | C17: =SUM(Dashboard!D7:D22) -> 1008.21 | D17: =IF(ABS(B17-C17)<0.01,"✅ PASS","❌ FAIL") -> ✅ PASS | E17: Held units must equal units bought minus units sold
A18: RISK METRIC CHECKS
A19: Test | B19: Expected Range | C19: Actual | D19: Status | E19: Framework
A20: Sharpe Ratio in valid range | B20: -3.0 to 5.0 | C20: =Dashboard!N3 -> 1.2122662 | D20: =IF(AND(C20>=-3,C20<=5),"✅ PASS","⚠️ CHECK") -> ✅ PASS | E20: Sharpe = (Rp−Rf)/σp; typical range -3 to 5 for diversified portfolios
A21: Portfolio Beta reasonable | B21: 0.3 to 2.5 | C21: =Dashboard!R3 -> 1.8150362 | D21: =IF(AND(C21>=0.3,C21<=2.5),"✅ PASS","⚠️ CHECK") -> ✅ PASS | E21: βp = Σ(wi×βi); 0.3-2.5 typical for equity-only portfolio
A22: Treynor Ratio valid | B22: -0.5 to 1.0 | C22: =Dashboard!S3 -> 0.17343393 | D22: =IF(AND(C22>=-0.5,C22<=1),"✅ PASS","⚠️ CHECK") -> ✅ PASS | E22: Treynor = (Rp−Rf)/βp; measures excess return per unit systematic risk
A23: Max Drawdown ≤ 0 | B23: ≤ 0% | C23: =Dashboard!Q3 -> -0.14841703 | D23: =IF(C23<=0,"✅ PASS","❌ FAIL") -> ✅ PASS | E23: 12-month peak-to-trough decline of the current holdings; must be ≤ 0
A24: Calmar Ratio positive (if CAGR positive) | B24: > 0 | C24: =Dashboard!R25 -> 2.4073308 | D24: =IF(C24>0,"✅ PASS","⚠️ CHECK") -> ✅ PASS | E24: Calmar = 12m return / |12m max drawdown|
A25: No negative holdings | B25: ≥ 0 | C25: =MIN(Dashboard!D7:D22) -> 2.55 | D25: =IF(C25>=0,"✅ PASS","❌ FAIL") -> ✅ PASS | E25: Every holding's net units must be zero or positive
A26: SUMMARY
A27: Tests Passed | B27: Tests Failed | C27: Tests Warning | D27: Overall Score
A28: =COUNTIF(D6:D17,"✅*")+COUNTIF(D20:D25,"✅*")+COUNTIF(D32:D39,"✅*") -> 26 | B28: {=COUNTIF(D6:D17,"❌*")+COUNTIF(D20:D25,"❌*")+COUNTIF(D32:D39,"❌*")+SUMPRODUCT(--ISERROR(D6:D17))+SUMPRODUCT(--ISERROR(D20:D25))+SUMPRODUCT(--ISERROR(D32:D39))} -> 0 | C28: =COUNTIF(D6:D17,"⚠️*")+COUNTIF(D20:D25,"⚠️*")+COUNTIF(D32:D39,"⚠️*") -> 0 | D28: =IF(B28=0,IF(C28=0,"✅ ALL PASS","⚠️ WARNINGS"),"❌ FAILURES") -> ✅ ALL PASS
A30: CROSS-SHEET CONSISTENCY CHECKS
A31: Test | B31: Sheet A | C31: Sheet B | D31: Status | E31: Detail
A32: CAGR: Dashboard ↔ Analytics | B32: =Dashboard!G3 -> 0.32227901 | C32: =Analytics!E6 -> 0.32227901 | D32: =IF(ABS(B32-C32)<0.0001,"✅ PASS","❌ FAIL") -> ✅ PASS | E32: Portfolio CAGR must match across Dashboard and Analytics
A33: Beta: Dashboard ↔ Risk Analytics | B33: =Dashboard!R3 -> 1.8150362 | C33: ='Risk Analytics'!C9 -> 1.8150362 | D33: =IF(ABS(B33-C33)<0.001,"✅ PASS","❌ FAIL") -> ✅ PASS | E33: Weighted portfolio beta must match between Dashboard KPI and Risk Analytics
A34: Sharpe: Dashboard ↔ Risk Analytics | B34: =Dashboard!N3 -> 1.2122662 | C34: ='Risk Analytics'!C18 -> 1.2122662 | D34: =IF(ABS(B34-C34)<0.001,"✅ PASS","❌ FAIL") -> ✅ PASS | E34: Sharpe Ratio must match between Dashboard KPI and Risk Analytics
A35: Treynor: Dashboard ↔ Risk Analytics | B35: =Dashboard!S3 -> 0.17343393 | C35: ='Risk Analytics'!C15 -> 0.17343393 | D35: =IF(ABS(B35-C35)<0.0001,"✅ PASS","❌ FAIL") -> ✅ PASS | E35: Treynor Ratio must match between Dashboard and Risk Analytics
A36: CAPM: E(Rp) = Rf + βp(Rm-Rf) | B36: ='Risk Analytics'!C10 -> 0.14686458 | C36: ='Risk Analytics'!C6+'Risk Analytics'!C9*('Risk Analytics'!C7-'Risk Analytics'!C6) -> 0.14686458 | D36: =IF(ABS(B36-C36)<0.0001,"✅ PASS","❌ FAIL") -> ✅ PASS | E36: CAPM expected return formula: Rf + βp × ERP must be internally consistent
A37: Jensen's α = Rp(12m) − E(Rp) | B37: ='Risk Analytics'!C11 -> 0.21042429 | C37: ='Portfolio Series'!B13-'Risk Analytics'!C10 -> 0.21042429 | D37: =IF(ABS(B37-C37)<0.0001,"✅ PASS","❌ FAIL") -> ✅ PASS | E37: Alpha = Actual CAGR minus CAPM expected return
A38: Risk decomp weights sum to 100% | B38: 1 | C38: ='Risk Analytics'!C55 -> 1 | D38: =IF(ABS(C38-1)<0.001,"✅ PASS","❌ FAIL") -> ✅ PASS | E38: Stock weights in risk decomposition table must sum to 100%
A39: Total gain = realised + unrealised | B39: =Dashboard!B3+SUMIFS(Ledger[Transaction Amount],Ledger[Transaction Type],"Sell")-SUMIFS(Ledger[Transaction Amount],Ledger[Transaction Type],"Buy") -> 183362.84 | C39: =Dashboard!E3+Dashboard!P25 -> 183362.84 | D39: =IF(ABS(B39-C39)<1,"✅ PASS","❌ FAIL") -> ✅ PASS | E39: Market value + sale proceeds − purchases = realised + unrealised P&L

Sheet Dashboard
U1: Ticker | V1: Return % | W1: Weight % | X1: Gain/Loss | Y1: Ann. Return | Z1: Ticker | AA1: Gain/Loss | AB1: Ticker | AC1: Ann. Return | AD1: Ticker | AE1: Weight
B2: PORTFOLIO VALUE | D2: COST BASIS | E2: UNREALISED P&L | F2: TOTAL RETURN | G2: ANN. RETURN (IRR) | H2: BEST STOCK | I2: WORST STOCK | J2: HHI INDEX | M2: DAILY P&L | N2: SHARPE RATIO | O2: WIN RATE | P2: AVG RETURN | Q2: MAX DRAWDOWN (12M) | R2: PORT. BETA | S2: TREYNOR | U2: =M7 -> AMD | V2: =K7 -> 10.32239 | W2: =L7 -> 0.17183225 | X2: =I7 -> 33106.867 | Y2: =Q7 -> 0.55674189 | Z2: =M7 -> AMD | AA2: =I7 -> 33106.867 | AB2: =M7 -> AMD | AC2: =Q7 -> 0.55674189 | AD2: =M7 -> AMD | AE2: =L7 -> 0.17183225
B3: =SUM(_xlfn.ANCHORARRAY(F7)) -> 211334.92 | D3: =SUM(F7:F22)-SUM(I7:I22) -> 42915.801 | E3: =SUM(I7:I22) -> 168419.12 | F3: =(B3+SUMIFS(Ledger[Transaction Amount],Ledger[Transaction Type],"Sell")-SUMIFS(Ledger[Transaction Amount],Ledger[Transaction Type],"Buy"))/SUMIFS(Ledger[Transaction Amount],Ledger[Transaction Type],"Buy") -> 2.291699 | G3: {=_xlfn.LET(_xlpm.v,_xlfn.VSTACK(IF(Ledger[Transaction Type]="Buy",-1,1)*Ledger[Transaction Amount],B3),_xlpm.d,_xlfn.VSTACK(Ledger[Date],TODAY()),_xlpm.r,XIRR(_xlfn.SORTBY(_xlpm.v,_xlpm.d),_xlfn._xlws.SORT(_xlpm.d),IF(SUM(_xlpm.v)<0,-0.1,0.1)),IF(ABS(_xlpm.r)<0.0000001,NA(),_xlpm.r))} -> 0.32227901 | H3: ="▲ "&INDEX(Ledger[Ticker],MATCH(INDEX(_xlfn.ANCHORARRAY(B7),MATCH(MAX(I7:I22),I7:I22,0)),Ledger[Stock],0)) -> ▲ NVDA | I3: ="▼ "&INDEX(Ledger[Ticker],MATCH(INDEX(_xlfn.ANCHORARRAY(B7),MATCH(MIN(I7:I22),I7:I22,0)),Ledger[Stock],0)) -> ▼ BA | J3: {=SUMPRODUCT((SUMIF(_xlfn.ANCHORARRAY(C7),_xlfn.UNIQUE(_xlfn.ANCHORARRAY(C7)),_xlfn.ANCHORARRAY(F7))/SUM(_xlfn.ANCHORARRAY(F7)))^2)} -> 0.40936259 | M3: =SUMPRODUCT(_xlfn.ANCHORARRAY(D7),_xlfn.ANCHORARRAY(G7)) -> -950.529 | N3: ='Risk Analytics'!C18 -> 1.2122662 | O3: =COUNTIF(I7:I22,">0")/COUNTA(I7:I22) -> 0.9375 | P3: =AVERAGE(K7:K22) -> 2.7406333 | Q3: ='Portfolio Series'!B16 -> -0.14841703 | R3: ='Risk Analytics'!C9 -> 1.8150362 | S3: ='Risk Analytics'!C15 -> 0.17343393 | U3: =M8 -> GOOG | V3: =K8 -> 2.5942224 | W3: =L8 -> 0.053377178 | X3: =I8 -> 8141.9631 | Y3: =Q8 -> 0.30156799 | Z3: =M8 -> GOOG | AA3: =I8 -> 8141.9631 | AB3: =M8 -> GOOG | AC3: =Q8 -> 0.30156799 | AD3: =M8 -> GOOG | AE3: =L8 -> 0.053377178
U4: =M9 -> AMZN | V4: =K9 -> 1.0848749 | W4: =L9 -> 0.024424575 | X4: =I9 -> 2685.9501 | Y4: =Q9 -> 0.19556205 | Z4: =M9 -> AMZN | AA4: =I9 -> 2685.9501 | AB4: =M9 -> AMZN | AC4: =Q9 -> 0.19556205 | AD4: =M9 -> AMZN | AE4: =L9 -> 0.024424575
B5: CURRENT HOLDINGS · 16 STOCKS · 10 INDUSTRIES | M5: FINANCIAL METRICS · PER-STOCK ANALYTICS · RISK ASSESSMENT | U5: =M10 -> AAPL | V5: =K10 -> 2.1898434 | W5: =L10 -> 0.047204845 | X5: =I10 -> 6848.5957 | Y5: =Q10 -> 0.28999216 | Z5: =M10 -> AAPL | AA5: =I10 -> 6848.5957 | AB5: =M10 -> AAPL | AC5: =Q10 -> 0.28999216 | AD5: =M10 -> AAPL | AE5: =L10 -> 0.047204845
B6: Stock(Exchange: Ticker) | C6: Industry | D6: Units | E6: Current Price | F6: Market Value | G6: Today's Change | I6: Gain/(Loss) | J6: Last 12 Months | K6: Return % | L6: Weight % | M6: Stock | N6: Cost Basis | O6: Avg Buy Price | P6: Price/Cost | Q6: Ann. Return (IRR) | R6: Risk Score | S6: Signal | U6: =M11 -> BLK | V6: =K11 -> 0.64601445 | W6: =L11 -> 0.023367944 | X6: =I11 -> 1938.2079 | Y6: =Q11 -> 0.13977041 | Z6: =M11 -> BLK | AA6: =I11 -> 1938.2079 | AB6: =M11 -> BLK | AC6: =Q11 -> 0.13977041 | AD6: =M11 -> BLK | AE6: =L11 -> 0.023367944
B7: {=_xlfn._xlws.SORT(_xlfn.UNIQUE(Ledger[Stock],FALSE,FALSE))} -> #VALUE! | C7: {=_FV(_xlfn.ANCHORARRAY(B7),"Industry")} -> Semiconductors & Semiconductor Equipment | D7: {=SUMIFS(Ledger[Units],Ledger[Stock],_xlfn.ANCHORARRAY(B7),Ledger[Transaction Type],"Buy")-SUMIFS(Ledger[Units],Ledger[Stock],_xlfn.ANCHORARRAY(B7),Ledger[Transaction Type],"Sell")} -> 59.74 | E7: {=_FV(_xlfn.ANCHORARRAY(B7),"Price")} -> 607.87 | F7: {=_xlfn.ANCHORARRAY(D7)*_xlfn.ANCHORARRAY(E7)} -> 36314.154 | G7: {=_xlfn.ANCHORARRAY(E7)-_FV(_xlfn.ANCHORARRAY(B7),"Previous close",TRUE)} -> -22.76 | H7: {=_xlfn.ANCHORARRAY(G7)/(_xlfn.ANCHORARRAY(E7)-_xlfn.ANCHORARRAY(G7))} -> -0.036090893 | I7: {=_xlfn.ANCHORARRAY(F7)-_xlfn.ANCHORARRAY(D7)*SUMIFS(Ledger[Transaction Amount],Ledger[Stock],_xlfn.ANCHORARRAY(B7),Ledger[Transaction Type],"Buy")/SUMIFS(Ledger[Units],Ledger[Stock],_xlfn.ANCHORARRAY(B7),Ledger[Transaction Type],"Buy")} -> 33106.867 | K7: =IF((F7-I7)=0,0,I7/(F7-I7)) -> 10.32239 | L7: =F7/SUM(F7:F22) -> 0.17183225 | M7: =INDEX(Ledger[Ticker],MATCH(B7,Ledger[Stock],0)) -> AMD | N7: =F7-I7 -> 3207.287 | O7: =N7/D7 -> 53.68743 | P7: =E7/O7 -> 11.32239 | Q7: {=_xlfn.LET(_xlpm.m,Ledger[Stock]=B7,_xlpm.v,_xlfn.VSTACK(_xlfn._xlws.FILTER(IF(Ledger[Transaction Type]="Buy",-1,1)*Ledger[Transaction Amount],_xlpm.m),F7),_xlpm.d,_xlfn.VSTACK(_xlfn._xlws.FILTER(Ledger[Date],_xlpm.m),TODAY()),_xlpm.r,XIRR(_xlfn.SORTBY(_xlpm.v,_xlpm.d),_xlfn._xlws.SORT(_xlpm.d),IF(SUM(_xlpm.v)<0,-0.1,0.1)),IF(ABS(_xlpm.r)<0.0000001,NA(),_xlpm.r))} -> 0.55674189 | R7: =IF(OR(K7<0,Q7<0,L7>0.2),"HIGH",IF(OR(K7<0.5,Q7<0.05,L7>0.15),"MEDIUM","LOW")) -> MEDIUM | S7: =IF(AND(Q7>0.1,K7>1,P7>1.5,R7="LOW"),"▲ STRONG",IF(OR(K7<0,Q7<0),"▼ REVIEW","▶ HOLD")) -> ▶ HOLD | U7: =M12 -> CVX | V7: =K12 -> 0.59446216 | W7: =L12 -> 0.0177236 | X7: =I12 -> 1396.4751 | Y7: =Q12 -> 0.077858725 | Z7: =M12 -> CVX | AA7: =I12 -> 1396.4751 | AB7: =M12 -> CVX | AC7: =Q12 -> 0.077858725 | AD7: =M12 -> CVX | AE7: =L12 -> 0.0177236
B8: #VALUE! | C8: Software & IT Services | D8: 33.26 | E8: 339.16 | F8: 11280.462 | G8: -1.92 | H8: -0.0056291779 | I8: 8141.9631 | K8: =IF((F8-I8)=0,0,I8/(F8-I8)) -> 2.5942224 | L8: =F8/SUM(F7:F22) -> 0.053377178 | M8: =INDEX(Ledger[Ticker],MATCH(B8,Ledger[Stock],0)) -> GOOG | N8: =F8-I8 -> 3138.4985 | O8: =N8/D8 -> 94.362552 | P8: =E8/O8 -> 3.5942224 | Q8: {=_xlfn.LET(_xlpm.m,Ledger[Stock]=B8,_xlpm.v,_xlfn.VSTACK(_xlfn._xlws.FILTER(IF(Ledger[Transaction Type]="Buy",-1,1)*Ledger[Transaction Amount],_xlpm.m),F8),_xlpm.d,_xlfn.VSTACK(_xlfn._xlws.FILTER(Ledger[Date],_xlpm.m),TODAY()),_xlpm.r,XIRR(_xlfn.SORTBY(_xlpm.v,_xlpm.d),_xlfn._xlws.SORT(_xlpm.d),IF(SUM(_xlpm.v)<0,-0.1,0.1)),IF(ABS(_xlpm.r)<0.0000001,NA(),_xlpm.r))} -> 0.30156799 | R8: =IF(OR(K8<0,Q8<0,L8>0.2),"HIGH",IF(OR(K8<0.5,Q8<0.05,L8>0.15),"MEDIUM","LOW")) -> LOW | S8: =IF(AND(Q8>0.1,K8>1,P8>1.5,R8="LOW"),"▲ STRONG",IF(OR(K8<0,Q8<0),"▼ REVIEW","▶ HOLD")) -> ▲ STRONG | U8: =M13 -> C | V8: =K13 -> 1.402836 | W8: =L13 -> 0.027357425 | X8: =I13 -> 3375.4312 | Y8: =Q13 -> 0.17262424 | Z8: =M13 -> C | AA8: =I13 -> 3375.4312 | AB8: =M13 -> C | AC8: =Q13 -> 0.17262424 | AD8: =M13 -> C | AE8: =L13 -> 0.027357425
B9: #VALUE! | C9: Diversified Retail | D9: 20.97 | E9: 246.15 | F9: 5161.7655 | G9: -3.52 | H9: -0.01409861 | I9: 2685.9501 | K9: =IF((F9-I9)=0,0,I9/(F9-I9)) -> 1.0848749 | L9: =F9/SUM(F7:F22) -> 0.024424575 | M9: =INDEX(Ledger[Ticker],MATCH(B9,Ledger[Stock],0)) -> AMZN | N9: =F9-I9 -> 2475.8154 | O9: =N9/D9 -> 118.06464 | P9: =E9/O9 -> 2.0848749 | Q9: {=_xlfn.LET(_xlpm.m,Ledger[Stock]=B9,_xlpm.v,_xlfn.VSTACK(_xlfn._xlws.FILTER(IF(Ledger[Transaction Type]="Buy",-1,1)*Ledger[Transaction Amount],_xlpm.m),F9),_xlpm.d,_xlfn.VSTACK(_xlfn._xlws.FILTER(Ledger[Date],_xlpm.m),TODAY()),_xlpm.r,XIRR(_xlfn.SORTBY(_xlpm.v,_xlpm.d),_xlfn._xlws.SORT(_xlpm.d),IF(SUM(_xlpm.v)<0,-0.1,0.1)),IF(ABS(_xlpm.r)<0.0000001,NA(),_xlpm.r))} -> 0.19556205 | R9: =IF(OR(K9<0,Q9<0,L9>0.2),"HIGH",IF(OR(K9<0.5,Q9<0.05,L9>0.15),"MEDIUM","LOW")) -> LOW | S9: =IF(AND(Q9>0.1,K9>1,P9>1.5,R9="LOW"),"▲ STRONG",IF(OR(K9<0,Q9<0),"▼ REVIEW","▶ HOLD")) -> ▲ STRONG | U9: =M14 -> F | V9: =K14 -> 0.1851305 | W9: =L14 -> 0.010201707 | X9: =I14 -> 336.78746 | Y9: =Q14 -> 0.032022062 | Z9: =M14 -> F | AA9: =I14 -> 336.78746 | AB9: =M14 -> F | AC9: =Q14 -> 0.032022062 | AD9: =M14 -> F | AE9: =L14 -> 0.010201707
B10: #VALUE! | C10: Computers, Phones & Household Electronics | D10: 29.48 | E10: 338.4 | F10: 9976.032 | G10: -2.67 | H10: -0.007828305 | I10: 6848.5957 | K10: =IF((F10-I10)=0,0,I10/(F10-I10)) -> 2.1898434 | L10: =F10/SUM(F7:F22) -> 0.047204845 | M10: =INDEX(Ledger[Ticker],MATCH(B10,Ledger[Stock],0)) -> AAPL | N10: =F10-I10 -> 3127.4363 | O10: =N10/D10 -> 106.08671 | P10: =E10/O10 -> 3.1898434 | Q10: {=_xlfn.LET(_xlpm.m,Ledger[Stock]=B10,_xlpm.v,_xlfn.VSTACK(_xlfn._xlws.FILTER(IF(Ledger[Transaction Type]="Buy",-1,1)*Ledger[Transaction Amount],_xlpm.m),F10),_xlpm.d,_xlfn.VSTACK(_xlfn._xlws.FILTER(Ledger[Date],_xlpm.m),TODAY()),_xlpm.r,XIRR(_xlfn.SORTBY(_xlpm.v,_xlpm.d),_xlfn._xlws.SORT(_xlpm.d),IF(SUM(_xlpm.v)<0,-0.1,0.1)),IF(ABS(_xlpm.r)<0.0000001,NA(),_xlpm.r))} -> 0.28999216 | R10: =IF(OR(K10<0,Q10<0,L10>0.2),"HIGH",IF(OR(K10<0.5,Q10<0.05,L10>0.15),"MEDIUM","LOW")) -> LOW | S10: =IF(AND(Q10>0.1,K10>1,P10>1.5,R10="LOW"),"▲ STRONG",IF(OR(K10<0,Q10<0),"▼ REVIEW","▶ HOLD")) -> ▲ STRONG | U10: =M15 -> HMC | V10: =K15 -> 0.15869699 | W10: =L15 -> 0.0075684733 | X10: =I15 -> 219.06771 | Y10: =Q15 -> 0.0072583467 | Z10: =M15 -> HMC | AA10: =I15 -> 219.06771 | AB10: =M15 -> HMC | AC10: =Q15 -> 0.0072583467 | AD10: =M15 -> HMC | AE10: =L15 -> 0.0075684733
B11: #VALUE! | C11: Investment Banking & Investment Services | D11: 4.61 | E11: 1071.25 | F11: 4938.4625 | G11: -15.06 | H11: -0.013863446 | I11: 1938.2079 | K11: =IF((F11-I11)=0,0,I11/(F11-I11)) -> 0.64601445 | L11: =F11/SUM(F7:F22) -> 0.023367944 | M11: =INDEX(Ledger[Ticker],MATCH(B11,Ledger[Stock],0)) -> BLK | N11: =F11-I11 -> 3000.2546 | O11: =N11/D11 -> 650.81446 | P11: =E11/O11 -> 1.6460145 | Q11: {=_xlfn.LET(_xlpm.m,Ledger[Stock]=B11,_xlpm.v,_xlfn.VSTACK(_xlfn._xlws.FILTER(IF(Ledger[Transaction Type]="Buy",-1,1)*Ledger[Transaction Amount],_xlpm.m),F11),_xlpm.d,_xlfn.VSTACK(_xlfn._xlws.FILTER(Ledger[Date],_xlpm.m),TODAY()),_xlpm.r,XIRR(_xlfn.SORTBY(_xlpm.v,_xlpm.d),_xlfn._xlws.SORT(_xlpm.d),IF(SUM(_xlpm.v)<0,-0.1,0.1)),IF(ABS(_xlpm.r)<0.0000001,NA(),_xlpm.r))} -> 0.13977041 | R11: =IF(OR(K11<0,Q11<0,L11>0.2),"HIGH",IF(OR(K11<0.5,Q11<0.05,L11>0.15),"MEDIUM","LOW")) -> LOW | S11: =IF(AND(Q11>0.1,K11>1,P11>1.5,R11="LOW"),"▲ STRONG",IF(OR(K11<0,Q11<0),"▼ REVIEW","▶ HOLD")) -> ▶ HOLD | U11: =M16 -> JPM | V11: =K16 -> 1.3670008 | W11: =L16 -> 0.037459956 | X11: =I16 -> 4572.0281 | Y11: =Q16 -> 0.20443895 | Z11: =M16 -> JPM | AA11: =I16 -> 4572.0281 | AB11: =M16 -> JPM | AC11: =Q16 -> 0.20443895 | AD11: =M16 -> JPM | AE11: =L16 -> 0.037459956
B12: #VALUE! | C12: Oil & Gas | D12: 18.15 | E12: 206.37 | F12: 3745.6155 | G12: 1.92 | H12: 0.0093910492 | I12: 1396.4751 | K12: =IF((F12-I12)=0,0,I12/(F12-I12)) -> 0.59446216 | L12: =F12/SUM(F7:F22) -> 0.0177236 | M12: =INDEX(Ledger[Ticker],MATCH(B12,Ledger[Stock],0)) -> CVX | N12: =F12-I12 -> 2349.1404 | O12: =N12/D12 -> 129.42922 | P12: =E12/O12 -> 1.5944622 | Q12: {=_xlfn.LET(_xlpm.m,Ledger[Stock]=B12,_xlpm.v,_xlfn.VSTACK(_xlfn._xlws.FILTER(IF(Ledger[Transaction Type]="Buy",-1,1)*Ledger[Transaction Amount],_xlpm.m),F12),_xlpm.d,_xlfn.VSTACK(_xlfn._xlws.FILTER(Ledger[Date],_xlpm.m),TODAY()),_xlpm.r,XIRR(_xlfn.SORTBY(_xlpm.v,_xlpm.d),_xlfn._xlws.SORT(_xlpm.d),IF(SUM(_xlpm.v)<0,-0.1,0.1)),IF(ABS(_xlpm.r)<0.0000001,NA(),_xlpm.r))} -> 0.077858725 | R12: =IF(OR(K12<0,Q12<0,L12>0.2),"HIGH",IF(OR(K12<0.5,Q12<0.05,L12>0.15),"MEDIUM","LOW")) -> LOW | S12: =IF(AND(Q12>0.1,K12>1,P12>1.5,R12="LOW"),"▲ STRONG",IF(OR(K12<0,Q12<0),"▼ REVIEW","▶ HOLD")) -> ▶ HOLD | U12: =M17 -> META | V12: =K17 -> 2.1443626 | W12: =L17 -> 0.053400202 | X12: =I17 -> 7696.2607 | Y12: =Q17 -> 0.29073516 | Z12: =M17 -> META | AA12: =I17 -> 7696.2607 | AB12: =M17 -> META | AC12: =Q17 -> 0.29073516 | AD12: =M17 -> META | AE12: =L17 -> 0.053400202
B13: #VALUE! | C13: Investment Banking & Investment Services | D13: 44.03 | E13: 131.31 | F13: 5781.5793 | G13: -2.97 | H13: -0.022117962 | I13: 3375.4312 | K13: =IF((F13-I13)=0,0,I13/(F13-I13)) -> 1.402836 | L13: =F13/SUM(F7:F22) -> 0.027357425 | M13: =INDEX(Ledger[Ticker],MATCH(B13,Ledger[Stock],0)) -> C | N13: =F13-I13 -> 2406.1481 | O13: =N13/D13 -> 54.647925 | P13: =E13/O13 -> 2.402836 | Q13: {=_xlfn.LET(_xlpm.m,Ledger[Stock]=B13,_xlpm.v,_xlfn.VSTACK(_xlfn._xlws.FILTER(IF(Ledger[Transaction Type]="Buy",-1,1)*Ledger[Transaction Amount],_xlpm.m),F13),_xlpm.d,_xlfn.VSTACK(_xlfn._xlws.FILTER(Ledger[Date],_xlpm.m),TODAY()),_xlpm.r,XIRR(_xlfn.SORTBY(_xlpm.v,_xlpm.d),_xlfn._xlws.SORT(_xlpm.d),IF(SUM(_xlpm.v)<0,-0.1,0.1)),IF(ABS(_xlpm.r)<0.0000001,NA(),_xlpm.r))} -> 0.17262424 | R13: =IF(OR(K13<0,Q13<0,L13>0.2),"HIGH",IF(OR(K13<0.5,Q13<0.05,L13>0.15),"MEDIUM","LOW")) -> LOW | S13: =IF(AND(Q13>0.1,K13>1,P13>1.5,R13="LOW"),"▲ STRONG",IF(OR(K13<0,Q13<0),"▼ REVIEW","▶ HOLD")) -> ▲ STRONG | U13: =M18 -> NVDA | V13: =K18 -> 18.777934 | W13: =L18 -> 0.45087609 | X13: =I18 -> 90468.075 | Y13: =Q18 -> 0.74484886 | Z13: =M18 -> NVDA | AA13: =I18 -> 90468.075 | AB13: =M18 -> NVDA | AC13: =Q18 -> 0.74484886 | AD13: =M18 -> NVDA | AE13: =L18 -> 0.45087609
B14: #VALUE! | C14: Automobiles & Auto Parts | D14: 174.15 | E14: 12.38 | F14: 2155.977 | G14: -0.33 | H14: -0.025963808 | I14: 336.78746 | K14: =IF((F14-I14)=0,0,I14/(F14-I14)) -> 0.1851305 | L14: =F14/SUM(F7:F22) -> 0.010201707 | M14: =INDEX(Ledger[Ticker],MATCH(B14,Ledger[Stock],0)) -> F | N14: =F14-I14 -> 1819.1895 | O14: =N14/D14 -> 10.446107 | P14: =E14/O14 -> 1.1851305 | Q14: {=_xlfn.LET(_xlpm.m,Ledger[Stock]=B14,_xlpm.v,_xlfn.VSTACK(_xlfn._xlws.FILTER(IF(Ledger[Transaction Type]="Buy",-1,1)*Ledger[Transaction Amount],_xlpm.m),F14),_xlpm.d,_xlfn.VSTACK(_xlfn._xlws.FILTER(Ledger[Date],_xlpm.m),TODAY()),_xlpm.r,XIRR(_xlfn.SORTBY(_xlpm.v,_xlpm.d),_xlfn._xlws.SORT(_xlpm.d),IF(SUM(_xlpm.v)<0,-0.1,0.1)),IF(ABS(_xlpm.r)<0.0000001,NA(),_xlpm.r))} -> 0.032022062 | R14: =IF(OR(K14<0,Q14<0,L14>0.2),"HIGH",IF(OR(K14<0.5,Q14<0.05,L14>0.15),"MEDIUM","LOW")) -> MEDIUM | S14: =IF(AND(Q14>0.1,K14>1,P14>1.5,R14="LOW"),"▲ STRONG",IF(OR(K14<0,Q14<0),"▼ REVIEW","▶ HOLD")) -> ▶ HOLD | U14: =M19 -> 0R2N | V14: =K19 -> 1.0248369 | W14: =L19 -> 0.020764038 | X14: =I19 -> 2220.996 | Y14: =Q19 -> 0.13563055 | Z14: =M19 -> 0R2N | AA14: =I19 -> 2220.996 | AB14: =M19 -> 0R2N | AC14: =Q19 -> 0.13563055 | AD14: =M19 -> 0R2N | AE14: =L19 -> 0.020764038
B15: #VALUE! | C15: Automobiles & Auto Parts | D15: 49.23 | E15: 32.49 | F15: 1599.4827 | G15: -0.44 | H15: -0.013361676 | I15: 219.06771 | K15: =IF((F15-I15)=0,0,I15/(F15-I15)) -> 0.15869699 | L15: =F15/SUM(F7:F22) -> 0.0075684733 | M15: =INDEX(Ledger[Ticker],MATCH(B15,Ledger[Stock],0)) -> HMC | N15: =F15-I15 -> 1380.415 | O15: =N15/D15 -> 28.040118 | P15: =E15/O15 -> 1.158697 | Q15: {=_xlfn.LET(_xlpm.m,Ledger[Stock]=B15,_xlpm.v,_xlfn.VSTACK(_xlfn._xlws.FILTER(IF(Ledger[Transaction Type]="Buy",-1,1)*Ledger[Transaction Amount],_xlpm.m),F15),_xlpm.d,_xlfn.VSTACK(_xlfn._xlws.FILTER(Ledger[Date],_xlpm.m),TODAY()),_xlpm.r,XIRR(_xlfn.SORTBY(_xlpm.v,_xlpm.d),_xlfn._xlws.SORT(_xlpm.d),IF(SUM(_xlpm.v)<0,-0.1,0.1)),IF(ABS(_xlpm.r)<0.0000001,NA(),_xlpm.r))} -> 0.0072583467 | R15: =IF(OR(K15<0,Q15<0,L15>0.2),"HIGH",IF(OR(K15<0.5,Q15<0.05,L15>0.15),"MEDIUM","LOW")) -> MEDIUM | S15: =IF(AND(Q15>0.1,K15>1,P15>1.5,R15="LOW"),"▲ STRONG",IF(OR(K15<0,Q15<0),"▼ REVIEW","▶ HOLD")) -> ▶ HOLD | U15: =M20 -> BA | V15: =K20 -> -0.26147276 | W15: =L20 -> 0.0022248784 | X15: =I20 -> -166.47057 | Y15: =Q20 -> -0.13631248 | Z15: =M20 -> BA | AA15: =I20 -> -166.47057 | AB15: =M20 -> BA | AC15: =Q20 -> -0.13631248 | AD15: =M20 -> BA | AE15: =L20 -> 0.0022248784
B16: #VALUE! | C16: Banking Services | D16: 23.52 | E16: 336.59 | F16: 7916.5968 | G16: -6.47 | H16: -0.018859675 | I16: 4572.0281 | K16: =IF((F16-I16)=0,0,I16/(F16-I16)) -> 1.3670008 | L16: =F16/SUM(F7:F22) -> 0.037459956 | M16: =INDEX(Ledger[Ticker],MATCH(B16,Ledger[Stock],0)) -> JPM | N16: =F16-I16 -> 3344.5687 | O16: =N16/D16 -> 142.20105 | P16: =E16/O16 -> 2.3670008 | Q16: {=_xlfn.LET(_xlpm.m,Ledger[Stock]=B16,_xlpm.v,_xlfn.VSTACK(_xlfn._xlws.FILTER(IF(Ledger[Transaction Type]="Buy",-1,1)*Ledger[Transaction Amount],_xlpm.m),F16),_xlpm.d,_xlfn.VSTACK(_xlfn._xlws.FILTER(Ledger[Date],_xlpm.m),TODAY()),_xlpm.r,XIRR(_xlfn.SORTBY(_xlpm.v,_xlpm.d),_xlfn._xlws.SORT(_xlpm.d),IF(SUM(_xlpm.v)<0,-0.1,0.1)),IF(ABS(_xlpm.r)<0.0000001,NA(),_xlpm.r))} -> 0.20443895 | R16: =IF(OR(K16<0,Q16<0,L16>0.2),"HIGH",IF(OR(K16<0.5,Q16<0.05,L16>0.15),"MEDIUM","LOW")) -> LOW | S16: =IF(AND(Q16>0.1,K16>1,P16>1.5,R16="LOW"),"▲ STRONG",IF(OR(K16<0,Q16<0),"▼ REVIEW","▶ HOLD")) -> ▲ STRONG | U16: =M21 -> TM | V16: =K21 -> 0.22035737 | W16: =L21 -> 0.010059421 | X16: =I21 -> 383.87057 | Y16: =Q21 -> 0.051768842 | Z16: =M21 -> TM | AA16: =I21 -> 383.87057 | AB16: =M21 -> TM | AC16: =Q21 -> 0.051768842 | AD16: =M21 -> TM | AE16: =L21 -> 0.010059421
B17: #VALUE! | C17: Software & IT Services | D17: 15.77 | E17: 715.62 | F17: 11285.327 | G17: -36.04 | H17: -0.04794721 | I17: 7696.2607 | K17: =IF((F17-I17)=0,0,I17/(F17-I17)) -> 2.1443626 | L17: =F17/SUM(F7:F22) -> 0.053400202 | M17: =INDEX(Ledger[Ticker],MATCH(B17,Ledger[Stock],0)) -> META | N17: =F17-I17 -> 3589.0667 | O17: =N17/D17 -> 227.58825 | P17: =E17/O17 -> 3.1443626 | Q17: {=_xlfn.LET(_xlpm.m,Ledger[Stock]=B17,_xlpm.v,_xlfn.VSTACK(_xlfn._xlws.FILTER(IF(Ledger[Transaction Type]="Buy",-1,1)*Ledger[Transaction Amount],_xlpm.m),F17),_xlpm.d,_xlfn.VSTACK(_xlfn._xlws.FILTER(Ledger[Date],_xlpm.m),TODAY()),_xlpm.r,XIRR(_xlfn.SORTBY(_xlpm.v,_xlpm.d),_xlfn._xlws.SORT(_xlpm.d),IF(SUM(_xlpm.v)<0,-0.1,0.1)),IF(ABS(_xlpm.r)<0.0000001,NA(),_xlpm.r))} -> 0.29073516 | R17: =IF(OR(K17<0,Q17<0,L17>0.2),"HIGH",IF(OR(K17<0.5,Q17<0.05,L17>0.15),"MEDIUM","LOW")) -> LOW | S17: =IF(AND(Q17>0.1,K17>1,P17>1.5,R17="LOW"),"▲ STRONG",IF(OR(K17<0,Q17<0),"▼ REVIEW","▶ HOLD")) -> ▲ STRONG | U17: =M22 -> WMT | V17: =K22 -> 1.3986435 | W17: =L22 -> 0.042157426 | X17: =I22 -> 5195.0135 | Y17: =Q22 -> 0.2164966 | Z17: =M22 -> WMT | AA17: =I22 -> 5195.0135 | AB17: =M22 -> WMT | AC17: =Q22 -> 0.2164966 | AD17: =M22 -> WMT | AE17: =L22 -> 0.042157426
B18: #VALUE! | C18: Semiconductors & Semiconductor Equipment | D18: 416.35 | E18: 228.86 | F18: 95285.861 | G18: 3.79 | H18: 0.016839206 | I18: 90468.075 | K18: =IF((F18-I18)=0,0,I18/(F18-I18)) -> 18.777934 | L18: =F18/SUM(F7:F22) -> 0.45087609 | M18: =INDEX(Ledger[Ticker],MATCH(B18,Ledger[Stock],0)) -> NVDA | N18: =F18-I18 -> 4817.7863 | O18: =N18/D18 -> 11.571481 | P18: =E18/O18 -> 19.777934 | Q18: {=_xlfn.LET(_xlpm.m,Ledger[Stock]=B18,_xlpm.v,_xlfn.VSTACK(_xlfn._xlws.FILTER(IF(Ledger[Transaction Type]="Buy",-1,1)*Ledger[Transaction Amount],_xlpm.m),F18),_xlpm.d,_xlfn.VSTACK(_xlfn._xlws.FILTER(Ledger[Date],_xlpm.m),TODAY()),_xlpm.r,XIRR(_xlfn.SORTBY(_xlpm.v,_xlpm.d),_xlfn._xlws.SORT(_xlpm.d),IF(SUM(_xlpm.v)<0,-0.1,0.1)),IF(ABS(_xlpm.r)<0.0000001,NA(),_xlpm.r))} -> 0.74484886 | R18: =IF(OR(K18<0,Q18<0,L18>0.2),"HIGH",IF(OR(K18<0.5,Q18<0.05,L18>0.15),"MEDIUM","LOW")) -> HIGH | S18: =IF(AND(Q18>0.1,K18>1,P18>1.5,R18="LOW"),"▲ STRONG",IF(OR(K18<0,Q18<0),"▼ REVIEW","▶ HOLD")) -> ▶ HOLD
B19: #VALUE! | C19: Aerospace & Defense | D19: 23.17 | E19: 189.39 | F19: 4388.1663 | G19: 0.39 | H19: 0.0020634921 | I19: 2220.996 | K19: =IF((F19-I19)=0,0,I19/(F19-I19)) -> 1.0248369 | L19: =F19/SUM(F7:F22) -> 0.020764038 | M19: =INDEX(Ledger[Ticker],MATCH(B19,Ledger[Stock],0)) -> 0R2N | N19: =F19-I19 -> 2167.1703 | O19: =N19/D19 -> 93.53346 | P19: =E19/O19 -> 2.0248369 | Q19: {=_xlfn.LET(_xlpm.m,Ledger[Stock]=B19,_xlpm.v,_xlfn.VSTACK(_xlfn._xlws.FILTER(IF(Ledger[Transaction Type]="Buy",-1,1)*Ledger[Transaction Amount],_xlpm.m),F19),_xlpm.d,_xlfn.VSTACK(_xlfn._xlws.FILTER(Ledger[Date],_xlpm.m),TODAY()),_xlpm.r,XIRR(_xlfn.SORTBY(_xlpm.v,_xlpm.d),_xlfn._xlws.SORT(_xlpm.d),IF(SUM(_xlpm.v)<0,-0.1,0.1)),IF(ABS(_xlpm.r)<0.0000001,NA(),_xlpm.r))} -> 0.13563055 | R19: =IF(OR(K19<0,Q19<0,L19>0.2),"HIGH",IF(OR(K19<0.5,Q19<0.05,L19>0.15),"MEDIUM","LOW")) -> LOW | S19: =IF(AND(Q19>0.1,K19>1,P19>1.5,R19="LOW"),"▲ STRONG",IF(OR(K19<0,Q19<0),"▼ REVIEW","▶ HOLD")) -> ▲ STRONG
B20: #VALUE! | C20: Aerospace & Defense | D20: 2.55 | E20: 184.39 | F20: 470.1945 | G20: -13.68 | H20: -0.069066492 | I20: -166.47057 | K20: =IF((F20-I20)=0,0,I20/(F20-I20)) -> -0.26147276 | L20: =F20/SUM(F7:F22) -> 0.0022248784 | M20: =INDEX(Ledger[Ticker],MATCH(B20,Ledger[Stock],0)) -> BA | N20: =F20-I20 -> 636.66507 | O20: =N20/D20 -> 249.67258 | P20: =E20/O20 -> 0.73852724 | Q20: {=_xlfn.LET(_xlpm.m,Ledger[Stock]=B20,_xlpm.v,_xlfn.VSTACK(_xlfn._xlws.FILTER(IF(Ledger[Transaction Type]="Buy",-1,1)*Ledger[Transaction Amount],_xlpm.m),F20),_xlpm.d,_xlfn.VSTACK(_xlfn._xlws.FILTER(Ledger[Date],_xlpm.m),TODAY()),_xlpm.r,XIRR(_xlfn.SORTBY(_xlpm.v,_xlpm.d),_xlfn._xlws.SORT(_xlpm.d),IF(SUM(_xlpm.v)<0,-0.1,0.1)),IF(ABS(_xlpm.r)<0.0000001,NA(),_xlpm.r))} -> -0.13631248 | R20: =IF(OR(K20<0,Q20<0,L20>0.2),"HIGH",IF(OR(K20<0.5,Q20<0.05,L20>0.15),"MEDIUM","LOW")) -> HIGH | S20: =IF(AND(Q20>0.1,K20>1,P20>1.5,R20="LOW"),"▲ STRONG",IF(OR(K20<0,Q20<0),"▼ REVIEW","▶ HOLD")) -> ▼ REVIEW
B21: #VALUE! | C21: Automobiles & Auto Parts | D21: 11.29 | E21: 188.3 | F21: 2125.907 | G21: -2.04 | H21: -0.010717663 | I21: 383.87057 | K21: =IF((F21-I21)=0,0,I21/(F21-I21)) -> 0.22035737 | L21: =F21/SUM(F7:F22) -> 0.010059421 | M21: =INDEX(Ledger[Ticker],MATCH(B21,Ledger[Stock],0)) -> TM | N21: =F21-I21 -> 1742.0364 | O21: =N21/D21 -> 154.29906 | P21: =E21/O21 -> 1.2203574 | Q21: {=_xlfn.LET(_xlpm.m,Ledger[Stock]=B21,_xlpm.v,_xlfn.VSTACK(_xlfn._xlws.FILTER(IF(Ledger[Transaction Type]="Buy",-1,1)*Ledger[Transaction Amount],_xlpm.m),F21),_xlpm.d,_xlfn.VSTACK(_xlfn._xlws.FILTER(Ledger[Date],_xlpm.m),TODAY()),_xlpm.r,XIRR(_xlfn.SORTBY(_xlpm.v,_xlpm.d),_xlfn._xlws.SORT(_xlpm.d),IF(SUM(_xlpm.v)<0,-0.1,0.1)),IF(ABS(_xlpm.r)<0.0000001,NA(),_xlpm.r))} -> 0.051768842 | R21: =IF(OR(K21<0,Q21<0,L21>0.2),"HIGH",IF(OR(K21<0.5,Q21<0.05,L21>0.15),"MEDIUM","LOW")) -> MEDIUM | S21: =IF(AND(Q21>0.1,K21>1,P21>1.5,R21="LOW"),"▲ STRONG",IF(OR(K21<0,Q21<0),"▼ REVIEW","▶ HOLD")) -> ▶ HOLD
B22: #VALUE! | C22: Food & Drug Retailing | D22: 81.94 | E22: 108.73 | F22: 8909.3362 | G22: 0.75 | H22: 0.0069457307 | I22: 5195.0135 | K22: =IF((F22-I22)=0,0,I22/(F22-I22)) -> 1.3986435 | L22: =F22/SUM(F7:F22) -> 0.042157426 | M22: =INDEX(Ledger[Ticker],MATCH(B22,Ledger[Stock],0)) -> WMT | N22: =F22-I22 -> 3714.3227 | O22: =N22/D22 -> 45.329787 | P22: =E22/O22 -> 2.3986435 | Q22: {=_xlfn.LET(_xlpm.m,Ledger[Stock]=B22,_xlpm.v,_xlfn.VSTACK(_xlfn._xlws.FILTER(IF(Ledger[Transaction Type]="Buy",-1,1)*Ledger[Transaction Amount],_xlpm.m),F22),_xlpm.d,_xlfn.VSTACK(_xlfn._xlws.FILTER(Ledger[Date],_xlpm.m),TODAY()),_xlpm.r,XIRR(_xlfn.SORTBY(_xlpm.v,_xlpm.d),_xlfn._xlws.SORT(_xlpm.d),IF(SUM(_xlpm.v)<0,-0.1,0.1)),IF(ABS(_xlpm.r)<0.0000001,NA(),_xlpm.r))} -> 0.2164966 | R22: =IF(OR(K22<0,Q22<0,L22>0.2),"HIGH",IF(OR(K22<0.5,Q22<0.05,L22>0.15),"MEDIUM","LOW")) -> LOW | S22: =IF(AND(Q22>0.1,K22>1,P22>1.5,R22="LOW"),"▲ STRONG",IF(OR(K22<0,Q22<0),"▼ REVIEW","▶ HOLD")) -> ▲ STRONG
B24: COST BASIS | C24: TOP HOLDING | E24: TOP 3 CONC. | G24: AVG RETURN | I24: PROFITABLE | K24: HHI INDEX | M24: ▲ STRONG | N24: ▶ HOLD | O24: ▼ REVIEW | P24: REALISED P&L | Q24: SORTINO RATIO | R24: CALMAR RATIO | S24: PORT. GRADE
B25: =SUM(_xlfn.ANCHORARRAY(F7))-SUM(_xlfn.ANCHORARRAY(I7)) -> 42915.801 | C25: =INDEX(Ledger[Ticker],MATCH(INDEX(_xlfn.ANCHORARRAY(B7),MATCH(MAX(L7:L22),L7:L22,0)),Ledger[Stock],0))&" "&TEXT(MAX(L7:L22),"0.0%") -> NVDA 45.1% | E25: =LARGE(L7:L22,1)+LARGE(L7:L22,2)+LARGE(L7:L22,3) -> 0.67610853 | G25: =AVERAGE(K7:K22) -> 2.7406333 | I25: =COUNTIF(I7:I22,">0")&" / "&COUNTA(I7:I22) -> 15 / 16 | K25: {=SUMPRODUCT((SUMIF(_xlfn.ANCHORARRAY(C7),_xlfn.UNIQUE(_xlfn.ANCHORARRAY(C7)),_xlfn.ANCHORARRAY(F7))/SUM(_xlfn.ANCHORARRAY(F7)))^2)} -> 0.40936259 | M25: =COUNTIF(S7:S22,"*STRONG*") -> 8 | N25: =COUNTIF(S7:S22,"*HOLD*") -> 7 | O25: =COUNTIF(S7:S22,"*REVIEW*") -> 1 | P25: =SUM(Analytics!I10:I25) -> 14943.725 | Q25: ='Risk Analytics'!C19 -> 1.8188661 | R25: ='Risk Analytics'!C20 -> 2.4073308 | S25: =Analytics!H44 -> B+
B28: SECTOR ALLOCATION | G28: REBALANCING ANALYSIS
B29: Industry | C29: Market Value | D29: Weight % | E29: HHI Contrib. | G29: Stock | H29: Current Wt. | I29: Equal Wt. | J29: Deviation | K29: Action
B30: {=_xlfn.UNIQUE(_xlfn.ANCHORARRAY(C7))} -> Semiconductors & Semiconductor Equipment | C30: {=SUMIF(_xlfn.ANCHORARRAY(C7),_xlfn.ANCHORARRAY(B30),_xlfn.ANCHORARRAY(F7))} -> 131600.01 | D30: =C30/SUM(C$30:C$39) -> 0.62270833 | E30: =D30^2 -> 0.38776567 | G30: =M7 -> AMD | H30: =L7 -> 0.17183225 | I30: =1/COUNTA(L$7:L$22) -> 0.0625 | J30: =L7-(1/COUNTA(L$7:L$22)) -> 0.10933225 | K30: =IF(ABS(J30)>0.1,IF(J30>0,"🔻 TRIM","🔺 ADD"),IF(ABS(J30)>0.03,IF(J30>0,"▿ trim","▵ add"),"✔ OK")) -> 🔻 TRIM
B31: Software & IT Services | C31: 22565.789 | D31: =C31/SUM(C$30:C$39) -> 0.10677738 | E31: =D31^2 -> 0.011401409 | G31: =M8 -> GOOG | H31: =L8 -> 0.053377178 | I31: =1/COUNTA(L$7:L$22) -> 0.0625 | J31: =L8-(1/COUNTA(L$7:L$22)) -> -0.009122822 | K31: =IF(ABS(J31)>0.1,IF(J31>0,"🔻 TRIM","🔺 ADD"),IF(ABS(J31)>0.03,IF(J31>0,"▿ trim","▵ add"),"✔ OK")) -> ✔ OK
B32: Diversified Retail | C32: 5161.7655 | D32: =C32/SUM(C$30:C$39) -> 0.024424575 | E32: =D32^2 -> 0.00059655985 | G32: =M9 -> AMZN | H32: =L9 -> 0.024424575 | I32: =1/COUNTA(L$7:L$22) -> 0.0625 | J32: =L9-(1/COUNTA(L$7:L$22)) -> -0.038075425 | K32: =IF(ABS(J32)>0.1,IF(J32>0,"🔻 TRIM","🔺 ADD"),IF(ABS(J32)>0.03,IF(J32>0,"▿ trim","▵ add"),"✔ OK")) -> ▵ add
B33: Computers, Phones & Household Electronics | C33: 9976.032 | D33: =C33/SUM(C$30:C$39) -> 0.047204845 | E33: =D33^2 -> 0.0022282973 | G33: =M10 -> AAPL | H33: =L10 -> 0.047204845 | I33: =1/COUNTA(L$7:L$22) -> 0.0625 | J33: =L10-(1/COUNTA(L$7:L$22)) -> -0.015295155 | K33: =IF(ABS(J33)>0.1,IF(J33>0,"🔻 TRIM","🔺 ADD"),IF(ABS(J33)>0.03,IF(J33>0,"▿ trim","▵ add"),"✔ OK")) -> ✔ OK
B34: Investment Banking & Investment Services | C34: 10720.042 | D34: =C34/SUM(C$30:C$39) -> 0.050725369 | E34: =D34^2 -> 0.0025730631 | G34: =M11 -> BLK | H34: =L11 -> 0.023367944 | I34: =1/COUNTA(L$7:L$22) -> 0.0625 | J34: =L11-(1/COUNTA(L$7:L$22)) -> -0.039132056 | K34: =IF(ABS(J34)>0.1,IF(J34>0,"🔻 TRIM","🔺 ADD"),IF(ABS(J34)>0.03,IF(J34>0,"▿ trim","▵ add"),"✔ OK")) -> ▵ add
B35: Oil & Gas | C35: 3745.6155 | D35: =C35/SUM(C$30:C$39) -> 0.0177236 | E35: =D35^2 -> 0.00031412598 | G35: =M12 -> CVX | H35: =L12 -> 0.0177236 | I35: =1/COUNTA(L$7:L$22) -> 0.0625 | J35: =L12-(1/COUNTA(L$7:L$22)) -> -0.0447764 | K35: =IF(ABS(J35)>0.1,IF(J35>0,"🔻 TRIM","🔺 ADD"),IF(ABS(J35)>0.03,IF(J35>0,"▿ trim","▵ add"),"✔ OK")) -> ▵ add
B36: Automobiles & Auto Parts | C36: 5881.3667 | D36: =C36/SUM(C$30:C$39) -> 0.027829602 | E36: =D36^2 -> 0.00077448675 | G36: =M13 -> C | H36: =L13 -> 0.027357425 | I36: =1/COUNTA(L$7:L$22) -> 0.0625 | J36: =L13-(1/COUNTA(L$7:L$22)) -> -0.035142575 | K36: =IF(ABS(J36)>0.1,IF(J36>0,"🔻 TRIM","🔺 ADD"),IF(ABS(J36)>0.03,IF(J36>0,"▿ trim","▵ add"),"✔ OK")) -> ▵ add
B37: Banking Services | C37: 7916.5968 | D37: =C37/SUM(C$30:C$39) -> 0.037459956 | E37: =D37^2 -> 0.0014032483 | G37: =M14 -> F | H37: =L14 -> 0.010201707 | I37: =1/COUNTA(L$7:L$22) -> 0.0625 | J37: =L14-(1/COUNTA(L$7:L$22)) -> -0.052298293 | K37: =IF(ABS(J37)>0.1,IF(J37>0,"🔻 TRIM","🔺 ADD"),IF(ABS(J37)>0.03,IF(J37>0,"▿ trim","▵ add"),"✔ OK")) -> ▵ add
B38: Aerospace & Defense | C38: 4858.3608 | D38: =C38/SUM(C$30:C$39) -> 0.022988916 | E38: =D38^2 -> 0.00052849028 | G38: =M15 -> HMC | H38: =L15 -> 0.0075684733 | I38: =1/COUNTA(L$7:L$22) -> 0.0625 | J38: =L15-(1/COUNTA(L$7:L$22)) -> -0.054931527 | K38: =IF(ABS(J38)>0.1,IF(J38>0,"🔻 TRIM","🔺 ADD"),IF(ABS(J38)>0.03,IF(J38>0,"▿ trim","▵ add"),"✔ OK")) -> ▵ add
B39: Food & Drug Retailing | C39: 8909.3362 | D39: =C39/SUM(C$30:C$39) -> 0.042157426 | E39: =D39^2 -> 0.0017772486 | G39: =M16 -> JPM | H39: =L16 -> 0.037459956 | I39: =1/COUNTA(L$7:L$22) -> 0.0625 | J39: =L16-(1/COUNTA(L$7:L$22)) -> -0.025040044 | K39: =IF(ABS(J39)>0.1,IF(J39>0,"🔻 TRIM","🔺 ADD"),IF(ABS(J39)>0.03,IF(J39>0,"▿ trim","▵ add"),"✔ OK")) -> ✔ OK
G40: =M17 -> META | H40: =L17 -> 0.053400202 | I40: =1/COUNTA(L$7:L$22) -> 0.0625 | J40: =L17-(1/COUNTA(L$7:L$22)) -> -0.0090997979 | K40: =IF(ABS(J40)>0.1,IF(J40>0,"🔻 TRIM","🔺 ADD"),IF(ABS(J40)>0.03,IF(J40>0,"▿ trim","▵ add"),"✔ OK")) -> ✔ OK
G41: =M18 -> NVDA | H41: =L18 -> 0.45087609 | I41: =1/COUNTA(L$7:L$22) -> 0.0625 | J41: =L18-(1/COUNTA(L$7:L$22)) -> 0.38837609 | K41: =IF(ABS(J41)>0.1,IF(J41>0,"🔻 TRIM","🔺 ADD"),IF(ABS(J41)>0.03,IF(J41>0,"▿ trim","▵ add"),"✔ OK")) -> 🔻 TRIM
G42: =M19 -> 0R2N | H42: =L19 -> 0.020764038 | I42: =1/COUNTA(L$7:L$22) -> 0.0625 | J42: =L19-(1/COUNTA(L$7:L$22)) -> -0.041735962 | K42: =IF(ABS(J42)>0.1,IF(J42>0,"🔻 TRIM","🔺 ADD"),IF(ABS(J42)>0.03,IF(J42>0,"▿ trim","▵ add"),"✔ OK")) -> ▵ add
G43: =M20 -> BA | H43: =L20 -> 0.0022248784 | I43: =1/COUNTA(L$7:L$22) -> 0.0625 | J43: =L20-(1/COUNTA(L$7:L$22)) -> -0.060275122 | K43: =IF(ABS(J43)>0.1,IF(J43>0,"🔻 TRIM","🔺 ADD"),IF(ABS(J43)>0.03,IF(J43>0,"▿ trim","▵ add"),"✔ OK")) -> ▵ add
G44: =M21 -> TM | H44: =L21 -> 0.010059421 | I44: =1/COUNTA(L$7:L$22) -> 0.0625 | J44: =L21-(1/COUNTA(L$7:L$22)) -> -0.052440579 | K44: =IF(ABS(J44)>0.1,IF(J44>0,"🔻 TRIM","🔺 ADD"),IF(ABS(J44)>0.03,IF(J44>0,"▿ trim","▵ add"),"✔ OK")) -> ▵ add
G45: =M22 -> WMT | H45: =L22 -> 0.042157426 | I45: =1/COUNTA(L$7:L$22) -> 0.0625 | J45: =L22-(1/COUNTA(L$7:L$22)) -> -0.020342574 | K45: =IF(ABS(J45)>0.1,IF(J45>0,"🔻 TRIM","🔺 ADD"),IF(ABS(J45)>0.03,IF(J45>0,"▿ trim","▵ add"),"✔ OK")) -> ✔ OK

Sheet WL Dashboard
B2: WATCHLIST DASHBOARD
B3: TOTAL MARKET CAP | C3: AVG P/E RATIO | D3: AVG BETA | E3: HIGHEST P/E | F3: LOWEST P/E | G3: TOP GAINER TODAY | H3: TOP LOSER TODAY | I3: STOCKS | J3: INDUSTRIES | K3: MEDIAN P/E
B4: =SUM(Watchlist!J2:INDEX(Watchlist!J:J,COUNTA(Watchlist!J:J))) -> 7311804479772 | C4: =AVERAGE(Watchlist!F2:INDEX(Watchlist!F:F,COUNTA(Watchlist!F:F))) -> 39.14644 | D4: =AVERAGE(Watchlist!E2:INDEX(Watchlist!E:E,COUNTA(Watchlist!E:E))) -> 1.04603 | E4: {=INDEX(Watchlist!B:B,MATCH(MAX(Watchlist!F$2:INDEX(Watchlist!F:F,COUNTA(Watchlist!F:F))),Watchlist!F$2:INDEX(Watchlist!F:F,COUNTA(Watchlist!F:F)),0)+1)&" "&TEXT(MAX(Watchlist!F$2:INDEX(Watchlist!F:F,COUNTA(Watchlist!F:F))),"0.0x")} -> AMD 155.1x | F4: {=INDEX(Watchlist!B:B,MATCH(MIN(Watchlist!F$2:INDEX(Watchlist!F:F,COUNTA(Watchlist!F:F))),Watchlist!F$2:INDEX(Watchlist!F:F,COUNTA(Watchlist!F:F)),0)+1)&" "&TEXT(MIN(Watchlist!F$2:INDEX(Watchlist!F:F,COUNTA(Watchlist!F:F))),"0.0x")} -> BAC 12.8x | G4: {="▲ "&INDEX(Watchlist!B:B,MATCH(MAX(Watchlist!G$2:INDEX(Watchlist!G:G,COUNTA(Watchlist!G:G))),Watchlist!G$2:INDEX(Watchlist!G:G,COUNTA(Watchlist!G:G)),0)+1)} -> ▲ XOM | H4: {="▼ "&INDEX(Watchlist!B:B,MATCH(MIN(Watchlist!G$2:INDEX(Watchlist!G:G,COUNTA(Watchlist!G:G))),Watchlist!G$2:INDEX(Watchlist!G:G,COUNTA(Watchlist!G:G)),0)+1)} -> ▼ AMD | I4: =COUNTA(Watchlist!B2:INDEX(Watchlist!B:B,COUNTA(Watchlist!B:B))) -> 10 | J4: =COUNTA(_xlfn.UNIQUE(Watchlist!K2:INDEX(Watchlist!K:K,COUNTA(Watchlist!K:K)))) -> 9 | K4: =MEDIAN(Watchlist!F2:INDEX(Watchlist!F:F,COUNTA(Watchlist!F:F))) -> 26.31065
B6: WATCHLIST STOCKS · LIVE MARKET DATA · 52-WEEK ANALYSIS
B7: Ticker | C7: Industry | D7: Current Price | E7: Change ($) | F7: P/E Ratio | G7: Beta | H7: Market Cap | I7: 52W High | J7: 52W Low | K7: 52W Range %
B8: =Watchlist!B2 -> AMD | C8: =Watchlist!K2 -> Semiconductors & Semiconductor Equipment | D8: =(Watchlist!H2+Watchlist!I2)/2 -> 612.91 | E8: =Watchlist!G2 -> -22.76 | F8: =Watchlist!F2 -> 155.1433 | G8: =Watchlist!E2 -> 2.4824 | H8: =Watchlist!J2 -> 992332578250 | I8: =Watchlist!C2 -> 639 | J8: =Watchlist!D2 -> 159.33 | K8: =((Watchlist!H2+Watchlist!I2)/2-Watchlist!D2)/(Watchlist!C2-Watchlist!D2) -> 0.94560844 | M8: Ticker | N8: 52W Range %
B9: =Watchlist!B3 -> MSFT | C9: =Watchlist!K3 -> Software & IT Services | D9: =(Watchlist!H3+Watchlist!I3)/2 -> 507.775 | E9: =Watchlist!G3 -> -6.95 | F9: =Watchlist!F3 -> 28.3741 | G9: =Watchlist!E3 -> 1.1008 | H9: =Watchlist!J3 -> 3781236024900 | I9: =Watchlist!C3 -> 553.72 | J9: =Watchlist!D3 -> 349.2 | K9: =((Watchlist!H3+Watchlist!I3)/2-Watchlist!D3)/(Watchlist!C3-Watchlist!D3) -> 0.77535204 | M9: =B8 -> AMD | N9: =K8 -> 0.94560844
B10: =Watchlist!B4 -> BABA | C10: =Watchlist!K4 -> Software & IT Services | D10: =(Watchlist!H4+Watchlist!I4)/2 -> 109.44 | E10: =Watchlist!G4 -> -0.98 | F10: =Watchlist!F4 -> 24.2472 | G10: =Watchlist!E4 -> 0.4616 | H10: =Watchlist!J4 -> 270336466240 | I10: =Watchlist!C4 -> 192.67 | J10: =Watchlist!D4 -> 91.99 | K10: =((Watchlist!H4+Watchlist!I4)/2-Watchlist!D4)/(Watchlist!C4-Watchlist!D4) -> 0.17332141 | M10: =B9 -> MSFT | N10: =K9 -> 0.77535204
B11: =Watchlist!B5 -> DELL | C11: =Watchlist!K5 -> Computers, Phones & Household Electronics | D11: =(Watchlist!H5+Watchlist!I5)/2 -> 546.25 | E11: =Watchlist!G5 -> -19.46 | F11: =Watchlist!F5 -> 31.5313 | G11: =Watchlist!E5 -> 1.3675 | H11: =Watchlist!J5 -> 345519695560 | I11: =Watchlist!C5 -> 595.51 | J11: =Watchlist!D5 -> 110.22 | K11: =((Watchlist!H5+Watchlist!I5)/2-Watchlist!D5)/(Watchlist!C5-Watchlist!D5) -> 0.89849368 | M11: =B10 -> BABA | N11: =K10 -> 0.17332141
B12: =Watchlist!B6 -> GS | C12: =Watchlist!K6 -> Investment Banking & Investment Services | D12: =(Watchlist!H6+Watchlist!I6)/2 -> 923.25 | E12: =Watchlist!G6 -> -19.17 | F12: =Watchlist!F6 -> 14.1387 | G12: =Watchlist!E6 -> 1.2712 | H12: =Watchlist!J6 -> 266794530392 | I12: =Watchlist!C6 -> 1153.99 | J12: =Watchlist!D6 -> 740.01 | K12: =((Watchlist!H6+Watchlist!I6)/2-Watchlist!D6)/(Watchlist!C6-Watchlist!D6) -> 0.44263008 | M12: =B11 -> DELL | N12: =K11 -> 0.89849368
B13: =Watchlist!B7 -> XOM | C13: =Watchlist!K7 -> Oil & Gas | D13: =(Watchlist!H7+Watchlist!I7)/2 -> 162.295 | E13: =Watchlist!G7 -> 1.93 | F13: =Watchlist!F7 -> 20.9585 | G13: =Watchlist!E7 -> 0.2089 | H13: =Watchlist!J7 -> 668267938240 | I13: =Watchlist!C7 -> 176.41 | J13: =Watchlist!D7 -> 110.385 | K13: =((Watchlist!H7+Watchlist!I7)/2-Watchlist!D7)/(Watchlist!C7-Watchlist!D7) -> 0.78621734 | M13: =B12 -> GS | N13: =K12 -> 0.44263008
B14: =Watchlist!B8 -> GM | C14: =Watchlist!K8 -> Automobiles & Auto Parts | D14: =(Watchlist!H8+Watchlist!I8)/2 -> 81.56 | E14: =Watchlist!G8 -> -1.99 | F14: =Watchlist!F8 -> 40.6735 | G14: =Watchlist!E8 -> 1.3933 | H14: =Watchlist!J8 -> 70757688960 | I14: =Watchlist!C8 -> 91.85 | J14: =Watchlist!D8 -> 54.33 | K14: =((Watchlist!H8+Watchlist!I8)/2-Watchlist!D8)/(Watchlist!C8-Watchlist!D8) -> 0.72574627 | M14: =B13 -> XOM | N14: =K13 -> 0.78621734
B15: =Watchlist!B9 -> BAC | C15: =Watchlist!K9 -> Banking Services | D15: =(Watchlist!H9+Watchlist!I9)/2 -> 56.0175 | E15: =Watchlist!G9 -> -1.23 | F15: =Watchlist!F9 -> 12.8487 | G15: =Watchlist!E9 -> 1.209 | H15: =Watchlist!J9 -> 387887787030 | I15: =Watchlist!C9 -> 65.225 | J15: =Watchlist!D9 -> 46.115 | K15: =((Watchlist!H9+Watchlist!I9)/2-Watchlist!D9)/(Watchlist!C9-Watchlist!D9) -> 0.5181842 | M15: =B14 -> GM | N15: =K14 -> 0.72574627
B16: =Watchlist!B10 -> LMT | C16: =Watchlist!K10 -> Aerospace & Defense | D16: =(Watchlist!H10+Watchlist!I10)/2 -> 520.185 | E16: =Watchlist!G10 -> -1.46 | F16: =Watchlist!F10 -> 19.091 | G16: =Watchlist!E10 -> 0.0903 | H16: =Watchlist!J10 -> 119572713480 | I16: =Watchlist!C10 -> 692 | J16: =Watchlist!D10 -> 437.25 | K16: =((Watchlist!H10+Watchlist!I10)/2-Watchlist!D10)/(Watchlist!C10-Watchlist!D10) -> 0.32555447 | M16: =B15 -> BAC | N16: =K15 -> 0.5181842
B17: =Watchlist!B11 -> COST | C17: =Watchlist!K11 -> Diversified Retail | D17: =(Watchlist!H11+Watchlist!I11)/2 -> 922.045 | E17: =Watchlist!G11 -> 0.155 | F17: =Watchlist!F11 -> 44.4581 | G17: =Watchlist!E11 -> 0.8753 | H17: =Watchlist!J11 -> 409099056720 | I17: =Watchlist!C11 -> 1096.5 | J17: =Watchlist!D11 -> 844.06 | K17: =((Watchlist!H11+Watchlist!I11)/2-Watchlist!D11)/(Watchlist!C11-Watchlist!D11) -> 0.30892489 | M17: =B16 -> LMT | N17: =K16 -> 0.32555447
M18: =B17 -> COST | N18: =K17 -> 0.30892489
B19: VISUALIZATIONS
B51: 52-WEEK RANGE ANALYSIS
B53: Industry | C53: Market Cap
B54: {=_xlfn.UNIQUE(C8:C17)} -> Semiconductors & Semiconductor Equipment | C54: {=SUMIF(C8:C17,_xlfn.ANCHORARRAY(B54),H8:H17)} -> 992332578250
B55: Software & IT Services | C55: 4051572491140
B56: Computers, Phones & Household Electronics | C56: 345519695560
B57: Investment Banking & Investment Services | C57: 266794530392
B58: Oil & Gas | C58: 668267938240
B59: Automobiles & Auto Parts | C59: 70757688960
B60: Banking Services | C60: 387887787030
B61: Aerospace & Defense | C61: 119572713480
B62: Diversified Retail | C62: 409099056720
B64: COMPARATIVE VALUATION & MOMENTUM ANALYTICS
B65: Multi-Factor Scoring Model — Ranks Watchlist Stocks by Value, Momentum & Risk
B66: Ticker | C66: P/E | D66: P/E Rank | E66: Beta | F66: Risk Rank | G66: 52W Range % | H66: Momentum | I66: Value Score | J66: Composite | K66: Signal
B67: =B8 -> AMD | C67: =F8 -> 155.1433 | D67: =RANK(F8,F$8:F$17,1) -> 10 | E67: =G8 -> 2.4824 | F67: =RANK(G8,G$8:G$17,1) -> 10 | G67: =K8 -> 0.94560844 | H67: =IF(K8>0.7,"▲ STRONG",IF(K8>0.3,"▶ NEUTRAL","▼ WEAK")) -> ▲ STRONG | I67: =(RANK(F8,F$8:F$17,1)*0.4)+(RANK(G8,G$8:G$17,1)*0.3)+(RANK(K8,K$8:K$17,0)*0.3) -> 7.3 | J67: =RANK(I67,I$67:I$76,1) -> 8 | K67: =IF(J67<=3,"⭐ BUY",IF(J67<=7,"🔍 WATCH","⚠️ AVOID")) -> ⚠️ AVOID
B68: =B9 -> MSFT | C68: =F9 -> 28.3741 | D68: =RANK(F9,F$8:F$17,1) -> 6 | E68: =G9 -> 1.1008 | F68: =RANK(G9,G$8:G$17,1) -> 5 | G68: =K9 -> 0.77535204 | H68: =IF(K9>0.7,"▲ STRONG",IF(K9>0.3,"▶ NEUTRAL","▼ WEAK")) -> ▲ STRONG | I68: =(RANK(F9,F$8:F$17,1)*0.4)+(RANK(G9,G$8:G$17,1)*0.3)+(RANK(K9,K$8:K$17,0)*0.3) -> 5.1 | J68: =RANK(I68,I$67:I$76,1) -> 5 | K68: =IF(J68<=3,"⭐ BUY",IF(J68<=7,"🔍 WATCH","⚠️ AVOID")) -> 🔍 WATCH
B69: =B10 -> BABA | C69: =F10 -> 24.2472 | D69: =RANK(F10,F$8:F$17,1) -> 5 | E69: =G10 -> 0.4616 | F69: =RANK(G10,G$8:G$17,1) -> 3 | G69: =K10 -> 0.17332141 | H69: =IF(K10>0.7,"▲ STRONG",IF(K10>0.3,"▶ NEUTRAL","▼ WEAK")) -> ▼ WEAK | I69: =(RANK(F10,F$8:F$17,1)*0.4)+(RANK(G10,G$8:G$17,1)*0.3)+(RANK(K10,K$8:K$17,0)*0.3) -> 5.9 | J69: =RANK(I69,I$67:I$76,1) -> 7 | K69: =IF(J69<=3,"⭐ BUY",IF(J69<=7,"🔍 WATCH","⚠️ AVOID")) -> 🔍 WATCH
B70: =B11 -> DELL | C70: =F11 -> 31.5313 | D70: =RANK(F11,F$8:F$17,1) -> 7 | E70: =G11 -> 1.3675 | F70: =RANK(G11,G$8:G$17,1) -> 8 | G70: =K11 -> 0.89849368 | H70: =IF(K11>0.7,"▲ STRONG",IF(K11>0.3,"▶ NEUTRAL","▼ WEAK")) -> ▲ STRONG | I70: =(RANK(F11,F$8:F$17,1)*0.4)+(RANK(G11,G$8:G$17,1)*0.3)+(RANK(K11,K$8:K$17,0)*0.3) -> 5.8 | J70: =RANK(I70,I$67:I$76,1) -> 6 | K70: =IF(J70<=3,"⭐ BUY",IF(J70<=7,"🔍 WATCH","⚠️ AVOID")) -> 🔍 WATCH
B71: =B12 -> GS | C71: =F12 -> 14.1387 | D71: =RANK(F12,F$8:F$17,1) -> 2 | E71: =G12 -> 1.2712 | F71: =RANK(G12,G$8:G$17,1) -> 7 | G71: =K12 -> 0.44263008 | H71: =IF(K12>0.7,"▲ STRONG",IF(K12>0.3,"▶ NEUTRAL","▼ WEAK")) -> ▶ NEUTRAL | I71: =(RANK(F12,F$8:F$17,1)*0.4)+(RANK(G12,G$8:G$17,1)*0.3)+(RANK(K12,K$8:K$17,0)*0.3) -> 5 | J71: =RANK(I71,I$67:I$76,1) -> 4 | K71: =IF(J71<=3,"⭐ BUY",IF(J71<=7,"🔍 WATCH","⚠️ AVOID")) -> 🔍 WATCH
B72: =B13 -> XOM | C72: =F13 -> 20.9585 | D72: =RANK(F13,F$8:F$17,1) -> 4 | E72: =G13 -> 0.2089 | F72: =RANK(G13,G$8:G$17,1) -> 2 | G72: =K13 -> 0.78621734 | H72: =IF(K13>0.7,"▲ STRONG",IF(K13>0.3,"▶ NEUTRAL","▼ WEAK")) -> ▲ STRONG | I72: =(RANK(F13,F$8:F$17,1)*0.4)+(RANK(G13,G$8:G$17,1)*0.3)+(RANK(K13,K$8:K$17,0)*0.3) -> 3.1 | J72: =RANK(I72,I$67:I$76,1) -> 1 | K72: =IF(J72<=3,"⭐ BUY",IF(J72<=7,"🔍 WATCH","⚠️ AVOID")) -> ⭐ BUY
B73: =B14 -> GM | C73: =F14 -> 40.6735 | D73: =RANK(F14,F$8:F$17,1) -> 8 | E73: =G14 -> 1.3933 | F73: =RANK(G14,G$8:G$17,1) -> 9 | G73: =K14 -> 0.72574627 | H73: =IF(K14>0.7,"▲ STRONG",IF(K14>0.3,"▶ NEUTRAL","▼ WEAK")) -> ▲ STRONG | I73: =(RANK(F14,F$8:F$17,1)*0.4)+(RANK(G14,G$8:G$17,1)*0.3)+(RANK(K14,K$8:K$17,0)*0.3) -> 7.4 | J73: =RANK(I73,I$67:I$76,1) -> 9 | K73: =IF(J73<=3,"⭐ BUY",IF(J73<=7,"🔍 WATCH","⚠️ AVOID")) -> ⚠️ AVOID
B74: =B15 -> BAC | C74: =F15 -> 12.8487 | D74: =RANK(F15,F$8:F$17,1) -> 1 | E74: =G15 -> 1.209 | F74: =RANK(G15,G$8:G$17,1) -> 6 | G74: =K15 -> 0.5181842 | H74: =IF(K15>0.7,"▲ STRONG",IF(K15>0.3,"▶ NEUTRAL","▼ WEAK")) -> ▶ NEUTRAL | I74: =(RANK(F15,F$8:F$17,1)*0.4)+(RANK(G15,G$8:G$17,1)*0.3)+(RANK(K15,K$8:K$17,0)*0.3) -> 4 | J74: =RANK(I74,I$67:I$76,1) -> 3 | K74: =IF(J74<=3,"⭐ BUY",IF(J74<=7,"🔍 WATCH","⚠️ AVOID")) -> ⭐ BUY
B75: =B16 -> LMT | C75: =F16 -> 19.091 | D75: =RANK(F16,F$8:F$17,1) -> 3 | E75: =G16 -> 0.0903 | F75: =RANK(G16,G$8:G$17,1) -> 1 | G75: =K16 -> 0.32555447 | H75: =IF(K16>0.7,"▲ STRONG",IF(K16>0.3,"▶ NEUTRAL","▼ WEAK")) -> ▶ NEUTRAL | I75: =(RANK(F16,F$8:F$17,1)*0.4)+(RANK(G16,G$8:G$17,1)*0.3)+(RANK(K16,K$8:K$17,0)*0.3) -> 3.9 | J75: =RANK(I75,I$67:I$76,1) -> 2 | K75: =IF(J75<=3,"⭐ BUY",IF(J75<=7,"🔍 WATCH","⚠️ AVOID")) -> ⭐ BUY
B76: =B17 -> COST | C76: =F17 -> 44.4581 | D76: =RANK(F17,F$8:F$17,1) -> 9 | E76: =G17 -> 0.8753 | F76: =RANK(G17,G$8:G$17,1) -> 4 | G76: =K17 -> 0.30892489 | H76: =IF(K17>0.7,"▲ STRONG",IF(K17>0.3,"▶ NEUTRAL","▼ WEAK")) -> ▶ NEUTRAL | I76: =(RANK(F17,F$8:F$17,1)*0.4)+(RANK(G17,G$8:G$17,1)*0.3)+(RANK(K17,K$8:K$17,0)*0.3) -> 7.5 | J76: =RANK(I76,I$67:I$76,1) -> 10 | K76: =IF(J76<=3,"⭐ BUY",IF(J76<=7,"🔍 WATCH","⚠️ AVOID")) -> ⚠️ AVOID
B78: ⭐ BUY SIGNALS | C78: 🔍 WATCH LIST | D78: ⚠️ AVOID | E78: AVG P/E (BUYS) | F78: AVG BETA (BUYS) | G78: CHEAPEST STOCK | H78: RISKIEST STOCK | I78: BEST VALUE/RISK | J78: STRONG MOMENTUM | K78: WEAK MOMENTUM
B79: =COUNTIF(K67:K76,"*BUY*") -> 3 | C79: =COUNTIF(K67:K76,"*WATCH*") -> 4 | D79: =COUNTIF(K67:K76,"*AVOID*") -> 3 | E79: =AVERAGEIF(K67:K76,"*BUY*",C67:C76) -> 17.632733 | F79: =AVERAGEIF(K67:K76,"*BUY*",E67:E76) -> 0.50273333 | G79: =INDEX(B67:B76,MATCH(MIN(C67:C76),C67:C76,0)) -> BAC | H79: =INDEX(B67:B76,MATCH(MAX(E67:E76),E67:E76,0)) -> AMD | I79: =INDEX(B67:B76,MATCH(1,J67:J76,0)) -> XOM | J79: =COUNTIF(H67:H76,"*STRONG*") -> 5 | K79: =COUNTIF(H67:H76,"*WEAK*") -> 1

Sheet Analytics
A1: PORTFOLIO ANALYTICS
A2: Advanced Financial Metrics & Risk Analysis
A4: KEY PORTFOLIO METRICS
A5: Total Cost Basis | B5: Total Market Value | C5: Unrealised P&L | D5: Total Return % (incl. realised) | E5: Ann. Return (IRR) | F5: # Holdings | G5: Best Performer | H5: Worst Performer
A6: =SUM(Dashboard!F7:F22)-SUM(Dashboard!I7:I22) -> 42915.801 | B6: =SUM(Dashboard!F7:F22) -> 211334.92 | C6: =SUM(Dashboard!I7:I22) -> 168419.12 | D6: =Dashboard!F3 -> 2.291699 | E6: =Dashboard!G3 -> 0.32227901 | F6: =COUNTA(Dashboard!M7:M22) -> 16 | G6: =INDEX(Dashboard!M7:M22,MATCH(MAX(Dashboard!I7:I22),Dashboard!I7:I22,0)) -> NVDA | H6: =INDEX(Dashboard!M7:M22,MATCH(MIN(Dashboard!I7:I22),Dashboard!I7:I22,0)) -> BA
A8: INDIVIDUAL STOCK ANALYSIS
A9: Stock | B9: Cost Basis | C9: Market Value | D9: Gain/(Loss) | E9: Return % | F9: Weight % | G9: Avg Buy Price | H9: Ann. Return (IRR) | I9: Realised P&L
A10: =Dashboard!M7 -> AMD | B10: =Dashboard!F7-Dashboard!I7 -> 3207.287 | C10: =Dashboard!F7 -> 36314.154 | D10: =Dashboard!I7 -> 33106.867 | E10: =Dashboard!K7 -> 10.32239 | F10: =Dashboard!L7 -> 0.17183225 | G10: =Dashboard!O7 -> 53.68743 | H10: =Dashboard!Q7 -> 0.55674189 | I10: =SUMIFS(Ledger[Transaction Amount],Ledger[Stock],Dashboard!B7,Ledger[Transaction Type],"Sell")-SUMIFS(Ledger[Units],Ledger[Stock],Dashboard!B7,Ledger[Transaction Type],"Sell")*SUMIFS(Ledger[Transaction Amount],Ledger[Stock],Dashboard!B7,Ledger[Transaction Type],"Buy")/SUMIFS(Ledger[Units],Ledger[Stock],Dashboard!B7,Ledger[Transaction Type],"Buy") -> 1641.4131
A11: =Dashboard!M8 -> GOOG | B11: =Dashboard!F8-Dashboard!I8 -> 3138.4985 | C11: =Dashboard!F8 -> 11280.462 | D11: =Dashboard!I8 -> 8141.9631 | E11: =Dashboard!K8 -> 2.5942224 | F11: =Dashboard!L8 -> 0.053377178 | G11: =Dashboard!O8 -> 94.362552 | H11: =Dashboard!Q8 -> 0.30156799 | I11: =SUMIFS(Ledger[Transaction Amount],Ledger[Stock],Dashboard!B8,Ledger[Transaction Type],"Sell")-SUMIFS(Ledger[Units],Ledger[Stock],Dashboard!B8,Ledger[Transaction Type],"Sell")*SUMIFS(Ledger[Transaction Amount],Ledger[Stock],Dashboard!B8,Ledger[Transaction Type],"Buy")/SUMIFS(Ledger[Units],Ledger[Stock],Dashboard!B8,Ledger[Transaction Type],"Buy") -> 1473.6352
A12: =Dashboard!M9 -> AMZN | B12: =Dashboard!F9-Dashboard!I9 -> 2475.8154 | C12: =Dashboard!F9 -> 5161.7655 | D12: =Dashboard!I9 -> 2685.9501 | E12: =Dashboard!K9 -> 1.0848749 | F12: =Dashboard!L9 -> 0.024424575 | G12: =Dashboard!O9 -> 118.06464 | H12: =Dashboard!Q9 -> 0.19556205 | I12: =SUMIFS(Ledger[Transaction Amount],Ledger[Stock],Dashboard!B9,Ledger[Transaction Type],"Sell")-SUMIFS(Ledger[Units],Ledger[Stock],Dashboard!B9,Ledger[Transaction Type],"Sell")*SUMIFS(Ledger[Transaction Amount],Ledger[Stock],Dashboard!B9,Ledger[Transaction Type],"Buy")/SUMIFS(Ledger[Units],Ledger[Stock],Dashboard!B9,Ledger[Transaction Type],"Buy") -> 1104.8408
A13: =Dashboard!M10 -> AAPL | B13: =Dashboard!F10-Dashboard!I10 -> 3127.4363 | C13: =Dashboard!F10 -> 9976.032 | D13: =Dashboard!I10 -> 6848.5957 | E13: =Dashboard!K10 -> 2.1898434 | F13: =Dashboard!L10 -> 0.047204845 | G13: =Dashboard!O10 -> 106.08671 | H13: =Dashboard!Q10 -> 0.28999216 | I13: =SUMIFS(Ledger[Transaction Amount],Ledger[Stock],Dashboard!B10,Ledger[Transaction Type],"Sell")-SUMIFS(Ledger[Units],Ledger[Stock],Dashboard!B10,Ledger[Transaction Type],"Sell")*SUMIFS(Ledger[Transaction Amount],Ledger[Stock],Dashboard!B10,Ledger[Transaction Type],"Buy")/SUMIFS(Ledger[Units],Ledger[Stock],Dashboard!B10,Ledger[Transaction Type],"Buy") -> 1563.2595
A14: =Dashboard!M11 -> BLK | B14: =Dashboard!F11-Dashboard!I11 -> 3000.2546 | C14: =Dashboard!F11 -> 4938.4625 | D14: =Dashboard!I11 -> 1938.2079 | E14: =Dashboard!K11 -> 0.64601445 | F14: =Dashboard!L11 -> 0.023367944 | G14: =Dashboard!O11 -> 650.81446 | H14: =Dashboard!Q11 -> 0.13977041 | I14: =SUMIFS(Ledger[Transaction Amount],Ledger[Stock],Dashboard!B11,Ledger[Transaction Type],"Sell")-SUMIFS(Ledger[Units],Ledger[Stock],Dashboard!B11,Ledger[Transaction Type],"Sell")*SUMIFS(Ledger[Transaction Amount],Ledger[Stock],Dashboard!B11,Ledger[Transaction Type],"Buy")/SUMIFS(Ledger[Units],Ledger[Stock],Dashboard!B11,Ledger[Transaction Type],"Buy") -> 1163.6182
A15: =Dashboard!M12 -> CVX | B15: =Dashboard!F12-Dashboard!I12 -> 2349.1404 | C15: =Dashboard!F12 -> 3745.6155 | D15: =Dashboard!I12 -> 1396.4751 | E15: =Dashboard!K12 -> 0.59446216 | F15: =Dashboard!L12 -> 0.0177236 | G15: =Dashboard!O12 -> 129.42922 | H15: =Dashboard!Q12 -> 0.077858725 | I15: =SUMIFS(Ledger[Transaction Amount],Ledger[Stock],Dashboard!B12,Ledger[Transaction Type],"Sell")-SUMIFS(Ledger[Units],Ledger[Stock],Dashboard!B12,Ledger[Transaction Type],"Sell")*SUMIFS(Ledger[Transaction Amount],Ledger[Stock],Dashboard!B12,Ledger[Transaction Type],"Buy")/SUMIFS(Ledger[Units],Ledger[Stock],Dashboard!B12,Ledger[Transaction Type],"Buy") -> 256.13621
A16: =Dashboard!M13 -> C | B16: =Dashboard!F13-Dashboard!I13 -> 2406.1481 | C16: =Dashboard!F13 -> 5781.5793 | D16: =Dashboard!I13 -> 3375.4312 | E16: =Dashboard!K13 -> 1.402836 | F16: =Dashboard!L13 -> 0.027357425 | G16: =Dashboard!O13 -> 54.647925 | H16: =Dashboard!Q13 -> 0.17262424 | I16: =SUMIFS(Ledger[Transaction Amount],Ledger[Stock],Dashboard!B13,Ledger[Transaction Type],"Sell")-SUMIFS(Ledger[Units],Ledger[Stock],Dashboard!B13,Ledger[Transaction Type],"Sell")*SUMIFS(Ledger[Transaction Amount],Ledger[Stock],Dashboard!B13,Ledger[Transaction Type],"Buy")/SUMIFS(Ledger[Units],Ledger[Stock],Dashboard!B13,Ledger[Transaction Type],"Buy") -> 646.95522
A17: =Dashboard!M14 -> F | B17: =Dashboard!F14-Dashboard!I14 -> 1819.1895 | C17: =Dashboard!F14 -> 2155.977 | D17: =Dashboard!I14 -> 336.78746 | E17: =Dashboard!K14 -> 0.1851305 | F17: =Dashboard!L14 -> 0.010201707 | G17: =Dashboard!O14 -> 10.446107 | H17: =Dashboard!Q14 -> 0.032022062 | I17: =SUMIFS(Ledger[Transaction Amount],Ledger[Stock],Dashboard!B14,Ledger[Transaction Type],"Sell")-SUMIFS(Ledger[Units],Ledger[Stock],Dashboard!B14,Ledger[Transaction Type],"Sell")*SUMIFS(Ledger[Transaction Amount],Ledger[Stock],Dashboard!B14,Ledger[Transaction Type],"Buy")/SUMIFS(Ledger[Units],Ledger[Stock],Dashboard!B14,Ledger[Transaction Type],"Buy") -> 142.88134
A18: =Dashboard!M15 -> HMC | B18: =Dashboard!F15-Dashboard!I15 -> 1380.415 | C18: =Dashboard!F15 -> 1599.4827 | D18: =Dashboard!I15 -> 219.06771 | E18: =Dashboard!K15 -> 0.15869699 | F18: =Dashboard!L15 -> 0.0075684733 | G18: =Dashboard!O15 -> 28.040118 | H18: =Dashboard!Q15 -> 0.0072583467 | I18: =SUMIFS(Ledger[Transaction Amount],Ledger[Stock],Dashboard!B15,Ledger[Transaction Type],"Sell")-SUMIFS(Ledger[Units],Ledger[Stock],Dashboard!B15,Ledger[Transaction Type],"Sell")*SUMIFS(Ledger[Transaction Amount],Ledger[Stock],Dashboard!B15,Ledger[Transaction Type],"Buy")/SUMIFS(Ledger[Units],Ledger[Stock],Dashboard!B15,Ledger[Transaction Type],"Buy") -> -127.66571
A19: =Dashboard!M16 -> JPM | B19: =Dashboard!F16-Dashboard!I16 -> 3344.5687 | C19: =Dashboard!F16 -> 7916.5968 | D19: =Dashboard!I16 -> 4572.0281 | E19: =Dashboard!K16 -> 1.3670008 | F19: =Dashboard!L16 -> 0.037459956 | G19: =Dashboard!O16 -> 142.20105 | H19: =Dashboard!Q16 -> 0.20443895 | I19: =SUMIFS(Ledger[Transaction Amount],Ledger[Stock],Dashboard!B16,Ledger[Transaction Type],"Sell")-SUMIFS(Ledger[Units],Ledger[Stock],Dashboard!B16,Ledger[Transaction Type],"Sell")*SUMIFS(Ledger[Transaction Amount],Ledger[Stock],Dashboard!B16,Ledger[Transaction Type],"Buy")/SUMIFS(Ledger[Units],Ledger[Stock],Dashboard!B16,Ledger[Transaction Type],"Buy") -> 1348.4299
A20: =Dashboard!M17 -> META | B20: =Dashboard!F17-Dashboard!I17 -> 3589.0667 | C20: =Dashboard!F17 -> 11285.327 | D20: =Dashboard!I17 -> 7696.2607 | E20: =Dashboard!K17 -> 2.1443626 | F20: =Dashboard!L17 -> 0.053400202 | G20: =Dashboard!O17 -> 227.58825 | H20: =Dashboard!Q17 -> 0.29073516 | I20: =SUMIFS(Ledger[Transaction Amount],Ledger[Stock],Dashboard!B17,Ledger[Transaction Type],"Sell")-SUMIFS(Ledger[Units],Ledger[Stock],Dashboard!B17,Ledger[Transaction Type],"Sell")*SUMIFS(Ledger[Transaction Amount],Ledger[Stock],Dashboard!B17,Ledger[Transaction Type],"Buy")/SUMIFS(Ledger[Units],Ledger[Stock],Dashboard!B17,Ledger[Transaction Type],"Buy") -> 1824.1765
A21: =Dashboard!M18 -> NVDA | B21: =Dashboard!F18-Dashboard!I18 -> 4817.7863 | C21: =Dashboard!F18 -> 95285.861 | D21: =Dashboard!I18 -> 90468.075 | E21: =Dashboard!K18 -> 18.777934 | F21: =Dashboard!L18 -> 0.45087609 | G21: =Dashboard!O18 -> 11.571481 | H21: =Dashboard!Q18 -> 0.74484886 | I21: =SUMIFS(Ledger[Transaction Amount],Ledger[Stock],Dashboard!B18,Ledger[Transaction Type],"Sell")-SUMIFS(Ledger[Units],Ledger[Stock],Dashboard!B18,Ledger[Transaction Type],"Sell")*SUMIFS(Ledger[Transaction Amount],Ledger[Stock],Dashboard!B18,Ledger[Transaction Type],"Buy")/SUMIFS(Ledger[Units],Ledger[Stock],Dashboard!B18,Ledger[Transaction Type],"Buy") -> 2957.9209
... A25: =Dashboard!M22 -> WMT | B25: =Dashboard!F22-Dashboard!I22 -> 3714.3227 | C25: =Dashboard!F22 -> 8909.3362 | D25: =Dashboard!I22 -> 5195.0135 | E25: =Dashboard!K22 -> 1.3986435 | F25: =Dashboard!L22 -> 0.042157426 | G25: =Dashboard!O22 -> 45.329787 | H25: =Dashboard!Q22 -> 0.2164966 | I25: =SUMIFS(Ledger[Transaction Amount],Ledger[Stock],Dashboard!B22,Ledger[Transaction Type],"Sell")-SUMIFS(Ledger[Units],Ledger[Stock],Dashboard!B22,Ledger[Transaction Type],"Sell")*SUMIFS(Ledger[Transaction Amount],Ledger[Stock],Dashboard!B22,Ledger[Transaction Type],"Buy")/SUMIFS(Ledger[Units],Ledger[Stock],Dashboard!B22,Ledger[Transaction Type],"Buy") -> 1617.4821
A27: SECTOR CONCENTRATION & RISK | F27: RISK METRICS
A28: Industry | B28: Market Value | C28: Weight % | D28: HHI Contrib. | F28: Metric | G28: Value | H28: Status
A29: {=IFERROR(INDEX(_xlfn.UNIQUE(Dashboard!C7:C22),1),"")} -> Semiconductors & Semiconductor Equipment | B29: =IF(A29="","",SUMIF(Dashboard!C7:C22,A29,Dashboard!F7:F22)) -> 131600.01 | C29: =IF(A29="","",B29/SUM($B$29:$B$38)) -> 0.62270833 | D29: =IF(A29="","",C29^2) -> 0.38776567 | F29: Total Invested | G29: =A6 -> 42915.801 | H29: =IF(B6>A6,"✅ Positive","⚠️ Loss") -> ✅ Positive
A30: {=IFERROR(INDEX(_xlfn.UNIQUE(Dashboard!C7:C22),2),"")} -> Software & IT Services | B30: =IF(A30="","",SUMIF(Dashboard!C7:C22,A30,Dashboard!F7:F22)) -> 22565.789 | C30: =IF(A30="","",B30/SUM($B$29:$B$38)) -> 0.10677738 | D30: =IF(A30="","",C30^2) -> 0.011401409 | F30: Current Value | G30: =B6 -> 211334.92 | H30: =IF(G30>G29*1.5,"✅ Strong Growth",IF(G30>G29,"🟢 Positive","🔴 Drawdown")) -> ✅ Strong Growth
A31: {=IFERROR(INDEX(_xlfn.UNIQUE(Dashboard!C7:C22),3),"")} -> Diversified Retail | B31: =IF(A31="","",SUMIF(Dashboard!C7:C22,A31,Dashboard!F7:F22)) -> 5161.7655 | C31: =IF(A31="","",B31/SUM($B$29:$B$38)) -> 0.024424575 | D31: =IF(A31="","",C31^2) -> 0.00059655985 | F31: Worst Stock Return | G31: =MIN(E10:E25) -> -0.26147276 | H31: =IF(G31<-0.2,"🔴 High Risk",IF(G31<-0.1,"🟡 Moderate","🟢 Low Risk")) -> 🔴 High Risk
A32: {=IFERROR(INDEX(_xlfn.UNIQUE(Dashboard!C7:C22),4),"")} -> Computers, Phones & Household Electronics | B32: =IF(A32="","",SUMIF(Dashboard!C7:C22,A32,Dashboard!F7:F22)) -> 9976.032 | C32: =IF(A32="","",B32/SUM($B$29:$B$38)) -> 0.047204845 | D32: =IF(A32="","",C32^2) -> 0.0022282973 | F32: Top Holding Weight | G32: =MAX(F10:F25) -> 0.45087609 | H32: =IF(G32>0.5,"🔴 Over-concentrated",IF(G32>0.3,"🟡 Monitor","🟢 Balanced")) -> 🟡 Monitor
A33: {=IFERROR(INDEX(_xlfn.UNIQUE(Dashboard!C7:C22),5),"")} -> Investment Banking & Investment Services | B33: =IF(A33="","",SUMIF(Dashboard!C7:C22,A33,Dashboard!F7:F22)) -> 10720.042 | C33: =IF(A33="","",B33/SUM($B$29:$B$38)) -> 0.050725369 | D33: =IF(A33="","",C33^2) -> 0.0025730631 | F33: Top 3 Concentration | G33: =LARGE(F10:F25,1)+LARGE(F10:F25,2)+LARGE(F10:F25,3) -> 0.67610853 | H33: =IF(G33>0.7,"🔴 Top-heavy",IF(G33>0.5,"🟡 Monitor","🟢 Balanced")) -> 🟡 Monitor
A34: {=IFERROR(INDEX(_xlfn.UNIQUE(Dashboard!C7:C22),6),"")} -> Oil & Gas | B34: =IF(A34="","",SUMIF(Dashboard!C7:C22,A34,Dashboard!F7:F22)) -> 3745.6155 | C34: =IF(A34="","",B34/SUM($B$29:$B$38)) -> 0.0177236 | D34: =IF(A34="","",C34^2) -> 0.00031412598 | F34: Avg Return per Stock | G34: =AVERAGE(E10:E25) -> 2.7406333 | H34: =IF(G34>1,"✅ Strong",IF(G34>0.5,"🟢 Positive","🟡 Weak")) -> ✅ Strong
A35: {=IFERROR(INDEX(_xlfn.UNIQUE(Dashboard!C7:C22),7),"")} -> Automobiles & Auto Parts | B35: =IF(A35="","",SUMIF(Dashboard!C7:C22,A35,Dashboard!F7:F22)) -> 5881.3667 | C35: =IF(A35="","",B35/SUM($B$29:$B$38)) -> 0.027829602 | D35: =IF(A35="","",C35^2) -> 0.00077448675 | F35: Profitable Positions | G35: =COUNTIF(D10:D25,">0")&"/"&COUNTA(D10:D25) -> 15/16 | H35: =IF(COUNTIF(D10:D25,">0")/COUNTA(D10:D25)>0.8,"✅ High Win Rate",IF(COUNTIF(D10:D25,">0")/COUNTA(D10:D25)>0.5,"🟢 Above 50%","🔴 Below 50%")) -> ✅ High Win Rate
A36: {=IFERROR(INDEX(_xlfn.UNIQUE(Dashboard!C7:C22),8),"")} -> Banking Services | B36: =IF(A36="","",SUMIF(Dashboard!C7:C22,A36,Dashboard!F7:F22)) -> 7916.5968 | C36: =IF(A36="","",B36/SUM($B$29:$B$38)) -> 0.037459956 | D36: =IF(A36="","",C36^2) -> 0.0014032483
A37: {=IFERROR(INDEX(_xlfn.UNIQUE(Dashboard!C7:C22),9),"")} -> Aerospace & Defense | B37: =IF(A37="","",SUMIF(Dashboard!C7:C22,A37,Dashboard!F7:F22)) -> 4858.3608 | C37: =IF(A37="","",B37/SUM($B$29:$B$38)) -> 0.022988916 | D37: =IF(A37="","",C37^2) -> 0.00052849028 | F37: PORTFOLIO HEALTH SCORECARD
A38: {=IFERROR(INDEX(_xlfn.UNIQUE(Dashboard!C7:C22),10),"")} -> Food & Drug Retailing | B38: =IF(A38="","",SUMIF(Dashboard!C7:C22,A38,Dashboard!F7:F22)) -> 8909.3362 | C38: =IF(A38="","",B38/SUM($B$29:$B$38)) -> 0.042157426 | D38: =IF(A38="","",C38^2) -> 0.0017772486 | F38: Category | G38: Score | H38: Grade
A39: HHI Index (Concentration) | D39: =SUM(D29:D38) -> 0.40936259 | F39: Return Performance | G39: =IF(E6>0.15,10,IF(E6>0.1,8,IF(E6>0.05,6,IF(E6>0,4,2)))) -> 10 | H39: =IF(G39>=8,"A",IF(G39>=6,"B",IF(G39>=4,"C","D"))) -> A
A40: Interpretation: | B40: =IF(D39<0.15,"Well Diversified",IF(D39<0.25,"Moderately Concentrated","Highly Concentrated")) -> Highly Concentrated | F40: Risk Management | G40: =IF(G31>-0.05,10,IF(G31>-0.1,8,IF(G31>-0.2,6,IF(G31>-0.5,4,2)))) -> 4 | H40: =IF(G40>=8,"A",IF(G40>=6,"B",IF(G40>=4,"C","D"))) -> C
F41: Diversification | G41: =IF(D39<0.1,10,IF(D39<0.15,8,IF(D39<0.25,6,IF(D39<0.5,4,2)))) -> 4 | H41: =IF(G41>=8,"A",IF(G41>=6,"B",IF(G41>=4,"C","D"))) -> C
A42: ADVANCED PORTFOLIO ANALYTICS | F42: Win Rate | G42: =IF(COUNTIF(D10:D25,">0")/COUNTA(D10:D25)>0.9,10,IF(COUNTIF(D10:D25,">0")/COUNTA(D10:D25)>0.75,8,IF(COUNTIF(D10:D25,">0")/COUNTA(D10:D25)>0.5,6,4))) -> 10 | H42: =IF(G42>=8,"A",IF(G42>=6,"B",IF(G42>=4,"C","D"))) -> A
A43: Risk & Return Decomposition | F43: Sector Breadth | G43: =IF(COUNTA(A29:A38)>=8,10,IF(COUNTA(A29:A38)>=6,8,IF(COUNTA(A29:A38)>=4,6,4))) -> 10 | H43: =IF(G43>=8,"A",IF(G43>=6,"B",IF(G43>=4,"C","D"))) -> A
F44: OVERALL PORTFOLIO GRADE | G44: =AVERAGE(G39:G43) -> 7.6 | H44: =IF(G44>=8,"A",IF(G44>=6,"B+",IF(G44>=5,"B",IF(G44>=4,"C","D")))) -> B+
A45: RETURN ATTRIBUTION & RISK DECOMPOSITION
A46: Metric | B46: Value | C46: Benchmark | D46: Assessment
A47: Portfolio Ann. Return (IRR) | B47: =E6 -> 0.32227901 | C47: ='Risk Analytics'!C7 -> 0.1 | D47: =IF(B47>C47,"✅ Outperforming","⚠️ Underperforming") -> ✅ Outperforming
A48: Portfolio Beta (βp) | B48: ='Risk Analytics'!C9 -> 1.8150362 | C48: β = 1.0 = Market | D48: =IF(B48>1.3,"🔴 Aggressive",IF(B48>1,"🟡 Above Market",IF(B48>0.7,"🟢 Moderate","🔵 Defensive"))) -> 🔴 Aggressive
A49: Jensen's Alpha (αp) | B49: ='Risk Analytics'!C11 -> 0.21042429 | C49: α > 0 = Skill | D49: =IF(B49>0.03,"✅ Significant Alpha",IF(B49>0,"🟢 Positive Alpha","🔴 Negative Alpha")) -> ✅ Significant Alpha
A50: Sharpe Ratio (Rp−Rf)/σp | B50: ='Risk Analytics'!C18 -> 1.2122662 | C50: Rf = 4.25% | D50: =IF(B50>2,"✅ Exceptional",IF(B50>1,"🟢 Good",IF(B50>0.5,"🟡 Adequate","🔴 Poor"))) -> 🟢 Good
A51: Treynor Ratio (Rp−Rf)/βp | B51: ='Risk Analytics'!C15 -> 0.17343393 | C51: Per unit β risk | D51: =IF(B51>0.1,"✅ Excellent",IF(B51>0.05,"🟢 Good","🟡 Weak")) -> ✅ Excellent
A52: Sortino Ratio | B52: ='Risk Analytics'!C19 -> 1.8188661 | C52: Downside σ Only | D52: =IF(B52>3,"✅ Excellent",IF(B52>2,"🟢 Good",IF(B52>1,"🟡 Adequate","🔴 Poor"))) -> 🟡 Adequate
A53: M² (Modigliani-Modigliani) | B53: ='Risk Analytics'!C68 -> 0.13040126 | C53: M² > 0 = outperform | D53: =IF(B53>0,"✅ Risk-Adj. Outperformance","🔴 Underperformance") -> ✅ Risk-Adj. Outperformance
A54: Calmar Ratio | B54: ='Risk Analytics'!C20 -> 2.4073308 | C54: CAGR / Max Loss | D54: =IF(B54>3,"✅ Excellent",IF(B54>1,"🟢 Good","🟡 Monitor")) -> 🟢 Good
A55: Avg Winner / Avg Loser (holding returns) | B55: {=AVERAGE(IF(E10:E25>0,E10:E25))/ABS(AVERAGE(IF(E10:E25<0,E10:E25)))} -> 11.24696 | C55: Avg Win / Avg Loss | D55: =IF(B55>5,"✅ Excellent Asymmetry",IF(B55>3,"✅ Strong",IF(B55>1.5,"🟢 Good","🟡 Thin"))) -> ✅ Excellent Asymmetry
A56: Total Gains / Total Losses (holdings) | B56: =SUMIF(D10:D25,">0")/ABS(SUMIF(D10:D25,"<0")) -> 1012.705 | C56: Profit / Loss | D56: =IF(B56>10,"✅ Overwhelming Gains",IF(B56>3,"✅ Excellent",IF(B56>1.5,"🟢 Profitable",IF(B56>1,"🟡 Marginal","🔴 Losing")))) -> ✅ Overwhelming Gains
A57: Effective # Sectors (1/sector HHI) | B57: =1/D39 -> 2.4428221 | C57: 10-20 ideal | D57: =IF(B57>=10,"✅ Well Diversified",IF(B57>=5,"🟡 Moderate","🔴 Concentrated")) -> 🔴 Concentrated
A58: PORTFOLIO CONSTRUCTION ANALYSIS
A59: Metric | B59: Value | C59: Optimal Range | D59: Assessment
A60: Effective # Sectors (1/sector HHI) | B60: =1/D39 -> 2.4428221 | C60: 10–20 ideal | D60: =IF(B60>=10,"✅ Well Diversified",IF(B60>=5,"🟡 Moderate","🔴 Concentrated")) -> 🔴 Concentrated
A61: Position Size Spread (Max/Min) | B61: =MAX(F10:F25)/MIN(F10:F25) -> 202.65201 | C61: < 5x balanced | D61: =IF(B61>10,"🔴 Extreme Dispersion",IF(B61>5,"🟡 Skewed","🟢 Balanced")) -> 🔴 Extreme Dispersion
A62: Top Sector Weight | B62: =MAX(C29:C38) -> 0.62270833 | C62: < 30% balanced | D62: =IF(B62>0.4,"🔴 Sector Risk",IF(B62>0.3,"🟡 Monitor","🟢 Balanced")) -> 🔴 Sector Risk
A63: Active Share (vs Equal Wt.) | B63: ='Risk Analytics'!C62 -> 0.49770833 | C63: > 60% Active | D63: =IF(B63>0.6,"✅ Stock Picker",IF(B63>0.3,"🟢 Active","🟡 Closet Indexer")) -> 🟢 Active
A64: Weighted Avg Holding Return | B64: =SUMPRODUCT(F10:F25,E10:E25) -> 10.823277 | C64: > CAGR = good | D64: =IF(B64>1,"✅ Large caps pulling weight",IF(B64>0.5,"🟢 Positive","🟡 Weak")) -> ✅ Large caps pulling weight

Sheet Risk Analytics
B1: RISK ANALYTICS
B2: Quantitative Risk & Return Decomposition
B4: CAPM & FACTOR ANALYSIS
B5: Metric | C5: Value | D5: Context | E5: Assessment
B6: Risk-Free Rate (Rf) | C6: 0.0425 | D6: US 10Y Treasury | E6: Input Assumption
B7: Market Return (Rm) | C7: 0.1 | D7: S&P 500 LT Avg | E7: Input Assumption
B8: Equity Risk Premium (Rm − Rf) | C8: =C7-C6 -> 0.0575 | D8: Historical: 4-6% | E8: =IF(C8>0.06,"✅ Above Average",IF(C8>0.04,"🟢 Normal Range","🟡 Below Average")) -> 🟢 Normal Range
B9: Portfolio Beta (βp) | C9: =SUMPRODUCT(C39:C54,D39:D54) -> 1.8150362 | D9: β = 1.0 = Market | E9: =IF(C9>1.3,"🔴 Aggressive",IF(C9>1,"🟡 Above Market",IF(C9>0.7,"🟢 Moderate","🔵 Defensive"))) -> 🔴 Aggressive
B10: Expected Return — CAPM: E(Rp) = Rf + βp(Rm − Rf) | C10: =C6+C9*(C7-C6) -> 0.14686458 | D10: CAPM Equilibrium | E10: =IF(C10>0.12,"✅ High Expected",IF(C10>0.08,"🟢 Moderate","🟡 Conservative")) -> ✅ High Expected
B11: Jensen's Alpha (αp) = Rp − [Rf + βp(Rm − Rf)] | C11: ='Portfolio Series'!B13-C10 -> 0.21042429 | D11: α > 0 = Skill | E11: =IF(C11>0.03,"✅ Significant Alpha",IF(C11>0,"🟢 Positive Alpha","🔴 Negative Alpha")) -> ✅ Significant Alpha
B12: Rp on this sheet = 12-month return of the current holdings ('Portfolio Series'); the since-inception IRR is on the Dashboard.
B13: ADVANCED RISK METRICS
B14: Metric | C14: Value | D14: Benchmark / Context | E14: Assessment
B15: Treynor Ratio = (Rp − Rf) / βp | C15: =IF(C9=0,"N/A",('Portfolio Series'!B13-C6)/C9) -> 0.17343393 | D15: Per unit β risk | E15: =IF(C9=0,"⚠️ Awaiting Beta",IF(C15>0.1,"✅ Excellent",IF(C15>0.05,"🟢 Good","🟡 Weak"))) -> ✅ Excellent
B16: Information Ratio = Active Return / Tracking Error (vs SPY) | C16: ='Portfolio Series'!B22 -> 1.2045123 | D16: > 0.5 Good, > 1.0 Elite | E16: =IF(C17=0,"⚠️ N/A",IF(C16>1,"✅ Exceptional",IF(C16>0.5,"🟢 Good",IF(C16>0,"🟡 Marginal","🔴 Negative")))) -> ✅ Exceptional
B17: Tracking Error vs SPY (12m daily, annualised) | C17: ='Portfolio Series'!B20 -> 0.16911893 | D17: < 2% Passive, > 5% Active | E17: =IF(ABS(C17)>0.05,"🔴 High Active Risk",IF(ABS(C17)>0.02,"🟡 Moderate","🟢 Index-Like")) -> 🔴 High Active Risk
B18: Sharpe Ratio = (Rp − Rf) / σp | C18: =('Portfolio Series'!B13-C6)/C25 -> 1.2122662 | D18: > 1.0 Good, > 2.0 Elite | E18: =IF(C18>2,"✅ Exceptional",IF(C18>1,"🟢 Good",IF(C18>0.5,"🟡 Adequate","🔴 Poor"))) -> 🟢 Good
B19: Sortino Ratio = (Rp − Rf) / Downside σ | C19: =('Portfolio Series'!B13-C6)/C30 -> 1.8188661 | D19: > 2.0 Good, > 3.0 Elite | E19: =IF(C19>3,"✅ Excellent",IF(C19>2,"🟢 Good",IF(C19>1,"🟡 Adequate","🔴 Poor"))) -> 🟡 Adequate
B20: Calmar Ratio = 12m Return / 12m Max Drawdown | C20: ='Portfolio Series'!B13/ABS('Portfolio Series'!B16) -> 2.4073308 | D20: > 1.0 Good, > 3.0 Elite | E20: =IF(C20>3,"✅ Excellent",IF(C20>1,"🟢 Good","🟡 Monitor")) -> 🟢 Good
B22: VALUE AT RISK (VaR) & TAIL RISK
B23: Metric | C23: Value | D23: Context | E23: Interpretation
B24: Expected Return (CAPM), mean for normal VaR | C24: =C10 -> 0.14686458 | D24: CAPM E(Rp) | E24: Arithmetic expectation
B25: Portfolio Volatility (realised, 12m daily) | C25: ='Portfolio Series'!B14 -> 0.25966975 | D25: Annualised from daily returns | E25: =IF(C25>0.3,"🔴 High Dispersion",IF(C25>0.15,"🟡 Moderate","🟢 Low")) -> 🟡 Moderate
B26: Parametric VaR (95%, 1-Year) | C26: =C24-1.645*C25 -> -0.28029216 | D26: 95% confidence | E26: ="95% VaR loss: "&TEXT(ABS(C26)*SUM(Dashboard!F7:F22),"$#,##0") -> 95% VaR loss: $59,236
B27: Parametric VaR (99%, 1-Year) | C27: =C24-2.326*C25 -> -0.45712727 | D27: 99% confidence | E27: ="99% VaR loss: "&TEXT(ABS(C27)*SUM(Dashboard!F7:F22),"$#,##0") -> 99% VaR loss: $96,607
B28: Expected Shortfall (CVaR 95%) | C28: =C24-2.063*C25 -> -0.38883412 | D28: Avg loss beyond VaR | E28: ="Expected shortfall: "&TEXT(ABS(C28)*SUM(Dashboard!F7:F22),"$#,##0") -> Expected shortfall: $82,174
B29: Max Individual Position Loss | C29: =MIN(Analytics!E10:E25) -> -0.26147276 | D29: =INDEX(Analytics!A10:A25,MATCH(MIN(Analytics!E10:E25),Analytics!E10:E25,0)) -> BA | E29: ="$ Loss: "&TEXT(ABS(MIN(Analytics!D10:D25)),"$#,##0") -> $ Loss: $166
B30: Downside Deviation (12m daily, annualised) | C30: ='Portfolio Series'!B15 -> 0.17306875 | D30: Negative daily returns only | E30: =IF(C30<C25/2,"✅ Low Downside",IF(C30<C25,"🟢 Acceptable","🔴 High Downside")) -> 🟢 Acceptable
B31: Historical VaR (95%, 1-day) | C31: ='Portfolio Series'!B17 -> 0.0267122 | D31: Worst 5% of daily moves | E31: ="1-day loss: "&TEXT(C31*SUM(Dashboard!F7:F22),"$#,##0") -> 1-day loss: $5,645
B32: PORTFOLIO CONSTRUCTION & DIVERSIFICATION
B33: Metric | C33: Value | D33: Optimal Range | E33: Assessment
B34: Effective # Holdings (1/HHI of holding weights) | C34: {=1/SUMPRODUCT((Dashboard!L7:'Dashboard'!L22)^2)} -> 4.0513897 | D34: 10–20 ideal | E34: =IF(C34>=10,"✅ Well Diversified",IF(C34>=5,"🟡 Moderate","🔴 Concentrated")) -> 🔴 Concentrated
B35: Largest / Smallest Position Ratio | C35: =MAX(Dashboard!L7:'Dashboard'!L22)/MIN(Dashboard!L7:'Dashboard'!L22) -> 202.65201 | D35: < 5x balanced | E35: =IF(C35>10,"🔴 Extreme Dispersion",IF(C35>5,"🟡 Skewed","🟢 Balanced")) -> 🔴 Extreme Dispersion
B37: INDIVIDUAL STOCK RISK DECOMPOSITION
B38: Ticker | C38: Weight | D38: Beta (βi) | E38: CAGR | F38: Return % | G38: Risk Contrib. | H38: CAPM E(Ri) | I38: Stock αi | J38: Return Band
B39: =Dashboard!M7 -> AMD | C39: =Dashboard!L7 -> 0.17183225 | D39: {=IFERROR(_FV(Dashboard!B7,"Beta"),1)} -> 2.4824 | E39: =Dashboard!Q7 -> 0.55674189 | F39: =Dashboard!K7 -> 10.32239 | G39: =C39*D39 -> 0.42655637 | H39: =$C$6+D39*($C$7-$C$6) -> 0.185238 | I39: =E39-H39 -> 0.37150389 | J39: =IF(F39<0,"Loss",IF(F39>1.5,"High",IF(F39>0.5,"Mid","Low"))) -> High
B40: =Dashboard!M8 -> GOOG | C40: =Dashboard!L8 -> 0.053377178 | D40: {=IFERROR(_FV(Dashboard!B8,"Beta"),1)} -> 1.2126 | E40: =Dashboard!Q8 -> 0.30156799 | F40: =Dashboard!K8 -> 2.5942224 | G40: =C40*D40 -> 0.064725166 | H40: =$C$6+D40*($C$7-$C$6) -> 0.1122245 | I40: =E40-H40 -> 0.18934349 | J40: =IF(F40<0,"Loss",IF(F40>1.5,"High",IF(F40>0.5,"Mid","Low"))) -> High
B41: =Dashboard!M9 -> AMZN | C41: =Dashboard!L9 -> 0.024424575 | D41: {=IFERROR(_FV(Dashboard!B9,"Beta"),1)} -> 1.4565 | E41: =Dashboard!Q9 -> 0.19556205 | F41: =Dashboard!K9 -> 1.0848749 | G41: =C41*D41 -> 0.035574393 | H41: =$C$6+D41*($C$7-$C$6) -> 0.12624875 | I41: =E41-H41 -> 0.069313297 | J41: =IF(F41<0,"Loss",IF(F41>1.5,"High",IF(F41>0.5,"Mid","Low"))) -> Mid
B42: =Dashboard!M10 -> AAPL | C42: =Dashboard!L10 -> 0.047204845 | D42: {=IFERROR(_FV(Dashboard!B10,"Beta"),1)} -> 1.0696 | E42: =Dashboard!Q10 -> 0.28999216 | F42: =Dashboard!K10 -> 2.1898434 | G42: =C42*D42 -> 0.050490302 | H42: =$C$6+D42*($C$7-$C$6) -> 0.104002 | I42: =E42-H42 -> 0.18599016 | J42: =IF(F42<0,"Loss",IF(F42>1.5,"High",IF(F42>0.5,"Mid","Low"))) -> High
B43: =Dashboard!M11 -> BLK | C43: =Dashboard!L11 -> 0.023367944 | D43: {=IFERROR(_FV(Dashboard!B11,"Beta"),1)} -> 1.4134 | E43: =Dashboard!Q11 -> 0.13977041 | F43: =Dashboard!K11 -> 0.64601445 | G43: =C43*D43 -> 0.033028252 | H43: =$C$6+D43*($C$7-$C$6) -> 0.1237705 | I43: =E43-H43 -> 0.015999906 | J43: =IF(F43<0,"Loss",IF(F43>1.5,"High",IF(F43>0.5,"Mid","Low"))) -> Mid
B44: =Dashboard!M12 -> CVX | C44: =Dashboard!L12 -> 0.0177236 | D44: {=IFERROR(_FV(Dashboard!B12,"Beta"),1)} -> 0.5212 | E44: =Dashboard!Q12 -> 0.077858725 | F44: =Dashboard!K12 -> 0.59446216 | G44: =C44*D44 -> 0.0092375401 | H44: =$C$6+D44*($C$7-$C$6) -> 0.072469 | I44: =E44-H44 -> 0.0053897252 | J44: =IF(F44<0,"Loss",IF(F44>1.5,"High",IF(F44>0.5,"Mid","Low"))) -> Mid
B45: =Dashboard!M13 -> C | C45: =Dashboard!L13 -> 0.027357425 | D45: {=IFERROR(_FV(Dashboard!B13,"Beta"),1)} -> 1.1091 | E45: =Dashboard!Q13 -> 0.17262424 | F45: =Dashboard!K13 -> 1.402836 | G45: =C45*D45 -> 0.030342121 | H45: =$C$6+D45*($C$7-$C$6) -> 0.10627325 | I45: =E45-H45 -> 0.066350986 | J45: =IF(F45<0,"Loss",IF(F45>1.5,"High",IF(F45>0.5,"Mid","Low"))) -> Mid
B46: =Dashboard!M14 -> F | C46: =Dashboard!L14 -> 0.010201707 | D46: {=IFERROR(_FV(Dashboard!B14,"Beta"),1)} -> 1.9253 | E46: =Dashboard!Q14 -> 0.032022062 | F46: =Dashboard!K14 -> 0.1851305 | G46: =C46*D46 -> 0.019641347 | H46: =$C$6+D46*($C$7-$C$6) -> 0.15320475 | I46: =E46-H46 -> -0.12118269 | J46: =IF(F46<0,"Loss",IF(F46>1.5,"High",IF(F46>0.5,"Mid","Low"))) -> Low
B47: =Dashboard!M15 -> HMC | C47: =Dashboard!L15 -> 0.0075684733 | D47: {=IFERROR(_FV(Dashboard!B15,"Beta"),1)} -> 0.488 | E47: =Dashboard!Q15 -> 0.0072583467 | F47: =Dashboard!K15 -> 0.15869699 | G47: =C47*D47 -> 0.003693415 | H47: =$C$6+D47*($C$7-$C$6) -> 0.07056 | I47: =E47-H47 -> -0.063301653 | J47: =IF(F47<0,"Loss",IF(F47>1.5,"High",IF(F47>0.5,"Mid","Low"))) -> Low
B48: =Dashboard!M16 -> JPM | C48: =Dashboard!L16 -> 0.037459956 | D48: {=IFERROR(_FV(Dashboard!B16,"Beta"),1)} -> 1.0116 | E48: =Dashboard!Q16 -> 0.20443895 | F48: =Dashboard!K16 -> 1.3670008 | G48: =C48*D48 -> 0.037894492 | H48: =$C$6+D48*($C$7-$C$6) -> 0.100667 | I48: =E48-H48 -> 0.10377195 | J48: =IF(F48<0,"Loss",IF(F48>1.5,"High",IF(F48>0.5,"Mid","Low"))) -> Mid
B49: =Dashboard!M17 -> META | C49: =Dashboard!L17 -> 0.053400202 | D49: {=IFERROR(_FV(Dashboard!B17,"Beta"),1)} -> 1.1962 | E49: =Dashboard!Q17 -> 0.29073516 | F49: =Dashboard!K17 -> 2.1443626 | G49: =C49*D49 -> 0.063877322 | H49: =$C$6+D49*($C$7-$C$6) -> 0.1112815 | I49: =E49-H49 -> 0.17945366 | J49: =IF(F49<0,"Loss",IF(F49>1.5,"High",IF(F49>0.5,"Mid","Low"))) -> High
B50: =Dashboard!M18 -> NVDA | C50: =Dashboard!L18 -> 0.45087609 | D50: {=IFERROR(_FV(Dashboard!B18,"Beta"),1)} -> 2.2191 | E50: =Dashboard!Q18 -> 0.74484886 | F50: =Dashboard!K18 -> 18.777934 | G50: =C50*D50 -> 1.0005391 | H50: =$C$6+D50*($C$7-$C$6) -> 0.17009825 | I50: =E50-H50 -> 0.57475061 | J50: =IF(F50<0,"Loss",IF(F50>1.5,"High",IF(F50>0.5,"Mid","Low"))) -> High
... B54: =Dashboard!M22 -> WMT | C54: =Dashboard!L22 -> 0.042157426 | D54: {=IFERROR(_FV(Dashboard!B22,"Beta"),1)} -> 0.5754 | E54: =Dashboard!Q22 -> 0.2164966 | F54: =Dashboard!K22 -> 1.3986435 | G54: =C54*D54 -> 0.024257383 | H54: =$C$6+D54*($C$7-$C$6) -> 0.0755855 | I54: =E54-H54 -> 0.1409111 | J54: =IF(F54<0,"Loss",IF(F54>1.5,"High",IF(F54>0.5,"Mid","Low"))) -> Mid
B55: PORTFOLIO TOTAL | C55: =SUM(C39:C54) -> 1 | D55: =C9 -> 1.8150362 | E55: =Analytics!E6 -> 0.32227901 | F55: =Analytics!D6 -> 2.291699 | G55: =SUM(G39:G54) -> 1.8150362 | H55: =C10 -> 0.14686458 | I55: =C11 -> 0.21042429 | J55: =COUNTIF(J39:J54,"High")&" High / "&COUNTIF(J39:J54,"Mid")&" Mid / "&COUNTIF(J39:J54,"Low")&" Low / "&COUNTIF(J39:J54,"Loss")&" Loss" -> 5 High / 7 Mid / 3 Low / 1 Loss
B57: RETURN BANDS & MARKET SENSITIVITY
B58: Factor | C58: Exposure | D58: Detail | E58: Assessment
B59: Return Band Mix (holding returns) | C59: =J55 -> 5 High / 7 Mid / 3 Low / 1 Loss | D59: Bands by unrealised return, not investment style | E59: =IF(COUNTIF(J39:J54,"Loss")>3,"🟡 Several losing holdings","🟢 Mostly positive") -> 🟢 Mostly positive
B60: Weighted Avg β (market sensitivity) | C60: =C9 -> 1.8150362 | D60: β = 1.0 neutral | E60: =IF(C9>1.3,"🟡 High market sensitivity",IF(C9>0.7,"🟢 Market-like","🔵 Defensive")) -> 🟡 High market sensitivity
B61: Sector Concentration (HHI) | C61: {=SUMPRODUCT((Dashboard!D30:'Dashboard'!D39)^2)} -> 0.40936259 | D61: < 15% diversified | E61: =IF(C61>0.25,"🔴 Concentrated",IF(C61>0.15,"🟡 Moderate","🟢 Diversified")) -> 🔴 Concentrated
B62: Active Share Proxy (vs Equal Wt.) | C62: {=0.5*SUMPRODUCT(ABS(Dashboard!L7:'Dashboard'!L22-1/16))} -> 0.49770833 | D62: > 60% Active | E62: =IF(C62>0.6,"✅ Stock Picker",IF(C62>0.3,"🟢 Active","🟡 Closet Indexer")) -> 🟢 Active
B64: CAPITAL MARKET LINE ANALYSIS
B65: Metric | C65: Value | D65: CML Position | E65: Assessment
B66: CML Expected Return at Port. σ | C66: =C6+(C7-C6)/0.155*C25 -> 0.1388291 | D66: CML benchmark | E66: =IF('Portfolio Series'!B13>C66,"✅ Above CML","🔴 Below CML") -> ✅ Above CML
B67: Portfolio vs CML Spread | C67: ='Portfolio Series'!B13-C66 -> 0.21845977 | D67: > 0 = efficient | E67: =IF(C67>0,"✅ Efficient Allocation","🔴 Suboptimal") -> ✅ Efficient Allocation
B68: M² (Modigliani-Modigliani) = Sp × σm + Rf − Rm | C68: =C18*0.155+C6-C7 -> 0.13040126 | D68: M² > 0 = outperform | E68: =IF(C68>0,"✅ Risk-Adj. Outperformance","🔴 Underperformance") -> ✅ Risk-Adj. Outperformance

Sheet Watchlist
A1: Stock | B1: Ticker symbol | C1: 52 week high | D1: 52 week low | E1: Beta | F1: P/E | G1: Change | H1: High | I1: Low | J1: Market cap | K1: Industry | L1: Exchange abbreviation | N1: Stock | O1: (All)
A2: #VALUE! | B2: {=_FV(Table2[[#This Row],[Stock]],"Ticker symbol",TRUE)} -> AMD | C2: {=_FV(Table2[[#This Row],[Stock]],"52 week high",TRUE)} -> 639 | D2: {=_FV(Table2[[#This Row],[Stock]],"52 week low",TRUE)} -> 159.33 | E2: {=_FV(Table2[[#This Row],[Stock]],"Beta")} -> 2.4824 | F2: {=_FV(Table2[[#This Row],[Stock]],"P/E",TRUE)} -> 155.1433 | G2: {=_FV(Table2[[#This Row],[Stock]],"Change")} -> -22.76 | H2: {=_FV(Table2[[#This Row],[Stock]],"High")} -> 629.75 | I2: {=_FV(Table2[[#This Row],[Stock]],"Low")} -> 596.07 | J2: {=_FV(Table2[[#This Row],[Stock]],"Market cap",TRUE)} -> 992332578250 | K2: {=_FV(Table2[[#This Row],[Stock]],"Industry")} -> Semiconductors & Semiconductor Equipment | L2: {=_FV(Table2[[#This Row],[Stock]],"Exchange abbreviation",TRUE)} -> XNAS
A3: #VALUE! | B3: {=_FV(Table2[[#This Row],[Stock]],"Ticker symbol",TRUE)} -> MSFT | C3: {=_FV(Table2[[#This Row],[Stock]],"52 week high",TRUE)} -> 553.72 | D3: {=_FV(Table2[[#This Row],[Stock]],"52 week low",TRUE)} -> 349.2 | E3: {=_FV(Table2[[#This Row],[Stock]],"Beta")} -> 1.1008 | F3: {=_FV(Table2[[#This Row],[Stock]],"P/E",TRUE)} -> 28.3741 | G3: {=_FV(Table2[[#This Row],[Stock]],"Change")} -> -6.95 | H3: {=_FV(Table2[[#This Row],[Stock]],"High")} -> 513.33 | I3: {=_FV(Table2[[#This Row],[Stock]],"Low")} -> 502.22 | J3: {=_FV(Table2[[#This Row],[Stock]],"Market cap",TRUE)} -> 3781236024900 | K3: {=_FV(Table2[[#This Row],[Stock]],"Industry")} -> Software & IT Services | L3: {=_FV(Table2[[#This Row],[Stock]],"Exchange abbreviation",TRUE)} -> XNAS | N3: Exchange abbreviation | O3: Ticker symbol
A4: #VALUE! | B4: {=_FV(Table2[[#This Row],[Stock]],"Ticker symbol",TRUE)} -> BABA | C4: {=_FV(Table2[[#This Row],[Stock]],"52 week high",TRUE)} -> 192.67 | D4: {=_FV(Table2[[#This Row],[Stock]],"52 week low",TRUE)} -> 91.99 | E4: {=_FV(Table2[[#This Row],[Stock]],"Beta")} -> 0.4616 | F4: {=_FV(Table2[[#This Row],[Stock]],"P/E",TRUE)} -> 24.2472 | G4: {=_FV(Table2[[#This Row],[Stock]],"Change")} -> -0.98 | H4: {=_FV(Table2[[#This Row],[Stock]],"High")} -> 110.12 | I4: {=_FV(Table2[[#This Row],[Stock]],"Low")} -> 108.76 | J4: {=_FV(Table2[[#This Row],[Stock]],"Market cap",TRUE)} -> 270336466240 | K4: {=_FV(Table2[[#This Row],[Stock]],"Industry")} -> Software & IT Services | L4: {=_FV(Table2[[#This Row],[Stock]],"Exchange abbreviation",TRUE)} -> XNYS | N4: XNAS | O4: AMD
A5: #VALUE! | B5: {=_FV(Table2[[#This Row],[Stock]],"Ticker symbol",TRUE)} -> DELL | C5: {=_FV(Table2[[#This Row],[Stock]],"52 week high",TRUE)} -> 595.51 | D5: {=_FV(Table2[[#This Row],[Stock]],"52 week low",TRUE)} -> 110.22 | E5: {=_FV(Table2[[#This Row],[Stock]],"Beta")} -> 1.3675 | F5: {=_FV(Table2[[#This Row],[Stock]],"P/E",TRUE)} -> 31.5313 | G5: {=_FV(Table2[[#This Row],[Stock]],"Change")} -> -19.46 | H5: {=_FV(Table2[[#This Row],[Stock]],"High")} -> 557 | I5: {=_FV(Table2[[#This Row],[Stock]],"Low")} -> 535.5 | J5: {=_FV(Table2[[#This Row],[Stock]],"Market cap",TRUE)} -> 345519695560 | K5: {=_FV(Table2[[#This Row],[Stock]],"Industry")} -> Computers, Phones & Household Electronics | L5: {=_FV(Table2[[#This Row],[Stock]],"Exchange abbreviation",TRUE)} -> XNYS | N5: XNAS | O5: COST
A6: #VALUE! | B6: {=_FV(Table2[[#This Row],[Stock]],"Ticker symbol",TRUE)} -> GS | C6: {=_FV(Table2[[#This Row],[Stock]],"52 week high",TRUE)} -> 1153.99 | D6: {=_FV(Table2[[#This Row],[Stock]],"52 week low",TRUE)} -> 740.01 | E6: {=_FV(Table2[[#This Row],[Stock]],"Beta")} -> 1.2712 | F6: {=_FV(Table2[[#This Row],[Stock]],"P/E",TRUE)} -> 14.1387 | G6: {=_FV(Table2[[#This Row],[Stock]],"Change")} -> -19.17 | H6: {=_FV(Table2[[#This Row],[Stock]],"High")} -> 932 | I6: {=_FV(Table2[[#This Row],[Stock]],"Low")} -> 914.5 | J6: {=_FV(Table2[[#This Row],[Stock]],"Market cap",TRUE)} -> 266794530392 | K6: {=_FV(Table2[[#This Row],[Stock]],"Industry")} -> Investment Banking & Investment Services | L6: {=_FV(Table2[[#This Row],[Stock]],"Exchange abbreviation",TRUE)} -> XNYS | N6: XNAS | O6: MSFT
A7: #VALUE! | B7: {=_FV(Table2[[#This Row],[Stock]],"Ticker symbol",TRUE)} -> XOM | C7: {=_FV(Table2[[#This Row],[Stock]],"52 week high",TRUE)} -> 176.41 | D7: {=_FV(Table2[[#This Row],[Stock]],"52 week low",TRUE)} -> 110.385 | E7: {=_FV(Table2[[#This Row],[Stock]],"Beta")} -> 0.2089 | F7: {=_FV(Table2[[#This Row],[Stock]],"P/E",TRUE)} -> 20.9585 | G7: {=_FV(Table2[[#This Row],[Stock]],"Change")} -> 1.93 | H7: {=_FV(Table2[[#This Row],[Stock]],"High")} -> 163.54 | I7: {=_FV(Table2[[#This Row],[Stock]],"Low")} -> 161.05 | J7: {=_FV(Table2[[#This Row],[Stock]],"Market cap",TRUE)} -> 668267938240 | K7: {=_FV(Table2[[#This Row],[Stock]],"Industry")} -> Oil & Gas | L7: {=_FV(Table2[[#This Row],[Stock]],"Exchange abbreviation",TRUE)} -> XNYS | N7: XNYS | O7: BABA
A8: #VALUE! | B8: {=_FV(Table2[[#This Row],[Stock]],"Ticker symbol",TRUE)} -> GM | C8: {=_FV(Table2[[#This Row],[Stock]],"52 week high",TRUE)} -> 91.85 | D8: {=_FV(Table2[[#This Row],[Stock]],"52 week low",TRUE)} -> 54.33 | E8: {=_FV(Table2[[#This Row],[Stock]],"Beta")} -> 1.3933 | F8: {=_FV(Table2[[#This Row],[Stock]],"P/E",TRUE)} -> 40.6735 | G8: {=_FV(Table2[[#This Row],[Stock]],"Change")} -> -1.99 | H8: {=_FV(Table2[[#This Row],[Stock]],"High")} -> 82.69 | I8: {=_FV(Table2[[#This Row],[Stock]],"Low")} -> 80.43 | J8: {=_FV(Table2[[#This Row],[Stock]],"Market cap",TRUE)} -> 70757688960 | K8: {=_FV(Table2[[#This Row],[Stock]],"Industry")} -> Automobiles & Auto Parts | L8: {=_FV(Table2[[#This Row],[Stock]],"Exchange abbreviation",TRUE)} -> XNYS | N8: XNYS | O8: BAC
A9: #VALUE! | B9: {=_FV(Table2[[#This Row],[Stock]],"Ticker symbol",TRUE)} -> BAC | C9: {=_FV(Table2[[#This Row],[Stock]],"52 week high",TRUE)} -> 65.225 | D9: {=_FV(Table2[[#This Row],[Stock]],"52 week low",TRUE)} -> 46.115 | E9: {=_FV(Table2[[#This Row],[Stock]],"Beta")} -> 1.209 | F9: {=_FV(Table2[[#This Row],[Stock]],"P/E",TRUE)} -> 12.8487 | G9: {=_FV(Table2[[#This Row],[Stock]],"Change")} -> -1.23 | H9: {=_FV(Table2[[#This Row],[Stock]],"High")} -> 56.67 | I9: {=_FV(Table2[[#This Row],[Stock]],"Low")} -> 55.365 | J9: {=_FV(Table2[[#This Row],[Stock]],"Market cap",TRUE)} -> 387887787030 | K9: {=_FV(Table2[[#This Row],[Stock]],"Industry")} -> Banking Services | L9: {=_FV(Table2[[#This Row],[Stock]],"Exchange abbreviation",TRUE)} -> XNYS | N9: XNYS | O9: DELL
A10: #VALUE! | B10: {=_FV(Table2[[#This Row],[Stock]],"Ticker symbol",TRUE)} -> LMT | C10: {=_FV(Table2[[#This Row],[Stock]],"52 week high",TRUE)} -> 692 | D10: {=_FV(Table2[[#This Row],[Stock]],"52 week low",TRUE)} -> 437.25 | E10: {=_FV(Table2[[#This Row],[Stock]],"Beta")} -> 0.0903 | F10: {=_FV(Table2[[#This Row],[Stock]],"P/E",TRUE)} -> 19.091 | G10: {=_FV(Table2[[#This Row],[Stock]],"Change")} -> -1.46 | H10: {=_FV(Table2[[#This Row],[Stock]],"High")} -> 524.27 | I10: {=_FV(Table2[[#This Row],[Stock]],"Low")} -> 516.1 | J10: {=_FV(Table2[[#This Row],[Stock]],"Market cap",TRUE)} -> 119572713480 | K10: {=_FV(Table2[[#This Row],[Stock]],"Industry")} -> Aerospace & Defense | L10: {=_FV(Table2[[#This Row],[Stock]],"Exchange abbreviation",TRUE)} -> XNYS | N10: XNYS | O10: GM
A11: #VALUE! | B11: {=_FV(Table2[[#This Row],[Stock]],"Ticker symbol",TRUE)} -> COST | C11: {=_FV(Table2[[#This Row],[Stock]],"52 week high",TRUE)} -> 1096.5 | D11: {=_FV(Table2[[#This Row],[Stock]],"52 week low",TRUE)} -> 844.06 | E11: {=_FV(Table2[[#This Row],[Stock]],"Beta")} -> 0.8753 | F11: {=_FV(Table2[[#This Row],[Stock]],"P/E",TRUE)} -> 44.4581 | G11: {=_FV(Table2[[#This Row],[Stock]],"Change")} -> 0.155 | H11: {=_FV(Table2[[#This Row],[Stock]],"High")} -> 931.09 | I11: {=_FV(Table2[[#This Row],[Stock]],"Low")} -> 913 | J11: {=_FV(Table2[[#This Row],[Stock]],"Market cap",TRUE)} -> 409099056720 | K11: {=_FV(Table2[[#This Row],[Stock]],"Industry")} -> Diversified Retail | L11: {=_FV(Table2[[#This Row],[Stock]],"Exchange abbreviation",TRUE)} -> XNAS | N11: XNYS | O11: GS
N12: XNYS | O12: LMT
N13: XNYS | O13: XOM

Sheet Price History
B2: {=TRANSPOSE(_xlfn.STOCKHISTORY(A3,TODAY()-365,TODAY(),0,0,0,1))} -> 45929 | C2: 45930 | D2: 45931 | E2: 45932 | F2: 45933 | G2: 45936 | H2: 45937 | I2: 45938 | J2: 45939 | K2: 45940 | L2: 45943 | M2: 45944 | N2: 45945 | O2: 45946 | P2: 45947 | Q2: 45950 | R2: 45951 | S2: 45952 | T2: 45953 | U2: 45954 | V2: 45957 | W2: 45958 | X2: 45959 | Y2: 45960 | Z2: 45961 | AA2: 45964 | AB2: 45965 | AC2: 45966 | AD2: 45967 | AE2: 45968 | AF2: 45971 | AG2: 45972 | AH2: 45973 | AI2: 45974 | AJ2: 45975 | AK2: 45978 | AL2: 45979 | AM2: 45980 | AN2: 45981 | AO2: 45982 | AP2: 45985 | AQ2: 45986 | AR2: 45987 | AS2: 45989 | AT2: 45992 | AU2: 45993 | AV2: 45994 | AW2: 45995 | AX2: 45996 | AY2: 45999 | AZ2: 46000 | BA2: 46001 | BB2: 46002 | BC2: 46003 | BD2: 46006 | BE2: 46007 | BF2: 46008 | BG2: 46009 | BH2: 46010 | BI2: 46013 | BJ2: 46014 | BK2: 46015 | BL2: 46017 | BM2: 46020 | BN2: 46021 | BO2: 46022 | BP2: 46024 | BQ2: 46027 | BR2: 46028 | BS2: 46029 | BT2: 46030 | BU2: 46031 | BV2: 46034 | BW2: 46035 | BX2: 46036 | BY2: 46037 | BZ2: 46038 | CA2: 46042 | CB2: 46043 | CC2: 46044 | CD2: 46045 | CE2: 46048 | CF2: 46049 | CG2: 46050 | CH2: 46051 | CI2: 46052 | CJ2: 46055 | CK2: 46056 | CL2: 46057 | CM2: 46058 | CN2: 46059 | CO2: 46062 | CP2: 46063 | CQ2: 46064 | CR2: 46065 | CS2: 46066 | CT2: 46070 | CU2: 46071 | CV2: 46072 | CW2: 46073 | CX2: 46076 | CY2: 46077 | CZ2: 46078 | DA2: 46079 | DB2: 46080 | DC2: 46083 | DD2: 46084 | DE2: 46085 | DF2: 46086 | DG2: 46087 | DH2: 46090 | DI2: 46091 | DJ2: 46092 | DK2: 46093 | DL2: 46094 | DM2: 46097 | DN2: 46098 | DO2: 46099 | DP2: 46100 | DQ2: 46101 | DR2: 46104 | DS2: 46105 | DT2: 46106 | DU2: 46107 | DV2: 46108 | DW2: 46111 | DX2: 46112 | DY2: 46113 | DZ2: 46114 | EA2: 46118 | EB2: 46119 | EC2: 46120 | ED2: 46121 | EE2: 46122 | EF2: 46125 | EG2: 46126 | EH2: 46127 | EI2: 46128 | EJ2: 46129 | EK2: 46132 | EL2: 46133 | EM2: 46134 | EN2: 46135 | EO2: 46136 | EP2: 46139 | EQ2: 46140 | ER2: 46141 | ES2: 46142 | ET2: 46143 | EU2: 46146 | EV2: 46147 | EW2: 46148 | EX2: 46149 | EY2: 46150 | EZ2: 46153 | FA2: 46154 | FB2: 46155 | FC2: 46156 | FD2: 46157 | FE2: 46160 | FF2: 46161 | FG2: 46162 | FH2: 46163 | FI2: 46164 | FJ2: 46168 | FK2: 46169 | FL2: 46170 | FM2: 46171 | FN2: 46174 | FO2: 46175 | FP2: 46176 | FQ2: 46177 | FR2: 46178 | FS2: 46181 | FT2: 46182 | FU2: 46183 | FV2: 46184 | FW2: 46185 | FX2: 46188 | FY2: 46189 | FZ2: 46190 | GA2: 46191 | GB2: 46195 | GC2: 46196 | GD2: 46197 | GE2: 46198 | GF2: 46199 | GG2: 46202 | GH2: 46203 | GI2: 46204 | GJ2: 46205 | GK2: 46209 | GL2: 46210 | GM2: 46211 | GN2: 46212 | GO2: 46213 | GP2: 46216 | GQ2: 46217 | GR2: 46218 | GS2: 46219 | GT2: 46220 | GU2: 46223 | GV2: 46224 | GW2: 46225 | GX2: 46226 | GY2: 46227 | GZ2: 46230 | HA2: 46231 | HB2: 46232 | HC2: 46233 | HD2: 46234 | HE2: 46237 | HF2: 46238 | HG2: 46239 | HH2: 46240 | HI2: 46241 | HJ2: 46244 | HK2: 46245 | HL2: 46246 | HM2: 46247 | HN2: 46248 | HO2: 46251 | HP2: 46252 | HQ2: 46253 | HR2: 46254 | HS2: 46255 | HT2: 46258 | HU2: 46259 | HV2: 46260 | HW2: 46261 | HX2: 46262 | HY2: 46265 | HZ2: 46266 | IA2: 46267 | IB2: 46268 | IC2: 46269 | ID2: 46273 | IE2: 46274 | IF2: 46275 | IG2: 46276 | IH2: 46279 | II2: 46280 | IJ2: 46281 | IK2: 46282 | IL2: 46283 | IM2: 46286 | IN2: 46287 | IO2: 46288 | IP2: 46289 | IQ2: 46290 | IR2: 46293
A3: =Dashboard!B7 -> #VALUE! | B3: 161.36 | C3: 161.79 | D3: 164.01 | E3: 169.73 | F3: 164.67 | G3: 203.71 | H3: 211.51 | I3: 235.56 | J3: 232.89 | K3: 214.9 | L3: 216.42 | M3: 218.09 | N3: 238.6 | O3: 234.56 | P3: 233.08 | Q3: 240.56 | R3: 238.03 | S3: 230.23 | T3: 234.99 | U3: 252.92 | V3: 259.67 | W3: 258.01 | X3: 264.33 | Y3: 254.84 | Z3: 256.12 | AA3: 259.65 | AB3: 250.05 | AC3: 256.33 | AD3: 237.7 | AE3: 233.54 | AF3: 243.98 | AG3: 237.52 | AH3: 258.89 | AI3: 247.96 | AJ3: 246.81 | AK3: 240.52 | AL3: 230.29 | AM3: 223.55 | AN3: 206.02 | AO3: 203.78 | AP3: 215.05 | AQ3: 206.13 | AR3: 214.24 | AS3: 217.53 | AT3: 219.76 | AU3: 215.24 | AV3: 217.6 | AW3: 215.98 | AX3: 217.97 | AY3: 221.11 | AZ3: 221.62 | BA3: 221.42 | BB3: 221.43 | BC3: 210.78 | BD3: 207.58 | BE3: 209.17 | BF3: 198.11 | BG3: 201.06 | BH3: 213.43 | BI3: 214.95 | BJ3: 214.9 | BK3: 215.04 | BL3: 214.99 | BM3: 215.61 | BN3: 215.34 | BO3: 214.16 | BP3: 223.47 | BQ3: 221.08 | BR3: 214.35 | BS3: 210.02 | BT3: 204.68 | BU3: 203.17 | BV3: 207.69 | BW3: 220.97 | BX3: 223.6 | BY3: 227.92 | BZ3: 231.83 | CA3: 231.92 | CB3: 249.8 | CC3: 253.73 | CD3: 259.68 | CE3: 251.31 | CF3: 252.03 | CG3: 252.74 | CH3: 252.18 | CI3: 236.73 | CJ3: 246.27 | CK3: 242.11 | CL3: 200.19 | CM3: 192.5 | CN3: 208.44 | CO3: 216 | CP3: 213.57 | CQ3: 213.58 | CR3: 205.94 | CS3: 207.32 | CT3: 203.08 | CU3: 200.12 | CV3: 203.37 | CW3: 200.15 | CX3: 196.6 | CY3: 213.84 | CZ3: 210.86 | DA3: 203.68 | DB3: 200.21 | DC3: 198.62 | DD3: 190.95 | DE3: 202.07 | DF3: 199.45 | DG3: 192.43 | DH3: 202.68 | DI3: 203.23 | DJ3: 204.83 | DK3: 197.74 | DL3: 193.39 | DM3: 196.58 | DN3: 196.31 | DO3: 199.46 | DP3: 205.27 | DQ3: 201.33 | DR3: 202.68 | DS3: 205.37 | DT3: 220.27 | DU3: 203.77 | DV3: 201.99 | DW3: 196.04 | DX3: 203.43 | DY3: 210.21 | DZ3: 217.5 | EA3: 220.18 | EB3: 221.53 | EC3: 231.82 | ED3: 236.64 | EE3: 245.04 | EF3: 246.83 | EG3: 255.07 | EH3: 258.12 | EI3: 278.26 | EJ3: 278.39 | EK3: 274.95 | EL3: 284.49 | EM3: 303.46 | EN3: 305.33 | EO3: 347.81 | EP3: 334.63 | EQ3: 323.21 | ER3: 337.11 | ES3: 354.49 | ET3: 360.54 | EU3: 341.54 | EV3: 355.26 | EW3: 421.39 | EX3: 408.46 | EY3: 455.19 | EZ3: 458.79 | FA3: 448.29 | FB3: 445.5 | FC3: 449.7 | FD3: 424.1 | FE3: 420.99 | FF3: 414.05 | FG3: 447.58 | FH3: 449.59 | FI3: 467.51 | FJ3: 503.89 | FK3: 495.54 | FL3: 518.09 | FM3: 516.1 | FN3: 510.13 | FO3: 521.54 | FP3: 542.52 | FQ3: 523.2 | FR3: 466.38 | FS3: 490.33 | FT3: 475.505 | FU3: 452.4 | FV3: 488.45 | FW3: 511.57 | FX3: 547.26 | FY3: 507.29 | FZ3: 512.48 | GA3: 537.37 | GB3: 551.63 | GC3: 519.85 | GD3: 519.74 | GE3: 532.57 | GF3: 521.58 | GG3: 539.49 | GH3: 580.91 | GI3: 540.88 | GJ3: 517.82 | GK3: 552.05 | GL3: 516.11 | GM3: 517.405 | GN3: 546.72 | GO3: 557.89 | GP3: 534.39 | GQ3: 548.13 | GR3: 529.14 | GS3: 500.94 | GT3: 495.76 | GU3: 503.57 | GV3: 544.43 | GW3: 552.33 | GX3: 539.69 | GY3: 521.95 | GZ3: 494.95 | HA3: 454.62 | HB3: 429.56 | HC3: 485.39 | HD3: 476.15 | HE3: 484.64 | HF3: 518.58 | HG3: 482.05 | HH3: 489.28 | HI3: 483.36 | HJ3: 469.56 | HK3: 474.32 | HL3: 482.93 | HM3: 483.01 | HN3: 514.39 | HO3: 506 | HP3: 484.39 | HQ3: 466.42 | HR3: 469.455 | HS3: 473.25 | HT3: 456.745 | HU3: 479.18 | HV3: 480.93 | HW3: 476.67 | HX3: 465.58 | HY3: 470.72 | HZ3: 459.61 | IA3: 457.06 | IB3: 456.16 | IC3: 477.57 | ID3: 505.74 | IE3: 521.095 | IF3: 503.6 | IG3: 516.13 | IH3: 493.41 | II3: 504.2 | IJ3: 512.5 | IK3: 545.09 | IL3: 559.82 | IM3: 615.52 | IN3: 623.77 | IO3: 614.61 | IP3: 629.26 | IQ3: 630.63 | IR3: 607.87
A4: =Dashboard!B8 -> #VALUE! | B4: {=TRANSPOSE(_xlfn.STOCKHISTORY(A4,TODAY()-365,TODAY(),0,0,1))} -> 244.36 | C4: 243.55 | D4: 245.54 | E4: 246.43 | F4: 246.45 | G4: 251.51 | H4: 247.13 | I4: 245.46 | J4: 242.21 | K4: 237.49 | L4: 244.64 | M4: 246.19 | N4: 251.71 | O4: 251.88 | P4: 253.79 | Q4: 257.02 | R4: 251.34 | S4: 252.53 | T4: 253.73 | U4: 260.51 | V4: 269.93 | W4: 268.43 | X4: 275.17 | Y4: 281.9 | Z4: 281.82 | AA4: 284.12 | AB4: 278.06 | AC4: 284.75 | AD4: 285.34 | AE4: 279.7 | AF4: 290.59 | AG4: 291.74 | AH4: 287.43 | AI4: 279.12 | AJ4: 276.98 | AK4: 285.6 | AL4: 284.96 | AM4: 292.99 | AN4: 289.98 | AO4: 299.65 | AP4: 318.47 | AQ4: 323.64 | AR4: 320.28 | AS4: 320.12 | AT4: 315.12 | AU4: 316.02 | AV4: 320.62 | AW4: 318.39 | AX4: 322.09 | AY4: 314.45 | AZ4: 317.75 | BA4: 321 | BB4: 313.7 | BC4: 310.52 | BD4: 309.32 | BE4: 307.73 | BF4: 298.06 | BG4: 303.75 | BH4: 308.61 | BI4: 311.33 | BJ4: 315.68 | BK4: 315.67 | BL4: 314.96 | BM4: 314.39 | BN4: 314.55 | BO4: 313.8 | BP4: 315.32 | BQ4: 317.32 | BR4: 314.55 | BS4: 322.43 | BT4: 326.01 | BU4: 329.14 | BV4: 332.73 | BW4: 336.43 | BX4: 336.31 | BY4: 333.16 | BZ4: 330.34 | CA4: 322.16 | CB4: 328.38 | CC4: 330.84 | CD4: 328.43 | CE4: 333.59 | CF4: 335 | CG4: 336.28 | CH4: 338.66 | CI4: 338.53 | CJ4: 344.9 | CK4: 340.7 | CL4: 333.34 | CM4: 331.33 | CN4: 323.1 | CO4: 324.4 | CP4: 318.63 | CQ4: 311.33 | CR4: 309.37 | CS4: 306.02 | CT4: 302.82 | CU4: 303.94 | CV4: 303.56 | CW4: 314.9 | CX4: 311.69 | CY4: 310.92 | CZ4: 313.03 | DA4: 307.15 | DB4: 311.43 | DC4: 306.36 | DD4: 303.56 | DE4: 303.45 | DF4: 300.91 | DG4: 298.3 | DH4: 306.01 | DI4: 306.93 | DJ4: 308.42 | DK4: 303.21 | DL4: 301.46 | DM4: 304.42 | DN4: 309.41 | DO4: 306.3 | DP4: 305.73 | DQ4: 298.79 | DR4: 299.02 | DS4: 289.2 | DT4: 289.59 | DU4: 280.74 | DV4: 273.76 | DW4: 273.14 | DX4: 286.86 | DY4: 294.9 | DZ4: 294.46 | EA4: 297.66 | EB4: 303.93 | EC4: 314.74 | ED4: 316.37 | EE4: 315.72 | EF4: 319.21 | EG4: 330.58 | EH4: 334.47 | EI4: 332.77 | EJ4: 339.4 | EK4: 335.4 | EL4: 330.47 | EM4: 337.73 | EN4: 337.75 | EO4: 342.32 | EP4: 348.52 | EQ4: 347.5 | ER4: 347.31 | ES4: 381.94 | ET4: 383.22 | EU4: 379.64 | EV4: 384.27 | EW4: 395.14 | EX4: 395.3 | EY4: 397.05 | EZ4: 386.77 | FA4: 383.82 | FB4: 399.04 | FC4: 397.17 | FD4: 393.32 | FE4: 393.11 | FF4: 384.9 | FG4: 384.9 | FH4: 383.47 | FI4: 379.38 | FJ4: 384.84 | FK4: 384.83 | FL4: 386.12 | FM4: 376.43 | FN4: 372.58 | FO4: 358.39 | FP4: 355.68 | FQ4: 369.27 | FR4: 365.76 | FS4: 361.17 | FT4: 362.29 | FU4: 353.32 | FV4: 356.56 | FW4: 358.16 | FX4: 367.11 | FY4: 371.1 | FZ4: 362.1 | GA4: 367.46 | GB4: 348.78 | GC4: 346.08 | GD4: 345.04 | GE4: 342.19 | GF4: 334.69 | GG4: 351.28 | GH4: 353.33 | GI4: 357.89 | GJ4: 356.18 | GK4: 364.9 | GL4: 363.62 | GM4: 358.71 | GN4: 356.24 | GO4: 355.03 | GP4: 350.67 | GQ4: 357.33 | GR4: 370.21 | GS4: 353.81 | GT4: 346.12 | GU4: 351.37 | GV4: 346.19 | GW4: 341.91 | GX4: 318.34 | GY4: 319.09 | GZ4: 326.57 | HA4: 332.6 | HB4: 335.76 | HC4: 333.68 | HD4: 356.65 | HE4: 372.47 | HF4: 375.35 | HG4: 360.13 | HH4: 356.62 | HI4: 353.47 | HJ4: 355.84 | HK4: 343 | HL4: 342.37 | HM4: 343.94 | HN4: 343.54 | HO4: 341.45 | HP4: 341.28 | HQ4: 341.7 | HR4: 338.2 | HS4: 341.75 | HT4: 344.59 | HU4: 343.34 | HV4: 339.1 | HW4: 337.71 | HX4: 342.88 | HY4: 335.41 | HZ4: 332.03 | IA4: 333.78 | IB4: 339.08 | IC4: 335.31 | ID4: 335.38 | IE4: 328.38 | IF4: 330.39 | IG4: 335.45 | IH4: 345.71 | II4: 341.43 | IJ4: 339.36 | IK4: 343.68 | IL4: 344.41 | IM4: 350.87 | IN4: 347.41 | IO4: 334.98 | IP4: 339.01 | IQ4: 341.08 | IR4: 339.16
A5: =Dashboard!B9 -> #VALUE! | B5: {=TRANSPOSE(_xlfn.STOCKHISTORY(A5,TODAY()-365,TODAY(),0,0,1))} -> 222.17 | C5: 219.57 | D5: 220.63 | E5: 222.41 | F5: 219.51 | G5: 220.9 | H5: 221.78 | I5: 225.22 | J5: 227.74 | K5: 216.37 | L5: 220.07 | M5: 216.39 | N5: 215.57 | O5: 214.47 | P5: 213.04 | Q5: 216.48 | R5: 222.03 | S5: 217.95 | T5: 221.09 | U5: 224.21 | V5: 226.97 | W5: 229.25 | X5: 230.3 | Y5: 222.86 | Z5: 244.22 | AA5: 254 | AB5: 249.32 | AC5: 250.2 | AD5: 243.04 | AE5: 244.41 | AF5: 248.4 | AG5: 249.1 | AH5: 244.2 | AI5: 237.58 | AJ5: 234.69 | AK5: 232.87 | AL5: 222.55 | AM5: 222.69 | AN5: 217.14 | AO5: 220.69 | AP5: 226.28 | AQ5: 229.67 | AR5: 229.16 | AS5: 233.22 | AT5: 233.88 | AU5: 234.42 | AV5: 232.38 | AW5: 229.11 | AX5: 229.53 | AY5: 226.89 | AZ5: 227.92 | BA5: 231.78 | BB5: 230.28 | BC5: 226.19 | BD5: 222.54 | BE5: 222.56 | BF5: 221.27 | BG5: 226.76 | BH5: 227.35 | BI5: 228.43 | BJ5: 232.14 | BK5: 232.38 | BL5: 232.52 | BM5: 232.07 | BN5: 232.53 | BO5: 230.82 | BP5: 226.5 | BQ5: 233.06 | BR5: 240.93 | BS5: 241.56 | BT5: 246.29 | BU5: 247.38 | BV5: 246.47 | BW5: 242.6 | BX5: 236.65 | BY5: 238.18 | BZ5: 239.12 | CA5: 231 | CB5: 231.31 | CC5: 234.34 | CD5: 239.16 | CE5: 238.42 | CF5: 244.68 | CG5: 243.01 | CH5: 241.73 | CI5: 239.3 | CJ5: 242.96 | CK5: 238.62 | CL5: 232.99 | CM5: 222.69 | CN5: 210.32 | CO5: 208.72 | CP5: 206.96 | CQ5: 204.08 | CR5: 199.6 | CS5: 198.79 | CT5: 201.15 | CU5: 204.79 | CV5: 204.86 | CW5: 210.11 | CX5: 205.27 | CY5: 208.56 | CZ5: 210.64 | DA5: 207.92 | DB5: 210 | DC5: 208.39 | DD5: 208.73 | DE5: 216.82 | DF5: 218.94 | DG5: 213.21 | DH5: 213.49 | DI5: 214.33 | DJ5: 212.65 | DK5: 209.53 | DL5: 207.67 | DM5: 211.74 | DN5: 215.2 | DO5: 209.87 | DP5: 208.76 | DQ5: 205.37 | DR5: 210.14 | DS5: 207.24 | DT5: 211.71 | DU5: 207.54 | DV5: 199.34 | DW5: 200.95 | DX5: 208.27 | DY5: 210.57 | DZ5: 209.77 | EA5: 212.79 | EB5: 213.77 | EC5: 221.25 | ED5: 233.65 | EE5: 238.38 | EF5: 239.89 | EG5: 249.02 | EH5: 248.5 | EI5: 249.7 | EJ5: 250.56 | EK5: 248.28 | EL5: 249.91 | EM5: 255.36 | EN5: 255.08 | EO5: 263.99 | EP5: 261.12 | EQ5: 259.7 | ER5: 263.04 | ES5: 265.06 | ET5: 268.26 | EU5: 272.05 | EV5: 273.55 | EW5: 274.99 | EX5: 271.17 | EY5: 272.68 | EZ5: 268.99 | FA5: 265.82 | FB5: 270.13 | FC5: 267.22 | FD5: 264.14 | FE5: 264.86 | FF5: 259.34 | FG5: 265.01 | FH5: 268.46 | FI5: 266.32 | FJ5: 265.29 | FK5: 271.85 | FL5: 274 | FM5: 270.64 | FN5: 261.26 | FO5: 256.52 | FP5: 250.02 | FQ5: 253.79 | FR5: 246.03 | FS5: 245.22 | FT5: 244.19 | FU5: 238 | FV5: 241.51 | FW5: 238.55 | FX5: 246.02 | FY5: 246 | FZ5: 237.5 | GA5: 244.39 | GB5: 232.79 | GC5: 234.11 | GD5: 234.27 | GE5: 227.01 | GF5: 232.69 | GG5: 240.14 | GH5: 238.34 | GI5: 241.7 | GJ5: 242.67 | GK5: 244.16 | GL5: 245.98 | GM5: 243.62 | GN5: 247.04 | GO5: 245.34 | GP5: 247.31 | GQ5: 247.49 | GR5: 254.96 | GS5: 249.89 | GT5: 247.23 | GU5: 249.99 | GV5: 247.55 | GW5: 244.85 | GX5: 233.66 | GY5: 232.11 | GZ5: 231.39 | HA5: 230.86 | HB5: 226.65 | HC5: 235.5 | HD5: 271.58 | HE5: 284.02 | HF5: 277.42 | HG5: 272.65 | HH5: 272.26 | HI5: 274.48 | HJ5: 278.09 | HK5: 272.27 | HL5: 267.28 | HM5: 265.13 | HN5: 262.65 | HO5: 261.31 | HP5: 259.45 | HQ5: 265.84 | HR5: 260.11 | HS5: 258.63 | HT5: 262.07 | HU5: 261.06 | HV5: 260.28 | HW5: 256.26 | HX5: 266.43 | HY5: 259.77 | HZ5: 254.92 | IA5: 254.98 | IB5: 258.9 | IC5: 258.51 | ID5: 256.97 | IE5: 252.4 | IF5: 251.89 | IG5: 256.78 | IH5: 253.54 | II5: 248.42 | IJ5: 245.96 | IK5: 251.19 | IL5: 253.71 | IM5: 258.45 | IN5: 254.98 | IO5: 249.27 | IP5: 249.38 | IQ5: 249.67 | IR5: 246.15
A6: =Dashboard!B10 -> #VALUE! | B6: {=TRANSPOSE(_xlfn.STOCKHISTORY(A6,TODAY()-365,TODAY(),0,0,1))} -> 254.43 | C6: 254.63 | D6: 255.45 | E6: 257.13 | F6: 258.02 | G6: 256.69 | H6: 256.48 | I6: 258.06 | J6: 254.04 | K6: 245.27 | L6: 247.66 | M6: 247.77 | N6: 249.34 | O6: 247.45 | P6: 252.29 | Q6: 262.24 | R6: 262.77 | S6: 258.45 | T6: 259.58 | U6: 262.82 | V6: 268.81 | W6: 269 | X6: 269.7 | Y6: 271.4 | Z6: 270.37 | AA6: 269.05 | AB6: 270.04 | AC6: 270.14 | AD6: 269.77 | AE6: 268.47 | AF6: 269.43 | AG6: 275.25 | AH6: 273.47 | AI6: 272.95 | AJ6: 272.41 | AK6: 267.46 | AL6: 267.44 | AM6: 268.56 | AN6: 266.25 | AO6: 271.49 | AP6: 275.92 | AQ6: 276.97 | AR6: 277.55 | AS6: 278.85 | AT6: 283.1 | AU6: 286.19 | AV6: 284.15 | AW6: 280.7 | AX6: 278.78 | AY6: 277.89 | AZ6: 277.18 | BA6: 278.78 | BB6: 278.03 | BC6: 278.28 | BD6: 274.11 | BE6: 274.61 | BF6: 271.84 | BG6: 272.19 | BH6: 273.67 | BI6: 270.97 | BJ6: 272.36 | BK6: 273.81 | BL6: 273.4 | BM6: 273.76 | BN6: 273.08 | BO6: 271.86 | BP6: 271.01 | BQ6: 267.26 | BR6: 262.36 | BS6: 260.33 | BT6: 259.04 | BU6: 259.37 | BV6: 260.25 | BW6: 261.05 | BX6: 259.96 | BY6: 258.21 | BZ6: 255.53 | CA6: 246.7 | CB6: 247.65 | CC6: 248.35 | CD6: 248.04 | CE6: 255.41 | CF6: 258.27 | CG6: 256.44 | CH6: 258.28 | CI6: 259.48 | CJ6: 270.01 | CK6: 269.48 | CL6: 276.49 | CM6: 275.91 | CN6: 278.12 | CO6: 274.62 | CP6: 273.68 | CQ6: 275.5 | CR6: 261.73 | CS6: 255.78 | CT6: 263.88 | CU6: 264.35 | CV6: 260.58 | CW6: 264.58 | CX6: 266.18 | CY6: 272.14 | CZ6: 274.23 | DA6: 272.95 | DB6: 264.18 | DC6: 264.72 | DD6: 263.75 | DE6: 262.52 | DF6: 260.29 | DG6: 257.46 | DH6: 259.88 | DI6: 260.83 | DJ6: 260.81 | DK6: 255.76 | DL6: 250.12 | DM6: 252.82 | DN6: 254.23 | DO6: 249.94 | DP6: 248.96 | DQ6: 247.99 | DR6: 251.49 | DS6: 251.64 | DT6: 252.62 | DU6: 252.89 | DV6: 248.8 | DW6: 246.63 | DX6: 253.79 | DY6: 255.63 | DZ6: 255.92 | EA6: 258.86 | EB6: 253.5 | EC6: 258.9 | ED6: 260.49 | EE6: 260.48 | EF6: 259.2 | EG6: 258.83 | EH6: 266.43 | EI6: 263.4 | EJ6: 270.23 | EK6: 273.05 | EL6: 266.17 | EM6: 273.17 | EN6: 273.43 | EO6: 271.06 | EP6: 267.61 | EQ6: 270.71 | ER6: 270.17 | ES6: 271.35 | ET6: 280.14 | EU6: 276.83 | EV6: 284.18 | EW6: 287.51 | EX6: 287.44 | EY6: 293.32 | EZ6: 292.68 | FA6: 294.8 | FB6: 298.87 | FC6: 298.21 | FD6: 300.23 | FE6: 297.84 | FF6: 298.97 | FG6: 302.25 | FH6: 304.99 | FI6: 308.82 | FJ6: 308.33 | FK6: 310.85 | FL6: 312.51 | FM6: 312.06 | FN6: 306.31 | FO6: 315.2 | FP6: 310.26 | FQ6: 311.23 | FR6: 307.34 | FS6: 301.54 | FT6: 290.55 | FU6: 291.58 | FV6: 295.63 | FW6: 291.13 | FX6: 296.42 | FY6: 299.24 | FZ6: 295.95 | GA6: 298.01 | GB6: 297.01 | GC6: 294.3 | GD6: 293.08 | GE6: 275.15 | GF6: 283.78 | GG6: 281.74 | GH6: 289.36 | GI6: 294.38 | GJ6: 308.63 | GK6: 312.66 | GL6: 310.66 | GM6: 313.39 | GN6: 316.22 | GO6: 315.32 | GP6: 317.31 | GQ6: 314.86 | GR6: 327.5 | GS6: 333.26 | GT6: 333.74 | GU6: 326.59 | GV6: 327.74 | GW6: 325.89 | GX6: 321.66 | GY6: 333.02 | GZ6: 336.91 | HA6: 340.08 | HB6: 338.19 | HC6: 333.43 | HD6: 308.91 | HE6: 303.42 | HF6: 309.38 | HG6: 311 | HH6: 312.41 | HI6: 313.33 | HJ6: 308.26 | HK6: 304.91 | HL6: 302.25 | HM6: 305.26 | HN6: 305.93 | HO6: 305.59 | HP6: 310.03 | HQ6: 316.83 | HR6: 311.3 | HS6: 309.35 | HT6: 310.34 | HU6: 309.9 | HV6: 313.45 | HW6: 314.58 | HX6: 319.7 | HY6: 316.85 | HZ6: 325.13 | IA6: 324.96 | IB6: 328.21 | IC6: 319.97 | ID6: 316.22 | IE6: 315.34 | IF6: 326.57 | IG6: 332.27 | IH6: 333.08 | II6: 331.34 | IJ6: 332.41 | IK6: 337 | IL6: 336.13 | IM6: 338.98 | IN6: 339.75 | IO6: 337.02 | IP6: 335.92 | IQ6: 341.07 | IR6: 338.4
A7: =Dashboard!B11 -> #VALUE! | B7: {=TRANSPOSE(_xlfn.STOCKHISTORY(A7,TODAY()-365,TODAY(),0,0,1))} -> 1175.56 | C7: 1165.87 | D7: 1141.07 | E7: 1160.54 | F7: 1160.69 | G7: 1179.27 | H7: 1166.23 | I7: 1165 | J7: 1167.43 | K7: 1132.36 | L7: 1155.12 | M7: 1194.26 | N7: 1202.59 | O7: 1171.36 | P7: 1161.16 | Q7: 1160 | R7: 1130 | S7: 1129.68 | T7: 1125 | U7: 1136.63 | V7: 1131.31 | W7: 1124.95 | X7: 1098 | Y7: 1098.05 | Z7: 1082.81 | AA7: 1068.83 | AB7: 1059.91 | AC7: 1073.57 | AD7: 1069.44 | AE7: 1082.2 | AF7: 1082.63 | AG7: 1085.76 | AH7: 1093.93 | AI7: 1069.65 | AJ7: 1057.94 | AK7: 1023.8 | AL7: 1019.14 | AM7: 1014.68 | AN7: 992.52 | AO7: 1014.72 | AP7: 1019.49 | AQ7: 1029.77 | AR7: 1040.06 | AS7: 1047.3 | AT7: 1039.94 | AU7: 1038.62 | AV7: 1079.87 | AW7: 1075.58 | AX7: 1072.16 | AY7: 1062.02 | AZ7: 1071.31 | BA7: 1083.36 | BB7: 1101.84 | BC7: 1089.09 | BD7: 1082.16 | BE7: 1068.14 | BF7: 1065 | BG7: 1064.99 | BH7: 1060.17 | BI7: 1088.21 | BJ7: 1086.55 | BK7: 1088.96 | BL7: 1088.11 | BM7: 1088.4 | BN7: 1083.31 | BO7: 1070.34 | BP7: 1085.06 | BQ7: 1119.76 | BR7: 1112.28 | BS7: 1075.09 | BT7: 1087.92 | BU7: 1085.1 | BV7: 1089.26 | BW7: 1089.54 | BX7: 1091.85 | BY7: 1156.65 | BZ7: 1163.17 | CA7: 1110.05 | CB7: 1127.85 | CC7: 1139.72 | CD7: 1129.91 | CE7: 1121.54 | CF7: 1106.69 | CG7: 1121.67 | CH7: 1127.78 | CI7: 1118.94 | CJ7: 1119.66 | CK7: 1070.08 | CL7: 1076.16 | CM7: 1054.8 | CN7: 1056.38 | CO7: 1079.9 | CP7: 1087.78 | CQ7: 1082.88 | CR7: 1055.63 | CS7: 1071.51 | CT7: 1072.67 | CU7: 1092.26 | CV7: 1081.28 | CW7: 1093.64 | CX7: 1071.01 | CY7: 1081.05 | CZ7: 1093.78 | DA7: 1090.27 | DB7: 1063.23 | DC7: 1068.31 | DD7: 1052.59 | DE7: 1049.23 | DF7: 1035 | DG7: 955.45 | DH7: 957.67 | DI7: 967.36 | DJ7: 951.17 | DK7: 922.9 | DL7: 924.11 | DM7: 943.26 | DN7: 971.01 | DO7: 968.31 | DP7: 969.6 | DQ7: 957.91 | DR7: 974.58 | DS7: 976.06 | DT7: 981.35 | DU7: 968.46 | DV7: 933.85 | DW7: 934.06 | DX7: 961.71 | DY7: 957.4 | DZ7: 966.56 | EA7: 959.41 | EB7: 958.46 | EC7: 1001.54 | ED7: 1001.62 | EE7: 999.31 | EF7: 1023.65 | EG7: 1054.56 | EH7: 1048.6 | EI7: 1024.95 | EJ7: 1052.14 | EK7: 1048.42 | EL7: 1042.85 | EM7: 1062.47 | EN7: 1053.47 | EO7: 1044.97 | EP7: 1056.86 | EQ7: 1049.76 | ER7: 1039.38 | ES7: 1065.6 | ET7: 1061.68 | EU7: 1052.25 | EV7: 1048.91 | EW7: 1073.57 | EX7: 1067.74 | EY7: 1084.83 | EZ7: 1081.32 | FA7: 1092.5 | FB7: 1094.1 | FC7: 1104.03 | FD7: 1081.9 | FE7: 1085.88 | FF7: 1036.3 | FG7: 1051.57 | FH7: 1063.75 | FI7: 1073 | FJ7: 1077.4 | FK7: 1070.34 | FL7: 1046.49 | FM7: 1046.88 | FN7: 1020.73 | FO7: 1018.96 | FP7: 990.87 | FQ7: 1022.56 | FR7: 995.6 | FS7: 994.77 | FT7: 1011.96 | FU7: 1010.68 | FV7: 1016.58 | FW7: 1032 | FX7: 1042.87 | FY7: 1052.23 | FZ7: 1057.38 | GA7: 1050.09 | GB7: 1051.74 | GC7: 1015.33 | GD7: 982.6 | GE7: 971.92 | GF7: 964.71 | GG7: 950.17 | GH7: 961.56 | GI7: 980.38 | GJ7: 995.73 | GK7: 1011.21 | GL7: 1009.43 | GM7: 990.34 | GN7: 1019.68 | GO7: 1036.11 | GP7: 1031.56 | GQ7: 1025.44 | GR7: 1093.4 | GS7: 1087.05 | GT7: 1072.2 | GU7: 1054.11 | GV7: 1038.24 | GW7: 1056.63 | GX7: 1037.16 | GY7: 1055.67 | GZ7: 1062.14 | HA7: 1097.55 | HB7: 1079.19 | HC7: 1098.37 | HD7: 1090.39 | HE7: 1126.63 | HF7: 1131.13 | HG7: 1133.58 | HH7: 1129.3 | HI7: 1136.39 | HJ7: 1131.4 | HK7: 1148.84 | HL7: 1160.91 | HM7: 1182.84 | HN7: 1173.73 | HO7: 1147.11 | HP7: 1154.35 | HQ7: 1158.92 | HR7: 1139.82 | HS7: 1156.55 | HT7: 1172.61 | HU7: 1176.64 | HV7: 1173.21 | HW7: 1167.57 | HX7: 1164.48 | HY7: 1155.61 | HZ7: 1128.1 | IA7: 1107.08 | IB7: 1126.15 | IC7: 1122.29 | ID7: 1095.37 | IE7: 1072.03 | IF7: 1062.4 | IG7: 1079.65 | IH7: 1065.6 | II7: 1058.66 | IJ7: 1037.24 | IK7: 1053.96 | IL7: 1069.78 | IM7: 1090.27 | IN7: 1066.66 | IO7: 1060.89 | IP7: 1073.45 | IQ7: 1086.31 | IR7: 1071.25
A8: =Dashboard!B12 -> #VALUE! | B8: {=TRANSPOSE(_xlfn.STOCKHISTORY(A8,TODAY()-365,TODAY(),0,0,1))} -> 156.1 | C8: 155.29 | D8: 154.58 | E8: 153.37 | F8: 153.55 | G8: 154.02 | H8: 154.91 | I8: 153.74 | J8: 151.64 | K8: 148.9 | L8: 151.94 | M8: 152.39 | N8: 152.11 | O8: 151.71 | P8: 153.08 | Q8: 154.48 | R8: 153.79 | S8: 155.57 | T8: 156.56 | U8: 155.56 | V8: 155.28 | W8: 154.13 | X8: 155.1 | Y8: 153.52 | Z8: 157.72 | AA8: 154.04 | AB8: 153.39 | AC8: 152.66 | AD8: 152.94 | AE8: 155.02 | AF8: 155.65 | AG8: 156.24 | AH8: 153.32 | AI8: 155.58 | AJ8: 157.62 | AK8: 154.82 | AL8: 153.62 | AM8: 151.7 | AN8: 150.31 | AO8: 149.98 | AP8: 149.75 | AQ8: 148.53 | AR8: 149.51 | AS8: 151.13 | AT8: 152.54 | AU8: 150.25 | AV8: 151.59 | AW8: 152.26 | AX8: 150 | AY8: 148.71 | AZ8: 148.49 | BA8: 151.41 | BB8: 150.72 | BC8: 149.99 | BD8: 149.8 | BE8: 146.75 | BF8: 149.52 | BG8: 147.69 | BH8: 147.75 | BI8: 149.8 | BJ8: 150.51 | BK8: 150.5 | BL8: 150.02 | BM8: 150.99 | BN8: 152.31 | BO8: 152.41 | BP8: 155.9 | BQ8: 163.85 | BR8: 156.54 | BS8: 155.2 | BT8: 159.25 | BU8: 162.11 | BV8: 162.34 | BW8: 163.87 | BX8: 167.24 | BY8: 166.16 | BZ8: 166.26 | CA8: 165.3 | CB8: 166.73 | CC8: 166.66 | CD8: 166.72 | CE8: 167.5 | CF8: 169.05 | CG8: 169.93 | CH8: 171.19 | CI8: 176.9 | CJ8: 174.03 | CK8: 178.04 | CL8: 181.23 | CM8: 179.23 | CN8: 180.86 | CO8: 182.6 | CP8: 182.26 | CQ8: 185.82 | CR8: 182.4 | CS8: 183.74 | CT8: 180.55 | CU8: 183.87 | CV8: 184.78 | CW8: 183.93 | CX8: 184.91 | CY8: 185.34 | CZ8: 184.22 | DA8: 184.16 | DB8: 186.76 | DC8: 189.6 | DD8: 188.77 | DE8: 186.03 | DF8: 189.9 | DG8: 189.94 | DH8: 189.44 | DI8: 186.29 | DJ8: 191.79 | DK8: 196.97 | DL8: 196.82 | DM8: 196.84 | DN8: 197.97 | DO8: 198.61 | DP8: 201.44 | DQ8: 201.73 | DR8: 205.21 | DS8: 206.79 | DT8: 205.15 | DU8: 207.79 | DV8: 211.15 | DW8: 210.71 | DX8: 206.9 | DY8: 197.41 | DZ8: 198.97 | EA8: 198.86 | EB8: 201.54 | EC8: 192.89 | ED8: 190.36 | EE8: 188.55 | EF8: 191.78 | EG8: 187.02 | EH8: 184.91 | EI8: 188.15 | EJ8: 183.99 | EK8: 183.25 | EL8: 185.98 | EM8: 186.32 | EN8: 187.6 | EO8: 185.21 | EP8: 184.78 | EQ8: 188.36 | ER8: 192.22 | ES8: 193.31 | ET8: 190.63 | EU8: 192.28 | EV8: 192.64 | EW8: 185.16 | EX8: 182.5 | EY8: 181.62 | EZ8: 184.74 | FA8: 185.95 | FB8: 186 | FC8: 186.64 | FD8: 191.1 | FE8: 196.12 | FF8: 197.25 | FG8: 191.33 | FH8: 191.01 | FI8: 191.43 | FJ8: 184.71 | FK8: 182.4 | FL8: 183.03 | FM8: 182.46 | FN8: 185.83 | FO8: 187.55 | FP8: 189.71 | FQ8: 188.35 | FR8: 187.31 | FS8: 189.24 | FT8: 186.76 | FU8: 189.8 | FV8: 185.82 | FW8: 187.22 | FX8: 180.4 | FY8: 180.11 | FZ8: 177.58 | GA8: 173.63 | GB8: 175.06 | GC8: 175.98 | GD8: 171.45 | GE8: 172.24 | GF8: 171.06 | GG8: 168.47 | GH8: 165.76 | GI8: 165.69 | GJ8: 169.2 | GK8: 168.1 | GL8: 174.01 | GM8: 175.97 | GN8: 174.05 | GO8: 176.4 | GP8: 182.2 | GQ8: 181.76 | GR8: 181.6 | GS8: 183.86 | GT8: 187.38 | GU8: 189.71 | GV8: 191.07 | GW8: 192.98 | GX8: 194.42 | GY8: 194.79 | GZ8: 190 | HA8: 187.58 | HB8: 191.86 | HC8: 192.31 | HD8: 196.83 | HE8: 193.18 | HF8: 190.4 | HG8: 186.41 | HH8: 189.23 | HI8: 186.56 | HJ8: 194.91 | HK8: 196.66 | HL8: 196.6 | HM8: 197.7 | HN8: 200 | HO8: 202.7 | HP8: 205.74 | HQ8: 205.76 | HR8: 205.77 | HS8: 205.27 | HT8: 203.09 | HU8: 199.89 | HV8: 200.21 | HW8: 199.77 | HX8: 201.86 | HY8: 206.14 | HZ8: 211.05 | IA8: 211.78 | IB8: 211.32 | IC8: 208.6 | ID8: 209.8 | IE8: 213.81 | IF8: 212.76 | IG8: 214.06 | IH8: 212.17 | II8: 217.77 | IJ8: 211.54 | IK8: 211.57 | IL8: 209.51 | IM8: 203.67 | IN8: 202.41 | IO8: 205.51 | IP8: 205.65 | IQ8: 204.45 | IR8: 206.37
A9: =Dashboard!B13 -> #VALUE! | B9: {=TRANSPOSE(_xlfn.STOCKHISTORY(A9,TODAY()-365,TODAY(),0,0,1))} -> 103.16 | C9: 101.5 | D9: 98.71 | E9: 97.34 | F9: 97.74 | G9: 98.05 | H9: 97.8 | I9: 96.7 | J9: 95.92 | K9: 93.93 | L9: 96.1 | M9: 99.84 | N9: 99.78 | O9: 96.26 | P9: 97.07 | Q9: 99.3 | R9: 98.25 | S9: 96.3 | T9: 96.69 | U9: 98.78 | V9: 100.99 | W9: 101.39 | X9: 99.12 | Y9: 100.22 | Z9: 101.23 | AA9: 101.61 | AB9: 101.01 | AC9: 101.69 | AD9: 100.85 | AE9: 100.79 | AF9: 101.49 | AG9: 100.76 | AH9: 102.87 | AI9: 100.67 | AJ9: 100.3 | AK9: 98.19 | AL9: 98.32 | AM9: 99.83 | AN9: 97.63 | AO9: 98.7 | AP9: 99.69 | AQ9: 101.17 | AR9: 102.5 | AS9: 103.6 | AT9: 102.68 | AU9: 103.19 | AV9: 106.72 | AW9: 107.79 | AX9: 108.88 | AY9: 108.92 | AZ9: 109.43 | BA9: 111.09 | BB9: 111.74 | BC9: 111.8 | BD9: 112.8 | BE9: 111.28 | BF9: 111.46 | BG9: 112.83 | BH9: 114.86 | BI9: 118.09 | BJ9: 119.4 | BK9: 121.56 | BL9: 120.42 | BM9: 118.13 | BN9: 117.21 | BO9: 116.69 | BP9: 118.7 | BQ9: 123.3 | BR9: 122.5 | BS9: 121.37 | BT9: 120.6 | BU9: 121.32 | BV9: 117.7 | BW9: 116.3 | BX9: 112.41 | BY9: 117.46 | BZ9: 118.04 | CA9: 112.8 | CB9: 113.86 | CC9: 115.66 | CD9: 113.59 | CE9: 114.82 | CF9: 114.79 | CG9: 114.2 | CH9: 115.2 | CI9: 115.71 | CJ9: 116.23 | CK9: 117.71 | CL9: 117.43 | CM9: 115.74 | CN9: 122.69 | CO9: 123.77 | CP9: 122.15 | CQ9: 117.39 | CR9: 111.15 | CS9: 110.86 | CT9: 113.78 | CU9: 116.27 | CV9: 115.55 | CW9: 116 | CX9: 110.75 | CY9: 109.56 | CZ9: 114.34 | DA9: 116.19 | DB9: 110.19 | DC9: 111.45 | DD9: 110.76 | DE9: 111.32 | DF9: 108.95 | DG9: 106.53 | DH9: 106.59 | DI9: 108.97 | DJ9: 109.19 | DK9: 105.5 | DL9: 105.69 | DM9: 107.35 | DN9: 107.71 | DO9: 108.67 | DP9: 109.85 | DQ9: 109.52 | DR9: 111.64 | DS9: 113.74 | DT9: 114.48 | DU9: 112.41 | DV9: 107.38 | DW9: 107.27 | DX9: 113.41 | DY9: 115.3 | DZ9: 115.25 | EA9: 117.36 | EB9: 117.13 | EC9: 123.49 | ED9: 124.92 | EE9: 124.39 | EF9: 126.28 | EG9: 129.58 | EH9: 131.69 | EI9: 129.34 | EJ9: 132.18 | EK9: 133.05 | EL9: 131.68 | EM9: 129.73 | EN9: 128.51 | EO9: 127.98 | EP9: 129.14 | EQ9: 128.53 | ER9: 127.61 | ES9: 127.98 | ET9: 127.44 | EU9: 125.63 | EV9: 128.01 | EW9: 127.6 | EX9: 129.09 | EY9: 125.55 | EZ9: 125.85 | FA9: 126.44 | FB9: 124.1 | FC9: 124.82 | FD9: 123.42 | FE9: 122.41 | FF9: 119.97 | FG9: 124.82 | FH9: 125.22 | FI9: 125.09 | FJ9: 126.86 | FK9: 125.39 | FL9: 124.68 | FM9: 125.9 | FN9: 129.09 | FO9: 131.26 | FP9: 129.93 | FQ9: 135.15 | FR9: 132.47 | FS9: 133.28 | FT9: 134.73 | FU9: 133.38 | FV9: 138.07 | FW9: 139.83 | FX9: 141.21 | FY9: 142.99 | FZ9: 143.78 | GA9: 143.06 | GB9: 145.67 | GC9: 144.97 | GD9: 143.59 | GE9: 144.98 | GF9: 141.76 | GG9: 142.49 | GH9: 139.96 | GI9: 140.13 | GJ9: 139.97 | GK9: 143.86 | GL9: 140.77 | GM9: 137.39 | GN9: 139.57 | GO9: 140.79 | GP9: 140.71 | GQ9: 133.27 | GR9: 134.89 | GS9: 131.71 | GT9: 129.36 | GU9: 128.72 | GV9: 132.84 | GW9: 132.25 | GX9: 131.88 | GY9: 132.19 | GZ9: 133.1 | HA9: 132.47 | HB9: 127.13 | HC9: 132.32 | HD9: 132.45 | HE9: 133.57 | HF9: 136.87 | HG9: 137.64 | HH9: 133.82 | HI9: 135 | HJ9: 135.22 | HK9: 135.77 | HL9: 137.58 | HM9: 138.73 | HN9: 139.33 | HO9: 138.51 | HP9: 137.65 | HQ9: 132.89 | HR9: 129.67 | HS9: 131.65 | HT9: 131.72 | HU9: 133.25 | HV9: 133.56 | HW9: 132.68 | HX9: 132.9 | HY9: 131.62 | HZ9: 132.54 | IA9: 134.34 | IB9: 138.14 | IC9: 137.72 | ID9: 136.74 | IE9: 137.8 | IF9: 138.5 | IG9: 138.82 | IH9: 136.18 | II9: 136.17 | IJ9: 132.95 | IK9: 132.7 | IL9: 131.77 | IM9: 135.05 | IN9: 132.47 | IO9: 131.93 | IP9: 132.1 | IQ9: 134.28 | IR9: 131.31
A10: =Dashboard!B14 -> #VALUE! | B10: {=TRANSPOSE(_xlfn.STOCKHISTORY(A10,TODAY()-365,TODAY(),0,0,1))} -> 12.09 | C10: 11.96 | D10: 12.27 | E10: 12.22 | F10: 12.67 | G10: 12.7 | H10: 11.92 | I10: 11.74 | J10: 11.5 | K10: 11.41 | L10: 11.54 | M10: 11.65 | N10: 11.76 | O10: 11.74 | P10: 11.92 | Q10: 11.99 | R10: 12.56 | S10: 12.43 | T10: 12.34 | U10: 13.84 | V10: 13.26 | W10: 13.13 | X10: 13.24 | Y10: 13.06 | Z10: 13.13 | AA10: 13.01 | AB10: 12.79 | AC10: 13.11 | AD10: 13.12 | AE10: 13.21 | AF10: 13.16 | AG10: 13.3 | AH10: 13.45 | AI10: 13.28 | AJ10: 13.19 | AK10: 12.88 | AL10: 13.02 | AM10: 12.9 | AN10: 12.41 | AO10: 12.83 | AP10: 12.96 | AQ10: 13.17 | AR10: 13.19 | AS10: 13.28 | AT10: 13.16 | AU10: 12.96 | AV10: 13.09 | AW10: 13.14 | AX10: 13.03 | AY10: 13.14 | AZ10: 13.08 | BA10: 13.41 | BB10: 13.63 | BC10: 13.76 | BD10: 13.65 | BE10: 13.67 | BF10: 13.31 | BG10: 13.32 | BH10: 13.47 | BI10: 13.46 | BJ10: 13.29 | BK10: 13.36 | BL10: 13.31 | BM10: 13.28 | BN10: 13.23 | BO10: 13.12 | BP10: 13.34 | BQ10: 13.47 | BR10: 13.8 | BS10: 13.74 | BT10: 14.4 | BU10: 14.2 | BV10: 14.03 | BW10: 13.98 | BX10: 13.84 | BY10: 13.81 | BZ10: 13.6 | CA10: 13.28 | CB10: 13.77 | CC10: 13.71 | CD10: 13.56 | CE10: 13.44 | CF10: 13.93 | CG10: 13.82 | CH10: 14 | CI10: 13.88 | CJ10: 13.81 | CK10: 13.73 | CL10: 13.82 | CM10: 13.72 | CN10: 13.8 | CO10: 13.59 | CP10: 13.57 | CQ10: 13.85 | CR10: 14 | CS10: 14.12 | CT10: 14.13 | CU10: 13.85 | CV10: 13.78 | CW10: 14.01 | CX10: 13.64 | CY10: 14.2 | CZ10: 14.43 | DA10: 14.41 | DB10: 14.09 | DC10: 13.39 | DD10: 12.7 | DE10: 12.81 | DF10: 12.34 | DG10: 12.15 | DH10: 12.19 | DI10: 12.24 | DJ10: 12.11 | DK10: 12.04 | DL10: 11.67 | DM10: 11.71 | DN10: 11.94 | DO10: 11.79 | DP10: 11.64 | DQ10: 11.52 | DR10: 11.76 | DS10: 11.84 | DT10: 11.67 | DU10: 11.6 | DV10: 11.37 | DW10: 11.21 | DX10: 11.54 | DY10: 11.68 | DZ10: 11.6 | EA10: 11.61 | EB10: 11.52 | EC10: 12.18 | ED10: 12.24 | EE10: 12.13 | EF10: 12.16 | EG10: 12.71 | EH10: 12.71 | EI10: 12.44 | EJ10: 12.87 | EK10: 12.87 | EL10: 12.78 | EM10: 12.63 | EN10: 12.48 | EO10: 12.38 | EP10: 12.49 | EQ10: 12.4 | ER10: 12.24 | ES10: 12.08 | ET10: 11.88 | EU10: 11.5 | EV10: 11.69 | EW10: 12.17 | EX10: 12.18 | EY10: 12.32 | EZ10: 12.05 | FA10: 11.99 | FB10: 13.57 | FC10: 14.48 | FD10: 13.4 | FE10: 13.03 | FF10: 13.06 | FG10: 13.22 | FH10: 13.67 | FI10: 14.93 | FJ10: 15.32 | FK10: 15.88 | FL10: 16.65 | FM10: 17.44 | FN10: 16.63 | FO10: 16.15 | FP10: 15.71 | FQ10: 15.34 | FR10: 14.9 | FS10: 15 | FT10: 14.95 | FU10: 14.3 | FV10: 14.71 | FW10: 14.84 | FX10: 14.77 | FY10: 14.41 | FZ10: 13.96 | GA10: 14.06 | GB10: 14.11 | GC10: 14 | GD10: 13.84 | GE10: 14.11 | GF10: 14.13 | GG10: 14.02 | GH10: 13.9 | GI10: 13.64 | GJ10: 13.36 | GK10: 13.83 | GL10: 13.56 | GM10: 13.5 | GN10: 13.61 | GO10: 14 | GP10: 13.85 | GQ10: 13.94 | GR10: 14.18 | GS10: 14.19 | GT10: 14.23 | GU10: 13.99 | GV10: 14.27 | GW10: 14.42 | GX10: 14.15 | GY10: 14.37 | GZ10: 14.68 | HA10: 14.96 | HB10: 15.28 | HC10: 14.86 | HD10: 14.68 | HE10: 14.43 | HF10: 14.24 | HG10: 14.13 | HH10: 13.79 | HI10: 13.98 | HJ10: 14 | HK10: 13.98 | HL10: 13.83 | HM10: 13.89 | HN10: 14.37 | HO10: 14.05 | HP10: 13.93 | HQ10: 14.5 | HR10: 13.99 | HS10: 14.41 | HT10: 13.93 | HU10: 13.95 | HV10: 13.9 | HW10: 13.95 | HX10: 13.88 | HY10: 13.94 | HZ10: 13.84 | IA10: 14.14 | IB10: 14.41 | IC10: 14.62 | ID10: 14 | IE10: 13.45 | IF10: 13.88 | IG10: 13.97 | IH10: 13.86 | II10: 13.5 | IJ10: 13.35 | IK10: 13.61 | IL10: 13.21 | IM10: 13.17 | IN10: 13.1 | IO10: 12.94 | IP10: 12.6 | IQ10: 12.71 | IR10: 12.38
A11: =Dashboard!B15 -> #VALUE! | B11: {=TRANSPOSE(_xlfn.STOCKHISTORY(A11,TODAY()-365,TODAY(),0,0,1))} -> 31.78 | C11: 30.8 | D11: 30.83 | E11: 30.55 | F11: 31.37 | G11: 31.91 | H11: 31.74 | I11: 31.45 | J11: 30.65 | K11: 29.84 | L11: 30.14 | M11: 30.63 | N11: 30.8 | O11: 30.6 | P11: 30.82 | Q11: 31.28 | R11: 31.28 | S11: 31.84 | T11: 31.59 | U11: 31.52 | V11: 31.75 | W11: 31.93 | X11: 31.19 | Y11: 31.07 | Z11: 30.5 | AA11: 30.57 | AB11: 30.71 | AC11: 30.88 | AD11: 30.41 | AE11: 29.81 | AF11: 29.48 | AG11: 29.7 | AH11: 30.04 | AI11: 29.73 | AJ11: 30.07 | AK11: 29 | AL11: 28.96 | AM11: 29.33 | AN11: 28.48 | AO11: 29.58 | AP11: 29.82 | AQ11: 29.96 | AR11: 30.3 | AS11: 30.25 | AT11: 29.77 | AU11: 29.45 | AV11: 29.36 | AW11: 29.66 | AX11: 29.43 | AY11: 29.35 | AZ11: 29.79 | BA11: 30.56 | BB11: 30.82 | BC11: 30.93 | BD11: 31.13 | BE11: 30.72 | BF11: 30.35 | BG11: 30.01 | BH11: 30.12 | BI11: 30.24 | BJ11: 30.12 | BK11: 30.11 | BL11: 29.8 | BM11: 29.64 | BN11: 29.62 | BO11: 29.48 | BP11: 29.96 | BQ11: 30.06 | BR11: 29.52 | BS11: 29.27 | BT11: 29.8 | BU11: 30.65 | BV11: 30.89 | BW11: 30.61 | BX11: 30.74 | BY11: 31.11 | BZ11: 30.85 | CA11: 30.3 | CB11: 31.19 | CC11: 31.22 | CD11: 30.42 | CE11: 30 | CF11: 29.93 | CG11: 29.42 | CH11: 30.29 | CI11: 30.33 | CJ11: 30.73 | CK11: 30.58 | CL11: 31.62 | CM11: 31.37 | CN11: 32.82 | CO11: 31.76 | CP11: 31.21 | CQ11: 32.4 | CR11: 31.43 | CS11: 31.78 | CT11: 31.13 | CU11: 30.92 | CV11: 30.34 | CW11: 30.27 | CX11: 30.07 | CY11: 30.04 | CZ11: 30.12 | DA11: 30.12 | DB11: 30.16 | DC11: 29.29 | DD11: 28.3 | DE11: 28.51 | DF11: 27.47 | DG11: 27.24 | DH11: 27.87 | DI11: 27.89 | DJ11: 27.54 | DK11: 26.09 | DL11: 25.78 | DM11: 25.7 | DN11: 25.48 | DO11: 24.81 | DP11: 24.61 | DQ11: 24.12 | DR11: 24.74 | DS11: 24.78 | DT11: 24.77 | DU11: 24.58 | DV11: 24.34 | DW11: 23.65 | DX11: 24.31 | DY11: 24.31 | DZ11: 24.15 | EA11: 23.84 | EB11: 23.49 | EC11: 24.5 | ED11: 24.37 | EE11: 24.04 | EF11: 24.2 | EG11: 24.16 | EH11: 24.26 | EI11: 24.36 | EJ11: 25 | EK11: 25.36 | EL11: 24.94 | EM11: 24.62 | EN11: 24.48 | EO11: 24.34 | EP11: 24.37 | EQ11: 24.2 | ER11: 24 | ES11: 24.34 | ET11: 24.09 | EU11: 23.86 | EV11: 24.16 | EW11: 24.71 | EX11: 24.06 | EY11: 24.51 | EZ11: 23.98 | FA11: 24.11 | FB11: 24.37 | FC11: 25.67 | FD11: 26.18 | FE11: 25.21 | FF11: 25.32 | FG11: 25.87 | FH11: 26.26 | FI11: 26.47 | FJ11: 26.42 | FK11: 26.88 | FL11: 27.29 | FM11: 26.99 | FN11: 26.24 | FO11: 26.48 | FP11: 27.71 | FQ11: 27.93 | FR11: 26.7 | FS11: 26.97 | FT11: 26.71 | FU11: 26.11 | FV11: 27.07 | FW11: 26.44 | FX11: 26.97 | FY11: 26.85 | FZ11: 26.19 | GA11: 26.26 | GB11: 25.99 | GC11: 25.58 | GD11: 25.76 | GE11: 26.14 | GF11: 26.83 | GG11: 27.28 | GH11: 27.11 | GI11: 27.26 | GJ11: 28.02 | GK11: 29.63 | GL11: 28.5 | GM11: 27.73 | GN11: 27.59 | GO11: 27.93 | GP11: 27.84 | GQ11: 28.09 | GR11: 27.89 | GS11: 28.77 | GT11: 28.16 | GU11: 28.17 | GV11: 28.56 | GW11: 28.53 | GX11: 27.99 | GY11: 28.16 | GZ11: 29.13 | HA11: 30.28 | HB11: 30.68 | HC11: 30.72 | HD11: 30.11 | HE11: 29.6 | HF11: 30.12 | HG11: 30.6 | HH11: 30.73 | HI11: 31.82 | HJ11: 31.72 | HK11: 31.7 | HL11: 31.31 | HM11: 31.2 | HN11: 31.58 | HO11: 31.9 | HP11: 31.95 | HQ11: 31.91 | HR11: 32.6 | HS11: 33.37 | HT11: 32.59 | HU11: 31.8 | HV11: 31.41 | HW11: 31.33 | HX11: 31.86 | HY11: 31.96 | HZ11: 32.03 | IA11: 32.44 | IB11: 33.04 | IC11: 32.67 | ID11: 31.06 | IE11: 31.3 | IF11: 31.62 | IG11: 32.52 | IH11: 32.49 | II11: 32.21 | IJ11: 32.11 | IK11: 32.53 | IL11: 32.2 | IM11: 32.53 | IN11: 32.42 | IO11: 32.15 | IP11: 32.19 | IQ11: 32.93 | IR11: 32.49
A12: =Dashboard!B16 -> #VALUE! | B12: {=TRANSPOSE(_xlfn.STOCKHISTORY(A12,TODAY()-365,TODAY(),0,0,1))} -> 315.69 | C12: 315.43 | D12: 310.71 | E12: 307.55 | F12: 310.03 | G12: 309.18 | H12: 307.69 | I12: 304.03 | J12: 305.53 | K12: 300.89 | L12: 307.97 | M12: 302.08 | N12: 305.69 | O12: 298.54 | P12: 297.56 | Q12: 302.36 | R12: 297.09 | S12: 294.11 | T12: 294.54 | U12: 300.44 | V12: 304.15 | W12: 305.36 | X12: 305.51 | Y12: 309.44 | Z12: 311.12 | AA12: 309.35 | AB12: 309.25 | AC12: 311.68 | AD12: 313.42 | AE12: 314.21 | AF12: 316.89 | AG12: 315.62 | AH12: 320.41 | AI12: 309.48 | AJ12: 303.61 | AK12: 300.37 | AL12: 299.41 | AM12: 303.27 | AN12: 298.38 | AO12: 298.02 | AP12: 298 | AQ12: 303 | AR12: 307.64 | AS12: 313.08 | AT12: 308.92 | AU12: 307.88 | AV12: 312.13 | AW12: 316.1 | AX12: 315.04 | AY12: 315.21 | AZ12: 300.51 | BA12: 310.11 | BB12: 317.38 | BC12: 318.52 | BD12: 320.02 | BE12: 315.55 | BF12: 314.98 | BG12: 313 | BH12: 317.21 | BI12: 323.09 | BJ12: 325.93 | BK12: 329.17 | BL12: 327.91 | BM12: 323.75 | BN12: 323.42 | BO12: 322.22 | BP12: 325.48 | BQ12: 334.04 | BR12: 334.61 | BS12: 326.99 | BT12: 329.79 | BU12: 329.19 | BV12: 324.49 | BW12: 310.9 | BX12: 307.87 | BY12: 309.26 | BZ12: 312.47 | CA12: 302.74 | CB12: 302.04 | CC12: 303.63 | CD12: 297.72 | CE12: 301.04 | CF12: 300.31 | CG12: 300.77 | CH12: 306.42 | CI12: 305.89 | CJ12: 308.14 | CK12: 314.85 | CL12: 317.27 | CM12: 310.16 | CN12: 322.4 | CO12: 322.1 | CP12: 318.28 | CQ12: 310.82 | CR12: 302.64 | CS12: 302.55 | CT12: 307.13 | CU12: 308.78 | CV12: 308.05 | CW12: 310.79 | CX12: 297.67 | CY12: 297.3 | CZ12: 303.3 | DA12: 306.13 | DB12: 300.3 | DC12: 297.56 | DD12: 300.26 | DE12: 299.39 | DF12: 293.55 | DG12: 289.48 | DH12: 289.92 | DI12: 288.73 | DJ12: 287.52 | DK12: 282.89 | DL12: 283.44 | DM12: 286.16 | DN12: 286.89 | DO12: 287.74 | DP12: 287.97 | DQ12: 286.56 | DR12: 289.91 | DS12: 292.4 | DT12: 295.42 | DU12: 291.66 | DV12: 282.84 | DW12: 283.77 | DX12: 294.16 | DY12: 295.38 | DZ12: 294.6 | EA12: 295.45 | EB12: 297.4 | EC12: 307.97 | ED12: 310.33 | EE12: 309.87 | EF12: 313.68 | EG12: 311.12 | EH12: 305.93 | EI12: 309.95 | EJ12: 310.29 | EK12: 316.99 | EL12: 313 | EM12: 313.02 | EN12: 311.69 | EO12: 308.28 | EP12: 311.63 | EQ12: 311.45 | ER12: 309.25 | ES12: 313.23 | ET12: 312.47 | EU12: 307.65 | EV12: 309.4 | EW12: 314.9 | EX12: 306.27 | EY12: 302.1 | EZ12: 300 | FA12: 304.88 | FB12: 300.25 | FC12: 299.91 | FD12: 297.81 | FE12: 300.73 | FF12: 295.7 | FG12: 301.98 | FH12: 303 | FI12: 306.38 | FJ12: 306.74 | FK12: 299.28 | FL12: 296.73 | FM12: 299.31 | FN12: 296.58 | FO12: 300.96 | FP12: 300.85 | FQ12: 310.89 | FR12: 312.37 | FS12: 311.11 | FT12: 312.7 | FU12: 309.14 | FV12: 313.49 | FW12: 320.72 | FX12: 319.4 | FY12: 331.14 | FZ12: 333.46 | GA12: 325.22 | GB12: 331.48 | GC12: 334.14 | GD12: 333.45 | GE12: 335.12 | GF12: 329.05 | GG12: 329.39 | GH12: 327.33 | GI12: 334.07 | GJ12: 334.47 | GK12: 337.72 | GL12: 339.22 | GM12: 330.62 | GN12: 335.47 | GO12: 336.47 | GP12: 334.53 | GQ12: 342.89 | GR12: 346.91 | GS12: 343.15 | GT12: 341.1 | GU12: 338.87 | GV12: 345.23 | GW12: 348.21 | GX12: 349.9 | GY12: 353.21 | GZ12: 356.2 | HA12: 357.31 | HB12: 344.71 | HC12: 350.85 | HD12: 351.79 | HE12: 352.64 | HF12: 357.52 | HG12: 359.24 | HH12: 356.3 | HI12: 357.52 | HJ12: 359.79 | HK12: 362.04 | HL12: 365.18 | HM12: 363.11 | HN12: 362.84 | HO12: 360.96 | HP12: 363.25 | HQ12: 357.26 | HR12: 351.55 | HS12: 351.58 | HT12: 356.39 | HU12: 356.69 | HV12: 356.5 | HW12: 354.22 | HX12: 357.62 | HY12: 356.02 | HZ12: 354.95 | IA12: 356.22 | IB12: 362.06 | IC12: 358.64 | ID12: 353.51 | IE12: 354.71 | IF12: 353.56 | IG12: 356.23 | IH12: 350.13 | II12: 352.49 | IJ12: 348.92 | IK12: 349.31 | IL12: 349.67 | IM12: 352.04 | IN12: 340 | IO12: 337.53 | IP12: 338.56 | IQ12: 343.06 | IR12: 336.59
A13: =Dashboard!B17 -> #VALUE! | B13: {=TRANSPOSE(_xlfn.STOCKHISTORY(A13,TODAY()-365,TODAY(),0,0,1))} -> 743.4 | C13: 734.38 | D13: 717.34 | E13: 727.05 | F13: 710.56 | G13: 715.66 | H13: 713.08 | I13: 717.84 | J13: 733.51 | K13: 705.3 | L13: 715.7 | M13: 708.65 | N13: 717.55 | O13: 712.07 | P13: 716.915 | Q13: 732.17 | R13: 733.27 | S13: 733.41 | T13: 734 | U13: 738.36 | V13: 750.82 | W13: 751.44 | X13: 751.67 | Y13: 666.47 | Z13: 648.35 | AA13: 637.71 | AB13: 627.32 | AC13: 635.95 | AD13: 618.94 | AE13: 621.71 | AF13: 631.76 | AG13: 627.08 | AH13: 609.01 | AI13: 609.89 | AJ13: 609.46 | AK13: 602.01 | AL13: 597.69 | AM13: 590.32 | AN13: 589.15 | AO13: 594.25 | AP13: 613.05 | AQ13: 636.22 | AR13: 633.61 | AS13: 647.95 | AT13: 640.87 | AU13: 647.1 | AV13: 639.6 | AW13: 661.53 | AX13: 673.42 | AY13: 666.8 | AZ13: 656.96 | BA13: 650.13 | BB13: 652.71 | BC13: 644.23 | BD13: 647.51 | BE13: 657.15 | BF13: 649.5 | BG13: 664.45 | BH13: 658.77 | BI13: 661.5 | BJ13: 664.94 | BK13: 667.55 | BL13: 663.29 | BM13: 658.69 | BN13: 665.95 | BO13: 660.09 | BP13: 650.41 | BQ13: 658.79 | BR13: 660.62 | BS13: 648.69 | BT13: 646.06 | BU13: 653.06 | BV13: 641.97 | BW13: 631.09 | BX13: 615.52 | BY13: 620.8 | BZ13: 620.25 | CA13: 604.12 | CB13: 612.96 | CC13: 647.63 | CD13: 658.76 | CE13: 672.36 | CF13: 672.97 | CG13: 668.73 | CH13: 738.31 | CI13: 716.5 | CJ13: 706.41 | CK13: 691.7 | CL13: 668.99 | CM13: 670.21 | CN13: 661.46 | CO13: 677.22 | CP13: 670.72 | CQ13: 668.69 | CR13: 649.81 | CS13: 639.77 | CT13: 639.29 | CU13: 643.22 | CV13: 644.78 | CW13: 655.66 | CX13: 637.25 | CY13: 639.3 | CZ13: 653.69 | DA13: 657.01 | DB13: 648.18 | DC13: 653.56 | DD13: 655.08 | DE13: 667.73 | DF13: 660.57 | DG13: 644.86 | DH13: 647.39 | DI13: 654.07 | DJ13: 654.86 | DK13: 638.18 | DL13: 613.71 | DM13: 627.45 | DN13: 622.66 | DO13: 615.68 | DP13: 606.7 | DQ13: 593.66 | DR13: 604.06 | DS13: 592.92 | DT13: 594.89 | DU13: 547.54 | DV13: 525.72 | DW13: 536.38 | DX13: 572.13 | DY13: 579.23 | DZ13: 574.46 | EA13: 573.02 | EB13: 575.05 | EC13: 612.42 | ED13: 628.39 | EE13: 629.86 | EF13: 634.53 | EG13: 662.49 | EH13: 671.58 | EI13: 676.87 | EJ13: 688.55 | EK13: 670.91 | EL13: 668.84 | EM13: 674.72 | EN13: 659.15 | EO13: 675.03 | EP13: 678.62 | EQ13: 671.34 | ER13: 669.12 | ES13: 611.91 | ET13: 608.745 | EU13: 610.41 | EV13: 604.96 | EW13: 612.88 | EX13: 616.81 | EY13: 609.63 | EZ13: 598.86 | FA13: 603 | FB13: 616.63 | FC13: 618.43 | FD13: 614.23 | FE13: 611.21 | FF13: 602.61 | FG13: 605.06 | FH13: 607.38 | FI13: 610.26 | FJ13: 612.34 | FK13: 635.255 | FL13: 635.29 | FM13: 632.51 | FN13: 600.47 | FO13: 597.63 | FP13: 622.98 | FQ13: 627.57 | FR13: 593 | FS13: 585.39 | FT13: 584.59 | FU13: 570.98 | FV13: 568.43 | FW13: 566.98 | FX13: 593.48 | FY13: 600.21 | FZ13: 567.58 | GA13: 577.22 | GB13: 563.85 | GC13: 562.2 | GD13: 557.67 | GE13: 542.87 | GF13: 550.25 | GG13: 562.6 | GH13: 563.29 | GI13: 612.91 | GJ13: 582.9 | GK13: 600.29 | GL13: 615.58 | GM13: 603.12 | GN13: 631.48 | GO13: 669.21 | GP13: 656.73 | GQ13: 661.04 | GR13: 681.31 | GS13: 664.54 | GT13: 646.01 | GU13: 645.85 | GV13: 643.81 | GW13: 627.17 | GX13: 606.1 | GY13: 595.19 | GZ13: 593.87 | HA13: 593.41 | HB13: 585.61 | HC13: 539.03 | HD13: 556.71 | HE13: 590.24 | HF13: 587.94 | HG13: 588.77 | HH13: 589.9 | HI13: 592.1 | HJ13: 594.92 | HK13: 599.12 | HL13: 578.85 | HM13: 594.97 | HN13: 589.85 | HO13: 568.97 | HP13: 543.67 | HQ13: 546.03 | HR13: 545.83 | HS13: 549.9 | HT13: 559.02 | HU13: 570.05 | HV13: 576.14 | HW13: 571.1 | HX13: 578.02 | HY13: 572.34 | HZ13: 578.54 | IA13: 592.85 | IB13: 610.68 | IC13: 616.77 | ID13: 613.48 | IE13: 653.69 | IF13: 644.38 | IG13: 648.03 | IH13: 665.6 | II13: 670.24 | IJ13: 673.31 | IK13: 682.31 | IL13: 665.75 | IM13: 741.245 | IN13: 736.595 | IO13: 744.1 | IP13: 777.59 | IQ13: 751.66 | IR13: 715.62
A14: =Dashboard!B18 -> #VALUE! | B14: {=TRANSPOSE(_xlfn.STOCKHISTORY(A14,TODAY()-365,TODAY(),0,0,1))} -> 181.85 | C14: 186.58 | D14: 187.24 | E14: 188.89 | F14: 187.62 | G14: 185.54 | H14: 185.04 | I14: 189.11 | J14: 192.57 | K14: 183.16 | L14: 188.32 | M14: 180.03 | N14: 179.83 | O14: 181.81 | P14: 183.22 | Q14: 182.64 | R14: 181.16 | S14: 180.28 | T14: 182.16 | U14: 186.26 | V14: 191.49 | W14: 201.03 | X14: 207.04 | Y14: 202.89 | Z14: 202.49 | AA14: 206.88 | AB14: 198.69 | AC14: 195.21 | AD14: 188.08 | AE14: 188.15 | AF14: 199.05 | AG14: 193.16 | AH14: 193.8 | AI14: 186.86 | AJ14: 190.17 | AK14: 186.6 | AL14: 181.36 | AM14: 186.52 | AN14: 180.64 | AO14: 178.88 | AP14: 182.55 | AQ14: 177.82 | AR14: 180.26 | AS14: 177 | AT14: 179.92 | AU14: 181.46 | AV14: 179.59 | AW14: 183.38 | AX14: 182.41 | AY14: 185.55 | AZ14: 184.97 | BA14: 183.78 | BB14: 180.93 | BC14: 175.02 | BD14: 176.29 | BE14: 177.72 | BF14: 170.94 | BG14: 174.14 | BH14: 180.99 | BI14: 183.69 | BJ14: 189.21 | BK14: 188.61 | BL14: 190.53 | BM14: 188.22 | BN14: 187.54 | BO14: 186.5 | BP14: 188.85 | BQ14: 188.12 | BR14: 187.24 | BS14: 189.11 | BT14: 185.04 | BU14: 184.86 | BV14: 184.94 | BW14: 185.81 | BX14: 183.14 | BY14: 187.05 | BZ14: 186.23 | CA14: 178.07 | CB14: 183.32 | CC14: 184.84 | CD14: 187.67 | CE14: 186.47 | CF14: 188.52 | CG14: 191.52 | CH14: 192.51 | CI14: 191.13 | CJ14: 185.61 | CK14: 180.34 | CL14: 174.19 | CM14: 171.88 | CN14: 185.41 | CO14: 190.04 | CP14: 188.54 | CQ14: 190.05 | CR14: 186.94 | CS14: 182.81 | CT14: 184.97 | CU14: 187.98 | CV14: 187.9 | CW14: 189.82 | CX14: 191.55 | CY14: 192.85 | CZ14: 195.56 | DA14: 184.89 | DB14: 177.19 | DC14: 182.48 | DD14: 180.05 | DE14: 183.04 | DF14: 183.34 | DG14: 177.82 | DH14: 182.65 | DI14: 184.77 | DJ14: 186.03 | DK14: 183.14 | DL14: 180.25 | DM14: 183.22 | DN14: 181.93 | DO14: 180.4 | DP14: 178.56 | DQ14: 172.7 | DR14: 175.64 | DS14: 175.2 | DT14: 178.68 | DU14: 171.24 | DV14: 167.52 | DW14: 165.17 | DX14: 174.4 | DY14: 175.75 | DZ14: 177.39 | EA14: 177.64 | EB14: 178.1 | EC14: 182.08 | ED14: 183.91 | EE14: 188.63 | EF14: 189.31 | EG14: 196.51 | EH14: 198.87 | EI14: 198.35 | EJ14: 201.68 | EK14: 202.06 | EL14: 199.88 | EM14: 202.5 | EN14: 199.64 | EO14: 208.27 | EP14: 216.61 | EQ14: 213.17 | ER14: 209.25 | ES14: 199.57 | ET14: 198.45 | EU14: 198.48 | EV14: 196.5 | EW14: 207.83 | EX14: 211.5 | EY14: 215.2 | EZ14: 219.44 | FA14: 220.78 | FB14: 225.83 | FC14: 235.74 | FD14: 225.32 | FE14: 222.32 | FF14: 220.61 | FG14: 223.47 | FH14: 219.51 | FI14: 215.33 | FJ14: 214.86 | FK14: 212.6 | FL14: 214.25 | FM14: 211.14 | FN14: 224.36 | FO14: 222.82 | FP14: 214.75 | FQ14: 218.66 | FR14: 205.1 | FS14: 208.64 | FT14: 208.19 | FU14: 200.42 | FV14: 204.87 | FW14: 205.19 | FX14: 212.45 | FY14: 207.41 | FZ14: 204.65 | GA14: 210.69 | GB14: 208.65 | GC14: 200.04 | GD14: 199 | GE14: 195.74 | GF14: 192.53 | GG14: 194.97 | GH14: 200.09 | GI14: 197.58 | GJ14: 194.83 | GK14: 195.55 | GL14: 196.93 | GM14: 204.12 | GN14: 202.78 | GO14: 210.96 | GP14: 203.53 | GQ14: 211.8 | GR14: 212.5 | GS14: 207.4 | GT14: 202.81 | GU14: 203.28 | GV14: 207.29 | GW14: 212.06 | GX14: 208.76 | GY14: 206.84 | GZ14: 196.51 | HA14: 197.01 | HB14: 190.01 | HC14: 195.04 | HD14: 200.75 | HE14: 206.64 | HF14: 211.94 | HG14: 219.22 | HH14: 218.99 | HI14: 223.96 | HJ14: 217.55 | HK14: 217.5 | HL14: 224.09 | HM14: 225.3 | HN14: 225.16 | HO14: 225.01 | HP14: 219.74 | HQ14: 217.56 | HR14: 216.85 | HS14: 214.72 | HT14: 208.48 | HU14: 213.05 | HV14: 209.66 | HW14: 227.98 | HX14: 217.55 | HY14: 220.78 | HZ14: 217.44 | IA14: 224.41 | IB14: 228.45 | IC14: 230.36 | ID14: 225.73 | IE14: 223.67 | IF14: 218.36 | IG14: 218.29 | IH14: 210.96 | II14: 212.17 | IJ14: 213.9 | IK14: 219.34 | IL14: 222.27 | IM14: 227.38 | IN14: 228.87 | IO14: 225.51 | IP14: 224.58 | IQ14: 225.07 | IR14: 228.86
A15: =Dashboard!B19 -> #VALUE! | B15: {=TRANSPOSE(_xlfn.STOCKHISTORY(A15,TODAY()-365,TODAY(),0,0,1))} -> #VALUE! | AT15: 132.2
A16: =Dashboard!B20 -> #VALUE! | B16: {=TRANSPOSE(_xlfn.STOCKHISTORY(A16,TODAY()-365,TODAY(),0,0,1))} -> 217.08 | C16: 215.83 | D16: 215.2 | E16: 217.43 | F16: 216.3 | G16: 219.73 | H16: 221.82 | I16: 225.32 | J16: 216 | K16: 210.73 | L16: 215.56 | M16: 214.3 | N16: 214 | O16: 211.89 | P16: 212.94 | Q16: 216.82 | R16: 217.26 | S16: 216.59 | T16: 217.77 | U16: 221.35 | V16: 223 | W16: 223.33 | X16: 213.58 | Y16: 200.08 | Z16: 201.02 | AA16: 204.55 | AB16: 198.05 | AC16: 197.62 | AD16: 196.5 | AE16: 194.61 | AF16: 194.81 | AG16: 195.21 | AH16: 195.5 | AI16: 194.58 | AJ16: 194.52 | AK16: 191.81 | AL16: 189.63 | AM16: 185.7 | AN16: 179.38 | AO16: 179.7 | AP16: 179.12 | AQ16: 182.44 | AR16: 186.92 | AS16: 189 | AT16: 186.46 | AU16: 205.38 | AV16: 202.54 | AW16: 201.87 | AX16: 201.89 | AY16: 206.27 | AZ16: 200.37 | BA16: 198.72 | BB16: 200.71 | BC16: 204.38 | BD16: 205.5 | BE16: 206.71 | BF16: 206.33 | BG16: 208.27 | BH16: 214.08 | BI16: 216.84 | BJ16: 216.85 | BK16: 218.16 | BL16: 216.44 | BM16: 217.25 | BN16: 218.5 | BO16: 217.12 | BP16: 227.77 | BQ16: 228.13 | BR16: 229.84 | BS16: 228.12 | BT16: 227.38 | BU16: 234.53 | BV16: 239.81 | BW16: 244.55 | BX16: 242.61 | BY16: 247.74 | BZ16: 247.68 | CA16: 249 | CB16: 250.07 | CC16: 251.41 | CD16: 252.15 | CE16: 248.43 | CF16: 244.56 | CG16: 241.59 | CH16: 234.04 | CI16: 233.72 | CJ16: 233.02 | CK16: 233.15 | CL16: 235.95 | CM16: 236.95 | CN16: 243.03 | CO16: 244.71 | CP16: 242.59 | CQ16: 236.26 | CR16: 239.35 | CS16: 242.96 | CT16: 244.04 | CU16: 238.93 | CV16: 233.71 | CW16: 232.03 | CX16: 230.44 | CY16: 233.39 | CZ16: 230.36 | DA16: 229.41 | DB16: 227.53 | DC16: 229.74 | DD16: 224.12 | DE16: 227.31 | DF16: 222.06 | DG16: 231.11 | DH16: 225 | DI16: 217.76 | DJ16: 214.1 | DK16: 204.76 | DL16: 209.89 | DM16: 213.47 | DN16: 210.82 | DO16: 205.99 | DP16: 201.18 | DQ16: 195.12 | DR16: 198.41 | DS16: 196.42 | DT16: 199.61 | DU16: 194.36 | DV16: 190.52 | DW16: 189.21 | DX16: 199.03 | DY16: 207.32 | DZ16: 208.22 | EA16: 212.3 | EB16: 210 | EC16: 217.8 | ED16: 220.06 | EE16: 217.63 | EF16: 222.14 | EG16: 223.77 | EH16: 223.93 | EI16: 218.88 | EJ16: 223.38 | EK16: 225.08 | EL16: 219.16 | EM16: 231.28 | EN16: 234.15 | EO16: 232.44 | EP16: 231.33 | EQ16: 230.72 | ER16: 224.11 | ES16: 229.03 | ET16: 227.38 | EU16: 221.3 | EV16: 224.38 | EW16: 229.93 | EX16: 231.03 | EY16: 237.36 | EZ16: 238.21 | FA16: 236.87 | FB16: 240.6 | FC16: 229.21 | FD16: 220.49 | FE16: 220.61 | FF16: 215.01 | FG16: 222.2 | FH16: 219.61 | FI16: 219.02 | FJ16: 218.9 | FK16: 224.3 | FL16: 228.78 | FM16: 231.15 | FN16: 224.3 | FO16: 217.7 | FP16: 210.58 | FQ16: 217.42 | FR16: 215.45 | FS16: 215.92 | FT16: 214.51 | FU16: 209 | FV16: 221.63 | FW16: 219.05 | FX16: 228.95 | FY16: 227.49 | FZ16: 225.63 | GA16: 222.72 | GB16: 220.83 | GC16: 216.71 | GD16: 220.25 | GE16: 218.12 | GF16: 217.25 | GG16: 214.69 | GH16: 216.47 | GI16: 218.58 | GJ16: 226.49 | GK16: 234.54 | GL16: 231.68 | GM16: 224.95 | GN16: 223.11 | GO16: 222.28 | GP16: 215.51 | GQ16: 217.11 | GR16: 218.12 | GS16: 214.34 | GT16: 214.03 | GU16: 209.48 | GV16: 204.8 | GW16: 208.65 | GX16: 209.23 | GY16: 209.52 | GZ16: 211.5 | HA16: 221.56 | HB16: 214.01 | HC16: 220.9 | HD16: 216.14 | HE16: 233.49 | HF16: 237.16 | HG16: 240.19 | HH16: 232.19 | HI16: 234.42 | HJ16: 232.79 | HK16: 233.24 | HL16: 231.2 | HM16: 230.33 | HN16: 231.67 | HO16: 225.95 | HP16: 223.06 | HQ16: 222.2 | HR16: 215.1 | HS16: 214.2 | HT16: 210.46 | HU16: 211.08 | HV16: 212.09 | HW16: 209.89 | HX16: 209.82 | HY16: 207.78 | HZ16: 205.66 | IA16: 208.87 | IB16: 210.51 | IC16: 212.25 | ID16: 210.73 | IE16: 206.42 | IF16: 204.8 | IG16: 210.45 | IH16: 210.27 | II16: 209.69 | IJ16: 201.96 | IK16: 197 | IL16: 198.2 | IM16: 201.15 | IN16: 197.72 | IO16: 199.93 | IP16: 196.8 | IQ16: 198.07 | IR16: 184.39
A17: =Dashboard!B21 -> #VALUE! | B17: {=TRANSPOSE(_xlfn.STOCKHISTORY(A17,TODAY()-365,TODAY(),0,0,1))} -> 196.44 | C17: 191.09 | D17: 191.83 | E17: 190.52 | F17: 194.59 | G17: 199.18 | H17: 199.89 | I17: 198.21 | J17: 192.33 | K17: 185.22 | L17: 187.88 | M17: 191.74 | N17: 194.33 | O17: 195.41 | P17: 197.83 | Q17: 200.11 | R17: 201.95 | S17: 203.51 | T17: 204.06 | U17: 205.37 | V17: 209.22 | W17: 211.24 | X17: 207.09 | Y17: 207.21 | Z17: 204.19 | AA17: 205.72 | AB17: 203.89 | AC17: 199.15 | AD17: 202.94 | AE17: 201.98 | AF17: 203.94 | AG17: 205.99 | AH17: 207.29 | AI17: 203.26 | AJ17: 204.08 | AK17: 199 | AL17: 195.96 | AM17: 196.78 | AN17: 191.25 | AO17: 197.62 | AP17: 199.06 | AQ17: 200.26 | AR17: 202.44 | AS17: 201.87 | AT17: 199.22 | AU17: 196.99 | AV17: 195.44 | AW17: 198.27 | AX17: 196.56 | AY17: 195.21 | AZ17: 196.34 | BA17: 200.78 | BB17: 203.56 | BC17: 208.12 | BD17: 214.81 | BE17: 214.42 | BF17: 214.24 | BG17: 216.08 | BH17: 219.38 | BI17: 219.51 | BJ17: 219.24 | BK17: 216.73 | BL17: 216.62 | BM17: 216.44 | BN17: 214.85 | BO17: 214.06 | BP17: 217.87 | BQ17: 218.86 | BR17: 215.27 | BS17: 213.33 | BT17: 214.73 | BU17: 221.52 | BV17: 222.59 | BW17: 229.03 | BX17: 227.3 | BY17: 232.33 | BZ17: 231.42 | CA17: 220.47 | CB17: 227.74 | CC17: 227.04 | CD17: 226.28 | CE17: 225.62 | CF17: 224.12 | CG17: 218.89 | CH17: 227.07 | CI17: 226.86 | CJ17: 231.58 | CK17: 231.42 | CL17: 241.39 | CM17: 237.19 | CN17: 244.22 | CO17: 242.39 | CP17: 238.24 | CQ17: 242.81 | CR17: 241.64 | CS17: 248.29 | CT17: 245.51 | CU17: 243.2 | CV17: 241.65 | CW17: 239.6 | CX17: 238.03 | CY17: 238.64 | CZ17: 241.73 | DA17: 242.62 | DB17: 242.38 | DC17: 243.66 | DD17: 232.17 | DE17: 232.81 | DF17: 221.48 | DG17: 219.14 | DH17: 219.53 | DI17: 221.01 | DJ17: 220.77 | DK17: 216.59 | DL17: 210.84 | DM17: 213.23 | DN17: 213.07 | DO17: 209.11 | DP17: 208.93 | DQ17: 205.02 | DR17: 210.64 | DS17: 209.78 | DT17: 210.93 | DU17: 209.93 | DV17: 206.73 | DW17: 202.94 | DX17: 206.09 | DY17: 209.67 | DZ17: 207.01 | EA17: 204.42 | EB17: 203.66 | EC17: 215 | ED17: 211.14 | EE17: 210.64 | EF17: 211.06 | EG17: 211.55 | EH17: 213.18 | EI17: 212.86 | EJ17: 217.2 | EK17: 215.25 | EL17: 203.97 | EM17: 200.43 | EN17: 196.08 | EO17: 192.32 | EP17: 192.17 | EQ17: 192.98 | ER17: 191.26 | ES17: 192.62 | ET17: 188.71 | EU17: 188.3 | EV17: 189.99 | EW17: 195.05 | EX17: 189 | EY17: 187.53 | EZ17: 183.8 | FA17: 181.67 | FB17: 186.89 | FC17: 190.5 | FD17: 190.68 | FE17: 187.37 | FF17: 185.47 | FG17: 189.94 | FH17: 189.66 | FI17: 189.08 | FJ17: 190.09 | FK17: 190.11 | FL17: 191.84 | FM17: 189.95 | FN17: 182.92 | FO17: 180.49 | FP17: 180.22 | FQ17: 179.5 | FR17: 177.16 | FS17: 178.45 | FT17: 175.78 | FU17: 172.03 | FV17: 174.95 | FW17: 174.95 | FX17: 180.22 | FY17: 178.19 | FZ17: 172.77 | GA17: 173.94 | GB17: 169.73 | GC17: 167.23 | GD17: 167.76 | GE17: 166.5 | GF17: 171.48 | GG17: 171.36 | GH17: 168.42 | GI17: 169.66 | GJ17: 174.59 | GK17: 179.8 | GL17: 179.43 | GM17: 177.15 | GN17: 174.32 | GO17: 176.45 | GP17: 174.75 | GQ17: 176.22 | GR17: 176.92 | GS17: 179.76 | GT17: 177.61 | GU17: 178.53 | GV17: 180.34 | GW17: 179.94 | GX17: 176.8 | GY17: 177.42 | GZ17: 182.15 | HA17: 186.3 | HB17: 192.84 | HC17: 191.45 | HD17: 188.99 | HE17: 186.17 | HF17: 189.17 | HG17: 185.89 | HH17: 187.49 | HI17: 190.09 | HJ17: 188.78 | HK17: 189.82 | HL17: 188.22 | HM17: 188.71 | HN17: 191.11 | HO17: 189.18 | HP17: 188.25 | HQ17: 188.78 | HR17: 192.24 | HS17: 197.35 | HT17: 193.81 | HU17: 192.95 | HV17: 191.84 | HW17: 192 | HX17: 194.48 | HY17: 196.54 | HZ17: 198.05 | IA17: 198.3 | IB17: 199.87 | IC17: 197.11 | ID17: 191.45 | IE17: 190.97 | IF17: 192.48 | IG17: 198.2 | IH17: 197.56 | II17: 195.47 | IJ17: 192.21 | IK17: 193.91 | IL17: 191.53 | IM17: 192.5 | IN17: 192.06 | IO17: 190.36 | IP17: 186.72 | IQ17: 190.34 | IR17: 188.3
A18: =Dashboard!B22 -> #VALUE! | B18: {=TRANSPOSE(_xlfn.STOCKHISTORY(A18,TODAY()-365,TODAY(),0,0,1))} -> 103.08 | C18: 103.06 | D18: 101.96 | E18: 101.7 | F18: 102.07 | G18: 102.7 | H18: 103.24 | I18: 102.9 | J18: 101.77 | K18: 101.84 | L18: 102.12 | M18: 107.21 | N18: 109.03 | O18: 106.47 | P18: 107.73 | Q18: 107.05 | R18: 106.22 | S18: 107.14 | T18: 106.86 | U18: 106.17 | V18: 104.47 | W18: 103.17 | X18: 102.46 | Y18: 102.23 | Z18: 101.18 | AA18: 101.59 | AB18: 102.27 | AC18: 101.47 | AD18: 101.68 | AE18: 102.59 | AF18: 102.42 | AG18: 103.44 | AH18: 103.44 | AI18: 102.54 | AJ18: 102.48 | AK18: 102.95 | AL18: 101.39 | AM18: 100.61 | AN18: 107.11 | AO18: 105.32 | AP18: 104.06 | AQ18: 107 | AR18: 109.1 | AS18: 110.51 | AT18: 111.53 | AU18: 112.41 | AV18: 114.41 | AW18: 114.84 | AX18: 115.11 | AY18: 113.56 | AZ18: 115.06 | BA18: 113.18 | BB18: 115.52 | BC18: 116.7 | BD18: 116.79 | BE18: 115.42 | BF18: 115.66 | BG18: 114.83 | BH18: 114.36 | BI18: 112.6 | BJ18: 110.9 | BK18: 111.61 | BL18: 111.74 | BM18: 112.53 | BN18: 111.92 | BO18: 111.41 | BP18: 112.76 | BQ18: 112.71 | BR18: 114.34 | BS18: 112.72 | BT18: 113.07 | BU18: 114.53 | BV18: 117.97 | BW18: 120.36 | BX18: 120.04 | BY18: 119.2 | BZ18: 119.7 | CA18: 118.71 | CB18: 119.36 | CC18: 117.83 | CD18: 117.73 | CE18: 117.64 | CF18: 116.94 | CG18: 116.57 | CH18: 117.41 | CI18: 119.14 | CJ18: 124.06 | CK18: 127.71 | CL18: 128 | CM18: 126.94 | CN18: 131.18 | CO18: 129.02 | CP18: 126.7 | CQ18: 128.77 | CR18: 133.64 | CS18: 133.89 | CT18: 128.85 | CU18: 126.62 | CV18: 124.87 | CW18: 122.99 | CX18: 125.81 | CY18: 126.75 | CZ18: 125.75 | DA18: 124.42 | DB18: 127.95 | DC18: 127.1 | DD18: 127.91 | DE18: 127.81 | DF18: 123.31 | DG18: 123.8 | DH18: 124.34 | DI18: 125.12 | DJ18: 123.49 | DK18: 125.33 | DL18: 126.52 | DM18: 125.99 | DN18: 125.08 | DO18: 121.98 | DP18: 121.09 | DQ18: 119.02 | DR18: 120.72 | DS18: 122.05 | DT18: 123.06 | DU18: 122.18 | DV18: 122.89 | DW18: 123.5 | DX18: 124.28 | DY18: 124.74 | DZ18: 125.79 | EA18: 126.79 | EB18: 122.49 | EC18: 127.26 | ED18: 129.13 | EE18: 126.77 | EF18: 124.57 | EG18: 125.05 | EH18: 124.76 | EI18: 124.82 | EJ18: 127.5 | EK18: 127.92 | EL18: 129.6 | EM18: 129.98 | EN18: 132.03 | EO18: 129.92 | EP18: 127.59 | EQ18: 127.59 | ER18: 128.01 | ES18: 131.93 | ET18: 131.6 | EU18: 130.33 | EV18: 130.79 | EW18: 130.08 | EX18: 130.2 | EY18: 130.43 | EZ18: 127.59 | FA18: 130.35 | FB18: 131.47 | FC18: 132.46 | FD18: 131.45 | FE18: 133.34 | FF18: 134.2 | FG18: 130.85 | FH18: 121.34 | FI18: 120.27 | FJ18: 118.57 | FK18: 118.54 | FL18: 118.9 | FM18: 115.75 | FN18: 114.6 | FO18: 113.06 | FP18: 116.89 | FQ18: 117.74 | FR18: 118.88 | FS18: 119.83 | FT18: 118.88 | FU18: 120.59 | FV18: 120.5 | FW18: 121.04 | FX18: 120.82 | FY18: 121.03 | FZ18: 118.13 | GA18: 117.18 | GB18: 117.18 | GC18: 119.42 | GD18: 119 | GE18: 115.78 | GF18: 115.69 | GG18: 114.6 | GH18: 113.26 | GI18: 108.82 | GJ18: 111.84 | GK18: 110.65 | GL18: 111.54 | GM18: 113.1 | GN18: 112.21 | GO18: 113.9 | GP18: 114.78 | GQ18: 113.7 | GR18: 112.53 | GS18: 114.95 | GT18: 114.24 | GU18: 112.2 | GV18: 110.39 | GW18: 109.33 | GX18: 108.4 | GY18: 109.47 | GZ18: 111.74 | HA18: 113.1 | HB18: 114.22 | HC18: 111.1 | HD18: 111.2 | HE18: 110.71 | HF18: 111.55 | HG18: 112.34 | HH18: 112.07 | HI18: 111.85 | HJ18: 112.66 | HK18: 113.26 | HL18: 116.01 | HM18: 115.72 | HN18: 115.27 | HO18: 114.33 | HP18: 115.2 | HQ18: 114.3 | HR18: 103.84 | HS18: 103.7 | HT18: 106.49 | HU18: 105.38 | HV18: 104.34 | HW18: 102.63 | HX18: 103.09 | HY18: 104.87 | HZ18: 105.92 | IA18: 106.09 | IB18: 108.42 | IC18: 107.14 | ID18: 106.05 | IE18: 105.83 | IF18: 105.73 | IG18: 107.15 | IH18: 109.08 | II18: 108.09 | IJ18: 107.5 | IK18: 106.79 | IL18: 106.73 | IM18: 107.44 | IN18: 110.12 | IO18: 110.53 | IP18: 107.59 | IQ18: 107.98 | IR18: 108.73

Sheet Ledger
A1: TRANSACTION LEDGER
B2: Date | C2: Stock | D2: Transaction Type | E2: Price | F2: Units | G2: Transaction Amount | H2: Ticker
B3: 43466 | C3: #VALUE! | D3: Buy | E3: 19.15 | F3: 29.24 | G3: =E3*F3 -> 559.946 | H3: {=_FV(Ledger[[#This Row],[Stock]],"Ticker symbol",TRUE)} -> AMD
B4: 43831 | C4: #VALUE! | D4: Buy | E4: 30.98 | F4: 18.07 | G4: =E4*F4 -> 559.8086 | H4: {=_FV(Ledger[[#This Row],[Stock]],"Ticker symbol",TRUE)} -> AMD
B5: 44197 | C5: #VALUE! | D5: Buy | E5: 89.33 | F5: 6.27 | G5: =E5*F5 -> 560.0991 | H5: {=_FV(Ledger[[#This Row],[Stock]],"Ticker symbol",TRUE)} -> AMD
B6: 44562 | C6: #VALUE! | D6: Sell | E6: 110.93 | F6: 5.05 | G6: =E6*F6 -> 560.1965 | H6: {=_FV(Ledger[[#This Row],[Stock]],"Ticker symbol",TRUE)} -> AMD
B7: 44927 | C7: #VALUE! | D7: Buy | E7: 66.09 | F7: 8.47 | G7: =E7*F7 -> 559.7823 | H7: {=_FV(Ledger[[#This Row],[Stock]],"Ticker symbol",TRUE)} -> AMD
B8: 45292 | C8: #VALUE! | D8: Buy | E8: 104.7 | F8: 21.4 | G8: =E8*F8 -> 2240.58 | H8: {=_FV(Ledger[[#This Row],[Stock]],"Ticker symbol",TRUE)} -> AMD
B9: 45658 | C9: #VALUE! | D9: Sell | E9: 126.16 | F9: 18.66 | G9: =E9*F9 -> 2354.1456 | H9: {=_FV(Ledger[[#This Row],[Stock]],"Ticker symbol",TRUE)} -> AMD
B10: 43466 | C10: #VALUE! | D10: Buy | E10: 97.62 | F10: 7.32 | G10: =E10*F10 -> 714.5784 | H10: {=_FV(Ledger[[#This Row],[Stock]],"Ticker symbol",TRUE)} -> JPM
B11: 43831 | C11: #VALUE! | D11: Buy | E11: 139.4 | F11: 5.12 | G11: =E11*F11 -> 713.728 | H11: {=_FV(Ledger[[#This Row],[Stock]],"Ticker symbol",TRUE)} -> JPM
B12: 44197 | C12: #VALUE! | D12: Buy | E12: 127.07 | F12: 5.62 | G12: =E12*F12 -> 714.1334 | H12: {=_FV(Ledger[[#This Row],[Stock]],"Ticker symbol",TRUE)} -> JPM
B13: 44562 | C13: #VALUE! | D13: Sell | E13: 167.89 | F13: 4.26 | G13: =E13*F13 -> 715.2114 | H13: {=_FV(Ledger[[#This Row],[Stock]],"Ticker symbol",TRUE)} -> JPM
B14: 44927 | C14: #VALUE! | D14: Buy | E14: 134.12 | F14: 5.32 | G14: =E14*F14 -> 713.5184 | H14: {=_FV(Ledger[[#This Row],[Stock]],"Ticker symbol",TRUE)} -> JPM
... B114: 45658 | C114: #VALUE! | D114: Sell | E114: 170.54 | F114: 12.59 | G114: =E114*F114 -> 2147.0986 | H114: {=_FV(Ledger[[#This Row],[Stock]],"Ticker symbol",TRUE)} -> TM

Sheet AMD
A1: Stock | B1: #VALUE!
A3: Exchange abbreviation | B3: Ticker symbol
A4: XNAS | B4: AMD | C4: {=TRANSPOSE(_xlfn.STOCKHISTORY(A4&":"&B4,TODAY()-365,TODAY(),0,0,1))} -> 161.36 | D4: 161.79 | E4: 164.01 | F4: 169.73 | G4: 164.67 | H4: 203.71 | I4: 211.51 | J4: 235.56 | K4: 232.89 | L4: 214.9 | M4: 216.42 | N4: 218.09 | O4: 238.6 | P4: 234.56 | Q4: 233.08 | R4: 240.56 | S4: 238.03 | T4: 230.23 | U4: 234.99 | V4: 252.92 | W4: 259.67 | X4: 258.01 | Y4: 264.33 | Z4: 254.84 | AA4: 256.12 | AB4: 259.65 | AC4: 250.05 | AD4: 256.33 | AE4: 237.7 | AF4: 233.54 | AG4: 243.98 | AH4: 237.52 | AI4: 258.89 | AJ4: 247.96 | AK4: 246.81 | AL4: 240.52 | AM4: 230.29 | AN4: 223.55 | AO4: 206.02 | AP4: 203.78 | AQ4: 215.05 | AR4: 206.13 | AS4: 214.24 | AT4: 217.53 | AU4: 219.76 | AV4: 215.24 | AW4: 217.6 | AX4: 215.98 | AY4: 217.97 | AZ4: 221.11 | BA4: 221.62 | BB4: 221.42 | BC4: 221.43 | BD4: 210.78 | BE4: 207.58 | BF4: 209.17 | BG4: 198.11 | BH4: 201.06 | BI4: 213.43 | BJ4: 214.95 | BK4: 214.9 | BL4: 215.04 | BM4: 214.99 | BN4: 215.61 | BO4: 215.34 | BP4: 214.16 | BQ4: 223.47 | BR4: 221.08 | BS4: 214.35 | BT4: 210.02 | BU4: 204.68 | BV4: 203.17 | BW4: 207.69 | BX4: 220.97 | BY4: 223.6 | BZ4: 227.92 | CA4: 231.83 | CB4: 231.92 | CC4: 249.8 | CD4: 253.73 | CE4: 259.68 | CF4: 251.31 | CG4: 252.03 | CH4: 252.74 | CI4: 252.18 | CJ4: 236.73 | CK4: 246.27 | CL4: 242.11 | CM4: 200.19 | CN4: 192.5 | CO4: 208.44 | CP4: 216 | CQ4: 213.57 | CR4: 213.58 | CS4: 205.94 | CT4: 207.32 | CU4: 203.08 | CV4: 200.12 | CW4: 203.37 | CX4: 200.15 | CY4: 196.6 | CZ4: 213.84 | DA4: 210.86 | DB4: 203.68 | DC4: 200.21 | DD4: 198.62 | DE4: 190.95 | DF4: 202.07 | DG4: 199.45 | DH4: 192.43 | DI4: 202.68 | DJ4: 203.23 | DK4: 204.83 | DL4: 197.74 | DM4: 193.39 | DN4: 196.58 | DO4: 196.31 | DP4: 199.46 | DQ4: 205.27 | DR4: 201.33 | DS4: 202.68 | DT4: 205.37 | DU4: 220.27 | DV4: 203.77 | DW4: 201.99 | DX4: 196.04 | DY4: 203.43 | DZ4: 210.21 | EA4: 217.5 | EB4: 220.18 | EC4: 221.53 | ED4: 231.82 | EE4: 236.64 | EF4: 245.04 | EG4: 246.83 | EH4: 255.07 | EI4: 258.12 | EJ4: 278.26 | EK4: 278.39 | EL4: 274.95 | EM4: 284.49 | EN4: 303.46 | EO4: 305.33 | EP4: 347.81 | EQ4: 334.63 | ER4: 323.21 | ES4: 337.11 | ET4: 354.49 | EU4: 360.54 | EV4: 341.54 | EW4: 355.26 | EX4: 421.39 | EY4: 408.46 | EZ4: 455.19 | FA4: 458.79 | FB4: 448.29 | FC4: 445.5 | FD4: 449.7 | FE4: 424.1 | FF4: 420.99 | FG4: 414.05 | FH4: 447.58 | FI4: 449.59 | FJ4: 467.51 | FK4: 503.89 | FL4: 495.54 | FM4: 518.09 | FN4: 516.1 | FO4: 510.13 | FP4: 521.54 | FQ4: 542.52 | FR4: 523.2 | FS4: 466.38 | FT4: 490.33 | FU4: 475.505 | FV4: 452.4 | FW4: 488.45 | FX4: 511.57 | FY4: 547.26 | FZ4: 507.29 | GA4: 512.48 | GB4: 537.37 | GC4: 551.63 | GD4: 519.85 | GE4: 519.74 | GF4: 532.57 | GG4: 521.58 | GH4: 539.49 | GI4: 580.91 | GJ4: 540.88 | GK4: 517.82 | GL4: 552.05 | GM4: 516.11 | GN4: 517.405 | GO4: 546.72 | GP4: 557.89 | GQ4: 534.39 | GR4: 548.13 | GS4: 529.14 | GT4: 500.94 | GU4: 495.76 | GV4: 503.57 | GW4: 544.43 | GX4: 552.33 | GY4: 539.69 | GZ4: 521.95 | HA4: 494.95 | HB4: 454.62 | HC4: 429.56 | HD4: 485.39 | HE4: 476.15 | HF4: 484.64 | HG4: 518.58 | HH4: 482.05 | HI4: 489.28 | HJ4: 483.36 | HK4: 469.56 | HL4: 474.32 | HM4: 482.93 | HN4: 483.01 | HO4: 514.39 | HP4: 506 | HQ4: 484.39 | HR4: 466.42 | HS4: 469.455 | HT4: 473.25 | HU4: 456.745 | HV4: 479.18 | HW4: 480.93 | HX4: 476.67 | HY4: 465.58 | HZ4: 470.72 | IA4: 459.61 | IB4: 457.06 | IC4: 456.16 | ID4: 477.57 | IE4: 505.74 | IF4: 521.095 | IG4: 503.6 | IH4: 516.13 | II4: 493.41 | IJ4: 504.2 | IK4: 512.5 | IL4: 545.09 | IM4: 559.82 | IN4: 615.52 | IO4: 623.77 | IP4: 614.61 | IQ4: 629.26 | IR4: 630.63 | IS4: 607.87
A6: {=_xlfn.STOCKHISTORY(A4&":"&B4,TODAY()-30,TODAY(),0,1,0,5,2,3,4,1)} -> Date | B6: Volume | C6: Open | D6: High | E6: Low | F6: Close
A7: 46265 | B7: 12462999 | C7: 466.22 | D7: 475.8099 | E7: 463.68 | F7: 470.72
A8: 46266 | B8: 16212787 | C8: 459.91 | D8: 461.5 | E8: 452.3 | F8: 459.61
A9: 46267 | B9: 11938812 | C9: 459.51 | D9: 462.21 | E9: 452.36 | F9: 457.06
A10: 46268 | B10: 14868085 | C10: 453.15 | D10: 459.77 | E10: 440.5 | F10: 456.16
A11: 46269 | B11: 19678742 | C11: 462 | D11: 478.83 | E11: 458 | F11: 477.57
A12: 46273 | B12: 28166529 | C12: 488.92 | D12: 512.3569 | E12: 486.5706 | F12: 505.74
A13: 46274 | B13: 22152382 | C13: 507.5 | D13: 526.79 | E13: 506.36 | F13: 521.095
A14: 46275 | B14: 15887968 | C14: 509.07 | D14: 516.3322 | E14: 502.81 | F14: 503.6
A15: 46276 | B15: 18760534 | C15: 510.71 | D15: 521.06 | E15: 501.35 | F15: 516.13
A16: 46279 | B16: 24810136 | C16: 486.28 | D16: 498.39 | E16: 480.33 | F16: 493.41
A17: 46280 | B17: 16833235 | C17: 501.7 | D17: 513.665 | E17: 497.511 | F17: 504.2
A18: 46281 | B18: 22317673 | C18: 517.39 | D18: 527.25 | E18: 506.05 | F18: 512.5
... A26: 46293 | B26: 22124072 | C26: 624.895 | D26: 629.75 | E26: 596.07 | F26: 607.87

Sheet Portfolio Series
A1: PORTFOLIO SERIES: 12-MONTH BACK-CAST OF CURRENT HOLDINGS
A2: Daily closes from Price History x today's net units. Holdings without price history are excluded (see B10:B11). SPY is the benchmark.
A4: Date | B4: {=_xlfn.TAKE('Price History'!B2:IZ2,,COUNT('Price History'!B2:IZ2))} -> 45929 | C4: 45930 | D4: 45931 | E4: 45932 | F4: 45933 | G4: 45936 | H4: 45937 | I4: 45938 | J4: 45939 | K4: 45940 | L4: 45943 | M4: 45944 | N4: 45945 | O4: 45946 | P4: 45947 | Q4: 45950 | R4: 45951 | S4: 45952 | T4: 45953 | U4: 45954 | V4: 45957 | W4: 45958 | X4: 45959 | Y4: 45960 | Z4: 45961 | AA4: 45964 | AB4: 45965 | AC4: 45966 | AD4: 45967 | AE4: 45968 | AF4: 45971 | AG4: 45972 | AH4: 45973 | AI4: 45974 | AJ4: 45975 | AK4: 45978 | AL4: 45979 | AM4: 45980 | AN4: 45981 | AO4: 45982 | AP4: 45985 | AQ4: 45986 | AR4: 45987 | AS4: 45989 | AT4: 45992 | AU4: 45993 | AV4: 45994 | AW4: 45995 | AX4: 45996 | AY4: 45999 | AZ4: 46000 | BA4: 46001 | BB4: 46002 | BC4: 46003 | BD4: 46006 | BE4: 46007 | BF4: 46008 | BG4: 46009 | BH4: 46010 | BI4: 46013 | BJ4: 46014 | BK4: 46015 | BL4: 46017 | BM4: 46020 | BN4: 46021 | BO4: 46022 | BP4: 46024 | BQ4: 46027 | BR4: 46028 | BS4: 46029 | BT4: 46030 | BU4: 46031 | BV4: 46034 | BW4: 46035 | BX4: 46036 | BY4: 46037 | BZ4: 46038 | CA4: 46042 | CB4: 46043 | CC4: 46044 | CD4: 46045 | CE4: 46048 | CF4: 46049 | CG4: 46050 | CH4: 46051 | CI4: 46052 | CJ4: 46055 | CK4: 46056 | CL4: 46057 | CM4: 46058 | CN4: 46059 | CO4: 46062 | CP4: 46063 | CQ4: 46064 | CR4: 46065 | CS4: 46066 | CT4: 46070 | CU4: 46071 | CV4: 46072 | CW4: 46073 | CX4: 46076 | CY4: 46077 | CZ4: 46078 | DA4: 46079 | DB4: 46080 | DC4: 46083 | DD4: 46084 | DE4: 46085 | DF4: 46086 | DG4: 46087 | DH4: 46090 | DI4: 46091 | DJ4: 46092 | DK4: 46093 | DL4: 46094 | DM4: 46097 | DN4: 46098 | DO4: 46099 | DP4: 46100 | DQ4: 46101 | DR4: 46104 | DS4: 46105 | DT4: 46106 | DU4: 46107 | DV4: 46108 | DW4: 46111 | DX4: 46112 | DY4: 46113 | DZ4: 46114 | EA4: 46118 | EB4: 46119 | EC4: 46120 | ED4: 46121 | EE4: 46122 | EF4: 46125 | EG4: 46126 | EH4: 46127 | EI4: 46128 | EJ4: 46129 | EK4: 46132 | EL4: 46133 | EM4: 46134 | EN4: 46135 | EO4: 46136 | EP4: 46139 | EQ4: 46140 | ER4: 46141 | ES4: 46142 | ET4: 46143 | EU4: 46146 | EV4: 46147 | EW4: 46148 | EX4: 46149 | EY4: 46150 | EZ4: 46153 | FA4: 46154 | FB4: 46155 | FC4: 46156 | FD4: 46157 | FE4: 46160 | FF4: 46161 | FG4: 46162 | FH4: 46163 | FI4: 46164 | FJ4: 46168 | FK4: 46169 | FL4: 46170 | FM4: 46171 | FN4: 46174 | FO4: 46175 | FP4: 46176 | FQ4: 46177 | FR4: 46178 | FS4: 46181 | FT4: 46182 | FU4: 46183 | FV4: 46184 | FW4: 46185 | FX4: 46188 | FY4: 46189 | FZ4: 46190 | GA4: 46191 | GB4: 46195 | GC4: 46196 | GD4: 46197 | GE4: 46198 | GF4: 46199 | GG4: 46202 | GH4: 46203 | GI4: 46204 | GJ4: 46205 | GK4: 46209 | GL4: 46210 | GM4: 46211 | GN4: 46212 | GO4: 46213 | GP4: 46216 | GQ4: 46217 | GR4: 46218 | GS4: 46219 | GT4: 46220 | GU4: 46223 | GV4: 46224 | GW4: 46225 | GX4: 46226 | GY4: 46227 | GZ4: 46230 | HA4: 46231 | HB4: 46232 | HC4: 46233 | HD4: 46234 | HE4: 46237 | HF4: 46238 | HG4: 46239 | HH4: 46240 | HI4: 46241 | HJ4: 46244 | HK4: 46245 | HL4: 46246 | HM4: 46247 | HN4: 46248 | HO4: 46251 | HP4: 46252 | HQ4: 46253 | HR4: 46254 | HS4: 46255 | HT4: 46258 | HU4: 46259 | HV4: 46260 | HW4: 46261 | HX4: 46262 | HY4: 46265 | HZ4: 46266 | IA4: 46267 | IB4: 46268 | IC4: 46269 | ID4: 46273 | IE4: 46274 | IF4: 46275 | IG4: 46276 | IH4: 46279 | II4: 46280 | IJ4: 46281 | IK4: 46282 | IL4: 46283 | IM4: 46286 | IN4: 46287 | IO4: 46288 | IP4: 46289 | IQ4: 46290 | IR4: 46293
A5: Portfolio value | B5: {=_xlfn.LET(_xlpm.n,COUNT('Price History'!B2:IZ2),_xlpm.p,IFERROR(--_xlfn.TAKE('Price History'!B3:IZ18,,_xlpm.n),0),_xlpm.u,IF(ISNUMBER('Price History'!B3:B18),Dashboard!D7:D22,0),MMULT(TRANSPOSE(_xlpm.u),_xlpm.p))} -> 152470.68 | C5: 153973.2 | D5: 153835.49 | E5: 155014.01 | F5: 154161.02 | G5: 156097.77 | H5: 156004.84 | I5: 159029.42 | J5: 160093.94 | K5: 153450.85 | L5: 156764.75 | M5: 153994.89 | N5: 155810.64 | O5: 155543.45 | P5: 156460.59 | Q5: 157625.33 | R5: 156550.57 | S5: 155518.19 | T5: 156715.64 | U5: 160440.42 | V5: 163739.1 | W5: 167524.43 | X5: 170324.49 | Y5: 166827.29 | Z5: 166822.71 | AA5: 168822.52 | AB5: 164310.13 | AC5: 163697.15 | AD5: 159231.67 | AE5: 159016.35 | AF5: 164901.94 | AG5: 162320.5 | AH5: 163528.57 | AI5: 158978.17 | AJ5: 159967.05 | AK5: 157580.31 | AL5: 154275.67 | AM5: 156242.7 | AN5: 152431.89 | AO5: 152384.62 | AP5: 155763.07 | AQ5: 154414.63 | AR5: 156229.76 | AS5: 155780.06 | AT5: 156846.17 | AU5: 157442.86 | AV5: 157364.29 | AW5: 159168.69 | AX5: 159085.15 | AY5: 159959.71 | AZ5: 159551.32 | BA5: 159567.1 | BB5: 158677.01 | BC5: 155405.27 | BD5: 155675.58 | BE5: 156057.91 | BF5: 151989.44 | BG5: 153971.65 | BH5: 157903.07 | BI5: 159510.03 | BJ5: 162074.88 | BK5: 162149.16 | BL5: 162734.21 | BM5: 161591.09 | BN5: 161279.04 | BO5: 160396.99 | BP5: 162252.96 | BQ5: 162775.62 | BR5: 161903.79 | BS5: 161844.48 | BT5: 160317.91 | BU5: 160677.88 | BV5: 160975.64 | BW5: 161931.04 | BX5: 160330.66 | BY5: 162723.86 | BZ5: 162568.35 | CA5: 157213.23 | CB5: 161253.45 | CC5: 162865.1 | CD5: 164231.44 | CE5: 163861.57 | CF5: 164969.11 | CG5: 166075.99 | CH5: 168102.62 | CI5: 166433.74 | CJ5: 165634.52 | CK5: 163057.03 | CL5: 157818.69 | CM5: 155578.96 | CN5: 162716.84 | CO5: 165149.6 | CP5: 163616.94 | CQ5: 163934.07 | CR5: 161037.25 | CS5: 159163.56 | CT5: 159695.72 | CU5: 160979.59 | CV5: 160744.81 | CW5: 162109.54 | CX5: 161675.06 | CY5: 163678.12 | CZ5: 165409.89 | DA5: 160326.43 | DB5: 156450.64 | DC5: 158308.22 | DD5: 156446.66 | DE5: 158660.71 | DF5: 157530.27 | DG5: 153698.62 | DH5: 156780.67 | DI5: 158013.91 | DJ5: 158481.23 | DK5: 155892.31 | DL5: 153769.95 | DM5: 155898.57 | DN5: 155677.46 | DO5: 154468.16 | DP5: 153827.9 | DQ5: 150246.01 | DR5: 152521.2 | DS5: 152236.65 | DT5: 154914.35 | DU5: 149401.04 | DV5: 146310 | DW5: 145045.43 | DX5: 151502.01 | DY5: 152994.41 | DZ5: 154101.13 | EA5: 154726.56 | EB5: 154782.13 | EC5: 159592.51 | ED5: 161447.72 | EE5: 163696.89 | EF5: 164463.33 | EG5: 169236.97 | EH5: 170792.67 | EI5: 171629.25 | EJ5: 174216.9 | EK5: 173993.47 | EL5: 173119.06 | EM5: 175989.43 | EN5: 174657.22 | EO5: 180877.36 | EP5: 183665.35 | EQ5: 181448.45 | ER5: 180549.93 | ES5: 178473.22 | ET5: 178456.33 | EU5: 176814.56 | EV5: 177375.58 | EW5: 186871.23 | EX5: 187313.47 | EY5: 191669.39 | EZ5: 192700.27 | FA5: 193003 | FB5: 196114.95 | FC5: 200774.01 | FD5: 194308.93 | FE5: 192903.4 | FF5: 190897.31 | FG5: 194518.82 | FH5: 192532.79 | FI5: 192098.49 | FJ5: 194176.47 | FK5: 193126.63 | FL5: 195323.21 | FM5: 193414.88 | FN5: 197210.66 | FO5: 196876.43 | FP5: 194922.65 | FQ5: 196641.18 | FR5: 186360.17 | FS5: 188965.73 | FT5: 187574.16 | FU5: 182193.51 | FV5: 186900.68 | FW5: 188624.05 | FX5: 194843.71 | FY5: 190993.4 | FZ5: 188717.93 | GA5: 192873.12 | GB5: 192009.56 | GC5: 186344.28 | GD5: 185417.57 | GE5: 183665.53 | GF5: 181657.85 | GG5: 184418.21 | GH5: 188966.07 | GI5: 186551.43 | GJ5: 184387.94 | GK5: 187888.99 | GL5: 186451.35 | GM5: 188826.5 | GN5: 190753.26 | GO5: 195759.58 | GP5: 191060.6 | GQ5: 195338.68 | GR5: 196195.81 | GS5: 191690.39 | GT5: 188617.72 | GU5: 188967.74 | GV5: 193067.23 | GW5: 195115.89 | GX5: 191287.31 | GY5: 189909.06 | GZ5: 184722.2 | HA5: 183203.71 | HB5: 178313.62 | HC5: 183129.22 | HD5: 186011.11 | HE5: 190198.31 | HF5: 194864.29 | HG5: 195220.75 | HH5: 195208.21 | HI5: 197096.05 | HJ5: 193889.98 | HK5: 193818.78 | HL5: 196918.07 | HM5: 197884.3 | HN5: 199690.11 | HO5: 198382.12 | HP5: 194723.75 | HQ5: 192826.53 | HR5: 191054.56 | HS5: 190799.1 | HT5: 187762.47 | HU5: 191004.1 | HV5: 189616.63 | HW5: 196547.46 | HX5: 192380.45 | HY5: 193592.71 | HZ5: 191727.48 | IA5: 194880.06 | IB5: 197817.44 | IC5: 199331.91 | ID5: 198284.23 | IE5: 198545.05 | IF5: 195565.17 | IG5: 197216.33 | IH5: 193152.49 | II5: 194015.07 | IJ5: 194617.25 | IK5: 199449.83 | IL5: 201228.46 | IM5: 208546.91 | IN5: 209081.44 | IO5: 206566.68 | IP5: 207431.65 | IQ5: 207906.32 | IR5: 206946.75
A6: Daily return | C6: {=_xlfn.DROP(_xlfn.ANCHORARRAY(B5),,1)/_xlfn.DROP(_xlfn.ANCHORARRAY(B5),,-1)-1} -> 0.0098544955 | D6: -0.00089439527 | E6: 0.0076609281 | F6: -0.0055026253 | G6: 0.012563125 | H6: -0.00059534419 | I6: 0.019387734 | J6: 0.0066938647 | K6: -0.041494913 | L6: 0.021595839 | M6: -0.01766893 | N6: 0.011790982 | O6: -0.0017148559 | P6: 0.0058963985 | Q6: 0.0074442627 | R6: -0.0068184259 | S6: -0.0065945611 | T6: 0.0076997309 | U6: 0.02376782 | V6: 0.020560102 | W6: 0.023118102 | X6: 0.016714297 | Y6: -0.020532579 | Z6: -2.7454142e-05 | AA6: 0.011987678 | AB6: -0.026728642 | AC6: -0.0037305893 | AD6: -0.027278927 | AE6: -0.0013522115 | AF6: 0.037012471 | AG6: -0.015654415 | AH6: 0.0074425159 | AI6: -0.027826331 | AJ6: 0.006220225 | AK6: -0.01492019 | AL6: -0.020971148 | AM6: 0.012750091 | AN6: -0.024390321 | AO6: -0.00031010309 | AP6: 0.022170515 | AQ6: -0.0086569648 | AR6: 0.011754869 | AS6: -0.0028784318 | AT6: 0.0068436667 | AU6: 0.0038043072 | AV6: -0.00049902804 | AW6: 0.011466382 | AX6: -0.00052483941 | AY6: 0.0054974339 | AZ6: -0.0025530554 | BA6: 9.8860978e-05 | BB6: -0.0055781186 | BC6: -0.02061887 | BD6: 0.0017393387 | BE6: 0.0024560018 | BF6: -0.026070312 | BG6: 0.013041774 | BH6: 0.025533411 | BI6: 0.010176905 | BJ6: 0.016079533 | BK6: 0.00045828138 | BL6: 0.0036081273 | BM6: -0.007024451 | BN6: -0.0019311176 | BO6: -0.0054691 | BP6: 0.011571091 | BQ6: 0.0032212725 | BR6: -0.0053560073 | BS6: -0.00036633731 | BT6: -0.0094323013 | BU6: 0.0022453324 | BV6: 0.0018531094 | BW6: 0.0059351032 | BX6: -0.0098831044 | BY6: 0.014926637 | BZ6: -0.00095563307 | CA6: -0.032940727 | CB6: 0.025698954 | CC6: 0.0099944869 | CD6: 0.0083894544 | CE6: -0.0022521412 | CF6: 0.0067590039 | CG6: 0.0067095869 | CH6: 0.012203026 | CI6: -0.0099277473 | CJ6: -0.0048020102 | CK6: -0.015561339 | CL6: -0.032125791 | CM6: -0.014191767 | CN6: 0.045879474 | CO6: 0.014950869 | CP6: -0.0092804692 | CQ6: 0.0019382657 | CR6: -0.017670661 | CS6: -0.011635122 | CT6: 0.0033435072 | CU6: 0.0080394795 | CV6: -0.0014584718 | CW6: 0.0084900458 | CX6: -0.0026801402 | CY6: 0.012389381 | CZ6: 0.010580377 | DA6: -0.030732524 | DB6: -0.024174375 | DC6: 0.011873248 | DD6: -0.011759042 | DE6: 0.0141521 | DF6: -0.0071249018 | DG6: -0.024323255 | DH6: 0.02005257 | DI6: 0.0078659957 | DJ6: 0.0029574814 | DK6: -0.016335854 | DL6: -0.013614243 | DM6: 0.01384291 | DN6: -0.0014183401 | DO6: -0.0077680013 | DP6: -0.0041448731 | DQ6: -0.023285045 | DR6: 0.015143063 | DS6: -0.0018656443 | DT6: 0.017589074 | DU6: -0.035589426 | DV6: -0.02068955 | DW6: -0.0086430519 | DX6: 0.044514204 | DY6: 0.009850634 | DZ6: 0.0072337338 | EA6: 0.0040586004 | EB6: 0.00035914519 | EC6: 0.031078412 | ED6: 0.011624662 | EE6: 0.013931235 | EF6: 0.004682078 | EG6: 0.02902558 | EH6: 0.0091924404 | EI6: 0.0048981638 | EJ6: 0.015076977 | EK6: -0.0012824612 | EL6: -0.0050255484 | EM6: 0.016580371 | EN6: -0.0075698556 | EO6: 0.035613429 | EP6: 0.015413685 | EQ6: -0.01207029 | ER6: -0.0049519744 | ES6: -0.011502143 | ET6: -9.4606633e-05 | EU6: -0.0091998297 | EV6: 0.003172884 | EW6: 0.053534151 | EX6: 0.0023665607 | EY6: 0.023254723 | EZ6: 0.0053784462 | FA6: 0.0015709874 | FB6: 0.016123843 | FC6: 0.023756747 | FD6: -0.032200763 | FE6: -0.0072334668 | FF6: -0.010399498 | FG6: 0.018971007 | FH6: -0.010209943 | FI6: -0.0022557581 | FJ6: 0.010817294 | FK6: -0.0054066244 | FL6: 0.011373764 | FM6: -0.0097701231 | FN6: 0.019625055 | FO6: -0.0016947385 | FP6: -0.009923919 | FQ6: 0.0088164896 | FR6: -0.052283099 | FS6: 0.013981282 | FT6: -0.0073641291 | FU6: -0.028685436 | FV6: 0.025836089 | FW6: 0.0092207846 | FX6: 0.03297384 | FY6: -0.019761016 | FZ6: -0.011913881 | GA6: 0.022018005 | GB6: -0.0044773258 | GC6: -0.029505195 | GD6: -0.0049731389 | GE6: -0.0094491284 | GF6: -0.010931212 | GG6: 0.015195424 | GH6: 0.02466054 | GI6: -0.012778153 | GJ6: -0.011597302 | GK6: 0.018987438 | GL6: -0.0076515542 | GM6: 0.012738731 | GN6: 0.010203873 | GO6: 0.026244967 | GP6: -0.024003816 | GQ6: 0.022391209 | GR6: 0.0043879252 | GS6: -0.022963869 | GT6: -0.016029388 | GU6: 0.0018557626 | GV6: 0.021694088 | GW6: 0.010611122 | GX6: -0.019622077 | GY6: -0.0072051393 | GZ6: -0.027312304 | HA6: -0.0082204049 | HB6: -0.026692104 | HC6: 0.027006365 | HD6: 0.015736936 | HE6: 0.022510433 | HF6: 0.02453219 | HG6: 0.0018292921 | HH6: -6.4216534e-05 | HI6: 0.009670883 | HJ6: -0.016266532 | HK6: -0.00036721856 | HL6: 0.015990642 | HM6: 0.0049068007 | HN6: 0.0091255681 | HO6: -0.00655012 | HP6: -0.018441 | HQ6: -0.0097431257 | HR6: -0.0091894573 | HS6: -0.0013371374 | HT6: -0.015915324 | HU6: 0.017264544 | HV6: -0.0072640964 | HW6: 0.036551805 | HX6: -0.021201008 | HY6: 0.0063013241 | HZ6: -0.0096348087 | IA6: 0.016443035 | IB6: 0.015072748 | IC6: 0.0076559161 | ID6: -0.0052559427 | IE6: 0.0013153804 | IF6: -0.015008624 | IG6: 0.008443018 | IH6: -0.020605976 | II6: 0.0044657767 | IJ6: 0.0031037791 | IK6: 0.024831213 | IL6: 0.0089176768 | IM6: 0.036368876 | IN6: 0.0025631168 | IO6: -0.012027681 | IP6: 0.0041873652 | IQ6: 0.0022883312 | IR6: -0.0046153734
A7: SPY close | B7: {=_xlfn.LET(_xlpm.h,_xlfn.STOCKHISTORY("SPY",TODAY()-365,TODAY(),0,0,0,1),_xlfn.XLOOKUP(_xlfn.ANCHORARRAY(B4),INDEX(_xlpm.h,,1),INDEX(_xlpm.h,,2)))} -> 663.68 | C7: 666.18 | D7: 668.45 | E7: 669.22 | F7: 669.21 | G7: 671.61 | H7: 669.12 | I7: 673.11 | J7: 671.16 | K7: 653.02 | L7: 663.04 | M7: 662.23 | N7: 665.17 | O7: 660.64 | P7: 664.39 | Q7: 671.3 | R7: 671.29 | S7: 667.8 | T7: 671.76 | U7: 677.25 | V7: 685.24 | W7: 687.06 | X7: 687.39 | Y7: 679.83 | Z7: 682.06 | AA7: 683.34 | AB7: 675.24 | AC7: 677.58 | AD7: 670.31 | AE7: 670.97 | AF7: 681.44 | AG7: 683 | AH7: 683.38 | AI7: 672.04 | AJ7: 671.93 | AK7: 665.67 | AL7: 660.08 | AM7: 662.63 | AN7: 652.53 | AO7: 659.03 | AP7: 668.73 | AQ7: 675.02 | AR7: 679.68 | AS7: 683.39 | AT7: 680.27 | AU7: 681.53 | AV7: 683.89 | AW7: 684.39 | AX7: 685.69 | AY7: 683.63 | AZ7: 683.04 | BA7: 687.57 | BB7: 689.17 | BC7: 681.76 | BD7: 680.73 | BE7: 678.87 | BF7: 671.4 | BG7: 676.47 | BH7: 680.59 | BI7: 684.83 | BJ7: 687.96 | BK7: 690.38 | BL7: 690.31 | BM7: 687.85 | BN7: 687.01 | BO7: 681.92 | BP7: 683.17 | BQ7: 687.72 | BR7: 691.81 | BS7: 689.58 | BT7: 689.51 | BU7: 694.07 | BV7: 695.16 | BW7: 693.77 | BX7: 690.36 | BY7: 692.24 | BZ7: 691.66 | CA7: 677.58 | CB7: 685.4 | CC7: 688.98 | CD7: 689.23 | CE7: 692.73 | CF7: 695.49 | CG7: 695.42 | CH7: 694.04 | CI7: 691.97 | CJ7: 695.41 | CK7: 689.53 | CL7: 686.19 | CM7: 677.62 | CN7: 690.62 | CO7: 693.95 | CP7: 692.12 | CQ7: 691.96 | CR7: 681.27 | CS7: 681.75 | CT7: 682.85 | CU7: 686.29 | CV7: 684.48 | CW7: 689.43 | CX7: 682.39 | CY7: 687.35 | CZ7: 693.15 | DA7: 689.3 | DB7: 685.99 | DC7: 686.38 | DD7: 680.33 | DE7: 685.13 | DF7: 681.31 | DG7: 672.38 | DH7: 678.27 | DI7: 677.18 | DJ7: 676.33 | DK7: 666.06 | DL7: 662.29 | DM7: 669.03 | DN7: 670.79 | DO7: 661.43 | DP7: 659.8 | DQ7: 648.57 | DR7: 655.38 | DS7: 653.18 | DT7: 656.82 | DU7: 645.09 | DV7: 634.09 | DW7: 631.97 | DX7: 650.34 | DY7: 655.24 | DZ7: 655.83 | EA7: 658.93 | EB7: 659.22 | EC7: 676.01 | ED7: 679.91 | EE7: 679.46 | EF7: 686.1 | EG7: 694.46 | EH7: 699.94 | EI7: 701.66 | EJ7: 710.14 | EK7: 708.72 | EL7: 704.08 | EM7: 711.21 | EN7: 708.45 | EO7: 713.94 | EP7: 715.17 | EQ7: 711.69 | ER7: 711.58 | ES7: 718.66 | ET7: 720.65 | EU7: 718.01 | EV7: 723.77 | EW7: 733.83 | EX7: 731.58 | EY7: 737.62 | EZ7: 739.3 | FA7: 738.18 | FB7: 742.31 | FC7: 748.17 | FD7: 739.17 | FE7: 738.65 | FF7: 733.73 | FG7: 741.25 | FH7: 742.72 | FI7: 745.64 | FJ7: 750.59 | FK7: 750.46 | FL7: 754.6 | FM7: 756.48 | FN7: 758.54 | FO7: 759.57 | FP7: 754.24 | FQ7: 757.09 | FR7: 737.55 | FS7: 739.22 | FT7: 737.05 | FU7: 725.43 | FV7: 737.76 | FW7: 741.75 | FX7: 754.83 | FY7: 750.33 | FZ7: 740.96 | GA7: 746.74 | GB7: 744.39 | GC7: 733.58 | GD7: 733.24 | GE7: 734.3 | GF7: 728.99 | GG7: 741 | GH7: 746.77 | GI7: 745.76 | GJ7: 744.78 | GK7: 751.28 | GL7: 747.71 | GM7: 745.4 | GN7: 751.71 | GO7: 754.95 | GP7: 749.17 | GQ7: 751.83 | GR7: 754.81 | GS7: 750.72 | GT7: 743.29 | GU7: 742.09 | GV7: 748.28 | GW7: 747.41 | GX7: 738.18 | GY7: 738.93 | GZ7: 739.09 | HA7: 740.86 | HB7: 729.46 | HC7: 741.69 | HD7: 747.03 | HE7: 757.67 | HF7: 771.33 | HG7: 769.79 | HH7: 768.56 | HI7: 773.26 | HJ7: 773.03 | HK7: 770.56 | HL7: 772.49 | HM7: 777.88 | HN7: 776.34 | HO7: 772.67 | HP7: 767.45 | HQ7: 769.06 | HR7: 762.6 | HS7: 765.72 | HT7: 763.47 | HU7: 765.91 | HV7: 766.08 | HW7: 771.1 | HX7: 769.35 | HY7: 767.05 | HZ7: 761.78 | IA7: 765.16 | IB7: 773.17 | IC7: 770.19 | ID7: 765.96 | IE7: 762.4 | IF7: 757.83 | IG7: 764.29 | IH7: 760.88 | II7: 757.39 | IJ7: 754.05 | IK7: 762.6 | IL7: 761.69 | IM7: 773.5 | IN7: 773.38 | IO7: 767.81 | IP7: 767.18 | IQ7: 771.35 | IR7: 765.61
A8: SPY daily return | C8: {=_xlfn.DROP(_xlfn.ANCHORARRAY(B7),,1)/_xlfn.DROP(_xlfn.ANCHORARRAY(B7),,-1)-1} -> 0.0037668756 | D8: 0.0034074875 | E8: 0.0011519186 | F8: -1.4942769e-05 | G8: 0.0035863182 | H8: -0.0037075088 | I8: 0.005963056 | J8: -0.0028970005 | K8: -0.027027832 | L8: 0.015344094 | M8: -0.0012216458 | N8: 0.0044395452 | O8: -0.0068102891 | P8: 0.0056763139 | Q8: 0.010400518 | R8: -1.489647e-05 | S8: -0.0051989453 | T8: 0.0059299191 | U8: 0.0081725616 | V8: 0.011797711 | W8: 0.0026560037 | X8: 0.0004803074 | Y8: -0.010998123 | Z8: 0.0032802318 | AA8: 0.0018766677 | AB8: -0.011853543 | AC8: 0.0034654345 | AD8: -0.01072936 | AE8: 0.00098461906 | AF8: 0.015604274 | AG8: 0.0022892698 | AH8: 0.00055636896 | AI8: -0.016593989 | AJ8: -0.00016368073 | AK8: -0.0093164467 | AL8: -0.0083975543 | AM8: 0.0038631681 | AN8: -0.015242292 | AO8: 0.0099612278 | AP8: 0.014718602 | AQ8: 0.0094058888 | AR8: 0.0069034992 | AS8: 0.005458451 | AT8: -0.0045654751 | AU8: 0.0018522057 | AV8: 0.0034627969 | AW8: 0.00073111173 | AX8: 0.0018995017 | AY8: -0.0030042731 | AZ8: -0.00086303995 | BA8: 0.0066321152 | BB8: 0.0023270358 | BC8: -0.010752064 | BD8: -0.0015107956 | BE8: -0.0027323608 | BF8: -0.011003579 | BG8: 0.0075513852 | BH8: 0.0060904401 | BI8: 0.0062298888 | BJ8: 0.0045704773 | BK8: 0.0035176464 | BL8: -0.00010139344 | BM8: -0.0035636163 | BN8: -0.0012211965 | BO8: -0.0074089169 | BP8: 0.0018330596 | BQ8: 0.0066601285 | BR8: 0.0059471878 | BS8: -0.0032234284 | BT8: -0.00010151106 | BU8: 0.0066133921 | BV8: 0.0015704468 | BW8: -0.0019995397 | BX8: -0.0049151736 | BY8: 0.0027232169 | BZ8: -0.0008378597 | CA8: -0.020356823 | CB8: 0.011541073 | CC8: 0.0052232273 | CD8: 0.00036285524 | CE8: 0.0050781307 | CF8: 0.0039842363 | CG8: -0.00010064846 | CH8: -0.0019844123 | CI8: -0.002982537 | CJ8: 0.0049713138 | CK8: -0.0084554436 | CL8: -0.0048438792 | CM8: -0.012489252 | CN8: 0.019184794 | CO8: 0.0048217544 | CP8: -0.0026370776 | CQ8: -0.00023117378 | CR8: -0.01544887 | CS8: 0.00070456647 | CT8: 0.0016134947 | CU8: 0.0050377096 | CV8: -0.002637369 | CW8: 0.0072317672 | CX8: -0.010211334 | CY8: 0.0072685708 | CZ8: 0.0084382047 | DA8: -0.0055543533 | DB8: -0.004801973 | DC8: 0.00056852141 | DD8: -0.0088143594 | DE8: 0.0070553996 | DF8: -0.0055755842 | DG8: -0.013107102 | DH8: 0.0087599274 | DI8: -0.0016070296 | DJ8: -0.0012552054 | DK8: -0.015184895 | DL8: -0.0056601507 | DM8: 0.010176811 | DN8: 0.0026306743 | DO8: -0.013953696 | DP8: -0.0024643575 | DQ8: -0.017020309 | DR8: 0.010500023 | DS8: -0.0033568312 | DT8: 0.0055727365 | DU8: -0.017858774 | DV8: -0.017051884 | DW8: -0.003343374 | DX8: 0.029067835 | DY8: 0.0075345204 | DZ8: 0.00090043343 | EA8: 0.0047268347 | EB8: 0.00044010745 | EC8: 0.025469494 | ED8: 0.0057691454 | EE8: -0.0006618523 | EF8: 0.0097724664 | EG8: 0.012184813 | EH8: 0.0078910232 | EI8: 0.0024573535 | EJ8: 0.012085626 | EK8: -0.0019996057 | EL8: -0.0065470143 | EM8: 0.01012669 | EN8: -0.0038807103 | EO8: 0.0077493119 | EP8: 0.0017228339 | EQ8: -0.0048659759 | ER8: -0.00015456168 | ES8: 0.0099496894 | ET8: 0.0027690424 | EU8: -0.0036633595 | EV8: 0.0080221724 | EW8: 0.013899443 | EX8: -0.0030661052 | EY8: 0.0082561032 | EZ8: 0.0022775955 | FA8: -0.0015149466 | FB8: 0.0055948414 | FC8: 0.007894276 | FD8: -0.012029352 | FE8: -0.00070349175 | FF8: -0.0066608001 | FG8: 0.010249002 | FH8: 0.0019831366 | FI8: 0.003931495 | FJ8: 0.0066385924 | FK8: -0.00017319708 | FL8: 0.0055166165 | FM8: 0.0024913862 | FN8: 0.0027231387 | FO8: 0.0013578717 | FP8: -0.0070171281 | FQ8: 0.0037786381 | FR8: -0.025809349 | FS8: 0.0022642533 | FT8: -0.0029355266 | FU8: -0.015765552 | FV8: 0.016996816 | FW8: 0.0054082628 | FX8: 0.017633974 | FY8: -0.0059616072 | FZ8: -0.012487839 | GA8: 0.007800691 | GB8: -0.0031470123 | GC8: -0.014521958 | GD8: -0.00046348047 | GE8: 0.0014456385 | GF8: -0.0072313768 | GG8: 0.016474849 | GH8: 0.0077867746 | GI8: -0.0013524914 | GJ8: -0.0013140957 | GK8: 0.0087274094 | GL8: -0.0047518901 | GM8: -0.0030894331 | GN8: 0.0084652536 | GO8: 0.0043101728 | GP8: -0.0076561362 | GQ8: 0.003550596 | GR8: 0.003963662 | GS8: -0.0054185822 | GT8: -0.0098971654 | GU8: -0.0016144439 | GV8: 0.0083413063 | GW8: -0.0011626664 | GX8: -0.012349313 | GY8: 0.0010160124 | GZ8: 0.00021652931 | HA8: 0.0023948369 | HB8: -0.015387523 | HC8: 0.016765827 | HD8: 0.0071997735 | HE8: 0.014243069 | HF8: 0.018028957 | HG8: -0.0019965514 | HH8: -0.0015978384 | HI8: 0.0061153326 | HJ8: -0.000297442 | HK8: -0.0031952188 | HL8: 0.0025046719 | HM8: 0.0069774366 | HN8: -0.0019797398 | HO8: -0.0047273102 | HP8: -0.0067557948 | HQ8: 0.0020978565 | HR8: -0.0083998648 | HS8: 0.0040912667 | HT8: -0.0029384109 | HU8: 0.0031959344 | HV8: 0.00022195819 | HW8: 0.0065528404 | HX8: -0.0022694852 | HY8: -0.0029895366 | HZ8: -0.0068704778 | IA8: 0.0044369766 | IB8: 0.010468399 | IC8: -0.0038542623 | ID8: -0.0054921513 | IE8: -0.0046477623 | IF8: -0.0059942288 | IG8: 0.0085243392 | IH8: -0.0044616572 | II8: -0.0045867942 | IJ8: -0.0044098813 | IK8: 0.011338771 | IL8: -0.0011932861 | IM8: 0.015504995 | IN8: -0.00015513898 | IO8: -0.0072021516 | IP8: -0.00082051549 | IQ8: 0.005435491 | IR8: -0.0074414987
A10: Holdings with price history (of 16) | B10: {=SUM(--ISNUMBER('Price History'!B3:B18))} -> 15
A11: Share of market value covered | B11: {=SUMPRODUCT(--ISNUMBER('Price History'!B3:B18),Dashboard!F7:F22)/SUM(Dashboard!F7:F22)} -> 0.97923596
A12: Daily returns in window | B12: =COLUMNS(_xlfn.ANCHORARRAY(C6)) -> 250
A13: 12-month return, current holdings | B13: {=INDEX(_xlfn.ANCHORARRAY(B5),COLUMNS(_xlfn.ANCHORARRAY(B5)))/INDEX(_xlfn.ANCHORARRAY(B5),1)-1} -> 0.35728887
A14: Annualised volatility | B14: =_xlfn.STDEV.S(_xlfn.ANCHORARRAY(C6))*SQRT(252) -> 0.25966975
A15: Annualised downside deviation | B15: {=SQRT(SUMPRODUCT((_xlfn.ANCHORARRAY(C6)<0)*_xlfn.ANCHORARRAY(C6)^2)/COLUMNS(_xlfn.ANCHORARRAY(C6)))*SQRT(252)} -> 0.17306875
A16: Maximum drawdown (12 months) | B16: {=MIN(_xlfn.ANCHORARRAY(B5)/_xlfn.SCAN(0,_xlfn.ANCHORARRAY(B5),_xlfn.LAMBDA(_xlpm.a,_xlpm.x,MAX(_xlpm.a,_xlpm.x)))-1)} -> -0.14841703
A17: Historical VaR, 1-day, 95% | B17: =-_xlfn.PERCENTILE.INC(_xlfn.ANCHORARRAY(C6),0.05) -> 0.0267122
A18: SPY 12-month return | B18: {=INDEX(_xlfn.ANCHORARRAY(B7),COLUMNS(_xlfn.ANCHORARRAY(B7)))/INDEX(_xlfn.ANCHORARRAY(B7),1)-1} -> 0.15358305
A19: Beta vs SPY (realised) | B19: =SLOPE(_xlfn.ANCHORARRAY(C6),_xlfn.ANCHORARRAY(C8)) -> 1.6444221
A20: Tracking error vs SPY | B20: {=_xlfn.STDEV.S(_xlfn.ANCHORARRAY(C6)-_xlfn.ANCHORARRAY(C8))*SQRT(252)} -> 0.16911893
A21: Active return vs SPY | B21: =B13-B18 -> 0.20370582
A22: Information ratio | B22: =B21/B20 -> 1.2045123
A24: Valuation date (used by every IRR) | B24: =TODAY() -> 46294

Sheet BABA
A1: Stock | B1: #VALUE!
A3: Exchange abbreviation | B3: Ticker symbol
A4: XNYS | B4: BABA | C4: {=TRANSPOSE(_xlfn.STOCKHISTORY(A4&":"&B4,TODAY()-365,TODAY(),0,0,1))} -> 179.9 | D4: 178.73 | E4: 182.78 | F4: 189.34 | G4: 188.03 | H4: 187.22 | I4: 181.33 | J4: 181.12 | K4: 173.68 | L4: 159.01 | M4: 166.81 | N4: 162.86 | O4: 165.91 | P4: 165.09 | Q4: 167.05 | R4: 173.47 | S4: 166.67 | T4: 165.86 | U4: 171.9 | V4: 174.7 | W4: 179.45 | X4: 176.72 | Y4: 179.97 | Z4: 173.93 | AA4: 170.43 | AB4: 167.69 | AC4: 164.3 | AD4: 164.82 | AE4: 167.61 | AF4: 166.34 | AG4: 165.89 | AH4: 160.8 | AI4: 157.91 | AJ4: 159.84 | AK4: 153.8 | AL4: 157.71 | AM4: 159.72 | AN4: 158.89 | AO4: 153.28 | AP4: 152.93 | AQ4: 160.73 | AR4: 157.01 | AS4: 157.6 | AT4: 157.3 | AU4: 164.26 | AV4: 161.13 | AW4: 158.08 | AX4: 157.44 | AY4: 158.32 | AZ4: 158.13 | BA4: 155.96 | BB4: 158.82 | BC4: 156.9 | BD4: 155.68 | BE4: 150.09 | BF4: 149.29 | BG4: 147.09 | BH4: 147.32 | BI4: 149.79 | BJ4: 150.96 | BK4: 151.23 | BL4: 150.06 | BM4: 152.24 | BN4: 148.49 | BO4: 147.36 | BP4: 146.58 | BQ4: 155.74 | BR4: 156.26 | BS4: 150.9 | BT4: 146.75 | BU4: 154.47 | BV4: 150.96 | BW4: 166.31 | BX4: 167.01 | BY4: 169.9 | BZ4: 170.93 | CA4: 165.4 | CB4: 162.39 | CC4: 168.67 | CD4: 177.18 | CE4: 173.23 | CF4: 171.37 | CG4: 172.72 | CH4: 175.66 | CI4: 174.25 | CJ4: 169.56 | CK4: 168.39 | CL4: 163.65 | CM4: 159.14 | CN4: 157.76 | CO4: 162.51 | CP4: 163 | CQ4: 166.51 | CR4: 164.32 | CS4: 158.73 | CT4: 155.73 | CU4: 155.43 | CV4: 155.77 | CW4: 154.27 | CX4: 154.45 | CY4: 152.78 | CZ4: 153.11 | DA4: 152.28 | DB4: 148.05 | DC4: 144.11 | DD4: 142.56 | DE4: 135.59 | DF4: 133.27 | DG4: 130.35 | DH4: 130.79 | DI4: 132.64 | DJ4: 136.85 | DK4: 136.29 | DL4: 134.2 | DM4: 135.21 | DN4: 136.71 | DO4: 136.57 | DP4: 134.43 | DQ4: 124.9 | DR4: 122.41 | DS4: 126.06 | DT4: 125.48 | DU4: 129.87 | DV4: 125.41 | DW4: 122.69 | DX4: 121.98 | DY4: 125.46 | DZ4: 123.73 | EA4: 122.05 | EB4: 122.31 | EC4: 119.72 | ED4: 125.32 | EE4: 127.68 | EF4: 127.33 | EG4: 128.01 | EH4: 131.35 | EI4: 133.28 | EJ4: 138.59 | EK4: 141.01 | EL4: 140.17 | EM4: 135.38 | EN4: 136.42 | EO4: 131.7 | EP4: 135.82 | EQ4: 132.52 | ER4: 130.85 | ES4: 130.43 | ET4: 131.88 | EU4: 131.5 | EV4: 133.27 | EW4: 132.26 | EX4: 141.44 | EY4: 141 | EZ4: 140.06 | FA4: 137.3 | FB4: 134.78 | FC4: 145.81 | FD4: 141.12 | FE4: 132.59 | FF4: 133.26 | FG4: 135.64 | FH4: 134.47 | FI4: 131.47 | FJ4: 130 | FK4: 129.47 | FL4: 127.76 | FM4: 126.16 | FN4: 124.22 | FO4: 125.4 | FP4: 130.82 | FQ4: 127.21 | FR4: 125.95 | FS4: 121.06 | FT4: 120.07 | FU4: 119.7 | FV4: 115.38 | FW4: 112.69 | FX4: 112.82 | FY4: 112.55 | FZ4: 110.97 | GA4: 107.44 | GB4: 107.1 | GC4: 104.97 | GD4: 102.6 | GE4: 99.8 | GF4: 95.07 | GG4: 94.81 | GH4: 95.51 | GI4: 95.98 | GJ4: 97.99 | GK4: 96.14 | GL4: 97.91 | GM4: 98.14 | GN4: 108.98 | GO4: 111.14 | GP4: 112.33 | GQ4: 112.35 | GR4: 112.32 | GS4: 117.69 | GT4: 117.49 | GU4: 114.97 | GV4: 120.34 | GW4: 117.97 | GX4: 116.56 | GY4: 114.06 | GZ4: 112.14 | HA4: 115 | HB4: 115.19 | HC4: 115.03 | HD4: 116.32 | HE4: 122.25 | HF4: 127.3 | HG4: 128.99 | HH4: 128.53 | HI4: 126.81 | HJ4: 128.41 | HK4: 132.32 | HL4: 127.85 | HM4: 125.22 | HN4: 122.16 | HO4: 123.81 | HP4: 124.71 | HQ4: 128.15 | HR4: 128.9 | HS4: 130.53 | HT4: 119.34 | HU4: 118.47 | HV4: 119.44 | HW4: 119.83 | HX4: 116.31 | HY4: 118.9 | HZ4: 114.02 | IA4: 112.85 | IB4: 111.81 | IC4: 111.81 | ID4: 113.24 | IE4: 112.66 | IF4: 109.4 | IG4: 108.56 | IH4: 109.3 | II4: 109.23 | IJ4: 109.34 | IK4: 107.27 | IL4: 108.54 | IM4: 113.24 | IN4: 115.75 | IO4: 116.31 | IP4: 110.8 | IQ4: 110.63 | IR4: 109.74 | IS4: 108.76
A6: {=_xlfn.STOCKHISTORY(A4&":"&B4,TODAY()-30,TODAY(),0,1,0,5,2,3,4,1)} -> Date | B6: Volume | C6: Open | D6: High | E6: Low | F6: Close
A7: 46265 | B7: 9340068 | C7: 116.67 | D7: 116.8268 | E7: 113.93 | F7: 114.02
A8: 46266 | B8: 9865205 | C8: 112.175 | D8: 113.855 | E8: 112.0655 | F8: 112.85
A9: 46267 | B9: 6875197 | C9: 112.52 | D9: 113.07 | E9: 111.53 | F9: 111.81
A10: 46268 | B10: 8604955 | C10: 110.39 | D10: 112.06 | E10: 109.67 | F10: 111.81
A11: 46269 | B11: 7182522 | C11: 112.37 | D11: 113.41 | E11: 111.97 | F11: 113.24
A12: 46273 | B12: 6965707 | C12: 112.56 | D12: 113.115 | E12: 111.2683 | F12: 112.66
A13: 46274 | B13: 9100923 | C13: 111.69 | D13: 111.8 | E13: 109.39 | F13: 109.4
A14: 46275 | B14: 6572796 | C14: 108.63 | D14: 109.19 | E14: 107.72 | F14: 108.56
A15: 46276 | B15: 4882700 | C15: 109.57 | D15: 110.69 | E15: 109 | F15: 109.3
A16: 46279 | B16: 6946666 | C16: 108.28 | D16: 110.435 | E16: 107.83 | F16: 109.23
A17: 46280 | B17: 6739481 | C17: 109.76 | D17: 111.25 | E17: 109.28 | F17: 109.34
A18: 46281 | B18: 7345873 | C18: 108.6 | D18: 108.63 | E18: 106.64 | F18: 107.27
... A26: 46293 | B26: 5876156 | C26: 109.64 | D26: 110.12 | E26: 108.76 | F26: 108.76

Sheet BAC
A1: Stock | B1: #VALUE!
A3: Exchange abbreviation | B3: Ticker symbol
A4: XNYS | B4: BAC | C4: {=TRANSPOSE(_xlfn.STOCKHISTORY(A4&":"&B4,TODAY()-365,TODAY(),0,0,1))} -> 52.42 | D4: 51.59 | E4: 50.68 | F4: 50.48 | G4: 50.64 | H4: 50.39 | I4: 50.29 | J4: 49.84 | K4: 49.79 | L4: 48.65 | M4: 48.86 | N4: 50.09 | O4: 52.28 | P4: 50.44 | Q4: 51.28 | R4: 52.04 | S4: 51.52 | T4: 51.1 | U4: 51.76 | V4: 52.57 | W4: 53.02 | X4: 52.87 | Y4: 52.58 | Z4: 53.03 | AA4: 53.45 | AB4: 53.56 | AC4: 53.54 | AD4: 52.45 | AE4: 53.29 | AF4: 53.2 | AG4: 53.42 | AH4: 53.63 | AI4: 54.11 | AJ4: 52.87 | AK4: 52.61 | AL4: 51.48 | AM4: 51.64 | AN4: 52.02 | AO4: 51 | AP4: 51.56 | AQ4: 51.93 | AR4: 52.48 | AS4: 52.99 | AT4: 53.65 | AU4: 53.24 | AV4: 53.19 | AW4: 54.09 | AX4: 54.16 | AY4: 53.95 | AZ4: 53.9 | BA4: 53.54 | BB4: 54.08 | BC4: 54.56 | BD4: 55.14 | BE4: 55.33 | BF4: 54.81 | BG4: 54.55 | BH4: 54.26 | BI4: 55.27 | BJ4: 55.88 | BK4: 55.97 | BL4: 56.25 | BM4: 56.17 | BN4: 55.35 | BO4: 55.28 | BP4: 55 | BQ4: 55.95 | BR4: 56.89 | BS4: 57.25 | BT4: 55.64 | BU4: 56.18 | BV4: 55.85 | BW4: 55.19 | BX4: 54.54 | BY4: 52.48 | BZ4: 52.59 | CA4: 52.97 | CB4: 52.1 | CC4: 52.07 | CD4: 52.45 | CE4: 51.72 | CF4: 52.02 | CG4: 52.17 | CH4: 51.81 | CI4: 53.08 | CJ4: 53.2 | CK4: 54.03 | CL4: 54.45 | CM4: 55.38 | CN4: 54.94 | CO4: 56.53 | CP4: 56.41 | CQ4: 55.39 | CR4: 53.85 | CS4: 52.52 | CT4: 52.55 | CU4: 52.74 | CV4: 53.36 | CW4: 52.77 | CX4: 53.06 | CY4: 51.07 | CZ4: 50.41 | DA4: 51.69 | DB4: 52.3 | DC4: 49.83 | DD4: 49.81 | DE4: 49.97 | DF4: 50.3 | DG4: 49.81 | DH4: 48.64 | DI4: 47.9 | DJ4: 48.56 | DK4: 48.52 | DL4: 47.13 | DM4: 46.72 | DN4: 47.06 | DO4: 47.28 | DP4: 46.83 | DQ4: 47.01 | DR4: 47.16 | DS4: 47.52 | DT4: 48.14 | DU4: 48.75 | DV4: 48.24 | DW4: 46.97 | DX4: 47.23 | DY4: 48.75 | DZ4: 49.27 | EA4: 49.38 | EB4: 50.06 | EC4: 50.28 | ED4: 51.88 | EE4: 52.71 | EF4: 52.54 | EG4: 53.35 | EH4: 53.35 | EI4: 54.32 | EJ4: 53.51 | EK4: 53.91 | EL4: 53.95 | EM4: 53.48 | EN4: 53.12 | EO4: 52.47 | EP4: 52.05 | EQ4: 52.63 | ER4: 52.66 | ES4: 52.88 | ET4: 53.46 | EU4: 53.24 | EV4: 52.19 | EW4: 53.12 | EX4: 53.6 | EY4: 52.75 | EZ4: 51.31 | FA4: 50.55 | FB4: 50.78 | FC4: 49.84 | FD4: 49.85 | FE4: 49.77 | FF4: 50.69 | FG4: 50.7 | FH4: 51.23 | FI4: 51.49 | FJ4: 51.8 | FK4: 52.2 | FL4: 51.1 | FM4: 50.77 | FN4: 51.6 | FO4: 51.51 | FP4: 52.48 | FQ4: 52.4 | FR4: 54.17 | FS4: 53.83 | FT4: 53.63 | FU4: 54.42 | FV4: 54.54 | FW4: 55.16 | FX4: 56.02 | FY4: 55.87 | FZ4: 56.84 | GA4: 56.53 | GB4: 56.2 | GC4: 57.37 | GD4: 57.91 | GE4: 57.73 | GF4: 58.19 | GG4: 57.88 | GH4: 57.88 | GI4: 56.98 | GJ4: 58.36 | GK4: 58.73 | GL4: 59.9 | GM4: 59.86 | GN4: 58.3 | GO4: 59.25 | GP4: 59.67 | GQ4: 59.5 | GR4: 60.62 | GS4: 61.59 | GT4: 61.49 | GU4: 61.27 | GV4: 60.42 | GW4: 61.22 | GX4: 61.62 | GY4: 61.28 | GZ4: 62.05 | HA4: 62.13 | HB4: 62.62 | HC4: 61.07 | HD4: 61.73 | HE4: 61.95 | HF4: 62.48 | HG4: 62.9 | HH4: 63.25 | HI4: 63 | HJ4: 63.17 | HK4: 63.86 | HL4: 64 | HM4: 64.81 | HN4: 64.09 | HO4: 64.49 | HP4: 63.89 | HQ4: 64.23 | HR4: 63.17 | HS4: 61.86 | HT4: 61.69 | HU4: 62.33 | HV4: 62.43 | HW4: 62.23 | HX4: 61.17 | HY4: 62.32 | HZ4: 61.94 | IA4: 61.99 | IB4: 62.6 | IC4: 63.04 | ID4: 62.68 | IE4: 62.39 | IF4: 62.67 | IG4: 62.56 | IH4: 62.69 | II4: 59.47 | IJ4: 59.52 | IK4: 57.9 | IL4: 58.18 | IM4: 57.73 | IN4: 57.96 | IO4: 56.2 | IP4: 56 | IQ4: 56.03 | IR4: 56.7 | IS4: 55.47
A6: {=_xlfn.STOCKHISTORY(A4&":"&B4,TODAY()-30,TODAY(),0,1,0,5,2,3,4,1)} -> Date | B6: Volume | C6: Open | D6: High | E6: Low | F6: Close
A7: 46265 | B7: 43470374 | C7: 62.25 | D7: 62.49 | E7: 61.9 | F7: 61.94
A8: 46266 | B8: 25056390 | C8: 61.97 | D8: 62.825 | E8: 61.7235 | F8: 61.99
A9: 46267 | B9: 28435758 | C9: 62.28 | D9: 63.55 | E9: 61.94 | F9: 62.6
A10: 46268 | B10: 29951603 | C10: 62.81 | D10: 63.27 | E10: 62.32 | F10: 63.04
A11: 46269 | B11: 26589402 | C11: 62.56 | D11: 62.9183 | E11: 61.96 | F11: 62.68
A12: 46273 | B12: 28339827 | C12: 62.49 | D12: 62.82 | E12: 62.11 | F12: 62.39
A13: 46274 | B13: 36025057 | C13: 61.97 | D13: 63.19 | E13: 61.425 | F13: 62.67
A14: 46275 | B14: 26478935 | C14: 62.645 | D14: 63.01 | E14: 62.22 | F14: 62.56
A15: 46276 | B15: 25844032 | C15: 63.225 | D15: 63.83 | E15: 62.375 | F15: 62.69
A16: 46279 | B16: 64773953 | C16: 62.335 | D16: 62.435 | E16: 58.92 | F16: 59.47
A17: 46280 | B17: 50667997 | C17: 59.365 | D17: 59.92 | E17: 58.77 | F17: 59.52
A18: 46281 | B18: 50145197 | C18: 59.27 | D18: 59.39 | E18: 57.18 | F18: 57.9
... A26: 46293 | B26: 29170534 | C26: 56.415 | D26: 56.67 | E26: 55.365 | F26: 55.47

Sheet COST
A1: Stock | B1: #VALUE!
A3: Exchange abbreviation | B3: Ticker symbol
A4: XNAS | B4: COST | C4: {=TRANSPOSE(_xlfn.STOCKHISTORY(A4&":"&B4,TODAY()-365,TODAY(),0,0,1))} -> 916.87 | D4: 925.63 | E4: 917.34 | F4: 916.77 | G4: 915.38 | H4: 910.94 | I4: 914.8 | J4: 914.8 | K4: 942.89 | L4: 930.01 | M4: 935.56 | N4: 946.51 | O4: 954.99 | P4: 925.62 | Q4: 936.33 | R4: 936.11 | S4: 937.5 | T4: 944.68 | U4: 942.05 | V4: 932.14 | W4: 929.85 | X4: 924.16 | Y4: 912.42 | Z4: 920.18 | AA4: 911.45 | AB4: 928.04 | AC4: 940.74 | AD4: 935.03 | AE4: 923.58 | AF4: 922.74 | AG4: 915.56 | AH4: 913.86 | AI4: 914 | AJ4: 925.08 | AK4: 922.98 | AL4: 912.59 | AM4: 895.08 | AN4: 890.6 | AO4: 893.29 | AP4: 899.01 | AQ4: 886.12 | AR4: 894.33 | AS4: 908.26 | AT4: 913.59 | AU4: 911.96 | AV4: 922.03 | AW4: 922.26 | AX4: 895.855 | AY4: 894.68 | AZ4: 887.52 | BA4: 888.44 | BB4: 874.41 | BC4: 884.48 | BD4: 884.47 | BE4: 860.56 | BF4: 860.39 | BG4: 862.65 | BH4: 857.59 | BI4: 855.62 | BJ4: 850 | BK4: 854.79 | BL4: 871.86 | BM4: 873.35 | BN4: 867.84 | BO4: 865.65 | BP4: 862.34 | BQ4: 854.5 | BR4: 875.74 | BS4: 889.1 | BT4: 882.58 | BU4: 915.31 | BV4: 924.88 | BW4: 943.08 | BX4: 941.93 | BY4: 950.98 | BZ4: 956.75 | CA4: 963.61 | CB4: 964.26 | CC4: 982.86 | CD4: 976.17 | CE4: 983.25 | CF4: 977.67 | CG4: 970.28 | CH4: 960.78 | CI4: 952.89 | CJ4: 940.25 | CK4: 968.36 | CL4: 977.92 | CM4: 978.35 | CN4: 989.29 | CO4: 1001.16 | CP4: 997.59 | CQ4: 971.23 | CR4: 978.14 | CS4: 998.86 | CT4: 1018.48 | CU4: 1012.05 | CV4: 996.08 | CW4: 987.82 | CX4: 985.27 | CY4: 986.02 | CZ4: 998.43 | DA4: 994.76 | DB4: 986.74 | DC4: 1010.79 | DD4: 1002.77 | DE4: 1007.77 | DF4: 1006.74 | DG4: 982.57 | DH4: 998.1 | DI4: 1005.3 | DJ4: 997.36 | DK4: 992.23 | DL4: 1003.32 | DM4: 1008.43 | DN4: 1001.74 | DO4: 996.16 | DP4: 979.92 | DQ4: 974.78 | DR4: 972.33 | DS4: 965.73 | DT4: 973.82 | DU4: 974.86 | DV4: 979.65 | DW4: 983.86 | DX4: 996.58 | DY4: 996.43 | DZ4: 996.56 | EA4: 1014.96 | EB4: 1018.55 | EC4: 1013.21 | ED4: 1030.27 | EE4: 1032.03 | EF4: 998.47 | EG4: 980.85 | EH4: 974.8 | EI4: 984.75 | EJ4: 987.21 | EK4: 999.89 | EL4: 997.84 | EM4: 1005.81 | EN4: 1003.7 | EO4: 1014.38 | EP4: 1011.15 | EQ4: 998.01 | ER4: 994 | ES4: 998.67 | ET4: 1014.53 | EU4: 1011.7 | EV4: 1012.79 | EW4: 1016.42 | EX4: 995.75 | EY4: 1012.06 | EZ4: 1008.79 | FA4: 999.47 | FB4: 1021.88 | FC4: 1033.08 | FD4: 1041.25 | FE4: 1048.95 | FF4: 1076.47 | FG4: 1094.32 | FH4: 1074.01 | FI4: 1050.45 | FJ4: 1028.24 | FK4: 1002.93 | FL4: 1003.69 | FM4: 995.2 | FN4: 956.32 | FO4: 946.11 | FP4: 954.27 | FQ4: 961.83 | FR4: 972.35 | FS4: 971.87 | FT4: 974.75 | FU4: 968.59 | FV4: 983.37 | FW4: 975.69 | FX4: 982.35 | FY4: 979.45 | FZ4: 986.68 | GA4: 965.59 | GB4: 951.45 | GC4: 951.35 | GD4: 957.68 | GE4: 961.09 | GF4: 942.24 | GG4: 952.54 | GH4: 946.68 | GI4: 935.47 | GJ4: 924.67 | GK4: 951.67 | GL4: 950.25 | GM4: 947.5 | GN4: 953.13 | GO4: 912.97 | GP4: 916.25 | GQ4: 926.43 | GR4: 921.75 | GS4: 916.54 | GT4: 945.57 | GU4: 940.87 | GV4: 935.8 | GW4: 929.22 | GX4: 927.31 | GY4: 926.06 | GZ4: 935.03 | HA4: 951.58 | HB4: 966.58 | HC4: 974.03 | HD4: 954.17 | HE4: 951.89 | HF4: 954.08 | HG4: 947.85 | HH4: 941.99 | HI4: 949.15 | HJ4: 947.82 | HK4: 952.75 | HL4: 944.32 | HM4: 949.575 | HN4: 961.85 | HO4: 961.1 | HP4: 953.5 | HQ4: 961.35 | HR4: 956.99 | HS4: 933.51 | HT4: 947.74 | HU4: 971.4 | HV4: 960.01 | HW4: 956.12 | HX4: 934.66 | HY4: 945.47 | HZ4: 943.89 | IA4: 939.96 | IB4: 928.48 | IC4: 925.41 | ID4: 915.74 | IE4: 910.18 | IF4: 902.6 | IG4: 902.38 | IH4: 904.77 | II4: 918.91 | IJ4: 901.35 | IK4: 893.74 | IL4: 893.93 | IM4: 895.31 | IN4: 898.48 | IO4: 899.41 | IP4: 904.7 | IQ4: 896.48 | IR4: 922.765 | IS4: 922.92
A6: {=_xlfn.STOCKHISTORY(A4&":"&B4,TODAY()-30,TODAY(),0,1,0,5,2,3,4,1)} -> Date | B6: Volume | C6: Open | D6: High | E6: Low | F6: Close
A7: 46265 | B7: 2393041 | C7: 945.19 | D7: 949.3 | E7: 940.71 | F7: 943.89
A8: 46266 | B8: 1508559 | C8: 947.35 | D8: 952.095 | E8: 935.925 | F8: 939.96
A9: 46267 | B9: 2166373 | C9: 938.49 | D9: 938.88 | E9: 920.3101 | F9: 928.48
A10: 46268 | B10: 2172780 | C10: 927.79 | D10: 930.76 | E10: 915.31 | F10: 925.41
A11: 46269 | B11: 2079070 | C11: 926.09 | D11: 928.04 | E11: 914.54 | F11: 915.74
A12: 46273 | B12: 2240323 | C12: 912.4 | D12: 915.13 | E12: 906.1 | F12: 910.18
A13: 46274 | B13: 2067832 | C13: 907 | D13: 909.2299 | E13: 898.43 | F13: 902.6
A14: 46275 | B14: 1921405 | C14: 906.62 | D14: 912.1 | E14: 899 | F14: 902.38
A15: 46276 | B15: 1763239 | C15: 905.17 | D15: 907.3588 | E15: 900.75 | F15: 904.77
A16: 46279 | B16: 2014224 | C16: 913.645 | D16: 921.99 | E16: 910.79 | F16: 918.91
A17: 46280 | B17: 2184182 | C17: 916.92 | D17: 916.92 | E17: 900.25 | F17: 901.35
A18: 46281 | B18: 2101651 | C18: 901.05 | D18: 902 | E18: 892.67 | F18: 893.74
... A26: 46293 | B26: 2443760 | C26: 924.385 | D26: 931.09 | E26: 913 | F26: 922.92

Sheet DELL
A1: Stock | B1: #VALUE!
A3: Exchange abbreviation | B3: Ticker symbol
A4: XNYS | B4: DELL | C4: {=TRANSPOSE(_xlfn.STOCKHISTORY(A4&":"&B4,TODAY()-365,TODAY(),0,0,1))} -> 133.9 | D4: 141.77 | E4: 149.68 | F4: 147.37 | G4: 140.74 | H4: 145.76 | I4: 150.87 | J4: 164.53 | K4: 155.95 | L4: 150.57 | M4: 153.4 | N4: 148.77 | O4: 153.7 | P4: 151.31 | Q4: 149.59 | R4: 147.87 | S4: 149.43 | T4: 150.13 | U4: 154.23 | V4: 158.64 | W4: 162.19 | X4: 164.88 | Y4: 163.6 | Z4: 161.01 | AA4: 162.01 | AB4: 160.11 | AC4: 154.64 | AD4: 152.41 | AE4: 149.18 | AF4: 146.7 | AG4: 142.69 | AH4: 138.76 | AI4: 140.71 | AJ4: 133.94 | AK4: 133.76 | AL4: 122.48 | AM4: 122.69 | AN4: 119.38 | AO4: 117.4 | AP4: 122.51 | AQ4: 127.22 | AR4: 125.92 | AS4: 133.26 | AT4: 133.35 | AU4: 132.09 | AV4: 135.95 | AW4: 133.63 | AX4: 138.99 | AY4: 138.91 | AZ4: 140.41 | BA4: 138.22 | BB4: 140.63 | BC4: 138.6 | BD4: 129.98 | BE4: 130.51 | BF4: 133.75 | BG4: 127.89 | BH4: 122.94 | BI4: 126.42 | BJ4: 126.61 | BK4: 127.62 | BL4: 128.38 | BM4: 129.24 | BN4: 127.46 | BO4: 127.92 | BP4: 125.88 | BQ4: 127.8 | BR4: 124.01 | BS4: 123.93 | BT4: 120.07 | BU4: 118.5 | BV4: 120.62 | BW4: 120.47 | BX4: 119.66 | BY4: 118.69 | BZ4: 119.66 | CA4: 120.53 | CB4: 111.07 | CC4: 113.26 | CD4: 117.17 | CE4: 115.43 | CF4: 115.93 | CG4: 114.66 | CH4: 117.32 | CI4: 118.49 | CJ4: 114.44 | CK4: 119.16 | CL4: 117.15 | CM4: 122.04 | CN4: 115.39 | CO4: 121.05 | CP4: 120.91 | CQ4: 126.01 | CR4: 124.16 | CS4: 112.82 | CT4: 117.49 | CU4: 116.09 | CV4: 116.78 | CW4: 119.06 | CX4: 122.27 | CY4: 119.14 | CZ4: 119.78 | DA4: 123.48 | DB4: 121.45 | DC4: 148.08 | DD4: 153.55 | DE4: 145.18 | DF4: 147.1 | DG4: 146.52 | DH4: 146.48 | DI4: 146.51 | DJ4: 143.8 | DK4: 147.37 | DL4: 149.91 | DM4: 151.62 | DN4: 156.54 | DO4: 153.01 | DP4: 149.21 | DQ4: 156.76 | DR4: 157.67 | DS4: 164.59 | DT4: 176.91 | DU4: 184.01 | DV4: 175.82 | DW4: 171.81 | DX4: 164.66 | DY4: 164.13 | DZ4: 169.38 | EA4: 174.37 | EB4: 173.18 | EC4: 177.69 | ED4: 185.47 | EE4: 181.46 | EF4: 177.8 | EG4: 189.79 | EH4: 184.51 | EI4: 177.28 | EJ4: 193.09 | EK4: 196.55 | EL4: 204.24 | EM4: 212.36 | EN4: 214.65 | EO4: 212.14 | EP4: 216.09 | EQ4: 215.97 | ER4: 205.93 | ES4: 205.66 | ET4: 208.95 | EU4: 210.17 | EV4: 211.64 | EW4: 216.32 | EX4: 238.8 | EY4: 230.27 | EZ4: 260.46 | FA4: 247.04 | FB4: 238.94 | FC4: 243.87 | FD4: 247.89 | FE4: 241.99 | FF4: 238.03 | FG4: 235.26 | FH4: 242.93 | FI4: 252.8 | FJ4: 295.19 | FK4: 305.08 | FL4: 305.32 | FM4: 317.05 | FN4: 420.91 | FO4: 465.96 | FP4: 435.31 | FQ4: 421.08 | FR4: 422.05 | FS4: 394.39 | FT4: 400.77 | FU4: 381.78 | FV4: 369.83 | FW4: 391.45 | FX4: 395.57 | FY4: 409.07 | FZ4: 404.08 | GA4: 419.32 | GB4: 409.5 | GC4: 418.71 | GD4: 427.78 | GE4: 434.06 | GF4: 409.45 | GG4: 399.49 | GH4: 414.61 | GI4: 431.46 | GJ4: 425.25 | GK4: 394.32 | GL4: 411.8 | GM4: 417.28 | GN4: 431.97 | GO4: 450.22 | GP4: 434.97 | GQ4: 427.11 | GR4: 457.54 | GS4: 412.68 | GT4: 391.38 | GU4: 396.34 | GV4: 381.88 | GW4: 404.15 | GX4: 441.8 | GY4: 439.34 | GZ4: 437.5 | HA4: 426.91 | HB4: 392.1 | HC4: 369.64 | HD4: 404.81 | HE4: 405.37 | HF4: 429.02 | HG4: 467.27 | HH4: 462.7 | HI4: 437.65 | HJ4: 453.77 | HK4: 457.88 | HL4: 440.97 | HM4: 484.5 | HN4: 494.51 | HO4: 490.81 | HP4: 479.81 | HQ4: 468.65 | HR4: 437.55 | HS4: 434.78 | HT4: 442.08 | HU4: 433.19 | HV4: 451.5 | HW4: 463.82 | HX4: 472.26 | HY4: 456.24 | HZ4: 456.01 | IA4: 425 | IB4: 492.2 | IC4: 516.39 | ID4: 524.14 | IE4: 533.88 | IF4: 535.25 | IG4: 506.62 | IH4: 567.29 | II4: 534.28 | IJ4: 543.51 | IK4: 563.29 | IL4: 588.4 | IM4: 568.06 | IN4: 575.31 | IO4: 548.92 | IP4: 549.83 | IQ4: 536.02 | IR4: 562.89 | IS4: 543.43
A6: {=_xlfn.STOCKHISTORY(A4&":"&B4,TODAY()-30,TODAY(),0,1,0,5,2,3,4,1)} -> Date | B6: Volume | C6: Open | D6: High | E6: Low | F6: Close
A7: 46265 | B7: 7686469 | C7: 459.85 | D7: 474.49 | E7: 456.01 | F7: 456.01
A8: 46266 | B8: 15947971 | C8: 455.69 | D8: 463 | E8: 421.8901 | F8: 425
A9: 46267 | B9: 36720176 | C9: 462.05 | D9: 497.9899 | E9: 432.2651 | F9: 492.2
A10: 46268 | B10: 20327994 | C10: 486.31 | D10: 530.78 | E10: 478.3064 | F10: 516.39
A11: 46269 | B11: 11118744 | C11: 513.78 | D11: 534.99 | E11: 510.15 | F11: 524.14
A12: 46273 | B12: 6662471 | C12: 521.15 | D12: 538.47 | E12: 515.5601 | F12: 533.88
A13: 46274 | B13: 7282344 | C13: 538.47 | D13: 562.9899 | E13: 532.3926 | F13: 535.25
A14: 46275 | B14: 5796790 | C14: 523.825 | D14: 530.51 | E14: 506.25 | F14: 506.62
A15: 46276 | B15: 14309811 | C15: 518.07 | D15: 567.75 | E15: 517.515 | F15: 567.29
A16: 46279 | B16: 9173770 | C16: 538.57 | D16: 546.29 | E16: 525.85 | F16: 534.28
A17: 46280 | B17: 9566824 | C17: 541.55 | D17: 568.67 | E17: 539 | F17: 543.51
A18: 46281 | B18: 13108085 | C18: 553.625 | D18: 576.75 | E18: 550.09 | F18: 563.29
