Workbook

Sheet Skills Matrix
A1: QUANTITATIVE FINANCE SKILLS MATRIX
A2: Technical Competencies Demonstrated in Portfolio Analytics Platform
A4: # | B4: Skill / Competency | C4: Category | D4: CFA Alignment | E4: Implementation | F4: Sheet Reference
A5: 1 | B5: Transaction Ledger with Data Validation | C5: Data Management | D5: Level I — Quant Methods | E5: Structured tables, drop-down controls, non-negative constraints | F5: Ledger
A6: 2 | B6: Tax-Aware Holding Period Tracking | C6: Tax Management | D6: Level I — Tax & Estate | E6: MAXIFS for lot matching, ST/LT gain classification per IRS §1222 | F6: Ledger I:J
A7: 3 | B7: Linked Data Type Integration | C7: Data Engineering | D7: Level I — Equity Investments | E7: Excel Stock entities, .Price, .Beta, .Industry dot-notation | F7: Ledger, Dashboard
A8: 4 | B8: Dynamic Array Portfolio Construction | C8: Portfolio Mgmt | D8: Level III — Portfolio Mgmt | E8: SORT(UNIQUE()) with INDEX/MATCH entity resolution | F8: Dashboard B7
A9: 5 | B9: Market-Cap Weighted Returns | C9: Performance | D9: Level I — Portfolio Mgmt | E9: SUMIF/SUMPRODUCT for weighted aggregation | F9: Dashboard F7:I22
A10: 6 | B10: CAPM Implementation | C10: Asset Pricing | D10: Level I — Corporate Finance | E10: Rf + β(Rm−Rf) with live beta from linked data types | F10: Risk Analytics
A11: 7 | B11: Jensen's Alpha (α) | C11: Performance Attr | D11: Level II — Equity Valuation | E11: α = Rp − [Rf + β(Rm−Rf)], portfolio-level excess return | F11: Risk Analytics C11
A12: 8 | B12: Sharpe Ratio | C12: Risk-Adjusted Perf | D12: Level I — Portfolio Mgmt | E12: (Rp−Rf)/σp — excess return per unit total risk | F12: Risk Analytics C18
A13: 9 | B13: Sortino Ratio | C13: Risk-Adjusted Perf | D13: Level II — Portfolio Mgmt | E13: (Rp−Rf)/Downside σ — penalises harmful volatility only | F13: Risk Analytics C19
A14: 10 | B14: Treynor Ratio | C14: Risk-Adjusted Perf | D14: Level II — Portfolio Mgmt | E14: (Rp−Rf)/β — excess return per unit systematic risk | F14: Risk Analytics C15
A15: 11 | B15: Information Ratio | C15: Active Mgmt | D15: Level III — Performance Eval | E15: α / Tracking Error — active return per unit active risk | F15: Risk Analytics C16
A16: 12 | B16: Calmar Ratio | C16: Hedge Fund Metrics | D16: Level III — Alternatives | E16: CAGR / |Max Drawdown| — return per unit worst-case loss | F16: Risk Analytics C20
... A34: 30 | B34: Cross-Sheet Validation Framework | C34: Model Integrity | D34: CFA Ethics — Diligence | E34: 23 automated consistency checks, tolerance-based assertions | F34: Validation
A36: PROFICIENCY SUMMARY
A37: Category | B37: Count | C37: CFA Level | D37: Depth
A38: Risk Management | B38: 6 | C38: Level II–III | D38: Advanced
A39: Risk-Adjusted Performance | B39: 5 | C39: Level I–III | D39: Comprehensive
A40: Portfolio Management | B40: 5 | C40: Level I–III | D40: Advanced
A41: Active Management | B41: 2 | C41: Level III | D41: Institutional
A42: Data Engineering | B42: 3 | C42: Level I | D42: Applied
A43: Asset Pricing & Attribution | B43: 3 | C43: Level I–II | D43: Core
A44: Factor Investing & Optimization | B44: 3 | C44: Level II–III | D44: Graduate
A45: Model Integrity & Validation | B45: 3 | C45: Level I–Ethics | D45: Professional
A47: VBA MACRO CODE (Copy to VBA Editor: Alt+F11 → Insert Module)
A48: Sub RefreshAllData() Application.CalculateFull Dim ws As Worksheet For Each ws In ThisWorkbook.Worksheets ws.UsedRange.Calculate Next ws MsgBox "All data refreshed.", vbInformation End Sub
A50: Sub ExportDashboardPDF() Dim ws As Worksheet: Set ws = Sheets("Dashboard") Dim fPath As String fPath = Application.GetSaveAsFilename("Portfolio_Dashboard", "PDF Files (*.pdf),*.pdf") If fPath <> "False" Then ws.ExportAsFixedFormat xlTypePDF, fPath, xlQualityStandard MsgBox "Dashboard exported to: " & fPath, vbInformation End If End Sub

Sheet README
A1: 📊 STOCK PORTFOLIO TRACKER & QUANTITATIVE ANALYTICS ENGINE
A2: An institutional-grade Excel-based portfolio analytics platform featuring CAPM, Black-Litterman optimization, Cornish-Fisher VaR, and multi-factor risk decomposition
A4: 🎯 PROJECT OVERVIEW
A5: Objective | B5: Build a production-quality stock portfolio analytics system demonstrating mastery of quantitative finance, risk management, and portfolio optimization - spanning CFA Level I–III curriculum concepts including CAPM, Black-Litterman, Cornish-Fisher VaR, multi-factor attribution, and tax-aware rebalancing.
A6: Scope | B6: 16 stocks across 10 GICS industries, tracked over 7 years (2019–2025) with 112 Buy/Sell transactions. Live market data via Excel Linked Data Types, automated P&L, risk decomposition, stress testing, and Bayesian portfolio optimization.
A7: Investment Strategy | B7: Long-only equity portfolio with systematic $10K annual allocation. 35% Technology, 20% Financials, 45% diversified sectors. Volatility-scaled rebalancing bands replace static thresholds. Tax-aware lot matching per IRS §1222.
A8: Data Sources | B8: Excel Linked Data Types (Stocks) for live prices, beta, industry, P/E. STOCKHISTORY for 12-month sparklines. CFA curriculum-aligned risk-free rate (US 10Y Treasury 4.25%), equity risk premium (5.75%), and market volatility (σm ≈ 15.5%).
A10: WORKBOOK STRUCTURE
A11: Sheet Name | B11: Description
A12: Dashboard | B12: Primary portfolio dashboard with dual-row KPI strip (Portfolio Value, CAGR, Sharpe, Sortino, Alpha, M², Treynor, Calmar, CF VaR), live prices via Linked Data Types, 16-stock analytics table, sector allocation, volatility-scaled rebalancing with tax flags, 3 embedded charts, and auto-refreshing narrative insight summary.
A13: Analytics | B13: Deeper per-stock analytics: individual CAGR, return attribution, cost basis breakdown, risk scores, and annualized return metrics. Mirrors Dashboard data with extended detail.
A14: Ledger | B14: Transaction ledger: 112 records, 16 stocks, 7 years. Includes Holding Period (MAXIFS lot matching) and Tax Status (LT/ST classification per IRS §1222). Data validation on Price (≥0), Units (≥0), and Transaction Type (Buy/Sell dropdown).
A15: Watchlist | B15: Competitor analysis: 10 rival stocks with live data, 52-week ranges, beta, P/E, market cap.
A16: Risk Analytics | B16: Comprehensive risk analytics: CAPM (Rf, Rm, ERP, βp), 6 performance ratios (Sharpe, Sortino, Treynor, IR, Calmar, M²), Parametric VaR (95%/99%), Cornish-Fisher VaR (skew/kurtosis-adjusted), Historical VaR, Expected Shortfall (CVaR), Drawdown Analysis (Max DD, Ulcer Index), Stress Testing (VIX, Tech, Rates), 16-stock risk decomposition with data-bar heatmaps, Fama-French style factors, and Capital Market Line positioning.
A17: WL Dashboard | B17: Watchlist scoring model: multi-factor evaluation (P/E, Beta, 52-week range, margin of safety) with composite rankings and entry-point signals.
A18: Validation | B18: Automated CFA-grade integrity tests: weight summation, P&L identity, HHI consistency, CAPM internal consistency, cross-sheet beta/Sharpe/Treynor reconciliation. 23 tests with real-time pass/fail status.
A19: Optimization | B19: Black-Litterman portfolio optimization: Bayesian framework combining market equilibrium priors (δ=2.5, τ=0.05) with investor views. 16-stock implied equilibrium returns, BL optimal weights, 5-slot view input panel (confidence-weighted), and dollar-denominated trade list with BUY/SELL/HOLD actions.
A20: Skills Matrix | B20: Recruiter-ready competency matrix: 30 quantitative finance skills mapped to CFA Level I–III curriculum, with implementation details and sheet references. 8-category proficiency summary. VBA macro code for data refresh and PDF export.
A21: Sparkline | B21: Price history data feeding Dashboard sparkline trend visualizations.
A22: Stock Sheets | B22: Individual stock deep-dives with STOCKHISTORY price series and charts.
A24: KEY FORMULAS & TECHNIQUES
A25: Technique | B25: Implementation
A26: Dynamic Arrays | B26: SORT, UNIQUE, FILTER, SORTBY with spill ranges for automatic data propagation
A27: Linked Data Types | B27: Excel Stocks data type with dot notation for real-time market data integration
A28: STOCKHISTORY | B28: Historical price series retrieval for sparklines and stock analysis sheets
A29: SUMIF / COUNTIF | B29: Cross-sheet aggregation for transaction totals and sector-level rollups from Ledger
A30: INDEX / MATCH | B30: Best and worst performer identification with dynamic lookups across spill ranges
A31: CAGR Formula | B31: Annualised return: (Ending Value / Beginning Value) ^ (1 / Years) - 1
A32: HHI Index | B32: Sum of squared sector weights to quantify portfolio concentration risk
A33: Conditional Formatting | B33: Automated color coding for negative/positive values with emoji risk indicators
A34: Allocation Model | B34: Weighted allocation with sector caps (Tech max 35%) and systematic Buy/Sell rules
A35: CAPM | B35: E(Ri) = Rf + βi(Rm − Rf). Capital Asset Pricing Model for expected returns. Jensen’s Alpha = Rp − E(Rp). Live betas from Linked Data Types.
A36: Cornish-Fisher VaR | B36: VaR adjusted for skewness (S) and kurtosis (K): z_cf = z + (z²−1)S/6 + (z³−3z)K/24 − (2z³−5z)S²/36. Per Jorion (2007), Maillard (2012).
... A44: Data Bar Heatmaps | B44: Conditional formatting data bars on risk decomposition table: Beta (red scale), Alpha (green/red), CAGR (blue), Weight (yellow for concentration). Visual risk identification.
A46: SKILLS DEMONSTRATED
A47: Category | B47: Skills
A48: Financial Modelling | B48: Portfolio construction, P&L tracking, CAGR analysis, 6 risk-adjusted performance metrics (Sharpe, Sortino, Treynor, IR, Calmar, M²), CAPM implementation, Jensen’s Alpha, Black-Litterman optimization
A49: Data Engineering | B49: Dynamic arrays (SORT, UNIQUE, FILTER), Linked Data Types with dot notation, structured table references, cross-sheet data pipelines, STOCKHISTORY integration, INDEX/MATCH entity resolution
A50: Risk Analysis | B50: CAPM, Parametric VaR (95%/99%), Cornish-Fisher adjusted VaR, Historical VaR, CVaR/Expected Shortfall, drawdown analysis, Ulcer Index, stress testing (3 scenarios), factor decomposition, CML analysis
A51: Dashboard Design | B51: Dual-row KPI strip with 14 metrics, conditional formatting data bars, doughnut/bar/scatter charts, emoji-coded signals, auto-refreshing narrative summary, professional #2D4A7A/#1E3A5F color system
A52: Data Visualisation | B52: Doughnut (sector allocation), clustered bar (returns), XY scatter (risk-return), data-bar heatmaps (beta, alpha, CAGR, weight), sparklines (12-month price history)
A53: Domain Knowledge | B53: GICS sector classification, IRS §1222 (ST/LT capital gains), CFA Level I–III curriculum alignment, stock market mechanics, Buy/Sell transaction modelling, tax-efficient rebalancing
A54: Portfolio Optimization | B54: Black-Litterman Bayesian framework, equilibrium implied returns, confidence-weighted investor views, BL posterior weights, dollar-denominated trade generation
A55: Tax & Compliance | B55: MAXIFS lot matching for holding period calculation, IRS short-term/long-term classification, tax-flag integration in rebalancing signals, data validation controls
A56: Model Integrity | B56: 23 automated validation tests (all passing), cross-sheet consistency checks (CAGR, beta, Sharpe, Treynor, CAPM), tolerance-based assertions, real-time audit trail
A57: Quantitative Methods | B57: Cornish-Fisher expansion (skewness/kurtosis adjustment), Fama-French factor classification, Active Share, HHI concentration, volatility-scaled thresholds, Capital Market Line positioning
A59: HOW TO USE
A60: 1. Enable Data Types | B60: Ensure Excel is connected to the internet. The Stocks linked data types in the Ledger and Dashboard require a Microsoft 365 subscription.
A61: 2. Review Dashboard | B61: The Dashboard auto-updates with live prices. Check KPI cards at top for portfolio summary, stock table for details, and sector breakdown below.
A62: 3. Explore Analytics | B62: The Analytics sheet provides deeper metrics: per-stock returns, sector HHI, risk flags, and allocation charts.
A63: 4. Monitor Watchlist | B63: Track competitor stocks with live data. Use this for benchmarking and identifying new investment opportunities.
A64: 5. Add Transactions | B64: Add new rows to the Ledger table. All Dashboard and Analytics formulas auto-update via structured references.
A65: 6. Analyse Risk | B65: Risk Analytics contains CAPM, VaR (3 methods), stress tests, and 16-stock decomposition. Review the Cornish-Fisher VaR for fat-tail risk and stress scenarios for tail events.
A66: 7. Run Optimization | B66: The Optimization sheet runs a Black-Litterman model. Add your views (e.g. 'NVDA will return 25%' with 70% confidence) in the Views table, then review the Trade List for suggested portfolio adjustments.
A67: 8. Review Validation | B67: The Validation sheet runs 23 automated tests covering data integrity, risk metric reasonableness, and cross-sheet consistency. All should show ✅ PASS. Any ❌ FAIL indicates a data issue to investigate.
A69: 📝 VERSION HISTORY
A70: Version | B70: Changes
A71: v1.0 — Initial Release | B71: Dashboard with KPI strip, Analytics, Ledger (112 transactions), Watchlist, Risk Analytics (CAPM, basic VaR), Sparklines, Stock Sheets, WL Dashboard, Validation (16 tests). Known issue: #VALUE! cascade from SORT(UNIQUE(Ledger[Stock])) on Linked Data Types.
A72: v2.0 — Quant Upgrade | B72: CRITICAL FIX: Resolved #VALUE! cascade — rewrote B7 to SORT(UNIQUE(Ledger[Ticker])) with INDEX/MATCH entity resolution for all dot-notation properties. All 16 stocks now display correctly.
B73: NEW: Ledger enhanced with Holding Period (MAXIFS lot matching) and Tax Status (IRS §1222 LT/ST classification) columns. Data validation on Price (≥0), Units (≥0), Transaction Type (dropdown).
B74: NEW: Risk Analytics expanded — Cornish-Fisher VaR (skew/kurtosis-adjusted), Historical VaR, CVaR/Expected Shortfall, Drawdown Analysis (Max DD, Ulcer Index), 3 Stress Test scenarios (VIX, Tech, Rates), data-bar heatmaps on risk decomposition.
B75: NEW: Optimization sheet — Black-Litterman portfolio optimization with equilibrium implied returns, 5-slot investor view panel, BL posterior weights, dollar-denominated trade list.
B76: NEW: Dashboard recruiter KPI strip (row 4) with Sortino, IR, Active Share, Alpha, M², Treynor, Calmar, CF VaR. Vol-scaled rebalancing bands (±0.5×βi×σm) with tax flags replacing static 3%/10% thresholds.
B77: NEW: 3 Dashboard charts (Sector Allocation doughnut, Returns bar, Risk-Return scatter). Auto-refreshing narrative insight formula. Skills Matrix sheet (30 CFA-mapped competencies).
B78: FIXED: Validation expanded from 16 to 23 tests (added cross-sheet CAPM consistency, beta/Sharpe/Treynor reconciliation, risk decomposition weight sum). All 23 passing.
A80: 📚 ACADEMIC REFERENCES & CFA ALIGNMENT
A81: Topic | B81: Source
A82: CAPM | B82: Sharpe, W.F. (1964). “Capital Asset Prices.” Journal of Finance. — CFA Level I: Corporate Finance, Portfolio Management
A83: Black-Litterman Model | B83: Black, F. & Litterman, R. (1992). “Global Portfolio Optimization.” Financial Analysts Journal. He, G. & Litterman, R. (1999). “The Intuition Behind BL.” Goldman Sachs. — CFA Level III
A84: Cornish-Fisher VaR | B84: Jorion, P. (2007). “Value at Risk.” 3rd ed., McGraw-Hill. Maillard, D. (2012). “A User’s Guide to the CF Expansion.” — CFA Level III: Risk Management
A85: Expected Shortfall | B85: Acerbi, C. & Tasche, D. (2002). “On the Coherence of ES.” Journal of Banking & Finance. Basel III FRTB (2019). — CFA Level III: Risk Management
A86: Sortino & Downside Risk | B86: Sortino, F. & Price, L. (1994). “Performance Measurement in a Downside Risk Framework.” Journal of Investing. — CFA Level II: Portfolio Management
A87: Vol-Scaled Rebalancing | B87: Kritzman, M. & Page, S. (2009). “Optimal Rebalancing.” Journal of Portfolio Management. — CFA Level III: Portfolio Management
A88: Fama-French Factors | B88: Fama, E. & French, K. (1993). “Common Risk Factors in Returns on Stocks and Bonds.” Journal of Financial Economics. — CFA Level II: Equity
A89: Drawdown & Ulcer Index | B89: Martin, P. (1987). “The Investor’s Guide to Fidelity Funds.” Magdon-Ismail, M. et al. (2004). “On the Maximum Drawdown.” — CFA Level III: Alternatives
A90: Modigliani-Modigliani | B90: Modigliani, F. & Modigliani, L. (1997). “Risk-Adjusted Performance.” Journal of Portfolio Management. — CFA Level II: Portfolio Management
A93: Built with Microsoft Excel 365 | Dynamic Arrays | Linked Data Types | CAPM | Black-Litterman | Cornish-Fisher VaR | 23 Validation Tests | 30 Quantitative Skills

Sheet Validation
A1: PORTFOLIO VALIDATION TESTS
A2: Automated integrity checks · Audit framework · Real-time validation
A4: DATA INTEGRITY CHECKS
A5: Test | B5: Expected | C5: Actual | D5: Status | E5: Notes
A6: Portfolio weights sum to 100% | B6: 1 | C6: =SUM(Dashboard!M7:M22) -> 1 | D6: =IF(ABS(C6-1)<0.001,"✅ PASS","❌ FAIL") -> ✅ PASS | E6: Sum of all portfolio weights must equal 100%
A7: Total MV = Sum of holdings MV | B7: =Dashboard!B3 -> 303680.39 | C7: =SUM(Dashboard!G7:G22) -> 303680.39 | D7: =IF(ABS(B7-C7)<1,"✅ PASS","❌ FAIL") -> ✅ PASS | E7: Portfolio value KPI matches sum of individual market values
A8: Cost basis consistency | B8: =Dashboard!E3 -> 132051.42 | C8: =SUM(Dashboard!O7:O22) -> 132051.42 | D8: =IF(ABS(B8-C8)<1,"✅ PASS","❌ FAIL") -> ✅ PASS | E8: Portfolio cost basis KPI matches sum of per-stock cost bases
A9: P&L identity: MV - CB = Unrealised P&L | B9: =Dashboard!F3 -> 171628.96 | C9: =Dashboard!B3-Dashboard!E3 -> 171628.96 | D9: =IF(ABS(B9-C9)<1,"✅ PASS","❌ FAIL") -> ✅ PASS | E9: Accounting identity: Unrealised P&L = Market Value − Cost Basis
A10: Unique stock count matches | B10: 16 | C10: =COUNTA(Dashboard!B7:B22) -> 16 | D10: =IF(B10=C10,"✅ PASS","❌ FAIL") -> ✅ PASS | E10: Dashboard shows all 16 unique stocks from Ledger
A11: Sector allocation weights sum to 100% | B11: 1 | C11: =SUM(Dashboard!E30:E39) -> 1 | D11: =IF(ABS(C11-1)<0.001,"✅ PASS","❌ FAIL") -> ✅ PASS | E11: Sector allocation must sum to 100%
A12: HHI consistency (Dashboard vs Analytics) | B12: =Dashboard!K3 -> 0.18756228 | C12: =Dashboard!L25 -> 0.18756228 | D12: =IF(ABS(B12-C12)<0.001,"✅ PASS","❌ FAIL") -> ✅ PASS | E12: HHI Index must be identical between KPI strip and bottom KPIs
A13: HHI = sum of sector squared weights | B13: =Dashboard!K3 -> 0.18756228 | C13: =SUM(Dashboard!F30:F39) -> 0.18756228 | D13: =IF(ABS(B13-C13)<0.001,"✅ PASS","❌ FAIL") -> ✅ PASS | E13: HHI = Σ(wi²) from sector allocation table
A14: Win rate consistency | B14: =Dashboard!P3 -> 0.875 | C14: =COUNTIF(Dashboard!J7:J22,">0")/COUNTA(Dashboard!J7:J22) -> 0.875 | D14: =IF(ABS(B14-C14)<0.001,"✅ PASS","❌ FAIL") -> ✅ PASS | E14: Win rate KPI matches manual count of profitable holdings
A15: Rebalancing equal weights = 1/N | B15: =1/16 -> 0.0625 | C15: =Dashboard!J30 -> 0.0625 | D15: =IF(ABS(B15-C15)<0.001,"✅ PASS","❌ FAIL") -> ✅ PASS | E15: Equal weight target = 1/N = 6.25% for 16 stocks
A16: Sector MV = sum of stock MVs per sector | B16: =Dashboard!B3 -> 303680.39 | C16: =SUM(Dashboard!D30:D39) -> 303680.39 | D16: =IF(ABS(B16-C16)<1,"✅ PASS","❌ FAIL") -> ✅ PASS | E16: Sum of sector market values equals total portfolio market value
A18: RISK METRIC CHECKS
A19: Test | B19: Expected Range | C19: Actual | D19: Status | E19: CFA Framework
A20: Sharpe Ratio in valid range | B20: -3.0 to 5.0 | C20: =Dashboard!O3 -> 0.46593002 | D20: =IF(AND(C20>=-3,C20<=5),"✅ PASS","⚠️ CHECK") -> ✅ PASS | E20: Sharpe = (Rp−Rf)/σp; typical range -3 to 5 for diversified portfolios
A21: Portfolio Beta reasonable | B21: 0.3 to 2.5 | C21: =Dashboard!S3 -> 1.4726694 | D21: =IF(AND(C21>=0.3,C21<=2.5),"✅ PASS","⚠️ CHECK") -> ✅ PASS | E21: βp = Σ(wi×βi); 0.3-2.5 typical for equity-only portfolio
A22: Treynor Ratio valid | B22: -0.5 to 1.0 | C22: =Dashboard!T3 -> 0.072219153 | D22: =IF(AND(C22>=-0.5,C22<=1),"✅ PASS","⚠️ CHECK") -> ✅ PASS | E22: Treynor = (Rp−Rf)/βp; measures excess return per unit systematic risk
A23: Worst stock return ≤ 0 | B23: ≤ 0% | C23: =Dashboard!R3 -> -0.13381728 | D23: =IF(C23<=0,"✅ PASS","❌ FAIL") -> ✅ PASS | E23: Max drawdown must be negative or zero (worst single-stock return)
A24: Calmar Ratio positive (if CAGR positive) | B24: > 0 | C24: =Dashboard!S25 -> 1.1123746 | D24: =IF(C24>0,"✅ PASS","⚠️ CHECK") -> ✅ PASS | E24: Calmar = CAGR/|Max DD|; positive when portfolio has positive CAGR
A26: SUMMARY
A27: Tests Passed | B27: Tests Failed | C27: Tests Warning | D27: Overall Score
A28: =COUNTIF(D6:D16,"✅*")+COUNTIF(D20:D24,"✅*")+COUNTIF(D32:D38,"✅*") -> 23 | B28: =COUNTIF(D6:D16,"❌*")+COUNTIF(D20:D24,"❌*")+COUNTIF(D32:D38,"❌*") -> 0 | C28: =COUNTIF(D6:D16,"⚠️*")+COUNTIF(D20:D24,"⚠️*")+COUNTIF(D32:D38,"⚠️*") -> 0 | D28: =IF(B28=0,IF(C28=0,"✅ ALL PASS","⚠️ WARNINGS"),"❌ FAILURES") -> ✅ ALL PASS
A30: CROSS-SHEET CONSISTENCY CHECKS
A31: Test | B31: Sheet A | C31: Sheet B | D31: Status | E31: Detail
A32: CAGR: Dashboard ↔ Analytics | B32: =Dashboard!H3 -> 0.14885493 | C32: =Analytics!E6 -> 0.14885493 | D32: =IF(ABS(B32-C32)<0.0001,"✅ PASS","❌ FAIL") -> ✅ PASS | E32: Portfolio CAGR must match across Dashboard and Analytics
A33: Beta: Dashboard ↔ Risk Analytics | B33: =Dashboard!S3 -> 1.4726694 | C33: ='Risk Analytics'!C9 -> 1.4726694 | D33: =IF(ABS(B33-C33)<0.001,"✅ PASS","❌ FAIL") -> ✅ PASS | E33: Weighted portfolio beta must match between Dashboard KPI and Risk Analytics
A34: Sharpe: Dashboard ↔ Risk Analytics | B34: =Dashboard!O3 -> 0.46593002 | C34: ='Risk Analytics'!C18 -> 0.46593002 | D34: =IF(ABS(B34-C34)<0.001,"✅ PASS","❌ FAIL") -> ✅ PASS | E34: Sharpe Ratio must match between Dashboard KPI and Risk Analytics
A35: Treynor: Dashboard ↔ Risk Analytics | B35: =Dashboard!T3 -> 0.072219153 | C35: ='Risk Analytics'!C15 -> 0.072219153 | D35: =IF(ABS(B35-C35)<0.0001,"✅ PASS","❌ FAIL") -> ✅ PASS | E35: Treynor Ratio must match between Dashboard and Risk Analytics
A36: CAPM: E(Rp) = Rf + βp(Rm-Rf) | B36: ='Risk Analytics'!C10 -> 0.12717849 | C36: ='Risk Analytics'!C6+'Risk Analytics'!C9*('Risk Analytics'!C7-'Risk Analytics'!C6) -> 0.12717849 | D36: =IF(ABS(B36-C36)<0.0001,"✅ PASS","❌ FAIL") -> ✅ PASS | E36: CAPM expected return formula: Rf + βp × ERP must be internally consistent
A37: Jensen's α = Rp - E(Rp) | B37: ='Risk Analytics'!C11 -> 0.021676445 | C37: =Analytics!E6-'Risk Analytics'!C10 -> 0.021676445 | D37: =IF(ABS(B37-C37)<0.0001,"✅ PASS","❌ FAIL") -> ✅ PASS | E37: Alpha = Actual CAGR minus CAPM expected return
A38: Risk decomp weights sum to 100% | B38: 1 | C38: ='Risk Analytics'!C55 -> 1 | D38: =IF(ABS(C38-1)<0.001,"✅ PASS","❌ FAIL") -> ✅ PASS | E38: Stock weights in risk decomposition table must sum to 100%

Sheet Optimization
A1: BLACK-LITTERMAN PORTFOLIO OPTIMIZATION
A2: Bayesian framework combining market equilibrium with investor views — Black & Litterman (1992), Goldman Sachs
A4: MODEL PARAMETERS
A5: Parameter | B5: Value | C5: Description
A6: Risk-Free Rate (Rf) | B6: ='Risk Analytics'!C6 -> 0.0425 | C6: Linked from Risk Analytics
A7: Risk Aversion (δ) | B7: 2.5 | C7: Market consensus ~2.5 (He & Litterman, 1999)
A8: Tau (τ) — Uncertainty | B8: 0.05 | C8: Proportional to (1/T). Lower = more certain about equilibrium
A10: EQUILIBRIUM WEIGHTS & IMPLIED RETURNS
A11: Ticker | B11: Current Wt | C11: Beta (βi) | D11: CAPM E(Ri) | E11: Implied Eq. Return | F11: BL Optimal Wt | G11: Trade (Δ Wt)
A12: =Dashboard!N7 -> 0R2N | B12: =Dashboard!M7 -> 0.051357301 | C12: ='Risk Analytics'!D39 -> 0.412 | D12: ='Risk Analytics'!H39 -> 0.06619 | E12: =$B$6+$B$7*C12*0.155^2 -> 0.06724575 | F12: =B12*(1+(D12-E12)*10) -> 0.050815096 | G12: =F12-B12 -> -0.00054220471
A13: =Dashboard!N8 -> AAPL | B13: =Dashboard!M8 -> 0.046889262 | C13: ='Risk Analytics'!D40 -> 1.1035 | D13: ='Risk Analytics'!H40 -> 0.10595125 | E13: =$B$6+$B$7*C13*0.155^2 -> 0.10877897 | F13: =B13*(1+(D13-E13)*10) -> 0.045563366 | G13: =F13-B13 -> -0.0013258965
A14: =Dashboard!N9 -> AMD | B14: =Dashboard!M9 -> 0.077751595 | C14: ='Risk Analytics'!D41 -> 1.9919 | D14: ='Risk Analytics'!H41 -> 0.15703425 | E14: =$B$6+$B$7*C14*0.155^2 -> 0.16213849 | F14: =B14*(1+(D14-E14)*10) -> 0.073782964 | G14: =F14-B14 -> -0.0039686309
A15: =Dashboard!N10 -> AMZN | B15: =Dashboard!M10 -> 0.031795354 | C15: ='Risk Analytics'!D42 -> 1.3631 | D15: ='Risk Analytics'!H42 -> 0.12087825 | E15: =$B$6+$B$7*C15*0.155^2 -> 0.12437119 | F15: =B15*(1+(D15-E15)*10) -> 0.03068476 | G15: =F15-B15 -> -0.0011105938
A16: =Dashboard!N11 -> BA | B16: =Dashboard!M11 -> 0.031768582 | C16: ='Risk Analytics'!D43 -> 1.1786 | D16: ='Risk Analytics'!H43 -> 0.1102695 | E16: =$B$6+$B$7*C16*0.155^2 -> 0.11328966 | F16: =B16*(1+(D16-E16)*10) -> 0.030809119 | G16: =F16-B16 -> -0.00095946279
A17: =Dashboard!N12 -> BLK | B17: =Dashboard!M12 -> 0.036674855 | C17: ='Risk Analytics'!D44 -> 1.4875 | D17: ='Risk Analytics'!H44 -> 0.12803125 | E17: =$B$6+$B$7*C17*0.155^2 -> 0.13184297 | F17: =B17*(1+(D17-E17)*10) -> 0.035276912 | G17: =F17-B17 -> -0.0013979423
A18: =Dashboard!N13 -> C | B18: =Dashboard!M13 -> 0.053780726 | C18: ='Risk Analytics'!D45 -> 1.1155 | D18: ='Risk Analytics'!H45 -> 0.10664125 | E18: =$B$6+$B$7*C18*0.155^2 -> 0.10949972 | F18: =B18*(1+(D18-E18)*10) -> 0.05224342 | G18: =F18-B18 -> -0.0015373052
A19: =Dashboard!N14 -> CVX | B19: =Dashboard!M14 -> 0.048281655 | C19: ='Risk Analytics'!D46 -> 0.6092 | D19: ='Risk Analytics'!H46 -> 0.077529 | E19: =$B$6+$B$7*C19*0.155^2 -> 0.079090075 | F19: =B19*(1+(D19-E19)*10) -> 0.047527943 | G19: =F19-B19 -> -0.00075371285
A20: =Dashboard!N15 -> F | B20: =Dashboard!M15 -> 0.028354674 | C20: ='Risk Analytics'!D47 -> 1.7561 | D20: ='Risk Analytics'!H47 -> 0.14347575 | E20: =$B$6+$B$7*C20*0.155^2 -> 0.14797576 | F20: =B20*(1+(D20-E20)*10) -> 0.027078712 | G20: =F20-B20 -> -0.0012759621
A21: =Dashboard!N16 -> GOOG | B21: =Dashboard!M16 -> 0.065883101 | C21: ='Risk Analytics'!D48 -> 1.1004 | D21: ='Risk Analytics'!H48 -> 0.105773 | E21: =$B$6+$B$7*C21*0.155^2 -> 0.10859278 | F21: =B21*(1+(D21-E21)*10) -> 0.064025346 | G21: =F21-B21 -> -0.0018577552
A22: =Dashboard!N17 -> HMC | B22: =Dashboard!M17 -> 0.020306274 | C22: ='Risk Analytics'!D49 -> 0.468 | D22: ='Risk Analytics'!H49 -> 0.06941 | E22: =$B$6+$B$7*C22*0.155^2 -> 0.07060925 | F22: =B22*(1+(D22-E22)*10) -> 0.020062751 | G22: =F22-B22 -> -0.00024352299
A23: =Dashboard!N18 -> JPM | B23: =Dashboard!M18 -> 0.055350051 | C23: ='Risk Analytics'!D50 -> 1.0615 | D23: ='Risk Analytics'!H50 -> 0.10353625 | E23: =$B$6+$B$7*C23*0.155^2 -> 0.10625634 | F23: =B23*(1+(D23-E23)*10) -> 0.053844478 | G23: =F23-B23 -> -0.0015055733
... A27: =Dashboard!N22 -> WMT | B27: =Dashboard!M22 -> 0.076046083 | C27: ='Risk Analytics'!D54 -> 0.6682 | D27: ='Risk Analytics'!H54 -> 0.0809215 | E27: =$B$6+$B$7*C27*0.155^2 -> 0.082633763 | F27: =B27*(1+(D27-E27)*10) -> 0.074743974 | G27: =F27-B27 -> -0.0013021086
A29: INVESTOR VIEWS (User Input)
A30: View # | B30: Description | C30: Expected Excess Return | D30: Confidence | E30: Status
A31: View 1 | B31: NVDA outperforms market by 10% | C31: 0.1 | D31: 0.75 | E31: Active
A32: View 2 | B32: MSFT (via META proxy) outperforms AAPL by 5% | C32: 0.05 | D32: 0.6 | E32: Active
A33: View 3 | B33: Financials (JPM, C, BLK) rally +8% | C33: 0.08 | D33: 0.5 | E33: Active
A34: View 4 | B34: (Enter your view here) | C34: 0 | D34: 0 | E34: Inactive
A35: View 5 | B35: (Enter your view here) | C35: 0 | D35: 0 | E35: Inactive
A37: VIEW-ADJUSTED REBALANCING TRADE LIST
A38: Ticker | B38: Current $ | C38: Target Wt | D38: Target $ | E38: Trade $ | F38: Action
A39: =A12 -> 0R2N | B39: =B12*SUM(Dashboard!G7:'Dashboard'!G22) -> 15596.205 | C39: =F12/SUM(F$12:F$27) -> 0.052807917 | D39: =C39*SUM(Dashboard!G7:'Dashboard'!G22) -> 16036.729 | E39: =D39-B39 -> 440.52354 | F39: =IF(ABS(E39)<500,"HOLD",IF(E39>0,"BUY "&TEXT(E39,"$#,##0"),"SELL "&TEXT(ABS(E39),"$#,##0"))) -> HOLD
A40: =A13 -> AAPL | B40: =B13*SUM(Dashboard!G7:'Dashboard'!G22) -> 14239.349 | C40: =F13/SUM(F$12:F$27) -> 0.047350228 | D40: =C40*SUM(Dashboard!G7:'Dashboard'!G22) -> 14379.336 | E40: =D40-B40 -> 139.98644 | F40: =IF(ABS(E40)<500,"HOLD",IF(E40>0,"BUY "&TEXT(E40,"$#,##0"),"SELL "&TEXT(ABS(E40),"$#,##0"))) -> HOLD
A41: =A14 -> AMD | B41: =B14*SUM(Dashboard!G7:'Dashboard'!G22) -> 23611.634 | C41: =F14/SUM(F$12:F$27) -> 0.076676518 | D41: =C41*SUM(Dashboard!G7:'Dashboard'!G22) -> 23285.154 | E41: =D41-B41 -> -326.47994 | F41: =IF(ABS(E41)<500,"HOLD",IF(E41>0,"BUY "&TEXT(E41,"$#,##0"),"SELL "&TEXT(ABS(E41),"$#,##0"))) -> HOLD
A42: =A15 -> AMZN | B42: =B15*SUM(Dashboard!G7:'Dashboard'!G22) -> 9655.6252 | C42: =F15/SUM(F$12:F$27) -> 0.031888127 | D42: =C42*SUM(Dashboard!G7:'Dashboard'!G22) -> 9683.7987 | E42: =D42-B42 -> 28.173433 | F42: =IF(ABS(E42)<500,"HOLD",IF(E42>0,"BUY "&TEXT(E42,"$#,##0"),"SELL "&TEXT(ABS(E42),"$#,##0"))) -> HOLD
A43: =A16 -> BA | B43: =B16*SUM(Dashboard!G7:'Dashboard'!G22) -> 9647.4951 | C43: =F16/SUM(F$12:F$27) -> 0.032017363 | D43: =C43*SUM(Dashboard!G7:'Dashboard'!G22) -> 9723.0451 | E43: =D43-B43 -> 75.550011 | F43: =IF(ABS(E43)<500,"HOLD",IF(E43>0,"BUY "&TEXT(E43,"$#,##0"),"SELL "&TEXT(ABS(E43),"$#,##0"))) -> HOLD
A44: =A17 -> BLK | B44: =B17*SUM(Dashboard!G7:'Dashboard'!G22) -> 11137.434 | C44: =F17/SUM(F$12:F$27) -> 0.03666037 | D44: =C44*SUM(Dashboard!G7:'Dashboard'!G22) -> 11133.035 | E44: =D44-B44 -> -4.3986004 | F44: =IF(ABS(E44)<500,"HOLD",IF(E44>0,"BUY "&TEXT(E44,"$#,##0"),"SELL "&TEXT(ABS(E44),"$#,##0"))) -> HOLD
A45: =A18 -> C | B45: =B18*SUM(Dashboard!G7:'Dashboard'!G22) -> 16332.151 | C45: =F18/SUM(F$12:F$27) -> 0.054292255 | D45: =C45*SUM(Dashboard!G7:'Dashboard'!G22) -> 16487.493 | E45: =D45-B45 -> 155.3416 | F45: =IF(ABS(E45)<500,"HOLD",IF(E45>0,"BUY "&TEXT(E45,"$#,##0"),"SELL "&TEXT(ABS(E45),"$#,##0"))) -> HOLD
A46: =A19 -> CVX | B46: =B19*SUM(Dashboard!G7:'Dashboard'!G22) -> 14662.192 | C46: =F19/SUM(F$12:F$27) -> 0.04939185 | D46: =C46*SUM(Dashboard!G7:'Dashboard'!G22) -> 14999.336 | E46: =D46-B46 -> 337.14443 | F46: =IF(ABS(E46)<500,"HOLD",IF(E46>0,"BUY "&TEXT(E46,"$#,##0"),"SELL "&TEXT(ABS(E46),"$#,##0"))) -> HOLD
A47: =A20 -> F | B47: =B20*SUM(Dashboard!G7:'Dashboard'!G22) -> 8610.7582 | C47: =F20/SUM(F$12:F$27) -> 0.02814066 | D47: =C47*SUM(Dashboard!G7:'Dashboard'!G22) -> 8545.7665 | E47: =D47-B47 -> -64.991762 | F47: =IF(ABS(E47)<500,"HOLD",IF(E47>0,"BUY "&TEXT(E47,"$#,##0"),"SELL "&TEXT(ABS(E47),"$#,##0"))) -> HOLD
A48: =A21 -> GOOG | B48: =B21*SUM(Dashboard!G7:'Dashboard'!G22) -> 20007.406 | C48: =F21/SUM(F$12:F$27) -> 0.066536234 | D48: =C48*SUM(Dashboard!G7:'Dashboard'!G22) -> 20205.749 | E48: =D48-B48 -> 198.34363 | F48: =IF(ABS(E48)<500,"HOLD",IF(E48>0,"BUY "&TEXT(E48,"$#,##0"),"SELL "&TEXT(ABS(E48),"$#,##0"))) -> HOLD
A49: =A22 -> HMC | B49: =B22*SUM(Dashboard!G7:'Dashboard'!G22) -> 6166.617 | C49: =F22/SUM(F$12:F$27) -> 0.020849553 | D49: =C49*SUM(Dashboard!G7:'Dashboard'!G22) -> 6331.6004 | E49: =D49-B49 -> 164.98342 | F49: =IF(ABS(E49)<500,"HOLD",IF(E49>0,"BUY "&TEXT(E49,"$#,##0"),"SELL "&TEXT(ABS(E49),"$#,##0"))) -> HOLD
A50: =A23 -> JPM | B50: =B23*SUM(Dashboard!G7:'Dashboard'!G22) -> 16808.725 | C50: =F23/SUM(F$12:F$27) -> 0.055956102 | D50: =C50*SUM(Dashboard!G7:'Dashboard'!G22) -> 16992.771 | E50: =D50-B50 -> 184.04571 | F50: =IF(ABS(E50)<500,"HOLD",IF(E50>0,"BUY "&TEXT(E50,"$#,##0"),"SELL "&TEXT(ABS(E50),"$#,##0"))) -> HOLD
A51: =A24 -> META | B51: =B24*SUM(Dashboard!G7:'Dashboard'!G22) -> 16490.625 | C51: =F24/SUM(F$12:F$27) -> 0.054554721 | D51: =C51*SUM(Dashboard!G7:'Dashboard'!G22) -> 16567.199 | E51: =D51-B51 -> 76.573326 | F51: =IF(ABS(E51)<500,"HOLD",IF(E51>0,"BUY "&TEXT(E51,"$#,##0"),"SELL "&TEXT(ABS(E51),"$#,##0"))) -> HOLD
A52: =A25 -> NVDA | B52: =B25*SUM(Dashboard!G7:'Dashboard'!G22) -> 89099.292 | C52: =F25/SUM(F$12:F$27) -> 0.28656929 | D52: =C52*SUM(Dashboard!G7:'Dashboard'!G22) -> 87025.472 | E52: =D52-B52 -> -2073.82 | F52: =IF(ABS(E52)<500,"HOLD",IF(E52>0,"BUY "&TEXT(E52,"$#,##0"),"SELL "&TEXT(ABS(E52),"$#,##0"))) -> SELL $2,074
A53: =A26 -> TM | B53: =B26*SUM(Dashboard!G7:'Dashboard'!G22) -> 8521.1733 | C53: =F26/SUM(F$12:F$27) -> 0.028633599 | D53: =C53*SUM(Dashboard!G7:'Dashboard'!G22) -> 8695.4623 | E53: =D53-B53 -> 174.28901 | F53: =IF(ABS(E53)<500,"HOLD",IF(E53>0,"BUY "&TEXT(E53,"$#,##0"),"SELL "&TEXT(ABS(E53),"$#,##0"))) -> HOLD
A54: =A27 -> WMT | B54: =B27*SUM(Dashboard!G7:'Dashboard'!G22) -> 23093.704 | C54: =F27/SUM(F$12:F$27) -> 0.077675216 | D54: =C54*SUM(Dashboard!G7:'Dashboard'!G22) -> 23588.44 | E54: =D54-B54 -> 494.73572 | F54: =IF(ABS(E54)<500,"HOLD",IF(E54>0,"BUY "&TEXT(E54,"$#,##0"),"SELL "&TEXT(ABS(E54),"$#,##0"))) -> HOLD

Sheet Dashboard
V1: Ticker | W1: Return % | X1: Weight % | Y1: Gain/Loss | Z1: Ann. Return | AA1: Ticker | AB1: Gain/Loss | AC1: Ticker | AD1: Ann. Return | AE1: Ticker | AF1: Weight
B2: PORTFOLIO VALUE | E2: COST BASIS | F2: UNREALISED P&L | G2: TOTAL RETURN | H2: ="CAGR ("&TEXT((MAX(Ledger[Date])-MIN(Ledger[Date]))/365.25,"0")&"YR)" -> CAGR (6YR) | I2: BEST STOCK | J2: WORST STOCK | K2: HHI INDEX | N2: DAILY P&L | O2: SHARPE RATIO | P2: WIN RATE | Q2: AVG RETURN | R2: WORST STOCK RETURN | S2: PORT. BETA | T2: TREYNOR | V2: =N7 -> 0R2N | W2: =L7 -> 0.97044958 | X2: =M7 -> 0.051357301 | Y2: =J7 -> 7681.156 | Z2: =R7 -> 0.1196519 | AA2: =N7 -> 0R2N | AB2: =J7 -> 7681.156 | AC2: =N7 -> 0R2N | AD2: =R7 -> 0.1196519 | AE2: =N7 -> 0R2N | AF2: =M7 -> 0.051357301
B3: =SUM(_xlfn.ANCHORARRAY(G7)) -> 303680.39 | E3: =SUM(G7:G22)-SUM(J7:J22) -> 132051.42 | F3: =SUM(J7:J22) -> 171628.96 | G3: =F3/E3 -> 1.2997131 | H3: =(B3/E3)^(1/((MAX(Ledger[Date])-MIN(Ledger[Date]))/365.25))-1 -> 0.14885493 | I3: ="▲ "&INDEX(_xlfn.ANCHORARRAY(B7),MATCH(MAX(J7:J22),J7:J22,0)) -> ▲ NVDA | J3: ="▼ "&INDEX(_xlfn.ANCHORARRAY(B7),MATCH(MIN(J7:J22),J7:J22,0)) -> ▼ HMC | K3: {=SUMPRODUCT((SUMIF(_xlfn.ANCHORARRAY(D7),_xlfn.UNIQUE(_xlfn.ANCHORARRAY(D7)),_xlfn.ANCHORARRAY(G7))/SUM(_xlfn.ANCHORARRAY(G7)))^2)} -> 0.18756228 | N3: =SUM(H7:H22) -> 14.5968 | O3: ='Risk Analytics'!C18 -> 0.46593002 | P3: =COUNTIF(J7:J22,">0")/COUNTA(J7:J22) -> 0.875 | Q3: =AVERAGE(L7:L22) -> 1.268515 | R3: =MIN(L7:L22) -> -0.13381728 | S3: ='Risk Analytics'!C9 -> 1.4726694 | T3: ='Risk Analytics'!C15 -> 0.072219153 | V3: =N8 -> AAPL | W3: =L8 -> 0.92640661 | X3: =M8 -> 0.046889262 | Y3: =J8 -> 6847.6858 | Z3: =R8 -> 0.11544245 | AA3: =N8 -> AAPL | AB3: =J8 -> 6847.6858 | AC3: =N8 -> AAPL | AD3: =R8 -> 0.11544245 | AE3: =N8 -> AAPL | AF3: =M8 -> 0.046889262
B4: SORTINO | D4: ='Risk Analytics'!C19 -> 3.0962339 | E4: INFO RATIO | F4: ='Risk Analytics'!C16 -> 0.18770861 | G4: ACTIVE SHARE | H4: ='Risk Analytics'!C62 -> 0.26307902 | I4: ALPHA (α) | J4: ='Risk Analytics'!C11 -> 0.021676445 | K4: M² | L4: ='Risk Analytics'!C68 -> 0.014719153 | N4: TREYNOR | O4: ='Risk Analytics'!C15 -> 0.072219153 | P4: CALMAR | Q4: ='Risk Analytics'!C20 -> 1.1123746 | R4: CF VaR 95% | S4: ='Risk Analytics'!C75 -> -0.27855525 | V4: =N9 -> AMD | W4: =L9 -> 2.1931096 | X4: =M9 -> 0.077751595 | Y4: =J9 -> 16217.076 | Z4: =R9 -> 0.21343486 | AA4: =N9 -> AMD | AB4: =J9 -> 16217.076 | AC4: =N9 -> AMD | AD4: =R9 -> 0.21343486 | AE4: =N9 -> AMD | AF4: =M9 -> 0.077751595
B5: ="CURRENT HOLDINGS · "&COUNTA(B7:B22)&" STOCKS · "&COUNTA(_xlfn.UNIQUE(D7:D22))&" INDUSTRIES" -> CURRENT HOLDINGS · 16 STOCKS · 10 INDUSTRIES | N5: FINANCIAL METRICS · PER-STOCK ANALYTICS · RISK ASSESSMENT | V5: =N10 -> AMZN | W5: =L10 -> 0.49216603 | X5: =M10 -> 0.031795354 | Y5: =J10 -> 3184.7467 | Z5: =R10 -> 0.0689636 | AA5: =N10 -> AMZN | AB5: =J10 -> 3184.7467 | AC5: =N10 -> AMZN | AD5: =R10 -> 0.0689636 | AE5: =N10 -> AMZN | AF5: =M10 -> 0.031795354
B6: Ticker | C6: Company | D6: Industry | E6: Units | F6: Current Price | G6: Market Value | H6: Today's Change | J6: Gain/(Loss) | K6: Last 12 Months | L6: Return % | M6: Weight % | N6: Stock | O6: Cost Basis | P6: Avg Buy Price | Q6: Price/Cost | R6: Ann. Return | S6: Risk Score | T6: Signal | V6: =N11 -> BA | W6: =L11 -> -0.031168065 | X6: =M11 -> 0.031768582 | Y6: =J11 -> -310.3673 | Z6: =R11 -> -0.0052622557 | AA6: =N11 -> BA | AB6: =J11 -> -310.3673 | AC6: =N11 -> BA | AD6: =R11 -> -0.0052622557 | AE6: =N11 -> BA | AF6: =M11 -> 0.031768582
B7: {=_xlfn._xlws.SORT(_xlfn.UNIQUE(Ledger[Ticker]))} -> 0R2N | C7: {=_FV(INDEX(Ledger[Stock],MATCH(_xlfn.ANCHORARRAY(B7),Ledger[Ticker],0)),"Name")} -> RTX CORPORATION | D7: {=_FV(INDEX(Ledger[Stock],MATCH(_xlfn.ANCHORARRAY(B7),Ledger[Ticker],0)),"Industry")} -> Aerospace & Defense | E7: {=SUMIF(Ledger[Ticker],_xlfn.ANCHORARRAY(B7),Ledger[Units])} -> 79.37 | F7: {=_FV(INDEX(Ledger[Stock],MATCH(_xlfn.ANCHORARRAY(B7),Ledger[Ticker],0)),"Price")} -> 196.5 | G7: {=_xlfn.ANCHORARRAY(E7)*_xlfn.ANCHORARRAY(F7)} -> 15596.205 | H7: {=_xlfn.ANCHORARRAY(F7)-_FV(INDEX(Ledger[Stock],MATCH(_xlfn.ANCHORARRAY(B7),Ledger[Ticker],0)),"Previous close",TRUE)} -> 1 | I7: {=_xlfn.ANCHORARRAY(H7)/(_xlfn.ANCHORARRAY(G7)-_xlfn.ANCHORARRAY(H7))} -> 6.4122273e-05 | J7: {=_xlfn.ANCHORARRAY(G7)-SUMIF(Ledger[Ticker],_xlfn.ANCHORARRAY(B7),Ledger[Transaction Amount])} -> 7681.156 | L7: =IF((G7-J7)=0,0,J7/(G7-J7)) -> 0.97044958 | M7: =G7/SUM(G7:G22) -> 0.051357301 | N7: {=_xlfn.ANCHORARRAY(B7)} -> 0R2N | O7: =G7-J7 -> 7915.049 | P7: =O7/E7 -> 99.723435 | Q7: =F7/P7 -> 1.9704496 | R7: =(F7/P7)^(1/((MAX(Ledger[Date])-MIN(Ledger[Date]))/365.25))-1 -> 0.1196519 | S7: =IF(OR(L7<0,R7<0,M7>0.2),"HIGH",IF(OR(L7<0.5,R7<0.05,M7>0.15),"MEDIUM","LOW")) -> LOW | T7: =IF(AND(R7>0.1,L7>1,Q7>1.5,S7="LOW"),"▲ STRONG",IF(OR(L7<0,R7<0),"▼ REVIEW","▶ HOLD")) -> ▶ HOLD | V7: =N12 -> BLK | W7: =L12 -> 0.28303688 | X7: =M12 -> 0.036674855 | Y7: =J12 -> 2456.9088 | Z7: =R12 -> 0.042403214 | AA7: =N12 -> BLK | AB7: =J12 -> 2456.9088 | AC7: =N12 -> BLK | AD7: =R12 -> 0.042403214 | AE7: =N12 -> BLK | AF7: =M12 -> 0.036674855
B8: AAPL | C8: APPLE INC. | D8: Computers, Phones & Household Electronics | E8: 54.94 | F8: 259.18 | G8: 14239.349 | H8: 3.26 | I8: 0.00022899547 | J8: 6847.6858 | L8: =IF((G8-J8)=0,0,J8/(G8-J8)) -> 0.92640661 | M8: =G8/SUM(G7:G22) -> 0.046889262 | N8: AAPL | O8: =G8-J8 -> 7391.6634 | P8: =O8/E8 -> 134.54065 | Q8: =F8/P8 -> 1.9264066 | R8: =(F8/P8)^(1/((MAX(Ledger[Date])-MIN(Ledger[Date]))/365.25))-1 -> 0.11544245 | S8: =IF(OR(L8<0,R8<0,M8>0.2),"HIGH",IF(OR(L8<0.5,R8<0.05,M8>0.15),"MEDIUM","LOW")) -> LOW | T8: =IF(AND(R8>0.1,L8>1,Q8>1.5,S8="LOW"),"▲ STRONG",IF(OR(L8<0,R8<0),"▼ REVIEW","▶ HOLD")) -> ▶ HOLD | V8: =N13 -> C | W8: =L13 -> 0.96659915 | X8: =M13 -> 0.053780726 | Y8: =J13 -> 8027.3826 | Z8: =R13 -> 0.11928704 | AA8: =N13 -> C | AB8: =J13 -> 8027.3826 | AC8: =N13 -> C | AD8: =R13 -> 0.11928704 | AE8: =N13 -> C | AF8: =M13 -> 0.053780726
B9: AMD | C9: ADVANCED MICRO DEVICES, INC. | D9: Semiconductors & Semiconductor Equipment | E9: 107.16 | F9: 220.34 | G9: 23611.634 | H9: 2.84 | I9: 0.00012029416 | J9: 16217.076 | L9: =IF((G9-J9)=0,0,J9/(G9-J9)) -> 2.1931096 | M9: =G9/SUM(G7:G22) -> 0.077751595 | N9: AMD | O9: =G9-J9 -> 7394.5581 | P9: =O9/E9 -> 69.004835 | Q9: =F9/P9 -> 3.1931096 | R9: =(F9/P9)^(1/((MAX(Ledger[Date])-MIN(Ledger[Date]))/365.25))-1 -> 0.21343486 | S9: =IF(OR(L9<0,R9<0,M9>0.2),"HIGH",IF(OR(L9<0.5,R9<0.05,M9>0.15),"MEDIUM","LOW")) -> LOW | T9: =IF(AND(R9>0.1,L9>1,Q9>1.5,S9="LOW"),"▲ STRONG",IF(OR(L9<0,R9<0),"▼ REVIEW","▶ HOLD")) -> ▲ STRONG | V9: =N14 -> CVX | W9: =L14 -> 0.48414783 | X9: =M14 -> 0.048281655 | Y9: =J14 -> 4782.9928 | Z9: =R14 -> 0.068004316 | AA9: =N14 -> CVX | AB9: =J14 -> 4782.9928 | AC9: =N14 -> CVX | AD9: =R14 -> 0.068004316 | AE9: =N14 -> CVX | AF9: =M14 -> 0.048281655
B10: AMZN | C10: AMAZON.COM, INC. | D10: Diversified Retail | E10: 45.45 | F10: 212.445 | G10: 9655.6252 | H10: 2.675 | I10: 0.00027711735 | J10: 3184.7467 | L10: =IF((G10-J10)=0,0,J10/(G10-J10)) -> 0.49216603 | M10: =G10/SUM(G7:G22) -> 0.031795354 | N10: AMZN | O10: =G10-J10 -> 6470.8786 | P10: =O10/E10 -> 142.37357 | Q10: =F10/P10 -> 1.492166 | R10: =(F10/P10)^(1/((MAX(Ledger[Date])-MIN(Ledger[Date]))/365.25))-1 -> 0.0689636 | S10: =IF(OR(L10<0,R10<0,M10>0.2),"HIGH",IF(OR(L10<0.5,R10<0.05,M10>0.15),"MEDIUM","LOW")) -> MEDIUM | T10: =IF(AND(R10>0.1,L10>1,Q10>1.5,S10="LOW"),"▲ STRONG",IF(OR(L10<0,R10<0),"▼ REVIEW","▶ HOLD")) -> ▶ HOLD | V10: =N15 -> F | W10: =L15 -> 0.088062562 | X10: =M15 -> 0.028354674 | Y10: =J15 -> 696.91345 | Z10: =R15 -> 0.014162585 | AA10: =N15 -> F | AB10: =J15 -> 696.91345 | AC10: =N15 -> F | AD10: =R15 -> 0.014162585 | AE10: =N15 -> F | AF10: =M15 -> 0.028354674
B11: BA | C11: THE BOEING COMPANY | D11: Aerospace & Defense | E11: 45.79 | F11: 210.69 | G11: 9647.4951 | H11: 2.47 | I11: 0.00025609057 | J11: -310.3673 | L11: =IF((G11-J11)=0,0,J11/(G11-J11)) -> -0.031168065 | M11: =G11/SUM(G7:G22) -> 0.031768582 | N11: BA | O11: =G11-J11 -> 9957.8624 | P11: =O11/E11 -> 217.46806 | Q11: =F11/P11 -> 0.96883194 | R11: =(F11/P11)^(1/((MAX(Ledger[Date])-MIN(Ledger[Date]))/365.25))-1 -> -0.0052622557 | S11: =IF(OR(L11<0,R11<0,M11>0.2),"HIGH",IF(OR(L11<0.5,R11<0.05,M11>0.15),"MEDIUM","LOW")) -> HIGH | T11: =IF(AND(R11>0.1,L11>1,Q11>1.5,S11="LOW"),"▲ STRONG",IF(OR(L11<0,R11<0),"▼ REVIEW","▶ HOLD")) -> ▼ REVIEW | V11: =N16 -> GOOG | W11: =L16 -> 1.5472763 | X11: =M16 -> 0.065883101 | Y11: =J16 -> 12152.975 | Z11: =R16 -> 0.16859468 | AA11: =N16 -> GOOG | AB11: =J16 -> 12152.975 | AC11: =N16 -> GOOG | AD11: =R16 -> 0.16859468 | AE11: =N16 -> GOOG | AF11: =M16 -> 0.065883101
B12: BLK | C12: BLACKROCK, INC. | D12: Investment Banking & Investment Services | E12: 11.55 | F12: 964.28 | G12: 11137.434 | H12: -2.28 | I12: -0.00020467312 | J12: 2456.9088 | L12: =IF((G12-J12)=0,0,J12/(G12-J12)) -> 0.28303688 | M12: =G12/SUM(G7:G22) -> 0.036674855 | N12: BLK | O12: =G12-J12 -> 8680.5252 | P12: =O12/E12 -> 751.56062 | Q12: =F12/P12 -> 1.2830369 | R12: =(F12/P12)^(1/((MAX(Ledger[Date])-MIN(Ledger[Date]))/365.25))-1 -> 0.042403214 | S12: =IF(OR(L12<0,R12<0,M12>0.2),"HIGH",IF(OR(L12<0.5,R12<0.05,M12>0.15),"MEDIUM","LOW")) -> MEDIUM | T12: =IF(AND(R12>0.1,L12>1,Q12>1.5,S12="LOW"),"▲ STRONG",IF(OR(L12<0,R12<0),"▼ REVIEW","▶ HOLD")) -> ▶ HOLD | V12: =N17 -> HMC | W12: =L17 -> -0.13381728 | X12: =M17 -> 0.020306274 | Y12: =J17 -> -952.6857 | Z12: =R17 -> -0.023653535 | AA12: =N17 -> HMC | AB12: =J17 -> -952.6857 | AC12: =N17 -> HMC | AD12: =R17 -> -0.023653535 | AE12: =N17 -> HMC | AF12: =M17 -> 0.020306274
B13: C | C13: CITIGROUP INC. | D13: Investment Banking & Investment Services | E13: 140.13 | F13: 116.55 | G13: 16332.151 | H13: 1.3 | I13: 7.9603932e-05 | J13: 8027.3826 | L13: =IF((G13-J13)=0,0,J13/(G13-J13)) -> 0.96659915 | M13: =G13/SUM(G7:G22) -> 0.053780726 | N13: C | O13: =G13-J13 -> 8304.7689 | P13: =O13/E13 -> 59.264746 | Q13: =F13/P13 -> 1.9665992 | R13: =(F13/P13)^(1/((MAX(Ledger[Date])-MIN(Ledger[Date]))/365.25))-1 -> 0.11928704 | S13: =IF(OR(L13<0,R13<0,M13>0.2),"HIGH",IF(OR(L13<0.5,R13<0.05,M13>0.15),"MEDIUM","LOW")) -> LOW | T13: =IF(AND(R13>0.1,L13>1,Q13>1.5,S13="LOW"),"▲ STRONG",IF(OR(L13<0,R13<0),"▼ REVIEW","▶ HOLD")) -> ▶ HOLD | V13: =N18 -> JPM | W13: =L18 -> 0.78225846 | X13: =M18 -> 0.055350051 | Y13: =J18 -> 7377.5872 | Z13: =R18 -> 0.10108008 | AA13: =N18 -> JPM | AB13: =J18 -> 7377.5872 | AC13: =N18 -> JPM | AD13: =R18 -> 0.10108008 | AE13: =N18 -> JPM | AF13: =M18 -> 0.055350051
B14: CVX | C14: CHEVRON CORPORATION | D14: Oil & Gas | E14: 74.35 | F14: 197.205 | G14: 14662.192 | H14: -1.765 | I14: -0.00012036315 | J14: 4782.9928 | L14: =IF((G14-J14)=0,0,J14/(G14-J14)) -> 0.48414783 | M14: =G14/SUM(G7:G22) -> 0.048281655 | N14: CVX | O14: =G14-J14 -> 9879.199 | P14: =O14/E14 -> 132.87423 | Q14: =F14/P14 -> 1.4841478 | R14: =(F14/P14)^(1/((MAX(Ledger[Date])-MIN(Ledger[Date]))/365.25))-1 -> 0.068004316 | S14: =IF(OR(L14<0,R14<0,M14>0.2),"HIGH",IF(OR(L14<0.5,R14<0.05,M14>0.15),"MEDIUM","LOW")) -> MEDIUM | T14: =IF(AND(R14>0.1,L14>1,Q14>1.5,S14="LOW"),"▲ STRONG",IF(OR(L14<0,R14<0),"▼ REVIEW","▶ HOLD")) -> ▶ HOLD | V14: =N19 -> META | W14: =L19 -> 0.98269703 | X14: =M19 -> 0.05430257 | Y14: =J19 -> 8173.3559 | Z14: =R19 -> 0.12080852 | AA14: =N19 -> META | AB14: =J19 -> 8173.3559 | AC14: =N19 -> META | AD14: =R19 -> 0.12080852 | AE14: =N19 -> META | AF14: =M19 -> 0.05430257
B15: F | C15: FORD MOTOR COMPANY | D15: Automobiles & Auto Parts | E15: 743.91 | F15: 11.575 | G15: 8610.7582 | H15: -0.025 | I15: -2.9033363e-06 | J15: 696.91345 | L15: =IF((G15-J15)=0,0,J15/(G15-J15)) -> 0.088062562 | M15: =G15/SUM(G7:G22) -> 0.028354674 | N15: F | O15: =G15-J15 -> 7913.8448 | P15: =O15/E15 -> 10.638175 | Q15: =F15/P15 -> 1.0880626 | R15: =(F15/P15)^(1/((MAX(Ledger[Date])-MIN(Ledger[Date]))/365.25))-1 -> 0.014162585 | S15: =IF(OR(L15<0,R15<0,M15>0.2),"HIGH",IF(OR(L15<0.5,R15<0.05,M15>0.15),"MEDIUM","LOW")) -> MEDIUM | T15: =IF(AND(R15>0.1,L15>1,Q15>1.5,S15="LOW"),"▲ STRONG",IF(OR(L15<0,R15<0),"▼ REVIEW","▶ HOLD")) -> ▶ HOLD | V15: =N20 -> NVDA | W15: =L20 -> 9.1481213 | X15: =M20 -> 0.29339824 | Y15: =J20 -> 80319.411 | Z15: =R20 -> 0.47127103 | AA15: =N20 -> NVDA | AB15: =J20 -> 80319.411 | AC15: =N20 -> NVDA | AD15: =R20 -> 0.47127103 | AE15: =N20 -> NVDA | AF15: =M20 -> 0.29339824
B16: GOOG | C16: ALPHABET INC. | D16: Software & IT Services | E16: 67.62 | F16: 295.88 | G16: 20007.406 | H16: 1.42 | I16: 7.0978757e-05 | J16: 12152.975 | L16: =IF((G16-J16)=0,0,J16/(G16-J16)) -> 1.5472763 | M16: =G16/SUM(G7:G22) -> 0.065883101 | N16: GOOG | O16: =G16-J16 -> 7854.4309 | P16: =O16/E16 -> 116.15544 | Q16: =F16/P16 -> 2.5472763 | R16: =(F16/P16)^(1/((MAX(Ledger[Date])-MIN(Ledger[Date]))/365.25))-1 -> 0.16859468 | S16: =IF(OR(L16<0,R16<0,M16>0.2),"HIGH",IF(OR(L16<0.5,R16<0.05,M16>0.15),"MEDIUM","LOW")) -> LOW | T16: =IF(AND(R16>0.1,L16>1,Q16>1.5,S16="LOW"),"▲ STRONG",IF(OR(L16<0,R16<0),"▼ REVIEW","▶ HOLD")) -> ▲ STRONG | V16: =N21 -> TM | W16: =L21 -> 0.26358854 | X16: =M21 -> 0.028059676 | Y16: =J21 -> 1777.5435 | Z16: =R21 -> 0.039753562 | AA16: =N21 -> TM | AB16: =J21 -> 1777.5435 | AC16: =N21 -> TM | AD16: =R21 -> 0.039753562 | AE16: =N21 -> TM | AF16: =M21 -> 0.028059676
B17: HMC | C17: HONDA MOTOR CO., LTD. | D17: Automobiles & Auto Parts | E17: 258.45 | F17: 23.86 | G17: 6166.617 | H17: -0.29 | I17: -4.7025194e-05 | J17: -952.6857 | L17: =IF((G17-J17)=0,0,J17/(G17-J17)) -> -0.13381728 | M17: =G17/SUM(G7:G22) -> 0.020306274 | N17: HMC | O17: =G17-J17 -> 7119.3027 | P17: =O17/E17 -> 27.546151 | Q17: =F17/P17 -> 0.86618272 | R17: =(F17/P17)^(1/((MAX(Ledger[Date])-MIN(Ledger[Date]))/365.25))-1 -> -0.023653535 | S17: =IF(OR(L17<0,R17<0,M17>0.2),"HIGH",IF(OR(L17<0.5,R17<0.05,M17>0.15),"MEDIUM","LOW")) -> HIGH | T17: =IF(AND(R17>0.1,L17>1,Q17>1.5,S17="LOW"),"▲ STRONG",IF(OR(L17<0,R17<0),"▼ REVIEW","▶ HOLD")) -> ▼ REVIEW | V17: =N22 -> WMT | W17: =L22 -> 1.3333052 | X17: =M22 -> 0.076046083 | Y17: =J22 -> 13196.283 | Z17: =R22 -> 0.15163433 | AA17: =N22 -> WMT | AB17: =J22 -> 13196.283 | AC17: =N22 -> WMT | AD17: =R22 -> 0.15163433 | AE17: =N22 -> WMT | AF17: =M22 -> 0.076046083
B18: JPM | C18: JPMORGAN CHASE & CO. | D18: Banking Services | E18: 56.84 | F18: 295.72 | G18: 16808.725 | H18: 2.62 | I18: 0.00015589573 | J18: 7377.5872 | L18: =IF((G18-J18)=0,0,J18/(G18-J18)) -> 0.78225846 | M18: =G18/SUM(G7:G22) -> 0.055350051 | N18: JPM | O18: =G18-J18 -> 9431.1376 | P18: =O18/E18 -> 165.92431 | Q18: =F18/P18 -> 1.7822585 | R18: =(F18/P18)^(1/((MAX(Ledger[Date])-MIN(Ledger[Date]))/365.25))-1 -> 0.10108008 | S18: =IF(OR(L18<0,R18<0,M18>0.2),"HIGH",IF(OR(L18<0.5,R18<0.05,M18>0.15),"MEDIUM","LOW")) -> LOW | T18: =IF(AND(R18>0.1,L18>1,Q18>1.5,S18="LOW"),"▲ STRONG",IF(OR(L18<0,R18<0),"▼ REVIEW","▶ HOLD")) -> ▶ HOLD
B19: META | C19: META PLATFORMS, INC. | D19: Software & IT Services | E19: 28.53 | F19: 578.01 | G19: 16490.625 | H19: 3.55 | I19: 0.00021532018 | J19: 8173.3559 | L19: =IF((G19-J19)=0,0,J19/(G19-J19)) -> 0.98269703 | M19: =G19/SUM(G7:G22) -> 0.05430257 | N19: META | O19: =G19-J19 -> 8317.2694 | P19: =O19/E19 -> 291.52714 | Q19: =F19/P19 -> 1.982697 | R19: =(F19/P19)^(1/((MAX(Ledger[Date])-MIN(Ledger[Date]))/365.25))-1 -> 0.12080852 | S19: =IF(OR(L19<0,R19<0,M19>0.2),"HIGH",IF(OR(L19<0.5,R19<0.05,M19>0.15),"MEDIUM","LOW")) -> LOW | T19: =IF(AND(R19>0.1,L19>1,Q19>1.5,S19="LOW"),"▲ STRONG",IF(OR(L19<0,R19<0),"▼ REVIEW","▶ HOLD")) -> ▶ HOLD
B20: NVDA | C20: NVIDIA CORPORATION | D20: Semiconductors & Semiconductor Equipment | E20: 503.13 | F20: 177.09 | G20: 89099.292 | H20: -0.3 | I20: -3.3670188e-06 | J20: 80319.411 | L20: =IF((G20-J20)=0,0,J20/(G20-J20)) -> 9.1481213 | M20: =G20/SUM(G7:G22) -> 0.29339824 | N20: NVDA | O20: =G20-J20 -> 8779.8804 | P20: =O20/E20 -> 17.450521 | Q20: =F20/P20 -> 10.148121 | R20: =(F20/P20)^(1/((MAX(Ledger[Date])-MIN(Ledger[Date]))/365.25))-1 -> 0.47127103 | S20: =IF(OR(L20<0,R20<0,M20>0.2),"HIGH",IF(OR(L20<0.5,R20<0.05,M20>0.15),"MEDIUM","LOW")) -> HIGH | T20: =IF(AND(R20>0.1,L20>1,Q20>1.5,S20="LOW"),"▲ STRONG",IF(OR(L20<0,R20<0),"▼ REVIEW","▶ HOLD")) -> ▶ HOLD
B21: TM | C21: TOYOTA MOTOR CORPORATION | D21: Automobiles & Auto Parts | E21: 41.67 | F21: 204.4918 | G21: 8521.1733 | H21: -2.5182 | I21: -0.00029543538 | J21: 1777.5435 | L21: =IF((G21-J21)=0,0,J21/(G21-J21)) -> 0.26358854 | M21: =G21/SUM(G7:G22) -> 0.028059676 | N21: TM | O21: =G21-J21 -> 6743.6298 | P21: =O21/E21 -> 161.83417 | Q21: =F21/P21 -> 1.2635885 | R21: =(F21/P21)^(1/((MAX(Ledger[Date])-MIN(Ledger[Date]))/365.25))-1 -> 0.039753562 | S21: =IF(OR(L21<0,R21<0,M21>0.2),"HIGH",IF(OR(L21<0.5,R21<0.05,M21>0.15),"MEDIUM","LOW")) -> MEDIUM | T21: =IF(AND(R21>0.1,L21>1,Q21>1.5,S21="LOW"),"▲ STRONG",IF(OR(L21<0,R21<0),"▼ REVIEW","▶ HOLD")) -> ▶ HOLD
B22: WMT | C22: WALMART INC. | D22: Food & Drug Retailing | E22: 182.66 | F22: 126.43 | G22: 23093.704 | H22: 0.64 | I22: 2.7713949e-05 | J22: 13196.283 | L22: =IF((G22-J22)=0,0,J22/(G22-J22)) -> 1.3333052 | M22: =G22/SUM(G7:G22) -> 0.076046083 | N22: WMT | O22: =G22-J22 -> 9897.421 | P22: =O22/E22 -> 54.184939 | Q22: =F22/P22 -> 2.3333052 | R22: =(F22/P22)^(1/((MAX(Ledger[Date])-MIN(Ledger[Date]))/365.25))-1 -> 0.15163433 | S22: =IF(OR(L22<0,R22<0,M22>0.2),"HIGH",IF(OR(L22<0.5,R22<0.05,M22>0.15),"MEDIUM","LOW")) -> LOW | T22: =IF(AND(R22>0.1,L22>1,Q22>1.5,S22="LOW"),"▲ STRONG",IF(OR(L22<0,R22<0),"▼ REVIEW","▶ HOLD")) -> ▲ STRONG
B24: COST BASIS | D24: TOP HOLDING | F24: TOP 3 CONC. | H24: AVG RETURN | J24: PROFITABLE | L24: HHI INDEX | N24: ▲ STRONG | O24: ▶ HOLD | P24: ▼ REVIEW | Q24: PROFIT FACTOR | R24: SORTINO RATIO | S24: CALMAR RATIO | T24: PORT. GRADE
B25: =SUM(_xlfn.ANCHORARRAY(G7))-SUM(_xlfn.ANCHORARRAY(J7)) -> 132051.42 | D25: =INDEX(_xlfn.ANCHORARRAY(B7),MATCH(MAX(M7:M22),M7:M22,0))&" "&TEXT(MAX(M7:M22),"0.0%") -> NVDA 29.3% | F25: =LARGE(M7:M22,1)+LARGE(M7:M22,2)+LARGE(M7:M22,3) -> 0.44719592 | H25: =AVERAGE(L7:L22) -> 1.268515 | J25: =COUNTIF(J7:J22,">0")&" / "&COUNTA(J7:J22) -> 14 / 16 | L25: {=SUMPRODUCT((SUMIF(_xlfn.ANCHORARRAY(D7),_xlfn.UNIQUE(_xlfn.ANCHORARRAY(D7)),_xlfn.ANCHORARRAY(G7))/SUM(_xlfn.ANCHORARRAY(G7)))^2)} -> 0.18756228 | N25: =COUNTIF(T7:T22,"*STRONG*") -> 3 | O25: =COUNTIF(T7:T22,"*HOLD*") -> 11 | P25: =COUNTIF(T7:T22,"*REVIEW*") -> 2 | Q25: =SUMIF(J7:J22,">0")/ABS(SUMIF(J7:J22,"<0")) -> 136.88421 | R25: {=(AVERAGE(L7:L22)-0.05)/SQRT(SUMPRODUCT((L7:L22<0)*(L7:L22)^2)/COUNTA(L7:L22))} -> 35.473741 | S25: =H3/ABS(R3) -> 1.1123746 | T25: =Analytics!H44 -> B+
B28: SECTOR ALLOCATION | H28: REBALANCING ANALYSIS
B29: Industry | D29: Market Value | E29: Weight % | F29: HHI Contrib. | H29: Stock | I29: Current Wt. | J29: Equal Wt. | K29: Deviation | L29: Action | M29: Vol Band (±) | N29: Tax Flag | O29: Vol Action
B30: {=_xlfn.UNIQUE(_xlfn.ANCHORARRAY(D7))} -> Aerospace & Defense | D30: {=SUMIF(_xlfn.ANCHORARRAY(D7),_xlfn.ANCHORARRAY(B30),_xlfn.ANCHORARRAY(G7))} -> 25243.7 | E30: =D30/SUM(D$30:D$39) -> 0.083125883 | F30: =E30^2 -> 0.0069099124 | H30: =N7 -> 0R2N | I30: =M7 -> 0.051357301 | J30: =1/COUNTA(M$7:M$22) -> 0.0625 | K30: =M7-(1/COUNTA(M$7:M$22)) -> -0.011142699 | L30: =IF(ABS(K30)>0.1,IF(K30>0,"🔻 TRIM","🔺 ADD"),IF(ABS(K30)>0.03,IF(K30>0,"▿ trim","▵ add"),"✔ OK")) -> ✔ OK | M30: =0.5*IFERROR(INDEX('Risk Analytics'!D$39:D$54,MATCH(H30,'Risk Analytics'!B$39:B$54,0))*0.155,0.08) -> 0.03193 | N30: =IF(AND(L30<>"✔ OK",COUNTIFS(Ledger[Ticker],H30,Ledger[Transaction Type],"Buy",Ledger[Holding Days],"<365")>0),"⚠ HIGH TAX","") | O30: =IF(ABS(K30)>M30,IF(K30>0,"🔻 VOL-TRIM","🔺 VOL-ADD"),"✔ WITHIN BAND") -> ✔ WITHIN BAND
B31: Computers, Phones & Household Electronics | D31: 14239.349 | E31: =D31/SUM(D$30:D$39) -> 0.046889262 | F31: =E31^2 -> 0.0021986029 | H31: =N8 -> AAPL | I31: =M8 -> 0.046889262 | J31: =1/COUNTA(M$7:M$22) -> 0.0625 | K31: =M8-(1/COUNTA(M$7:M$22)) -> -0.015610738 | L31: =IF(ABS(K31)>0.1,IF(K31>0,"🔻 TRIM","🔺 ADD"),IF(ABS(K31)>0.03,IF(K31>0,"▿ trim","▵ add"),"✔ OK")) -> ✔ OK | M31: =0.5*IFERROR(INDEX('Risk Analytics'!D$39:D$54,MATCH(H31,'Risk Analytics'!B$39:B$54,0))*0.155,0.08) -> 0.08552125 | N31: =IF(AND(L31<>"✔ OK",COUNTIFS(Ledger[Ticker],H31,Ledger[Transaction Type],"Buy",Ledger[Holding Days],"<365")>0),"⚠ HIGH TAX","") | O31: =IF(ABS(K31)>M31,IF(K31>0,"🔻 VOL-TRIM","🔺 VOL-ADD"),"✔ WITHIN BAND") -> ✔ WITHIN BAND
B32: Semiconductors & Semiconductor Equipment | D32: 112710.93 | E32: =D32/SUM(D$30:D$39) -> 0.37114984 | F32: =E32^2 -> 0.1377522 | H32: =N9 -> AMD | I32: =M9 -> 0.077751595 | J32: =1/COUNTA(M$7:M$22) -> 0.0625 | K32: =M9-(1/COUNTA(M$7:M$22)) -> 0.015251595 | L32: =IF(ABS(K32)>0.1,IF(K32>0,"🔻 TRIM","🔺 ADD"),IF(ABS(K32)>0.03,IF(K32>0,"▿ trim","▵ add"),"✔ OK")) -> ✔ OK | M32: =0.5*IFERROR(INDEX('Risk Analytics'!D$39:D$54,MATCH(H32,'Risk Analytics'!B$39:B$54,0))*0.155,0.08) -> 0.15437225 | N32: =IF(AND(L32<>"✔ OK",COUNTIFS(Ledger[Ticker],H32,Ledger[Transaction Type],"Buy",Ledger[Holding Days],"<365")>0),"⚠ HIGH TAX","") | O32: =IF(ABS(K32)>M32,IF(K32>0,"🔻 VOL-TRIM","🔺 VOL-ADD"),"✔ WITHIN BAND") -> ✔ WITHIN BAND
B33: Diversified Retail | D33: 9655.6252 | E33: =D33/SUM(D$30:D$39) -> 0.031795354 | F33: =E33^2 -> 0.0010109445 | H33: =N10 -> AMZN | I33: =M10 -> 0.031795354 | J33: =1/COUNTA(M$7:M$22) -> 0.0625 | K33: =M10-(1/COUNTA(M$7:M$22)) -> -0.030704646 | L33: =IF(ABS(K33)>0.1,IF(K33>0,"🔻 TRIM","🔺 ADD"),IF(ABS(K33)>0.03,IF(K33>0,"▿ trim","▵ add"),"✔ OK")) -> ▵ add | M33: =0.5*IFERROR(INDEX('Risk Analytics'!D$39:D$54,MATCH(H33,'Risk Analytics'!B$39:B$54,0))*0.155,0.08) -> 0.10564025 | N33: =IF(AND(L33<>"✔ OK",COUNTIFS(Ledger[Ticker],H33,Ledger[Transaction Type],"Buy",Ledger[Holding Days],"<365")>0),"⚠ HIGH TAX","") | O33: =IF(ABS(K33)>M33,IF(K33>0,"🔻 VOL-TRIM","🔺 VOL-ADD"),"✔ WITHIN BAND") -> ✔ WITHIN BAND
B34: Investment Banking & Investment Services | D34: 27469.586 | E34: =D34/SUM(D$30:D$39) -> 0.09045558 | F34: =E34^2 -> 0.008182212 | H34: =N11 -> BA | I34: =M11 -> 0.031768582 | J34: =1/COUNTA(M$7:M$22) -> 0.0625 | K34: =M11-(1/COUNTA(M$7:M$22)) -> -0.030731418 | L34: =IF(ABS(K34)>0.1,IF(K34>0,"🔻 TRIM","🔺 ADD"),IF(ABS(K34)>0.03,IF(K34>0,"▿ trim","▵ add"),"✔ OK")) -> ▵ add | M34: =0.5*IFERROR(INDEX('Risk Analytics'!D$39:D$54,MATCH(H34,'Risk Analytics'!B$39:B$54,0))*0.155,0.08) -> 0.0913415 | N34: =IF(AND(L34<>"✔ OK",COUNTIFS(Ledger[Ticker],H34,Ledger[Transaction Type],"Buy",Ledger[Holding Days],"<365")>0),"⚠ HIGH TAX","") | O34: =IF(ABS(K34)>M34,IF(K34>0,"🔻 VOL-TRIM","🔺 VOL-ADD"),"✔ WITHIN BAND") -> ✔ WITHIN BAND
B35: Oil & Gas | D35: 14662.192 | E35: =D35/SUM(D$30:D$39) -> 0.048281655 | F35: =E35^2 -> 0.0023311182 | H35: =N12 -> BLK | I35: =M12 -> 0.036674855 | J35: =1/COUNTA(M$7:M$22) -> 0.0625 | K35: =M12-(1/COUNTA(M$7:M$22)) -> -0.025825145 | L35: =IF(ABS(K35)>0.1,IF(K35>0,"🔻 TRIM","🔺 ADD"),IF(ABS(K35)>0.03,IF(K35>0,"▿ trim","▵ add"),"✔ OK")) -> ✔ OK | M35: =0.5*IFERROR(INDEX('Risk Analytics'!D$39:D$54,MATCH(H35,'Risk Analytics'!B$39:B$54,0))*0.155,0.08) -> 0.11528125 | N35: =IF(AND(L35<>"✔ OK",COUNTIFS(Ledger[Ticker],H35,Ledger[Transaction Type],"Buy",Ledger[Holding Days],"<365")>0),"⚠ HIGH TAX","") | O35: =IF(ABS(K35)>M35,IF(K35>0,"🔻 VOL-TRIM","🔺 VOL-ADD"),"✔ WITHIN BAND") -> ✔ WITHIN BAND
B36: Automobiles & Auto Parts | D36: 23298.549 | E36: =D36/SUM(D$30:D$39) -> 0.076720624 | F36: =E36^2 -> 0.0058860541 | H36: =N13 -> C | I36: =M13 -> 0.053780726 | J36: =1/COUNTA(M$7:M$22) -> 0.0625 | K36: =M13-(1/COUNTA(M$7:M$22)) -> -0.0087192744 | L36: =IF(ABS(K36)>0.1,IF(K36>0,"🔻 TRIM","🔺 ADD"),IF(ABS(K36)>0.03,IF(K36>0,"▿ trim","▵ add"),"✔ OK")) -> ✔ OK | M36: =0.5*IFERROR(INDEX('Risk Analytics'!D$39:D$54,MATCH(H36,'Risk Analytics'!B$39:B$54,0))*0.155,0.08) -> 0.08645125 | N36: =IF(AND(L36<>"✔ OK",COUNTIFS(Ledger[Ticker],H36,Ledger[Transaction Type],"Buy",Ledger[Holding Days],"<365")>0),"⚠ HIGH TAX","") | O36: =IF(ABS(K36)>M36,IF(K36>0,"🔻 VOL-TRIM","🔺 VOL-ADD"),"✔ WITHIN BAND") -> ✔ WITHIN BAND
B37: Software & IT Services | D37: 36498.031 | E37: =D37/SUM(D$30:D$39) -> 0.12018567 | F37: =E37^2 -> 0.014444595 | H37: =N14 -> CVX | I37: =M14 -> 0.048281655 | J37: =1/COUNTA(M$7:M$22) -> 0.0625 | K37: =M14-(1/COUNTA(M$7:M$22)) -> -0.014218345 | L37: =IF(ABS(K37)>0.1,IF(K37>0,"🔻 TRIM","🔺 ADD"),IF(ABS(K37)>0.03,IF(K37>0,"▿ trim","▵ add"),"✔ OK")) -> ✔ OK | M37: =0.5*IFERROR(INDEX('Risk Analytics'!D$39:D$54,MATCH(H37,'Risk Analytics'!B$39:B$54,0))*0.155,0.08) -> 0.047213 | N37: =IF(AND(L37<>"✔ OK",COUNTIFS(Ledger[Ticker],H37,Ledger[Transaction Type],"Buy",Ledger[Holding Days],"<365")>0),"⚠ HIGH TAX","") | O37: =IF(ABS(K37)>M37,IF(K37>0,"🔻 VOL-TRIM","🔺 VOL-ADD"),"✔ WITHIN BAND") -> ✔ WITHIN BAND
B38: Banking Services | D38: 16808.725 | E38: =D38/SUM(D$30:D$39) -> 0.055350051 | F38: =E38^2 -> 0.0030636281 | H38: =N15 -> F | I38: =M15 -> 0.028354674 | J38: =1/COUNTA(M$7:M$22) -> 0.0625 | K38: =M15-(1/COUNTA(M$7:M$22)) -> -0.034145326 | L38: =IF(ABS(K38)>0.1,IF(K38>0,"🔻 TRIM","🔺 ADD"),IF(ABS(K38)>0.03,IF(K38>0,"▿ trim","▵ add"),"✔ OK")) -> ▵ add | M38: =0.5*IFERROR(INDEX('Risk Analytics'!D$39:D$54,MATCH(H38,'Risk Analytics'!B$39:B$54,0))*0.155,0.08) -> 0.13609775 | N38: =IF(AND(L38<>"✔ OK",COUNTIFS(Ledger[Ticker],H38,Ledger[Transaction Type],"Buy",Ledger[Holding Days],"<365")>0),"⚠ HIGH TAX","") | O38: =IF(ABS(K38)>M38,IF(K38>0,"🔻 VOL-TRIM","🔺 VOL-ADD"),"✔ WITHIN BAND") -> ✔ WITHIN BAND
B39: Food & Drug Retailing | D39: 23093.704 | E39: =D39/SUM(D$30:D$39) -> 0.076046083 | F39: =E39^2 -> 0.0057830067 | H39: =N16 -> GOOG | I39: =M16 -> 0.065883101 | J39: =1/COUNTA(M$7:M$22) -> 0.0625 | K39: =M16-(1/COUNTA(M$7:M$22)) -> 0.0033831012 | L39: =IF(ABS(K39)>0.1,IF(K39>0,"🔻 TRIM","🔺 ADD"),IF(ABS(K39)>0.03,IF(K39>0,"▿ trim","▵ add"),"✔ OK")) -> ✔ OK | M39: =0.5*IFERROR(INDEX('Risk Analytics'!D$39:D$54,MATCH(H39,'Risk Analytics'!B$39:B$54,0))*0.155,0.08) -> 0.085281 | N39: =IF(AND(L39<>"✔ OK",COUNTIFS(Ledger[Ticker],H39,Ledger[Transaction Type],"Buy",Ledger[Holding Days],"<365")>0),"⚠ HIGH TAX","") | O39: =IF(ABS(K39)>M39,IF(K39>0,"🔻 VOL-TRIM","🔺 VOL-ADD"),"✔ WITHIN BAND") -> ✔ WITHIN BAND
H40: =N17 -> HMC | I40: =M17 -> 0.020306274 | J40: =1/COUNTA(M$7:M$22) -> 0.0625 | K40: =M17-(1/COUNTA(M$7:M$22)) -> -0.042193726 | L40: =IF(ABS(K40)>0.1,IF(K40>0,"🔻 TRIM","🔺 ADD"),IF(ABS(K40)>0.03,IF(K40>0,"▿ trim","▵ add"),"✔ OK")) -> ▵ add | M40: =0.5*IFERROR(INDEX('Risk Analytics'!D$39:D$54,MATCH(H40,'Risk Analytics'!B$39:B$54,0))*0.155,0.08) -> 0.03627 | N40: =IF(AND(L40<>"✔ OK",COUNTIFS(Ledger[Ticker],H40,Ledger[Transaction Type],"Buy",Ledger[Holding Days],"<365")>0),"⚠ HIGH TAX","") | O40: =IF(ABS(K40)>M40,IF(K40>0,"🔻 VOL-TRIM","🔺 VOL-ADD"),"✔ WITHIN BAND") -> 🔺 VOL-ADD
B41: ="📊 Portfolio: "&TEXT(B3,"$#,##0")&" | "&TEXT(G3,"0.0%")&" total return ("&TEXT(H3,"0.0%")&" CAGR) | Sharpe "&TEXT(O3,"0.00")&" | Sortino "&TEXT(D4,"0.00")&" | "&COUNTIF(T7:T22,"▲ STRONG")&" strong, "&COUNTIF(T7:T22,"▼ REVIEW")&" review | "&TEXT(S4,"0.0%")&" CF VaR95 | "&IF(J4>0,"Positive","Negative")&" alpha" -> 📊 Portfolio: $303,680 | 130.0% total return (14.9% CAGR) | Sharpe 0.47 | Sortino 3.10 | 3 strong, 2 review | -27.9% CF VaR95 | Positive alpha | H41: =N18 -> JPM | I41: =M18 -> 0.055350051 | J41: =1/COUNTA(M$7:M$22) -> 0.0625 | K41: =M18-(1/COUNTA(M$7:M$22)) -> -0.0071499492 | L41: =IF(ABS(K41)>0.1,IF(K41>0,"🔻 TRIM","🔺 ADD"),IF(ABS(K41)>0.03,IF(K41>0,"▿ trim","▵ add"),"✔ OK")) -> ✔ OK | M41: =0.5*IFERROR(INDEX('Risk Analytics'!D$39:D$54,MATCH(H41,'Risk Analytics'!B$39:B$54,0))*0.155,0.08) -> 0.08226625 | N41: =IF(AND(L41<>"✔ OK",COUNTIFS(Ledger[Ticker],H41,Ledger[Transaction Type],"Buy",Ledger[Holding Days],"<365")>0),"⚠ HIGH TAX","") | O41: =IF(ABS(K41)>M41,IF(K41>0,"🔻 VOL-TRIM","🔺 VOL-ADD"),"✔ WITHIN BAND") -> ✔ WITHIN BAND
H42: =N19 -> META | I42: =M19 -> 0.05430257 | J42: =1/COUNTA(M$7:M$22) -> 0.0625 | K42: =M19-(1/COUNTA(M$7:M$22)) -> -0.0081974304 | L42: =IF(ABS(K42)>0.1,IF(K42>0,"🔻 TRIM","🔺 ADD"),IF(ABS(K42)>0.03,IF(K42>0,"▿ trim","▵ add"),"✔ OK")) -> ✔ OK | M42: =0.5*IFERROR(INDEX('Risk Analytics'!D$39:D$54,MATCH(H42,'Risk Analytics'!B$39:B$54,0))*0.155,0.08) -> 0.10061825 | N42: =IF(AND(L42<>"✔ OK",COUNTIFS(Ledger[Ticker],H42,Ledger[Transaction Type],"Buy",Ledger[Holding Days],"<365")>0),"⚠ HIGH TAX","") | O42: =IF(ABS(K42)>M42,IF(K42>0,"🔻 VOL-TRIM","🔺 VOL-ADD"),"✔ WITHIN BAND") -> ✔ WITHIN BAND
H43: =N20 -> NVDA | I43: =M20 -> 0.29339824 | J43: =1/COUNTA(M$7:M$22) -> 0.0625 | K43: =M20-(1/COUNTA(M$7:M$22)) -> 0.23089824 | L43: =IF(ABS(K43)>0.1,IF(K43>0,"🔻 TRIM","🔺 ADD"),IF(ABS(K43)>0.03,IF(K43>0,"▿ trim","▵ add"),"✔ OK")) -> 🔻 TRIM | M43: =0.5*IFERROR(INDEX('Risk Analytics'!D$39:D$54,MATCH(H43,'Risk Analytics'!B$39:B$54,0))*0.155,0.08) -> 0.18186925 | N43: =IF(AND(L43<>"✔ OK",COUNTIFS(Ledger[Ticker],H43,Ledger[Transaction Type],"Buy",Ledger[Holding Days],"<365")>0),"⚠ HIGH TAX","") | O43: =IF(ABS(K43)>M43,IF(K43>0,"🔻 VOL-TRIM","🔺 VOL-ADD"),"✔ WITHIN BAND") -> 🔻 VOL-TRIM
H44: =N21 -> TM | I44: =M21 -> 0.028059676 | J44: =1/COUNTA(M$7:M$22) -> 0.0625 | K44: =M21-(1/COUNTA(M$7:M$22)) -> -0.034440324 | L44: =IF(ABS(K44)>0.1,IF(K44>0,"🔻 TRIM","🔺 ADD"),IF(ABS(K44)>0.03,IF(K44>0,"▿ trim","▵ add"),"✔ OK")) -> ▵ add | M44: =0.5*IFERROR(INDEX('Risk Analytics'!D$39:D$54,MATCH(H44,'Risk Analytics'!B$39:B$54,0))*0.155,0.08) -> 0.0546065 | N44: =IF(AND(L44<>"✔ OK",COUNTIFS(Ledger[Ticker],H44,Ledger[Transaction Type],"Buy",Ledger[Holding Days],"<365")>0),"⚠ HIGH TAX","") | O44: =IF(ABS(K44)>M44,IF(K44>0,"🔻 VOL-TRIM","🔺 VOL-ADD"),"✔ WITHIN BAND") -> ✔ WITHIN BAND
H45: =N22 -> WMT | I45: =M22 -> 0.076046083 | J45: =1/COUNTA(M$7:M$22) -> 0.0625 | K45: =M22-(1/COUNTA(M$7:M$22)) -> 0.013546083 | L45: =IF(ABS(K45)>0.1,IF(K45>0,"🔻 TRIM","🔺 ADD"),IF(ABS(K45)>0.03,IF(K45>0,"▿ trim","▵ add"),"✔ OK")) -> ✔ OK | M45: =0.5*IFERROR(INDEX('Risk Analytics'!D$39:D$54,MATCH(H45,'Risk Analytics'!B$39:B$54,0))*0.155,0.08) -> 0.0517855 | N45: =IF(AND(L45<>"✔ OK",COUNTIFS(Ledger[Ticker],H45,Ledger[Transaction Type],"Buy",Ledger[Holding Days],"<365")>0),"⚠ HIGH TAX","") | O45: =IF(ABS(K45)>M45,IF(K45>0,"🔻 VOL-TRIM","🔺 VOL-ADD"),"✔ WITHIN BAND") -> ✔ WITHIN BAND

Sheet WL Dashboard
B2: WATCHLIST DASHBOARD
B3: TOTAL MARKET CAP | C3: AVG P/E RATIO | D3: AVG BETA | E3: HIGHEST P/E | F3: LOWEST P/E | G3: TOP GAINER TODAY | H3: TOP LOSER TODAY | I3: STOCKS | J3: INDUSTRIES | K3: MEDIAN P/E
B4: =SUM(Watchlist!J2:INDEX(Watchlist!J:J,COUNTA(Watchlist!J:J))) -> 5465783557158 | C4: =AVERAGE(Watchlist!F2:INDEX(Watchlist!F:F,COUNTA(Watchlist!F:F))) -> 30.44653 | D4: =AVERAGE(Watchlist!E2:INDEX(Watchlist!E:E,COUNTA(Watchlist!E:E))) -> 0.98949 | E4: {=INDEX(Watchlist!B:B,MATCH(MAX(Watchlist!F$2:INDEX(Watchlist!F:F,COUNTA(Watchlist!F:F))),Watchlist!F$2:INDEX(Watchlist!F:F,COUNTA(Watchlist!F:F)),0)+1)&" "&TEXT(MAX(Watchlist!F$2:INDEX(Watchlist!F:F,COUNTA(Watchlist!F:F))),"0.0x")} -> AMD 84.6x | F4: {=INDEX(Watchlist!B:B,MATCH(MIN(Watchlist!F$2:INDEX(Watchlist!F:F,COUNTA(Watchlist!F:F))),Watchlist!F$2:INDEX(Watchlist!F:F,COUNTA(Watchlist!F:F)),0)+1)&" "&TEXT(MIN(Watchlist!F$2:INDEX(Watchlist!F:F,COUNTA(Watchlist!F:F))),"0.0x")} -> BAC 13.2x | G4: {="▲ "&INDEX(Watchlist!B:B,MATCH(MAX(Watchlist!G$2:INDEX(Watchlist!G:G,COUNTA(Watchlist!G:G))),Watchlist!G$2:INDEX(Watchlist!G:G,COUNTA(Watchlist!G:G)),0)+1)} -> ▲ AMD | H4: {="▼ "&INDEX(Watchlist!B:B,MATCH(MIN(Watchlist!G$2:INDEX(Watchlist!G:G,COUNTA(Watchlist!G:G))),Watchlist!G$2:INDEX(Watchlist!G:G,COUNTA(Watchlist!G:G)),0)+1)} -> ▼ MSFT | I4: =COUNTA(Watchlist!B2:INDEX(Watchlist!B:B,COUNTA(Watchlist!B:B))) -> 10 | J4: =COUNTA(_xlfn.UNIQUE(Watchlist!K2:INDEX(Watchlist!K:K,COUNTA(Watchlist!K:K)))) -> 9 | K4: =MEDIAN(Watchlist!F2:INDEX(Watchlist!F:F,COUNTA(Watchlist!F:F))) -> 22.813
B6: ="WATCHLIST · "&COUNTA(Watchlist!B2:B100)&" STOCKS · LIVE MARKET DATA · 52-WEEK ANALYSIS" -> WATCHLIST · 10 STOCKS · LIVE MARKET DATA · 52-WEEK ANALYSIS
B7: Ticker | C7: Industry | D7: Current Price | E7: Change ($) | F7: P/E Ratio | G7: Beta | H7: Market Cap | I7: 52W High | J7: 52W Low | K7: 52W Range % | L7: In Portfolio?
B8: =Watchlist!B3 -> MSFT | C8: =Watchlist!K3 -> Software & IT Services | D8: {=_FV(Watchlist!A3,"Price")} -> 371.44 | E8: =Watchlist!G3 -> -2.02 | F8: =Watchlist!F3 -> 23.2406 | G8: =Watchlist!E3 -> 1.103 | H8: =Watchlist!J3 -> 2758175635760 | I8: =Watchlist!C3 -> 555.45 | J8: =Watchlist!D3 -> 344.79 | K8: {=(_FV(Watchlist!A3,"Price")-Watchlist!D3)/(Watchlist!C3-Watchlist!D3)} -> 0.12650717 | L8: =IF(COUNTIF(Ledger[Ticker],B8)>0,"⚠ IN PORTFOLIO","✔ UNIQUE") -> ✔ UNIQUE | M8: =B8 -> MSFT | N8: =K8 -> 0.12650717
B9: =Watchlist!B4 -> BABA | C9: =Watchlist!K4 -> Software & IT Services | D9: {=_FV(Watchlist!A4,"Price")} -> 122.68 | E9: =Watchlist!G4 -> 0.63 | F9: =Watchlist!F4 -> 16.6848 | G9: =Watchlist!E4 -> 0.4949 | H9: =Watchlist!J4 -> 292887826840 | I9: =Watchlist!C4 -> 192.67 | J9: =Watchlist!D4 -> 94.9742 | K9: {=(_FV(Watchlist!A4,"Price")-Watchlist!D4)/(Watchlist!C4-Watchlist!D4)} -> 0.28359254 | L9: =IF(COUNTIF(Ledger[Ticker],B9)>0,"⚠ IN PORTFOLIO","✔ UNIQUE") -> ✔ UNIQUE | M9: =B9 -> BABA | N9: =K9 -> 0.28359254
B10: =Watchlist!B5 -> DELL | C10: =Watchlist!K5 -> Computers, Phones & Household Electronics | D10: {=_FV(Watchlist!A5,"Price")} -> 173.15 | E10: =Watchlist!G5 -> -1.22 | F10: =Watchlist!F5 -> 19.8578 | G10: =Watchlist!E5 -> 0.8573 | H10: =Watchlist!J5 -> 111811352775 | I10: =Watchlist!C5 -> 186.39 | J10: =Watchlist!D5 -> 66.245 | K10: {=(_FV(Watchlist!A5,"Price")-Watchlist!D5)/(Watchlist!C5-Watchlist!D5)} -> 0.88979983 | L10: =IF(COUNTIF(Ledger[Ticker],B10)>0,"⚠ IN PORTFOLIO","✔ UNIQUE") -> ✔ UNIQUE | M10: =B10 -> DELL | N10: =K10 -> 0.88979983
B11: =Watchlist!B6 -> GS | C11: =Watchlist!K6 -> Investment Banking & Investment Services | D11: {=_FV(Watchlist!A6,"Price")} -> 865.7427 | E11: =Watchlist!G6 -> 2.7027 | F11: =Watchlist!F6 -> 16.8759 | G11: =Watchlist!E6 -> 1.3147 | H11: =Watchlist!J6 -> 255388815469 | I11: =Watchlist!C6 -> 984.7 | J11: =Watchlist!D6 -> 439.38 | K11: {=(_FV(Watchlist!A6,"Price")-Watchlist!D6)/(Watchlist!C6-Watchlist!D6)} -> 0.78185781 | L11: =IF(COUNTIF(Ledger[Ticker],B11)>0,"⚠ IN PORTFOLIO","✔ UNIQUE") -> ✔ UNIQUE | M11: =B11 -> GS | N11: =K11 -> 0.78185781
B12: =Watchlist!B7 -> XOM | C12: =Watchlist!K7 -> Oil & Gas | D12: {=_FV(Watchlist!A7,"Price")} -> 161.03 | E12: =Watchlist!G7 -> 0.34 | F12: =Watchlist!F7 -> 24.1045 | G12: =Watchlist!E7 -> 0.2919 | H12: =Watchlist!J7 -> 670974006920 | I12: =Watchlist!C7 -> 176.41 | J12: =Watchlist!D7 -> 97.8 | K12: {=(_FV(Watchlist!A7,"Price")-Watchlist!D7)/(Watchlist!C7-Watchlist!D7)} -> 0.80435059 | L12: =IF(COUNTIF(Ledger[Ticker],B12)>0,"⚠ IN PORTFOLIO","✔ UNIQUE") -> ✔ UNIQUE | M12: =B12 -> XOM | N12: =K12 -> 0.80435059
B13: =Watchlist!B8 -> GM | C13: =Watchlist!K8 -> Automobiles & Auto Parts | D13: {=_FV(Watchlist!A8,"Price")} -> 73.16 | E13: =Watchlist!G8 -> 0.62 | F13: =Watchlist!F8 -> 22.3854 | G13: =Watchlist!E8 -> 1.3733 | H13: =Watchlist!J8 -> 66134284248 | I13: =Watchlist!C8 -> 87.62 | J13: =Watchlist!D8 -> 41.6 | K13: {=(_FV(Watchlist!A8,"Price")-Watchlist!D8)/(Watchlist!C8-Watchlist!D8)} -> 0.68578879 | L13: =IF(COUNTIF(Ledger[Ticker],B13)>0,"⚠ IN PORTFOLIO","✔ UNIQUE") -> ✔ UNIQUE | M13: =B13 -> GM | N13: =K13 -> 0.68578879
B14: =Watchlist!B9 -> BAC | C14: =Watchlist!K9 -> Banking Services | D14: {=_FV(Watchlist!A9,"Price")} -> 49.835 | E14: =Watchlist!G9 -> 0.455 | F14: =Watchlist!F9 -> 13.1741 | G14: =Watchlist!E9 -> 1.2422 | H14: =Watchlist!J9 -> 356106408015 | I14: =Watchlist!C9 -> 57.55 | J14: =Watchlist!D9 -> 33.065 | K14: {=(_FV(Watchlist!A9,"Price")-Watchlist!D9)/(Watchlist!C9-Watchlist!D9)} -> 0.68490913 | L14: =IF(COUNTIF(Ledger[Ticker],B14)>0,"⚠ IN PORTFOLIO","✔ UNIQUE") -> ✔ UNIQUE | M14: =B14 -> BAC | N14: =K14 -> 0.68490913
B15: =Watchlist!B10 -> LMT | C15: =Watchlist!K10 -> Aerospace & Defense | D15: {=_FV(Watchlist!A10,"Price")} -> 624.5687 | E15: =Watchlist!G10 -> 1.7787 | F15: =Watchlist!F10 -> 29.0685 | G15: =Watchlist!E10 -> 0.2367 | H15: =Watchlist!J10 -> 143939414196 | I15: =Watchlist!C10 -> 692 | J15: =Watchlist!D10 -> 410.11 | K15: {=(_FV(Watchlist!A10,"Price")-Watchlist!D10)/(Watchlist!C10-Watchlist!D10)} -> 0.76078861 | L15: =IF(COUNTIF(Ledger[Ticker],B15)>0,"⚠ IN PORTFOLIO","✔ UNIQUE") -> ✔ UNIQUE | M15: =B15 -> LMT | N15: =K15 -> 0.76078861
B16: =Watchlist!B11 -> COST | C16: =Watchlist!K11 -> Diversified Retail | D16: {=_FV(Watchlist!A11,"Price")} -> 1016.87 | E16: =Watchlist!G11 -> 1.91 | F16: =Watchlist!F11 -> 54.4707 | G16: =Watchlist!E11 -> 0.989 | H16: =Watchlist!J11 -> 451136917675 | I16: =Watchlist!C11 -> 1067.08 | J16: =Watchlist!D11 -> 844.06 | K16: {=(_FV(Watchlist!A11,"Price")-Watchlist!D11)/(Watchlist!C11-Watchlist!D11)} -> 0.77486324 | L16: =IF(COUNTIF(Ledger[Ticker],B16)>0,"⚠ IN PORTFOLIO","✔ UNIQUE") -> ✔ UNIQUE | M16: =B16 -> COST | N16: =K16 -> 0.77486324
B17: =Watchlist!B2 -> AMD | C17: =Watchlist!K2 -> Semiconductors & Semiconductor Equipment | D17: {=_FV(Watchlist!A2,"Price")} -> 220.34 | E17: =Watchlist!G2 -> 2.84 | F17: =Watchlist!F2 -> 84.603 | G17: =Watchlist!E2 -> 1.9919 | H17: =Watchlist!J2 -> 359228895260 | I17: =Watchlist!C2 -> 267.0799 | J17: =Watchlist!D2 -> 76.48 | K17: {=(_FV(Watchlist!A2,"Price")-Watchlist!D2)/(Watchlist!C2-Watchlist!D2)} -> 0.75477479 | L17: =IF(COUNTIF(Ledger[Ticker],B17)>0,"⚠ IN PORTFOLIO","✔ UNIQUE") -> ⚠ IN PORTFOLIO | M17: =B17 -> AMD | N17: =K17 -> 0.75477479
B18: VISUALIZATIONS
B50: 52-WEEK RANGE ANALYSIS
B52: Industry | C52: Market Cap
B53: {=_xlfn.UNIQUE(C8:C16)} -> Software & IT Services | C53: {=SUMIF(C8:C16,_xlfn.ANCHORARRAY(B53),H8:H16)} -> 3051063462600
B54: Computers, Phones & Household Electronics | C54: 111811352775
B55: Investment Banking & Investment Services | C55: 255388815469
B56: Oil & Gas | C56: 670974006920
B57: Automobiles & Auto Parts | C57: 66134284248
B58: Banking Services | C58: 356106408015
B59: Aerospace & Defense | C59: 143939414196
B60: Diversified Retail | C60: 451136917675
B63: COMPARATIVE VALUATION & MOMENTUM ANALYTICS
B64: Multi-Factor Scoring Model — Ranks Watchlist Stocks by Value, Momentum & Risk
B65: Ticker | C65: P/E | D65: P/E Rank | E65: Beta | F65: Risk Rank | G65: 52W Range % | H65: Momentum | I65: Value Score | J65: Composite | K65: Signal
B66: =B8 -> MSFT | C66: =F8 -> 23.2406 | D66: =RANK(F8,F$8:F$17,1) -> 6 | E66: =G8 -> 1.103 | F66: =RANK(G8,G$8:G$17,1) -> 6 | G66: =K8 -> 0.12650717 | H66: =IF(K8>0.7,"▲ STRONG",IF(K8>0.3,"▶ NEUTRAL","▼ WEAK")) -> ▼ WEAK | I66: =(RANK(F8,F$8:F$17,1)*0.4)+(RANK(G8,G$8:G$17,1)*0.3)+(RANK(K8,K$8:K$17,0)*0.3) -> 7.2 | J66: =RANK(I66,I$66:I$75,1) -> 9 | K66: =IF(J66<=3,"⭐ BUY",IF(J66<=7,"🔍 WATCH","⚠️ AVOID")) -> ⚠️ AVOID
B67: =B9 -> BABA | C67: =F9 -> 16.6848 | D67: =RANK(F9,F$8:F$17,1) -> 2 | E67: =G9 -> 0.4949 | F67: =RANK(G9,G$8:G$17,1) -> 3 | G67: =K9 -> 0.28359254 | H67: =IF(K9>0.7,"▲ STRONG",IF(K9>0.3,"▶ NEUTRAL","▼ WEAK")) -> ▼ WEAK | I67: =(RANK(F9,F$8:F$17,1)*0.4)+(RANK(G9,G$8:G$17,1)*0.3)+(RANK(K9,K$8:K$17,0)*0.3) -> 4.4 | J67: =RANK(I67,I$66:I$75,1) -> 3 | K67: =IF(J67<=3,"⭐ BUY",IF(J67<=7,"🔍 WATCH","⚠️ AVOID")) -> ⭐ BUY
B68: =B10 -> DELL | C68: =F10 -> 19.8578 | D68: =RANK(F10,F$8:F$17,1) -> 4 | E68: =G10 -> 0.8573 | F68: =RANK(G10,G$8:G$17,1) -> 4 | G68: =K10 -> 0.88979983 | H68: =IF(K10>0.7,"▲ STRONG",IF(K10>0.3,"▶ NEUTRAL","▼ WEAK")) -> ▲ STRONG | I68: =(RANK(F10,F$8:F$17,1)*0.4)+(RANK(G10,G$8:G$17,1)*0.3)+(RANK(K10,K$8:K$17,0)*0.3) -> 3.1 | J68: =RANK(I68,I$66:I$75,1) -> 1 | K68: =IF(J68<=3,"⭐ BUY",IF(J68<=7,"🔍 WATCH","⚠️ AVOID")) -> ⭐ BUY
B69: =B11 -> GS | C69: =F11 -> 16.8759 | D69: =RANK(F11,F$8:F$17,1) -> 3 | E69: =G11 -> 1.3147 | F69: =RANK(G11,G$8:G$17,1) -> 8 | G69: =K11 -> 0.78185781 | H69: =IF(K11>0.7,"▲ STRONG",IF(K11>0.3,"▶ NEUTRAL","▼ WEAK")) -> ▲ STRONG | I69: =(RANK(F11,F$8:F$17,1)*0.4)+(RANK(G11,G$8:G$17,1)*0.3)+(RANK(K11,K$8:K$17,0)*0.3) -> 4.5 | J69: =RANK(I69,I$66:I$75,1) -> 4 | K69: =IF(J69<=3,"⭐ BUY",IF(J69<=7,"🔍 WATCH","⚠️ AVOID")) -> 🔍 WATCH
B70: =B12 -> XOM | C70: =F12 -> 24.1045 | D70: =RANK(F12,F$8:F$17,1) -> 7 | E70: =G12 -> 0.2919 | F70: =RANK(G12,G$8:G$17,1) -> 2 | G70: =K12 -> 0.80435059 | H70: =IF(K12>0.7,"▲ STRONG",IF(K12>0.3,"▶ NEUTRAL","▼ WEAK")) -> ▲ STRONG | I70: =(RANK(F12,F$8:F$17,1)*0.4)+(RANK(G12,G$8:G$17,1)*0.3)+(RANK(K12,K$8:K$17,0)*0.3) -> 4 | J70: =RANK(I70,I$66:I$75,1) -> 2 | K70: =IF(J70<=3,"⭐ BUY",IF(J70<=7,"🔍 WATCH","⚠️ AVOID")) -> ⭐ BUY
B71: =B13 -> GM | C71: =F13 -> 22.3854 | D71: =RANK(F13,F$8:F$17,1) -> 5 | E71: =G13 -> 1.3733 | F71: =RANK(G13,G$8:G$17,1) -> 9 | G71: =K13 -> 0.68578879 | H71: =IF(K13>0.7,"▲ STRONG",IF(K13>0.3,"▶ NEUTRAL","▼ WEAK")) -> ▶ NEUTRAL | I71: =(RANK(F13,F$8:F$17,1)*0.4)+(RANK(G13,G$8:G$17,1)*0.3)+(RANK(K13,K$8:K$17,0)*0.3) -> 6.8 | J71: =RANK(I71,I$66:I$75,1) -> 8 | K71: =IF(J71<=3,"⭐ BUY",IF(J71<=7,"🔍 WATCH","⚠️ AVOID")) -> ⚠️ AVOID
B72: =B14 -> BAC | C72: =F14 -> 13.1741 | D72: =RANK(F14,F$8:F$17,1) -> 1 | E72: =G14 -> 1.2422 | F72: =RANK(G14,G$8:G$17,1) -> 7 | G72: =K14 -> 0.68490913 | H72: =IF(K14>0.7,"▲ STRONG",IF(K14>0.3,"▶ NEUTRAL","▼ WEAK")) -> ▶ NEUTRAL | I72: =(RANK(F14,F$8:F$17,1)*0.4)+(RANK(G14,G$8:G$17,1)*0.3)+(RANK(K14,K$8:K$17,0)*0.3) -> 4.9 | J72: =RANK(I72,I$66:I$75,1) -> 5 | K72: =IF(J72<=3,"⭐ BUY",IF(J72<=7,"🔍 WATCH","⚠️ AVOID")) -> 🔍 WATCH
B73: =B15 -> LMT | C73: =F15 -> 29.0685 | D73: =RANK(F15,F$8:F$17,1) -> 8 | E73: =G15 -> 0.2367 | F73: =RANK(G15,G$8:G$17,1) -> 1 | G73: =K15 -> 0.76078861 | H73: =IF(K15>0.7,"▲ STRONG",IF(K15>0.3,"▶ NEUTRAL","▼ WEAK")) -> ▲ STRONG | I73: =(RANK(F15,F$8:F$17,1)*0.4)+(RANK(G15,G$8:G$17,1)*0.3)+(RANK(K15,K$8:K$17,0)*0.3) -> 5 | J73: =RANK(I73,I$66:I$75,1) -> 6 | K73: =IF(J73<=3,"⭐ BUY",IF(J73<=7,"🔍 WATCH","⚠️ AVOID")) -> 🔍 WATCH
B74: =B16 -> COST | C74: =F16 -> 54.4707 | D74: =RANK(F16,F$8:F$17,1) -> 9 | E74: =G16 -> 0.989 | F74: =RANK(G16,G$8:G$17,1) -> 5 | G74: =K16 -> 0.77486324 | H74: =IF(K16>0.7,"▲ STRONG",IF(K16>0.3,"▶ NEUTRAL","▼ WEAK")) -> ▲ STRONG | I74: =(RANK(F16,F$8:F$17,1)*0.4)+(RANK(G16,G$8:G$17,1)*0.3)+(RANK(K16,K$8:K$17,0)*0.3) -> 6.3 | J74: =RANK(I74,I$66:I$75,1) -> 7 | K74: =IF(J74<=3,"⭐ BUY",IF(J74<=7,"🔍 WATCH","⚠️ AVOID")) -> 🔍 WATCH
B75: =B17 -> AMD | C75: =F17 -> 84.603 | D75: =RANK(F17,F$8:F$17,1) -> 10 | E75: =G17 -> 1.9919 | F75: =RANK(G17,G$8:G$17,1) -> 10 | G75: =K17 -> 0.75477479 | H75: =IF(K17>0.7,"▲ STRONG",IF(K17>0.3,"▶ NEUTRAL","▼ WEAK")) -> ▲ STRONG | I75: =(RANK(F17,F$8:F$17,1)*0.4)+(RANK(G17,G$8:G$17,1)*0.3)+(RANK(K17,K$8:K$17,0)*0.3) -> 8.8 | J75: =RANK(I75,I$66:I$75,1) -> 10 | K75: =IF(J75<=3,"⭐ BUY",IF(J75<=7,"🔍 WATCH","⚠️ AVOID")) -> ⚠️ AVOID
B77: ⭐ BUY SIGNALS | C77: 🔍 WATCH LIST | D77: ⚠️ AVOID | E77: AVG P/E (BUYS) | F77: AVG BETA (BUYS) | G77: CHEAPEST STOCK | H77: RISKIEST STOCK | I77: BEST VALUE/RISK | J77: STRONG MOMENTUM | K77: WEAK MOMENTUM
B78: =COUNTIF(K66:K75,"*BUY*") -> 3 | C78: =COUNTIF(K66:K75,"*WATCH*") -> 4 | D78: =COUNTIF(K66:K75,"*AVOID*") -> 3 | E78: =AVERAGEIF(K66:K75,"*BUY*",C66:C75) -> 20.2157 | F78: =AVERAGEIF(K66:K75,"*BUY*",E66:E75) -> 0.54803333 | G78: =INDEX(B66:B75,MATCH(MIN(C66:C75),C66:C75,0)) -> BAC | H78: =INDEX(B66:B75,MATCH(MAX(E66:E75),E66:E75,0)) -> AMD | I78: =INDEX(B66:B75,MATCH(1,J66:J75,0)) -> DELL | J78: =COUNTIF(H66:H75,"*STRONG*") -> 6 | K78: =COUNTIF(H66:H75,"*WEAK*") -> 2

Sheet Analytics
A1: PORTFOLIO ANALYTICS
A2: Advanced Financial Metrics & Risk Analysis
A4: KEY PORTFOLIO METRICS
A5: Total Cost Basis | B5: Total Market Value | C5: Unrealised P&L | D5: Total Return % | E5: CAGR | F5: # Holdings | G5: Best Performer | H5: Worst Performer
A6: =SUM(Dashboard!G7:G22)-SUM(Dashboard!J7:J22) -> 132051.42 | B6: =SUM(Dashboard!G7:G22) -> 303680.39 | C6: =SUM(Dashboard!J7:J22) -> 171628.96 | D6: =C6/A6 -> 1.2997131 | E6: =(B6/A6)^(1/((MAX(Ledger[Date])-MIN(Ledger[Date]))/365.25))-1 -> 0.14885493 | F6: =COUNTA(Dashboard!N7:N22) -> 16 | G6: =INDEX(Dashboard!N7:N22,MATCH(MAX(Dashboard!J7:J22),Dashboard!J7:J22,0)) -> NVDA | H6: =INDEX(Dashboard!N7:N22,MATCH(MIN(Dashboard!J7:J22),Dashboard!J7:J22,0)) -> HMC
A8: INDIVIDUAL STOCK ANALYSIS
A9: Stock | B9: Cost Basis | C9: Market Value | D9: Gain/(Loss) | E9: Return % | F9: Weight % | G9: Avg Buy Price | H9: ="CAGR ("&TEXT((MAX(Ledger[Date])-MIN(Ledger[Date]))/365.25,"0")&"yr)" -> CAGR (6yr)
A10: =Dashboard!N7 -> 0R2N | B10: =Dashboard!G7-Dashboard!J7 -> 7915.049 | C10: =Dashboard!G7 -> 15596.205 | D10: =Dashboard!J7 -> 7681.156 | E10: =Dashboard!L7 -> 0.97044958 | F10: =Dashboard!M7 -> 0.051357301 | G10: =Dashboard!P7 -> 99.723435 | H10: =Dashboard!R7 -> 0.1196519
A11: =Dashboard!N8 -> AAPL | B11: =Dashboard!G8-Dashboard!J8 -> 7391.6634 | C11: =Dashboard!G8 -> 14239.349 | D11: =Dashboard!J8 -> 6847.6858 | E11: =Dashboard!L8 -> 0.92640661 | F11: =Dashboard!M8 -> 0.046889262 | G11: =Dashboard!P8 -> 134.54065 | H11: =Dashboard!R8 -> 0.11544245
A12: =Dashboard!N9 -> AMD | B12: =Dashboard!G9-Dashboard!J9 -> 7394.5581 | C12: =Dashboard!G9 -> 23611.634 | D12: =Dashboard!J9 -> 16217.076 | E12: =Dashboard!L9 -> 2.1931096 | F12: =Dashboard!M9 -> 0.077751595 | G12: =Dashboard!P9 -> 69.004835 | H12: =Dashboard!R9 -> 0.21343486
A13: =Dashboard!N10 -> AMZN | B13: =Dashboard!G10-Dashboard!J10 -> 6470.8786 | C13: =Dashboard!G10 -> 9655.6252 | D13: =Dashboard!J10 -> 3184.7467 | E13: =Dashboard!L10 -> 0.49216603 | F13: =Dashboard!M10 -> 0.031795354 | G13: =Dashboard!P10 -> 142.37357 | H13: =Dashboard!R10 -> 0.0689636
A14: =Dashboard!N11 -> BA | B14: =Dashboard!G11-Dashboard!J11 -> 9957.8624 | C14: =Dashboard!G11 -> 9647.4951 | D14: =Dashboard!J11 -> -310.3673 | E14: =Dashboard!L11 -> -0.031168065 | F14: =Dashboard!M11 -> 0.031768582 | G14: =Dashboard!P11 -> 217.46806 | H14: =Dashboard!R11 -> -0.0052622557
A15: =Dashboard!N12 -> BLK | B15: =Dashboard!G12-Dashboard!J12 -> 8680.5252 | C15: =Dashboard!G12 -> 11137.434 | D15: =Dashboard!J12 -> 2456.9088 | E15: =Dashboard!L12 -> 0.28303688 | F15: =Dashboard!M12 -> 0.036674855 | G15: =Dashboard!P12 -> 751.56062 | H15: =Dashboard!R12 -> 0.042403214
A16: =Dashboard!N13 -> C | B16: =Dashboard!G13-Dashboard!J13 -> 8304.7689 | C16: =Dashboard!G13 -> 16332.151 | D16: =Dashboard!J13 -> 8027.3826 | E16: =Dashboard!L13 -> 0.96659915 | F16: =Dashboard!M13 -> 0.053780726 | G16: =Dashboard!P13 -> 59.264746 | H16: =Dashboard!R13 -> 0.11928704
A17: =Dashboard!N14 -> CVX | B17: =Dashboard!G14-Dashboard!J14 -> 9879.199 | C17: =Dashboard!G14 -> 14662.192 | D17: =Dashboard!J14 -> 4782.9928 | E17: =Dashboard!L14 -> 0.48414783 | F17: =Dashboard!M14 -> 0.048281655 | G17: =Dashboard!P14 -> 132.87423 | H17: =Dashboard!R14 -> 0.068004316
A18: =Dashboard!N15 -> F | B18: =Dashboard!G15-Dashboard!J15 -> 7913.8448 | C18: =Dashboard!G15 -> 8610.7582 | D18: =Dashboard!J15 -> 696.91345 | E18: =Dashboard!L15 -> 0.088062562 | F18: =Dashboard!M15 -> 0.028354674 | G18: =Dashboard!P15 -> 10.638175 | H18: =Dashboard!R15 -> 0.014162585
A19: =Dashboard!N16 -> GOOG | B19: =Dashboard!G16-Dashboard!J16 -> 7854.4309 | C19: =Dashboard!G16 -> 20007.406 | D19: =Dashboard!J16 -> 12152.975 | E19: =Dashboard!L16 -> 1.5472763 | F19: =Dashboard!M16 -> 0.065883101 | G19: =Dashboard!P16 -> 116.15544 | H19: =Dashboard!R16 -> 0.16859468
A20: =Dashboard!N17 -> HMC | B20: =Dashboard!G17-Dashboard!J17 -> 7119.3027 | C20: =Dashboard!G17 -> 6166.617 | D20: =Dashboard!J17 -> -952.6857 | E20: =Dashboard!L17 -> -0.13381728 | F20: =Dashboard!M17 -> 0.020306274 | G20: =Dashboard!P17 -> 27.546151 | H20: =Dashboard!R17 -> -0.023653535
A21: =Dashboard!N18 -> JPM | B21: =Dashboard!G18-Dashboard!J18 -> 9431.1376 | C21: =Dashboard!G18 -> 16808.725 | D21: =Dashboard!J18 -> 7377.5872 | E21: =Dashboard!L18 -> 0.78225846 | F21: =Dashboard!M18 -> 0.055350051 | G21: =Dashboard!P18 -> 165.92431 | H21: =Dashboard!R18 -> 0.10108008
... A25: =Dashboard!N22 -> WMT | B25: =Dashboard!G22-Dashboard!J22 -> 9897.421 | C25: =Dashboard!G22 -> 23093.704 | D25: =Dashboard!J22 -> 13196.283 | E25: =Dashboard!L22 -> 1.3333052 | F25: =Dashboard!M22 -> 0.076046083 | G25: =Dashboard!P22 -> 54.184939 | H25: =Dashboard!R22 -> 0.15163433
A27: SECTOR CONCENTRATION & RISK | F27: RISK METRICS
A28: Industry | B28: Market Value | C28: Weight % | D28: HHI Contrib. | F28: Metric | G28: Value | H28: Status
A29: {=IFERROR(INDEX(_xlfn.UNIQUE(Dashboard!D7:D22),1),"")} -> Aerospace & Defense | B29: =IF(A29="","",SUMIF(Dashboard!D7:D22,A29,Dashboard!G7:G22)) -> 25243.7 | C29: =IF(A29="","",B29/SUM($B$29:$B$38)) -> 0.083125883 | D29: =IF(A29="","",C29^2) -> 0.0069099124 | F29: Total Invested | G29: =A6 -> 132051.42 | H29: =IF(B6>A6,"✅ Positive","⚠️ Loss") -> ✅ Positive
A30: {=IFERROR(INDEX(_xlfn.UNIQUE(Dashboard!D7:D22),2),"")} -> Computers, Phones & Household Electronics | B30: =IF(A30="","",SUMIF(Dashboard!D7:D22,A30,Dashboard!G7:G22)) -> 14239.349 | C30: =IF(A30="","",B30/SUM($B$29:$B$38)) -> 0.046889262 | D30: =IF(A30="","",C30^2) -> 0.0021986029 | F30: Current Value | G30: =B6 -> 303680.39 | H30: =IF(G30>G29*1.5,"✅ Strong Growth",IF(G30>G29,"🟢 Positive","🔴 Drawdown")) -> ✅ Strong Growth
A31: {=IFERROR(INDEX(_xlfn.UNIQUE(Dashboard!D7:D22),3),"")} -> Semiconductors & Semiconductor Equipment | B31: =IF(A31="","",SUMIF(Dashboard!D7:D22,A31,Dashboard!G7:G22)) -> 112710.93 | C31: =IF(A31="","",B31/SUM($B$29:$B$38)) -> 0.37114984 | D31: =IF(A31="","",C31^2) -> 0.1377522 | F31: Worst Stock Return | G31: =MIN(E10:E25) -> -0.13381728 | H31: =IF(G31<-0.2,"🔴 High Risk",IF(G31<-0.1,"🟡 Moderate","🟢 Low Risk")) -> 🟡 Moderate
A32: {=IFERROR(INDEX(_xlfn.UNIQUE(Dashboard!D7:D22),4),"")} -> Diversified Retail | B32: =IF(A32="","",SUMIF(Dashboard!D7:D22,A32,Dashboard!G7:G22)) -> 9655.6252 | C32: =IF(A32="","",B32/SUM($B$29:$B$38)) -> 0.031795354 | D32: =IF(A32="","",C32^2) -> 0.0010109445 | F32: Top Holding Weight | G32: =MAX(F10:F25) -> 0.29339824 | H32: =IF(G32>0.5,"🔴 Over-concentrated",IF(G32>0.3,"🟡 Monitor","🟢 Balanced")) -> 🟢 Balanced
A33: {=IFERROR(INDEX(_xlfn.UNIQUE(Dashboard!D7:D22),5),"")} -> Investment Banking & Investment Services | B33: =IF(A33="","",SUMIF(Dashboard!D7:D22,A33,Dashboard!G7:G22)) -> 27469.586 | C33: =IF(A33="","",B33/SUM($B$29:$B$38)) -> 0.09045558 | D33: =IF(A33="","",C33^2) -> 0.008182212 | F33: Top 3 Concentration | G33: =LARGE(F10:F25,1)+LARGE(F10:F25,2)+LARGE(F10:F25,3) -> 0.44719592 | H33: =IF(G33>0.7,"🔴 Top-heavy",IF(G33>0.5,"🟡 Monitor","🟢 Balanced")) -> 🟢 Balanced
A34: {=IFERROR(INDEX(_xlfn.UNIQUE(Dashboard!D7:D22),6),"")} -> Oil & Gas | B34: =IF(A34="","",SUMIF(Dashboard!D7:D22,A34,Dashboard!G7:G22)) -> 14662.192 | C34: =IF(A34="","",B34/SUM($B$29:$B$38)) -> 0.048281655 | D34: =IF(A34="","",C34^2) -> 0.0023311182 | F34: Avg Return per Stock | G34: =AVERAGE(E10:E25) -> 1.268515 | H34: =IF(G34>1,"✅ Strong",IF(G34>0.5,"🟢 Positive","🟡 Weak")) -> ✅ Strong
A35: {=IFERROR(INDEX(_xlfn.UNIQUE(Dashboard!D7:D22),7),"")} -> Automobiles & Auto Parts | B35: =IF(A35="","",SUMIF(Dashboard!D7:D22,A35,Dashboard!G7:G22)) -> 23298.549 | C35: =IF(A35="","",B35/SUM($B$29:$B$38)) -> 0.076720624 | D35: =IF(A35="","",C35^2) -> 0.0058860541 | F35: Profitable Positions | G35: =COUNTIF(D10:D25,">0")&"/"&COUNTA(D10:D25) -> 14/16 | H35: =IF(COUNTIF(D10:D25,">0")/COUNTA(D10:D25)>0.8,"✅ High Win Rate",IF(COUNTIF(D10:D25,">0")/COUNTA(D10:D25)>0.5,"🟢 Above 50%","🔴 Below 50%")) -> ✅ High Win Rate
A36: {=IFERROR(INDEX(_xlfn.UNIQUE(Dashboard!D7:D22),8),"")} -> Software & IT Services | B36: =IF(A36="","",SUMIF(Dashboard!D7:D22,A36,Dashboard!G7:G22)) -> 36498.031 | C36: =IF(A36="","",B36/SUM($B$29:$B$38)) -> 0.12018567 | D36: =IF(A36="","",C36^2) -> 0.014444595
A37: {=IFERROR(INDEX(_xlfn.UNIQUE(Dashboard!D7:D22),9),"")} -> Banking Services | B37: =IF(A37="","",SUMIF(Dashboard!D7:D22,A37,Dashboard!G7:G22)) -> 16808.725 | C37: =IF(A37="","",B37/SUM($B$29:$B$38)) -> 0.055350051 | D37: =IF(A37="","",C37^2) -> 0.0030636281 | F37: PORTFOLIO HEALTH SCORECARD
A38: {=IFERROR(INDEX(_xlfn.UNIQUE(Dashboard!D7:D22),10),"")} -> Food & Drug Retailing | B38: =IF(A38="","",SUMIF(Dashboard!D7:D22,A38,Dashboard!G7:G22)) -> 23093.704 | C38: =IF(A38="","",B38/SUM($B$29:$B$38)) -> 0.076046083 | D38: =IF(A38="","",C38^2) -> 0.0057830067 | F38: Category | G38: Score | H38: Grade
A39: HHI Index (Concentration) | D39: =SUM(D29:D38) -> 0.18756228 | F39: Return Performance | G39: =IF(E6>0.15,10,IF(E6>0.1,8,IF(E6>0.05,6,IF(E6>0,4,2)))) -> 8 | H39: =IF(G39>=8,"A",IF(G39>=6,"B",IF(G39>=4,"C","D"))) -> A
A40: Interpretation: | B40: =IF(D39<0.15,"Well Diversified",IF(D39<0.25,"Moderately Concentrated","Highly Concentrated")) -> Moderately Concentrated | F40: Risk Management | G40: =IF(G31>-0.05,10,IF(G31>-0.1,8,IF(G31>-0.2,6,IF(G31>-0.5,4,2)))) -> 6 | H40: =IF(G40>=8,"A",IF(G40>=6,"B",IF(G40>=4,"C","D"))) -> B
F41: Diversification | G41: =IF(D39<0.1,10,IF(D39<0.15,8,IF(D39<0.25,6,IF(D39<0.5,4,2)))) -> 6 | H41: =IF(G41>=8,"A",IF(G41>=6,"B",IF(G41>=4,"C","D"))) -> B
A42: ADVANCED PORTFOLIO ANALYTICS | F42: Win Rate | G42: =IF(COUNTIF(D10:D25,">0")/COUNTA(D10:D25)>0.9,10,IF(COUNTIF(D10:D25,">0")/COUNTA(D10:D25)>0.75,8,IF(COUNTIF(D10:D25,">0")/COUNTA(D10:D25)>0.5,6,4))) -> 8 | H42: =IF(G42>=8,"A",IF(G42>=6,"B",IF(G42>=4,"C","D"))) -> A
A43: Institutional-Grade Risk & Return Decomposition | F43: Sector Breadth | G43: =IF(COUNTA(A29:A38)>=8,10,IF(COUNTA(A29:A38)>=6,8,IF(COUNTA(A29:A38)>=4,6,4))) -> 10 | H43: =IF(G43>=8,"A",IF(G43>=6,"B",IF(G43>=4,"C","D"))) -> A
F44: OVERALL PORTFOLIO GRADE | G44: =AVERAGE(G39:G43) -> 7.6 | H44: =IF(G44>=8,"A",IF(G44>=6,"B+",IF(G44>=5,"B",IF(G44>=4,"C","D")))) -> B+
A45: RETURN ATTRIBUTION & RISK DECOMPOSITION
A46: Metric | B46: Value | C46: Benchmark | D46: Assessment
A47: Portfolio CAGR (7yr) | B47: =E6 -> 0.14885493 | C47: 0.1 | D47: =IF(B47>C47,"✅ Outperforming","⚠️ Underperforming") -> ✅ Outperforming
A48: Portfolio Beta (βp) | B48: ='Risk Analytics'!C9 -> 1.4726694 | C48: β = 1.0 = Market | D48: =IF(B48>1.3,"🔴 Aggressive",IF(B48>1,"🟡 Above Market",IF(B48>0.7,"🟢 Moderate","🔵 Defensive"))) -> 🔴 Aggressive
A49: Jensen's Alpha (αp) | B49: ='Risk Analytics'!C11 -> 0.021676445 | C49: α > 0 = Skill | D49: =IF(B49>0.03,"✅ Significant Alpha",IF(B49>0,"🟢 Positive Alpha","🔴 Negative Alpha")) -> 🟢 Positive Alpha
A50: Sharpe Ratio (Rp−Rf)/σp | B50: ='Risk Analytics'!C18 -> 0.46593002 | C50: Rf = 4.25% | D50: =IF(B50>2,"✅ Exceptional",IF(B50>1,"🟢 Good",IF(B50>0.5,"🟡 Adequate","🔴 Poor"))) -> 🔴 Poor
A51: Treynor Ratio (Rp−Rf)/βp | B51: ='Risk Analytics'!C15 -> 0.072219153 | C51: Per unit β risk | D51: =IF(B51>0.1,"✅ Excellent",IF(B51>0.05,"🟢 Good","🟡 Weak")) -> 🟢 Good
A52: Sortino Ratio | B52: ='Risk Analytics'!C19 -> 3.0962339 | C52: Downside σ Only | D52: =IF(B52>3,"✅ Excellent",IF(B52>2,"🟢 Good",IF(B52>1,"🟡 Adequate","🔴 Poor"))) -> ✅ Excellent
A53: M² (Modigliani-Modigliani) | B53: ='Risk Analytics'!C68 -> 0.014719153 | C53: M² > 0 = outperform | D53: =IF(B53>0,"✅ Risk-Adj. Outperformance","🔴 Underperformance") -> ✅ Risk-Adj. Outperformance
A54: Calmar Ratio | B54: ='Risk Analytics'!C20 -> 1.1123746 | C54: CAGR / Max Loss | D54: =IF(B54>3,"✅ Excellent",IF(B54>1,"🟢 Good","🟡 Monitor")) -> 🟢 Good
A55: Win/Loss Ratio | B55: {=AVERAGE(IF(E10:E25>0,E10:E25))/ABS(AVERAGE(IF(E10:E25<0,E10:E25)))} -> 17.71692 | C55: Avg Win / Avg Loss | D55: =IF(B55>5,"✅ Excellent Asymmetry",IF(B55>3,"✅ Strong",IF(B55>1.5,"🟢 Good","🟡 Thin"))) -> ✅ Excellent Asymmetry
A56: Profit Factor | B56: =SUMIF(D10:D25,">0")/ABS(SUMIF(D10:D25,"<0")) -> 136.88421 | C56: Profit / Loss | D56: =IF(B56>10,"✅ Overwhelming Gains",IF(B56>3,"✅ Excellent",IF(B56>1.5,"🟢 Profitable",IF(B56>1,"🟡 Marginal","🔴 Losing")))) -> ✅ Overwhelming Gains
A57: Effective Diversification (1/HHI) | B57: =1/D39 -> 5.3315625 | C57: 10-20 ideal | D57: =IF(B57>=10,"✅ Well Diversified",IF(B57>=5,"🟡 Moderate","🔴 Concentrated")) -> 🟡 Moderate
A58: PORTFOLIO CONSTRUCTION ANALYSIS
A59: Metric | B59: Value | C59: Optimal Range | D59: Assessment
A60: Effective Diversification (1/HHI) | B60: =1/D39 -> 5.3315625 | C60: 10–20 ideal | D60: =IF(B60>=10,"✅ Well Diversified",IF(B60>=5,"🟡 Moderate","🔴 Concentrated")) -> 🟡 Moderate
A61: Position Size Spread (Max/Min) | B61: =MAX(F10:F25)/MIN(F10:F25) -> 14.44865 | C61: < 5x balanced | D61: =IF(B61>10,"🔴 Extreme Dispersion",IF(B61>5,"🟡 Skewed","🟢 Balanced")) -> 🔴 Extreme Dispersion
A62: Top Sector Weight | B62: =MAX(C29:C38) -> 0.37114984 | C62: < 30% balanced | D62: =IF(B62>0.4,"🔴 Sector Risk",IF(B62>0.3,"🟡 Monitor","🟢 Balanced")) -> 🟡 Monitor
A63: Active Share (vs Equal Wt.) | B63: ='Risk Analytics'!C62 -> 0.26307902 | C63: > 60% Active | D63: =IF(B63>0.6,"✅ Stock Picker",IF(B63>0.3,"🟢 Active","🟡 Closet Indexer")) -> 🟡 Closet Indexer
A64: Weighted Avg Return | B64: =SUMPRODUCT(F10:F25,E10:E25) -> 3.3554062 | C64: > CAGR = good | D64: =IF(B64>1,"✅ Large caps pulling weight",IF(B64>0.5,"🟢 Positive","🟡 Weak")) -> ✅ Large caps pulling weight

Sheet Risk Analytics
B1: RISK ANALYTICS
B2: CFA-Level Quantitative Risk & Return Decomposition
B4: CAPM & FACTOR ANALYSIS
B5: Metric | C5: Value | D5: Context | E5: Assessment
B6: Risk-Free Rate (Rf) | C6: 0.0425 | D6: US 10Y Treasury | E6: Input Assumption
B7: Market Return (Rm) | C7: 0.1 | D7: S&P 500 LT Avg | E7: Input Assumption
B8: Equity Risk Premium (Rm − Rf) | C8: =C7-C6 -> 0.0575 | D8: Historical: 4-6% | E8: =IF(C8>0.06,"✅ Above Average",IF(C8>0.04,"🟢 Normal Range","🟡 Below Average")) -> 🟢 Normal Range
B9: Portfolio Beta (βp) | C9: =SUMPRODUCT(C39:C54,D39:D54) -> 1.4726694 | D9: β = 1.0 = Market | E9: =IF(C9>1.3,"🔴 Aggressive",IF(C9>1,"🟡 Above Market",IF(C9>0.7,"🟢 Moderate","🔵 Defensive"))) -> 🔴 Aggressive
B10: Expected Return — CAPM: E(Rp) = Rf + βp(Rm − Rf) | C10: =C6+C9*(C7-C6) -> 0.12717849 | D10: CAPM Equilibrium | E10: =IF(C10>0.12,"✅ High Expected",IF(C10>0.08,"🟢 Moderate","🟡 Conservative")) -> ✅ High Expected
B11: Jensen's Alpha (αp) = Rp − [Rf + βp(Rm − Rf)] | C11: =Analytics!E6-C10 -> 0.021676445 | D11: α > 0 = Skill | E11: =IF(C11>0.03,"✅ Significant Alpha",IF(C11>0,"🟢 Positive Alpha","🔴 Negative Alpha")) -> 🟢 Positive Alpha
B13: ADVANCED RISK METRICS
B14: Metric | C14: Value | D14: Benchmark / Context | E14: Assessment
B15: Treynor Ratio = (Rp − Rf) / βp | C15: =IF(C9=0,"N/A",(Analytics!E6-C6)/C9) -> 0.072219153 | D15: Per unit β risk | E15: =IF(C9=0,"⚠️ Awaiting Beta",IF(C15>0.1,"✅ Excellent",IF(C15>0.05,"🟢 Good","🟡 Weak"))) -> 🟢 Good
B16: Information Ratio = α / Tracking Error | C16: =IF(C17=0,"N/A",C11/C17) -> 0.18770861 | D16: > 0.5 Good, > 1.0 Elite | E16: =IF(C17=0,"⚠️ N/A",IF(C16>1,"✅ Exceptional",IF(C16>0.5,"🟢 Good",IF(C16>0,"🟡 Marginal","🔴 Negative")))) -> 🟡 Marginal
B17: Tracking Error (σε) — Active Risk | C17: {=STDEV(Analytics!H10:H25-Analytics!E6)} -> 0.11547923 | D17: < 2% Passive, > 5% Active | E17: =IF(ABS(C17)>0.05,"🔴 High Active Risk",IF(ABS(C17)>0.02,"🟡 Moderate","🟢 Index-Like")) -> 🔴 High Active Risk
B18: Sharpe Ratio = (Rp − Rf) / σp | C18: =(Analytics!E6-C6)/C25 -> 0.46593002 | D18: > 1.0 Good, > 2.0 Elite | E18: =IF(C18>2,"✅ Exceptional",IF(C18>1,"🟢 Good",IF(C18>0.5,"🟡 Adequate","🔴 Poor"))) -> 🔴 Poor
B19: Sortino Ratio = (Rp − Rf) / Downside σ | C19: {=(Analytics!E6-C6)/SQRT(SUMPRODUCT((Analytics!E10:E25<0)*(Analytics!E10:E25)^2)/COUNT(Analytics!E10:E25))} -> 3.0962339 | D19: > 2.0 Good, > 3.0 Elite | E19: =IF(C19>3,"✅ Excellent",IF(C19>2,"🟢 Good",IF(C19>1,"🟡 Adequate","🔴 Poor"))) -> ✅ Excellent
B20: Calmar Ratio = CAGR / Max Drawdown | C20: =Analytics!E6/ABS(MIN(Analytics!E10:E25)) -> 1.1123746 | D20: > 1.0 Good, > 3.0 Elite | E20: =IF(C20>3,"✅ Excellent",IF(C20>1,"🟢 Good","🟡 Monitor")) -> 🟢 Good
B22: VALUE AT RISK (VaR) & TAIL RISK
B23: Metric | C23: Value | D23: Context | E23: Interpretation
B24: Portfolio Mean Return (Annualised) | C24: =Analytics!E6 -> 0.14885493 | D24: ="CAGR ("&TEXT((MAX(Ledger[Date])-MIN(Ledger[Date]))/365.25,"0")&"yr)" -> CAGR (6yr) | E24: Geometric mean
B25: Est. Portfolio Volatility (βp × σm) | C25: =C9*0.155 -> 0.22826375 | D25: βp × σm (est.) | E25: =IF(C25>0.3,"🔴 High Dispersion",IF(C25>0.15,"🟡 Moderate","🟢 Low")) -> 🟡 Moderate
B26: Parametric VaR (95%, 1-Year) | C26: =C24-1.645*C25 -> -0.22663894 | D26: 95% confidence | E26: ="Max 1Y loss: "&TEXT(ABS(C26)*SUM(Dashboard!G7:G22),"$#,##0") -> Max 1Y loss: $68,826
B27: Parametric VaR (99%, 1-Year) | C27: =C24-2.326*C25 -> -0.38208656 | D27: 99% confidence | E27: ="Max 1Y loss: "&TEXT(ABS(C27)*SUM(Dashboard!G7:G22),"$#,##0") -> Max 1Y loss: $116,032
B28: Expected Shortfall (CVaR 95%) | C28: =C24-2.063*C25 -> -0.32205319 | D28: Avg loss beyond VaR | E28: ="Tail loss: "&TEXT(ABS(C28)*SUM(Dashboard!G7:G22),"$#,##0") -> Tail loss: $97,801
B29: Max Individual Position Loss | C29: =MIN(Analytics!E10:E25) -> -0.13381728 | D29: =INDEX(Analytics!A10:A25,MATCH(MIN(Analytics!E10:E25),Analytics!E10:E25,0)) -> HMC | E29: ="$ Loss: "&TEXT(ABS(MIN(Analytics!D10:D25)),"$#,##0") -> $ Loss: $953
B30: Downside Deviation (Semi-σ) | C30: {=SQRT(SUMPRODUCT((Analytics!E10:E25<0)*(Analytics!E10:E25)^2)/COUNT(Analytics!E10:E25))} -> 0.034349774 | D30: Negative returns only | E30: =IF(C30<C25/2,"✅ Low Downside",IF(C30<C25,"🟢 Acceptable","🔴 High Downside")) -> ✅ Low Downside
B32: PORTFOLIO CONSTRUCTION & DIVERSIFICATION
B33: Metric | C33: Value | D33: Optimal Range | E33: Assessment
B34: Effective # Positions (1/HHI) | C34: {=1/SUMPRODUCT((Dashboard!M7:'Dashboard'!M22)^2)} -> 8.0845713 | D34: 10–20 ideal | E34: =IF(C34>=10,"✅ Well Diversified",IF(C34>=5,"🟡 Moderate","🔴 Concentrated")) -> 🟡 Moderate
B35: Largest / Smallest Position Ratio | C35: =MAX(Dashboard!M7:'Dashboard'!M22)/MIN(Dashboard!M7:'Dashboard'!M22) -> 14.44865 | D35: < 5x balanced | E35: =IF(C35>10,"🔴 Extreme Dispersion",IF(C35>5,"🟡 Skewed","🟢 Balanced")) -> 🔴 Extreme Dispersion
B37: INDIVIDUAL STOCK RISK DECOMPOSITION
B38: Ticker | C38: Weight | D38: Beta (βi) | E38: CAGR | F38: Return % | G38: Risk Contrib. | H38: CAPM E(Ri) | I38: Stock αi | J38: Style
B39: =Dashboard!N7 -> 0R2N | C39: =Dashboard!M7 -> 0.051357301 | D39: {=IFERROR(_FV(INDEX(Ledger[Stock],MATCH(B39,Ledger[Ticker],0)),"Beta"),1)} -> 0.412 | E39: =Dashboard!R7 -> 0.1196519 | F39: =Dashboard!L7 -> 0.97044958 | G39: =C39*D39 -> 0.021159208 | H39: =$C$6+D39*($C$7-$C$6) -> 0.06619 | I39: =E39-H39 -> 0.053461903 | J39: =IF(F39>1.5,"Growth",IF(F39>0.5,"Blend",IF(F39>0,"Value","Distressed"))) -> Blend
B40: =Dashboard!N8 -> AAPL | C40: =Dashboard!M8 -> 0.046889262 | D40: {=IFERROR(_FV(INDEX(Ledger[Stock],MATCH(B40,Ledger[Ticker],0)),"Beta"),1)} -> 1.1035 | E40: =Dashboard!R8 -> 0.11544245 | F40: =Dashboard!L8 -> 0.92640661 | G40: =C40*D40 -> 0.051742301 | H40: =$C$6+D40*($C$7-$C$6) -> 0.10595125 | I40: =E40-H40 -> 0.009491199 | J40: =IF(F40>1.5,"Growth",IF(F40>0.5,"Blend",IF(F40>0,"Value","Distressed"))) -> Blend
B41: =Dashboard!N9 -> AMD | C41: =Dashboard!M9 -> 0.077751595 | D41: {=IFERROR(_FV(INDEX(Ledger[Stock],MATCH(B41,Ledger[Ticker],0)),"Beta"),1)} -> 1.9919 | E41: =Dashboard!R9 -> 0.21343486 | F41: =Dashboard!L9 -> 2.1931096 | G41: =C41*D41 -> 0.1548734 | H41: =$C$6+D41*($C$7-$C$6) -> 0.15703425 | I41: =E41-H41 -> 0.056400614 | J41: =IF(F41>1.5,"Growth",IF(F41>0.5,"Blend",IF(F41>0,"Value","Distressed"))) -> Growth
B42: =Dashboard!N10 -> AMZN | C42: =Dashboard!M10 -> 0.031795354 | D42: {=IFERROR(_FV(INDEX(Ledger[Stock],MATCH(B42,Ledger[Ticker],0)),"Beta"),1)} -> 1.3631 | E42: =Dashboard!R10 -> 0.0689636 | F42: =Dashboard!L10 -> 0.49216603 | G42: =C42*D42 -> 0.043340246 | H42: =$C$6+D42*($C$7-$C$6) -> 0.12087825 | I42: =E42-H42 -> -0.05191465 | J42: =IF(F42>1.5,"Growth",IF(F42>0.5,"Blend",IF(F42>0,"Value","Distressed"))) -> Value
B43: =Dashboard!N11 -> BA | C43: =Dashboard!M11 -> 0.031768582 | D43: {=IFERROR(_FV(INDEX(Ledger[Stock],MATCH(B43,Ledger[Ticker],0)),"Beta"),1)} -> 1.1786 | E43: =Dashboard!R11 -> -0.0052622557 | F43: =Dashboard!L11 -> -0.031168065 | G43: =C43*D43 -> 0.03744245 | H43: =$C$6+D43*($C$7-$C$6) -> 0.1102695 | I43: =E43-H43 -> -0.11553176 | J43: =IF(F43>1.5,"Growth",IF(F43>0.5,"Blend",IF(F43>0,"Value","Distressed"))) -> Distressed
B44: =Dashboard!N12 -> BLK | C44: =Dashboard!M12 -> 0.036674855 | D44: {=IFERROR(_FV(INDEX(Ledger[Stock],MATCH(B44,Ledger[Ticker],0)),"Beta"),1)} -> 1.4875 | E44: =Dashboard!R12 -> 0.042403214 | F44: =Dashboard!L12 -> 0.28303688 | G44: =C44*D44 -> 0.054553846 | H44: =$C$6+D44*($C$7-$C$6) -> 0.12803125 | I44: =E44-H44 -> -0.085628036 | J44: =IF(F44>1.5,"Growth",IF(F44>0.5,"Blend",IF(F44>0,"Value","Distressed"))) -> Value
B45: =Dashboard!N13 -> C | C45: =Dashboard!M13 -> 0.053780726 | D45: {=IFERROR(_FV(INDEX(Ledger[Stock],MATCH(B45,Ledger[Ticker],0)),"Beta"),1)} -> 1.1155 | E45: =Dashboard!R13 -> 0.11928704 | F45: =Dashboard!L13 -> 0.96659915 | G45: =C45*D45 -> 0.059992399 | H45: =$C$6+D45*($C$7-$C$6) -> 0.10664125 | I45: =E45-H45 -> 0.01264579 | J45: =IF(F45>1.5,"Growth",IF(F45>0.5,"Blend",IF(F45>0,"Value","Distressed"))) -> Blend
B46: =Dashboard!N14 -> CVX | C46: =Dashboard!M14 -> 0.048281655 | D46: {=IFERROR(_FV(INDEX(Ledger[Stock],MATCH(B46,Ledger[Ticker],0)),"Beta"),1)} -> 0.6092 | E46: =Dashboard!R14 -> 0.068004316 | F46: =Dashboard!L14 -> 0.48414783 | G46: =C46*D46 -> 0.029413184 | H46: =$C$6+D46*($C$7-$C$6) -> 0.077529 | I46: =E46-H46 -> -0.0095246839 | J46: =IF(F46>1.5,"Growth",IF(F46>0.5,"Blend",IF(F46>0,"Value","Distressed"))) -> Value
B47: =Dashboard!N15 -> F | C47: =Dashboard!M15 -> 0.028354674 | D47: {=IFERROR(_FV(INDEX(Ledger[Stock],MATCH(B47,Ledger[Ticker],0)),"Beta"),1)} -> 1.7561 | E47: =Dashboard!R15 -> 0.014162585 | F47: =Dashboard!L15 -> 0.088062562 | G47: =C47*D47 -> 0.049793642 | H47: =$C$6+D47*($C$7-$C$6) -> 0.14347575 | I47: =E47-H47 -> -0.12931316 | J47: =IF(F47>1.5,"Growth",IF(F47>0.5,"Blend",IF(F47>0,"Value","Distressed"))) -> Value
B48: =Dashboard!N16 -> GOOG | C48: =Dashboard!M16 -> 0.065883101 | D48: {=IFERROR(_FV(INDEX(Ledger[Stock],MATCH(B48,Ledger[Ticker],0)),"Beta"),1)} -> 1.1004 | E48: =Dashboard!R16 -> 0.16859468 | F48: =Dashboard!L16 -> 1.5472763 | G48: =C48*D48 -> 0.072497765 | H48: =$C$6+D48*($C$7-$C$6) -> 0.105773 | I48: =E48-H48 -> 0.062821679 | J48: =IF(F48>1.5,"Growth",IF(F48>0.5,"Blend",IF(F48>0,"Value","Distressed"))) -> Growth
B49: =Dashboard!N17 -> HMC | C49: =Dashboard!M17 -> 0.020306274 | D49: {=IFERROR(_FV(INDEX(Ledger[Stock],MATCH(B49,Ledger[Ticker],0)),"Beta"),1)} -> 0.468 | E49: =Dashboard!R17 -> -0.023653535 | F49: =Dashboard!L17 -> -0.13381728 | G49: =C49*D49 -> 0.009503336 | H49: =$C$6+D49*($C$7-$C$6) -> 0.06941 | I49: =E49-H49 -> -0.093063535 | J49: =IF(F49>1.5,"Growth",IF(F49>0.5,"Blend",IF(F49>0,"Value","Distressed"))) -> Distressed
B50: =Dashboard!N18 -> JPM | C50: =Dashboard!M18 -> 0.055350051 | D50: {=IFERROR(_FV(INDEX(Ledger[Stock],MATCH(B50,Ledger[Ticker],0)),"Beta"),1)} -> 1.0615 | E50: =Dashboard!R18 -> 0.10108008 | F50: =Dashboard!L18 -> 0.78225846 | G50: =C50*D50 -> 0.058754079 | H50: =$C$6+D50*($C$7-$C$6) -> 0.10353625 | I50: =E50-H50 -> -0.0024561683 | J50: =IF(F50>1.5,"Growth",IF(F50>0.5,"Blend",IF(F50>0,"Value","Distressed"))) -> Blend
... B54: =Dashboard!N22 -> WMT | C54: =Dashboard!M22 -> 0.076046083 | D54: {=IFERROR(_FV(INDEX(Ledger[Stock],MATCH(B54,Ledger[Ticker],0)),"Beta"),1)} -> 0.6682 | E54: =Dashboard!R22 -> 0.15163433 | F54: =Dashboard!L22 -> 1.3333052 | G54: =C54*D54 -> 0.050813993 | H54: =$C$6+D54*($C$7-$C$6) -> 0.0809215 | I54: =E54-H54 -> 0.070712828 | J54: =IF(F54>1.5,"Growth",IF(F54>0.5,"Blend",IF(F54>0,"Value","Distressed"))) -> Blend
B55: PORTFOLIO TOTAL | C55: =SUM(C39:C54) -> 1 | D55: =C9 -> 1.4726694 | E55: =Analytics!E6 -> 0.14885493 | F55: =Analytics!D6 -> 1.2997131 | G55: =SUM(G39:G54) -> 1.4726694 | H55: =C10 -> 0.12717849 | I55: =C11 -> 0.021676445 | J55: =IF(COUNTIF(J39:J54,"Growth")>COUNTIF(J39:J54,"Value"),"Growth Tilt",IF(COUNTIF(J39:J54,"Value")>COUNTIF(J39:J54,"Growth"),"Value Tilt","Blend")) -> Value Tilt
B57: STYLE FACTOR EXPOSURE
B58: Factor | C58: Exposure | D58: Detail | E58: Assessment
B59: Growth vs Value Tilt | C59: =COUNTIF(J39:J54,"Growth")&" Growth / "&COUNTIF(J39:J54,"Blend")&" Blend / "&COUNTIF(J39:J54,"Value")&" Value" -> 3 Growth / 6 Blend / 5 Value | D59: =J55 -> Value Tilt | E59: =IF(COUNTIF(J39:J54,"Growth")>8,"🟡 Growth Heavy",IF(COUNTIF(J39:J54,"Value")>8,"🟡 Value Heavy","🟢 Balanced Mix")) -> 🟢 Balanced Mix
B60: Size Factor (Weighted Avg β) | C60: =C9 -> 1.4726694 | D60: β = 1.0 neutral | E60: =IF(C9>1.3,"🟡 Momentum/Growth",IF(C9>0.7,"🟢 Core","🔵 Defensive")) -> 🟡 Momentum/Growth
B61: Sector Concentration (HHI) | C61: {=SUMPRODUCT((Dashboard!E30:'Dashboard'!E39)^2)} -> 0.18756228 | D61: < 15% diversified | E61: =IF(C61>0.25,"🔴 Concentrated",IF(C61>0.15,"🟡 Moderate","🟢 Diversified")) -> 🟡 Moderate
B62: Active Share Proxy (vs Equal Wt.) | C62: {=0.5*SUMPRODUCT(ABS(Dashboard!M7:'Dashboard'!M22-1/16))} -> 0.26307902 | D62: > 60% Active | E62: =IF(C62>0.6,"✅ Stock Picker",IF(C62>0.3,"🟢 Active","🟡 Closet Indexer")) -> 🟡 Closet Indexer
B64: CAPITAL MARKET LINE ANALYSIS
B65: Metric | C65: Value | D65: CML Position | E65: Assessment
B66: CML Expected Return at Port. σ | C66: =C6+(C7-C6)/0.155*C25 -> 0.12717849 | D66: CML benchmark | E66: =IF(Analytics!E6>C66,"✅ Above CML","🔴 Below CML") -> ✅ Above CML
B67: Portfolio vs CML Spread | C67: =Analytics!E6-C66 -> 0.021676445 | D67: > 0 = efficient | E67: =IF(C67>0,"✅ Efficient Allocation","🔴 Suboptimal") -> ✅ Efficient Allocation
B68: M² (Modigliani-Modigliani) = Sp × σm + Rf − Rm | C68: =C18*0.155+C6-C7 -> 0.014719153 | D68: M² > 0 = outperform | E68: =IF(C68>0,"✅ Risk-Adj. Outperformance","🔴 Underperformance") -> ✅ Risk-Adj. Outperformance
B70: CORNISH-FISHER ADJUSTED VAR
B71: Metric | C71: Value | D71: Context | E71: Assessment
B72: Portfolio Skewness (S) | C72: {=SUMPRODUCT(C39:C54*(F39:F54-AVERAGE(F39:F54))^3)/COUNT(F39:F54)/STDEV(F39:F54)^3} -> 0.85373572 | D72: S=0 normal, S<0 left tail | E72: =IF(C72<-0.5,"🔴 Left-Skewed",IF(C72<0,"🟡 Slight Left Skew","🟢 Positive Skew")) -> 🟢 Positive Skew
B73: Excess Kurtosis (K) | C73: {=SUMPRODUCT(C39:C54*(F39:F54-AVERAGE(F39:F54))^4)/COUNT(F39:F54)/STDEV(F39:F54)^4-3} -> 0.07869813 | D73: K=0 normal, K>0 fat tails | E73: =IF(C73>3,"🔴 Extreme Fat Tails",IF(C73>0,"🟡 Fat Tails","🟢 Thin Tails")) -> 🟡 Fat Tails
B74: CF z-adj (95%) | C74: =1.645+(1.645^2-1)/6*C72+(1.645^3-3*1.645)/24*C73-(2*1.645^3-5*1.645)/36*C72^2 -> 1.87244 | D74: Adj. normal quantile | E74: =IF(ABS(C74-1.645)>0.3,"🟡 Material Adjustment","🟢 Near-Normal") -> 🟢 Near-Normal
B75: Cornish-Fisher VaR (95%) | C75: =C24-C74*C25 -> -0.27855525 | D75: Skew & kurtosis adjusted | E75: ="CF VaR Loss: "&TEXT(ABS(C75)*SUM(Dashboard!G7:G22),"$#,##0") -> CF VaR Loss: $84,592
B76: Cornish-Fisher VaR (99%) | C76: =C24-(2.326+(2.326^2-1)/6*C72+(2.326^3-3*2.326)/24*C73-(2*2.326^3-5*2.326)/36*C72^2)*C25 -> -0.46695793 | D76: 99% CF confidence | E76: ="CF VaR Loss: "&TEXT(ABS(C76)*SUM(Dashboard!G7:G22),"$#,##0") -> CF VaR Loss: $141,806
B78: HISTORICAL VAR & EXPECTED SHORTFALL
B79: Metric | C79: Value | D79: Context | E79: Assessment
B80: Historical VaR (95%, based on CAGR distribution) | C80: =PERCENTILE(E39:E54,0.05) -> -0.0098600756 | D80: 5th percentile of stock CAGRs | E80: ="Worst 5%ile CAGR: "&TEXT(C80,"0.0%") -> Worst 5%ile CAGR: -1.0%
B81: Historical VaR (99%, extreme tail) | C81: =PERCENTILE(E39:E54,0.01) -> -0.020894843 | D81: 1st percentile of stock CAGRs | E81: ="Extreme tail: "&TEXT(C81,"0.0%") -> Extreme tail: -2.1%
B82: Expected Shortfall (CVaR 95%) | C82: =AVERAGEIF(E39:E54,"<="&C80) -> -0.023653535 | D82: Avg loss beyond VaR | E82: =IF(ISERROR(C82),"No obs below VaR","Tail avg: "&TEXT(C82,"0.0%")) -> Tail avg: -2.4%
B84: DRAWDOWN ANALYSIS
B85: Metric | C85: Value | D85: Context | E85: Assessment | F85: Recovery
B86: Max Drawdown (Worst Stock) | C86: =MIN(E39:E54) -> -0.023653535 | D86: =INDEX(B39:B54,MATCH(MIN(E39:E54),E39:E54,0))&" — deepest peak-to-trough" -> HMC — deepest peak-to-trough | E86: =IF(C86<-0.2,"🔴 Severe",IF(C86<-0.1,"🟡 Moderate","🟢 Shallow")) -> 🟢 Shallow | F86: N/A — position still held
B87: Avg Drawdown (losing positions) | C87: =AVERAGEIF(E39:E54,"<0") -> -0.014457895 | D87: Mean loss across losers | E87: =IF(ISERROR(C87),"🟢 No Losers",IF(C87<-0.1,"🔴 Deep","🟡 Contained")) -> 🟡 Contained
B88: Calmar Ratio | C88: =C24/ABS(MIN(E39:E54)) -> 6.2931369 | D88: CAGR / |Max Drawdown| | E88: =IF(C88>3,"✅ Excellent",IF(C88>1,"🟢 Good","🟡 Monitor")) -> ✅ Excellent
B89: Ulcer Index (pain measure) | C89: {=SQRT(SUMPRODUCT(IF(E39:E54<0,(E39:E54)^2,0))/COUNT(E39:E54))} -> 0.0060579548 | D89: RMS of negative returns | E89: =IF(C89>0.1,"🔴 High Pain",IF(C89>0.05,"🟡 Moderate","🟢 Low Pain")) -> 🟢 Low Pain
B91: STRESS TESTING — SCENARIO ANALYSIS
B92: Scenario | C92: Shock | D92: Est. Portfolio Impact | E92: Dollar Impact | F92: Risk Assessment
B93: VIX +100% Spike | C93: Volatility doubles | D93: =-0.18*C9 -> -0.26508049 | E93: =TEXT(D93*SUM(Dashboard!G7:G22),"$#,##0") -> -$80,500 | F93: =IF(ABS(D93)>0.25,"🔴 Severe",IF(ABS(D93)>0.15,"🟡 Significant","🟢 Manageable")) -> 🔴 Severe
B94: Tech Sector −20% Crash | C94: Semis & Software −20% | D94: =-0.2*(SUMIF(Dashboard!D7:'Dashboard'!D22,"Semiconductors & Semiconductor Equipment",Dashboard!M7:'Dashboard'!M22)+SUMIF(Dashboard!D7:'Dashboard'!D22,"Software & IT Services",Dashboard!M7:'Dashboard'!M22)) -> -0.098267102 | E94: =TEXT(D94*SUM(Dashboard!G7:G22),"$#,##0") -> -$29,842 | F94: =IF(ABS(D94)>0.15,"🔴 Severe",IF(ABS(D94)>0.08,"🟡 Significant","🟢 Manageable")) -> 🟡 Significant
B95: +150bps Yield Curve Shift | C95: Rates shock, duration impact | D95: {=-0.015*SUMPRODUCT(C39:C54,IF(J39:J54="Growth",D39:D54,IF(J39:J54="Distressed",D39:D54*0.5,-D39:D54*0.3)))} -> -0.011796169 | E95: =TEXT(D95*SUM(Dashboard!G7:G22),"$#,##0") -> -$3,582 | F95: =IF(ABS(D95)>0.1,"🔴 Severe",IF(ABS(D95)>0.05,"🟡 Significant","🟢 Manageable")) -> 🟢 Manageable

Sheet Watchlist
A1: Stock | B1: Ticker symbol | C1: 52 week high | D1: 52 week low | E1: Beta | F1: P/E | G1: Change | H1: High | I1: Low | J1: Market cap | K1: Industry | L1: Exchange abbreviation | N1: Stock | O1: (All)
A2: #VALUE! | B2: {=_FV(Table2[[#This Row],[Stock]],"Ticker symbol",TRUE)} -> AMD | C2: {=_FV(Table2[[#This Row],[Stock]],"52 week high",TRUE)} -> 267.0799 | D2: {=_FV(Table2[[#This Row],[Stock]],"52 week low",TRUE)} -> 76.48 | E2: {=_FV(Table2[[#This Row],[Stock]],"Beta")} -> 1.9919 | F2: {=_FV(Table2[[#This Row],[Stock]],"P/E",TRUE)} -> 84.603 | G2: {=_FV(Table2[[#This Row],[Stock]],"Change")} -> 2.84 | H2: {=_FV(Table2[[#This Row],[Stock]],"High")} -> 226.31 | I2: {=_FV(Table2[[#This Row],[Stock]],"Low")} -> 219.3 | J2: {=_FV(Table2[[#This Row],[Stock]],"Market cap",TRUE)} -> 359228895260 | K2: {=_FV(Table2[[#This Row],[Stock]],"Industry")} -> Semiconductors & Semiconductor Equipment | L2: {=_FV(Table2[[#This Row],[Stock]],"Exchange abbreviation",TRUE)} -> XNAS
A3: #VALUE! | B3: {=_FV(Table2[[#This Row],[Stock]],"Ticker symbol",TRUE)} -> MSFT | C3: {=_FV(Table2[[#This Row],[Stock]],"52 week high",TRUE)} -> 555.45 | D3: {=_FV(Table2[[#This Row],[Stock]],"52 week low",TRUE)} -> 344.79 | E3: {=_FV(Table2[[#This Row],[Stock]],"Beta")} -> 1.103 | F3: {=_FV(Table2[[#This Row],[Stock]],"P/E",TRUE)} -> 23.2406 | G3: {=_FV(Table2[[#This Row],[Stock]],"Change")} -> -2.02 | H3: {=_FV(Table2[[#This Row],[Stock]],"High")} -> 373.73 | I3: {=_FV(Table2[[#This Row],[Stock]],"Low")} -> 369.5014 | J3: {=_FV(Table2[[#This Row],[Stock]],"Market cap",TRUE)} -> 2758175635760 | K3: {=_FV(Table2[[#This Row],[Stock]],"Industry")} -> Software & IT Services | L3: {=_FV(Table2[[#This Row],[Stock]],"Exchange abbreviation",TRUE)} -> XNAS | N3: Exchange abbreviation | O3: Ticker symbol
A4: #VALUE! | B4: {=_FV(Table2[[#This Row],[Stock]],"Ticker symbol",TRUE)} -> BABA | C4: {=_FV(Table2[[#This Row],[Stock]],"52 week high",TRUE)} -> 192.67 | D4: {=_FV(Table2[[#This Row],[Stock]],"52 week low",TRUE)} -> 94.9742 | E4: {=_FV(Table2[[#This Row],[Stock]],"Beta")} -> 0.4949 | F4: {=_FV(Table2[[#This Row],[Stock]],"P/E",TRUE)} -> 16.6848 | G4: {=_FV(Table2[[#This Row],[Stock]],"Change")} -> 0.63 | H4: {=_FV(Table2[[#This Row],[Stock]],"High")} -> 123.65 | I4: {=_FV(Table2[[#This Row],[Stock]],"Low")} -> 122 | J4: {=_FV(Table2[[#This Row],[Stock]],"Market cap",TRUE)} -> 292887826840 | K4: {=_FV(Table2[[#This Row],[Stock]],"Industry")} -> Software & IT Services | L4: {=_FV(Table2[[#This Row],[Stock]],"Exchange abbreviation",TRUE)} -> XNYS | N4: XNAS | O4: AMD
A5: #VALUE! | B5: {=_FV(Table2[[#This Row],[Stock]],"Ticker symbol",TRUE)} -> DELL | C5: {=_FV(Table2[[#This Row],[Stock]],"52 week high",TRUE)} -> 186.39 | D5: {=_FV(Table2[[#This Row],[Stock]],"52 week low",TRUE)} -> 66.245 | E5: {=_FV(Table2[[#This Row],[Stock]],"Beta")} -> 0.8573 | F5: {=_FV(Table2[[#This Row],[Stock]],"P/E",TRUE)} -> 19.8578 | G5: {=_FV(Table2[[#This Row],[Stock]],"Change")} -> -1.22 | H5: {=_FV(Table2[[#This Row],[Stock]],"High")} -> 176.5 | I5: {=_FV(Table2[[#This Row],[Stock]],"Low")} -> 172.9 | J5: {=_FV(Table2[[#This Row],[Stock]],"Market cap",TRUE)} -> 111811352775 | K5: {=_FV(Table2[[#This Row],[Stock]],"Industry")} -> Computers, Phones & Household Electronics | L5: {=_FV(Table2[[#This Row],[Stock]],"Exchange abbreviation",TRUE)} -> XNYS | N5: XNAS | O5: COST
A6: #VALUE! | B6: {=_FV(Table2[[#This Row],[Stock]],"Ticker symbol",TRUE)} -> GS | C6: {=_FV(Table2[[#This Row],[Stock]],"52 week high",TRUE)} -> 984.7 | D6: {=_FV(Table2[[#This Row],[Stock]],"52 week low",TRUE)} -> 439.38 | E6: {=_FV(Table2[[#This Row],[Stock]],"Beta")} -> 1.3147 | F6: {=_FV(Table2[[#This Row],[Stock]],"P/E",TRUE)} -> 16.8759 | G6: {=_FV(Table2[[#This Row],[Stock]],"Change")} -> 2.7027 | H6: {=_FV(Table2[[#This Row],[Stock]],"High")} -> 873.21 | I6: {=_FV(Table2[[#This Row],[Stock]],"Low")} -> 859.83 | J6: {=_FV(Table2[[#This Row],[Stock]],"Market cap",TRUE)} -> 255388815469 | K6: {=_FV(Table2[[#This Row],[Stock]],"Industry")} -> Investment Banking & Investment Services | L6: {=_FV(Table2[[#This Row],[Stock]],"Exchange abbreviation",TRUE)} -> XNYS | N6: XNAS | O6: MSFT
A7: #VALUE! | B7: {=_FV(Table2[[#This Row],[Stock]],"Ticker symbol",TRUE)} -> XOM | C7: {=_FV(Table2[[#This Row],[Stock]],"52 week high",TRUE)} -> 176.41 | D7: {=_FV(Table2[[#This Row],[Stock]],"52 week low",TRUE)} -> 97.8 | E7: {=_FV(Table2[[#This Row],[Stock]],"Beta")} -> 0.2919 | F7: {=_FV(Table2[[#This Row],[Stock]],"P/E",TRUE)} -> 24.1045 | G7: {=_FV(Table2[[#This Row],[Stock]],"Change")} -> 0.34 | H7: {=_FV(Table2[[#This Row],[Stock]],"High")} -> 161.94 | I7: {=_FV(Table2[[#This Row],[Stock]],"Low")} -> 159.53 | J7: {=_FV(Table2[[#This Row],[Stock]],"Market cap",TRUE)} -> 670974006920 | K7: {=_FV(Table2[[#This Row],[Stock]],"Industry")} -> Oil & Gas | L7: {=_FV(Table2[[#This Row],[Stock]],"Exchange abbreviation",TRUE)} -> XNYS | N7: XNYS | O7: BABA
A8: #VALUE! | B8: {=_FV(Table2[[#This Row],[Stock]],"Ticker symbol",TRUE)} -> GM | C8: {=_FV(Table2[[#This Row],[Stock]],"52 week high",TRUE)} -> 87.62 | D8: {=_FV(Table2[[#This Row],[Stock]],"52 week low",TRUE)} -> 41.6 | E8: {=_FV(Table2[[#This Row],[Stock]],"Beta")} -> 1.3733 | F8: {=_FV(Table2[[#This Row],[Stock]],"P/E",TRUE)} -> 22.3854 | G8: {=_FV(Table2[[#This Row],[Stock]],"Change")} -> 0.62 | H8: {=_FV(Table2[[#This Row],[Stock]],"High")} -> 73.315 | I8: {=_FV(Table2[[#This Row],[Stock]],"Low")} -> 72.15 | J8: {=_FV(Table2[[#This Row],[Stock]],"Market cap",TRUE)} -> 66134284248 | K8: {=_FV(Table2[[#This Row],[Stock]],"Industry")} -> Automobiles & Auto Parts | L8: {=_FV(Table2[[#This Row],[Stock]],"Exchange abbreviation",TRUE)} -> XNYS | N8: XNYS | O8: BAC
A9: #VALUE! | B9: {=_FV(Table2[[#This Row],[Stock]],"Ticker symbol",TRUE)} -> BAC | C9: {=_FV(Table2[[#This Row],[Stock]],"52 week high",TRUE)} -> 57.55 | D9: {=_FV(Table2[[#This Row],[Stock]],"52 week low",TRUE)} -> 33.065 | E9: {=_FV(Table2[[#This Row],[Stock]],"Beta")} -> 1.2422 | F9: {=_FV(Table2[[#This Row],[Stock]],"P/E",TRUE)} -> 13.1741 | G9: {=_FV(Table2[[#This Row],[Stock]],"Change")} -> 0.455 | H9: {=_FV(Table2[[#This Row],[Stock]],"High")} -> 50.08 | I9: {=_FV(Table2[[#This Row],[Stock]],"Low")} -> 49.25 | J9: {=_FV(Table2[[#This Row],[Stock]],"Market cap",TRUE)} -> 356106408015 | K9: {=_FV(Table2[[#This Row],[Stock]],"Industry")} -> Banking Services | L9: {=_FV(Table2[[#This Row],[Stock]],"Exchange abbreviation",TRUE)} -> XNYS | N9: XNYS | O9: DELL
A10: #VALUE! | B10: {=_FV(Table2[[#This Row],[Stock]],"Ticker symbol",TRUE)} -> LMT | C10: {=_FV(Table2[[#This Row],[Stock]],"52 week high",TRUE)} -> 692 | D10: {=_FV(Table2[[#This Row],[Stock]],"52 week low",TRUE)} -> 410.11 | E10: {=_FV(Table2[[#This Row],[Stock]],"Beta")} -> 0.2367 | F10: {=_FV(Table2[[#This Row],[Stock]],"P/E",TRUE)} -> 29.0685 | G10: {=_FV(Table2[[#This Row],[Stock]],"Change")} -> 1.7787 | H10: {=_FV(Table2[[#This Row],[Stock]],"High")} -> 627.22 | I10: {=_FV(Table2[[#This Row],[Stock]],"Low")} -> 621.365 | J10: {=_FV(Table2[[#This Row],[Stock]],"Market cap",TRUE)} -> 143939414196 | K10: {=_FV(Table2[[#This Row],[Stock]],"Industry")} -> Aerospace & Defense | L10: {=_FV(Table2[[#This Row],[Stock]],"Exchange abbreviation",TRUE)} -> XNYS | N10: XNYS | O10: GM
A11: #VALUE! | B11: {=_FV(Table2[[#This Row],[Stock]],"Ticker symbol",TRUE)} -> COST | C11: {=_FV(Table2[[#This Row],[Stock]],"52 week high",TRUE)} -> 1067.08 | D11: {=_FV(Table2[[#This Row],[Stock]],"52 week low",TRUE)} -> 844.06 | E11: {=_FV(Table2[[#This Row],[Stock]],"Beta")} -> 0.989 | F11: {=_FV(Table2[[#This Row],[Stock]],"P/E",TRUE)} -> 54.4707 | G11: {=_FV(Table2[[#This Row],[Stock]],"Change")} -> 1.91 | H11: {=_FV(Table2[[#This Row],[Stock]],"High")} -> 1017.46 | I11: {=_FV(Table2[[#This Row],[Stock]],"Low")} -> 1004.01 | J11: {=_FV(Table2[[#This Row],[Stock]],"Market cap",TRUE)} -> 451136917675 | K11: {=_FV(Table2[[#This Row],[Stock]],"Industry")} -> Diversified Retail | L11: {=_FV(Table2[[#This Row],[Stock]],"Exchange abbreviation",TRUE)} -> XNAS | N11: XNYS | O11: GS
N12: XNYS | O12: LMT
N13: XNYS | O13: XOM

Sheet Sparkline
A3: =Dashboard!B7 -> 0R2N | B3: {=TRANSPOSE(_xlfn.STOCKHISTORY(A3,TODAY()-365,TODAY(),0,0,1))} -> 115.3 | C3: 122.1 | D3: 120.8 | E3: 126.9 | F3: 125.6 | G3: 129.6 | H3: 129.6 | I3: 129.6 | J3: 128.6 | K3: 115.1 | L3: 121.4 | M3: 120.2 | N3: 123.7 | O3: 125.2 | P3: 125.2 | Q3: 124.4 | R3: 126.7 | S3: 129.2 | T3: 128.956 | U3: 128 | V3: 128.8 | W3: 129 | X3: 126.7 | Y3: 130.5 | Z3: 131.3 | AA3: 130.3 | AB3: 133 | AC3: 135.3 | AD3: 136.4 | AE3: 137.2 | AF3: 137.4 | AG3: 134.9 | AH3: 132 | AI3: #N/A | AJ3: 132.4 | AK3: 132 | AL3: 133.6 | AM3: 134.9 | AN3: 136.2 | AO3: 137.6 | AP3: 137.4 | AQ3: 138.7 | AR3: 139.5 | AS3: 139.3 | AT3: 138.1 | AU3: 138.5 | AV3: 141.4 | AW3: 144.4 | AX3: 146.9 | AY3: 147.7 | AZ3: 147.3 | BA3: 147.3 | BB3: 146.7 | BC3: 145.8 | BD3: 142.3 | BE3: 142.1 | BF3: 141.8 | BG3: 144 | BH3: 146.1 | BI3: 144 | BJ3: 142.9 | BK3: 145.4 | BL3: 145 | BM3: 146.7 | BN3: 144.2 | BO3: 145.8 | BP3: 145 | BQ3: 146.3 | BR3: 149.2 | BS3: 149.8 | BT3: 148.8 | BU3: 150.9 | BV3: 151.5 | BW3: 152.6 | BX3: 149.6 | BY3: 151.5 | BZ3: 155.7 | CA3: 154.3 | CB3: 156.6 | CC3: 156.4 | CD3: 157.6 | CE3: 157.8 | CF3: 155.5 | CG3: 157.2 | CH3: 156.6 | CI3: 157 | CJ3: 153.4 | CK3: 156.2 | CL3: 154.9 | CM3: 155.7 | CN3: 154.1 | CO3: 156.2 | CP3: 153.8 | CQ3: 154.7 | CR3: 154.1 | CS3: 154.7 | CT3: 157 | CU3: 157.8 | CV3: 156.67 | CW3: 158.1 | CX3: 159.5 | CY3: 159.3 | CZ3: 160 | DA3: 159.1 | DB3: 157.4 | DC3: 157.8 | DD3: 158.5 | DE3: 157.2 | DF3: 156 | DG3: 151.7 | DH3: 152.6 | DI3: 155.3 | DJ3: 157.2 | DK3: 157.4 | DL3: 157.6 | DM3: 158.5 | DN3: 157.6 | DO3: 156.8 | DP3: 158.9 | DQ3: 160.8 | DR3: 162.9 | DS3: 160.2 | DT3: 164.6 | DU3: 165.6 | DV3: 166.7 | DW3: 166.7 | DX3: 166.1 | DY3: 165.8 | DZ3: 169 | EA3: 168.8 | EB3: 170.7 | EC3: 167.1 | ED3: 160 | EE3: 159.3 | EF3: 158.3 | EG3: 160.4 | EH3: 157.4 | EI3: 157.2 | EJ3: 160.8 | EK3: 173.6 | EL3: 176.4 | EM3: 179.1 | EN3: 179.5 | EO3: 178.1 | EP3: 180.6 | EQ3: 177.6 | ER3: 177.6 | ES3: 176.8 | ET3: 176.6 | EU3: 176.6 | EV3: 175.7 | EW3: 174.3 | EX3: 174.1 | EY3: 177.8 | EZ3: 178.5 | FA3: 179.1 | FB3: 174.5 | FC3: 174.5 | FD3: 175.5 | FE3: 176 | FF3: 173 | FG3: 177 | FH3: 170.1 | FI3: 171.1 | FJ3: 171.1 | FK3: 172.8 | FL3: 173 | FM3: 173.6 | FN3: 170.5 | FO3: 169 | FP3: 168.2 | FQ3: 170.7 | FR3: 170.3 | FS3: 171.5 | FT3: 174.9 | FU3: 172.4 | FV3: 177.6 | FW3: 177 | FX3: 180 | FY3: 181.2 | FZ3: 179.5 | GA3: 179.1 | GB3: 181 | GC3: 184.8 | GD3: 187.7 | GE3: 186.5 | GF3: 184.4 | GG3: 184 | GH3: 184 | GI3: 183.1 | GJ3: 187.1 | GK3: 188.6 | GL3: 191.15 | GM3: 189.6 | GN3: 187.5 | GO3: 191.05 | GP3: 196.3 | GQ3: 195.85 | GR3: 197.2 | GS3: 199.65 | GT3: 202.45 | GU3: 201.1 | GV3: 196.75 | GW3: 197.2 | GX3: 195.4 | GY3: 194.4 | GZ3: 196.85 | HA3: 201.45 | HB3: 200.2 | HC3: 199.2 | HD3: 199.2 | HE3: 203.35 | HF3: 197.75 | HG3: 196.2 | HH3: 199.2 | HI3: 198.65 | HJ3: 193.85 | HK3: 196.3 | HL3: 200.55 | HM3: 202.55 | HN3: 199.55 | HO3: 201.1 | HP3: 202.9 | HQ3: 204.9 | HR3: 204.9 | HS3: 203.35 | HT3: 199.1 | HU3: 193.5 | HV3: 197.2 | HW3: 197.75 | HX3: 212 | HY3: 209.25 | HZ3: 207.35 | IA3: 202.9 | IB3: 206.7 | IC3: 209.15 | ID3: 207.8 | IE3: 207.25 | IF3: 204.9 | IG3: 205.45 | IH3: 207.15 | II3: 201 | IJ3: 204.45 | IK3: 199.2 | IL3: 199.2 | IM3: 198.1 | IN3: 193.5 | IO3: 194.5 | IP3: 192.5 | IQ3: 191.5 | IR3: 190.5 | IS3: 190.5 | IT3: 195.5 | IU3: 196.5
A4: =Dashboard!B8 -> AAPL | B4: {=TRANSPOSE(_xlfn.STOCKHISTORY(A4,TODAY()-365,TODAY(),0,0,1))} -> 181.46 | C4: 172.42 | D4: 198.85 | E4: 190.42 | F4: 198.15 | G4: 202.52 | H4: 202.14 | I4: 194.27 | J4: 196.98 | K4: 193.16 | L4: 199.74 | M4: 204.6 | N4: 208.37 | O4: 209.28 | P4: 210.14 | Q4: 211.21 | R4: 212.5 | S4: 213.32 | T4: 205.35 | U4: 198.89 | V4: 198.51 | W4: 196.25 | X4: 197.49 | Y4: 198.53 | Z4: 210.79 | AA4: 212.93 | AB4: 212.33 | AC4: 211.45 | AD4: 211.26 | AE4: 208.78 | AF4: 206.86 | AG4: 202.09 | AH4: 201.36 | AI4: 195.27 | AJ4: 200.21 | AK4: 200.42 | AL4: 199.95 | AM4: 200.85 | AN4: 201.7 | AO4: 203.27 | AP4: 202.82 | AQ4: 200.63 | AR4: 203.92 | AS4: 201.45 | AT4: 202.67 | AU4: 198.78 | AV4: 199.2 | AW4: 196.45 | AX4: 198.42 | AY4: 195.64 | AZ4: 196.58 | BA4: 201 | BB4: 201.5 | BC4: 200.3 | BD4: 201.56 | BE4: 201 | BF4: 201.08 | BG4: 205.17 | BH4: 207.82 | BI4: 212.44 | BJ4: 213.55 | BK4: 209.95 | BL4: 210.01 | BM4: 211.14 | BN4: 212.41 | BO4: 211.16 | BP4: 208.62 | BQ4: 209.11 | BR4: 210.16 | BS4: 210.02 | BT4: 211.18 | BU4: 212.48 | BV4: 214.4 | BW4: 214.15 | BX4: 213.76 | BY4: 213.88 | BZ4: 214.05 | CA4: 211.27 | CB4: 209.05 | CC4: 207.57 | CD4: 202.38 | CE4: 203.35 | CF4: 202.92 | CG4: 213.25 | CH4: 220.03 | CI4: 229.35 | CJ4: 227.18 | CK4: 229.65 | CL4: 233.33 | CM4: 232.78 | CN4: 231.59 | CO4: 230.89 | CP4: 230.56 | CQ4: 226.01 | CR4: 224.9 | CS4: 227.76 | CT4: 227.16 | CU4: 229.31 | CV4: 230.49 | CW4: 232.56 | CX4: 232.14 | CY4: 229.72 | CZ4: 238.47 | DA4: 239.78 | DB4: 239.69 | DC4: 237.88 | DD4: 234.35 | DE4: 226.79 | DF4: 230.03 | DG4: 234.07 | DH4: 236.7 | DI4: 238.15 | DJ4: 238.99 | DK4: 237.88 | DL4: 245.5 | DM4: 256.08 | DN4: 254.43 | DO4: 252.31 | DP4: 256.87 | DQ4: 255.46 | DR4: 254.43 | DS4: 254.63 | DT4: 255.45 | DU4: 257.13 | DV4: 258.02 | DW4: 256.69 | DX4: 256.48 | DY4: 258.06 | DZ4: 254.04 | EA4: 245.27 | EB4: 247.66 | EC4: 247.77 | ED4: 249.34 | EE4: 247.45 | EF4: 252.29 | EG4: 262.24 | EH4: 262.77 | EI4: 258.45 | EJ4: 259.58 | EK4: 262.82 | EL4: 268.81 | EM4: 269 | EN4: 269.7 | EO4: 271.4 | EP4: 270.37 | EQ4: 269.05 | ER4: 270.04 | ES4: 270.14 | ET4: 269.77 | EU4: 268.47 | EV4: 269.43 | EW4: 275.25 | EX4: 273.47 | EY4: 272.95 | EZ4: 272.41 | FA4: 267.46 | FB4: 267.44 | FC4: 268.56 | FD4: 266.25 | FE4: 271.49 | FF4: 275.92 | FG4: 276.97 | FH4: 277.55 | FI4: 278.85 | FJ4: 283.1 | FK4: 286.19 | FL4: 284.15 | FM4: 280.7 | FN4: 278.78 | FO4: 277.89 | FP4: 277.18 | FQ4: 278.78 | FR4: 278.03 | FS4: 278.28 | FT4: 274.11 | FU4: 274.61 | FV4: 271.84 | FW4: 272.19 | FX4: 273.67 | FY4: 270.97 | FZ4: 272.36 | GA4: 273.81 | GB4: 273.4 | GC4: 273.76 | GD4: 273.08 | GE4: 271.86 | GF4: 271.01 | GG4: 267.26 | GH4: 262.36 | GI4: 260.33 | GJ4: 259.04 | GK4: 259.37 | GL4: 260.25 | GM4: 261.05 | GN4: 259.96 | GO4: 258.21 | GP4: 255.53 | GQ4: 246.7 | GR4: 247.65 | GS4: 248.35 | GT4: 248.04 | GU4: 255.41 | GV4: 258.27 | GW4: 256.44 | GX4: 258.28 | GY4: 259.48 | GZ4: 270.01 | HA4: 269.48 | HB4: 276.49 | HC4: 275.91 | HD4: 278.12 | HE4: 274.62 | HF4: 273.68 | HG4: 275.5 | HH4: 261.73 | HI4: 255.78 | HJ4: 263.88 | HK4: 264.35 | HL4: 260.58 | HM4: 264.58 | HN4: 266.18 | HO4: 272.14 | HP4: 274.23 | HQ4: 272.95 | HR4: 264.18 | HS4: 264.72 | HT4: 263.75 | HU4: 262.52 | HV4: 260.29 | HW4: 257.46 | HX4: 259.88 | HY4: 260.83 | HZ4: 260.81 | IA4: 255.76 | IB4: 250.12 | IC4: 252.82 | ID4: 254.23 | IE4: 249.94 | IF4: 248.96 | IG4: 247.99 | IH4: 251.49 | II4: 251.64 | IJ4: 252.62 | IK4: 252.89 | IL4: 248.8 | IM4: 246.63 | IN4: 253.79 | IO4: 255.63 | IP4: 255.92
A5: =Dashboard!B9 -> AMD | B5: {=TRANSPOSE(_xlfn.STOCKHISTORY(A5,TODAY()-365,TODAY(),0,0,1))} -> 83.64 | C5: 78.21 | D5: 96.84 | E5: 88.7 | F5: 93.4 | G5: 94.5 | H5: 95.29 | I5: 88.29 | J5: 87.5 | K5: 85.56 | L5: 86.26 | M5: 90.39 | N5: 94.47 | O5: 96.645 | P5: 96.39 | Q5: 96.06 | R5: 97.35 | S5: 96.65 | T5: 98.8 | U5: 100.59 | V5: 98.62 | W5: 100.36 | X5: 101.7 | Y5: 102.84 | Z5: 108.12 | AA5: 112.46 | AB5: 117.72 | AC5: 114.99 | AD5: 117.17 | AE5: 114.74 | AF5: 113.51 | AG5: 112.06 | AH5: 110.71 | AI5: 110.31 | AJ5: 114.56 | AK5: 112.86 | AL5: 113.03 | AM5: 110.73 | AN5: 114.63 | AO5: 117.31 | AP5: 118.58 | AQ5: 115.69 | AR5: 116.19 | AS5: 121.73 | AT5: 123.24 | AU5: 121.14 | AV5: 118.5 | AW5: 116.16 | AX5: 126.39 | AY5: 127.1 | AZ5: 126.79 | BA5: 128.24 | BB5: 129.58 | BC5: 138.43 | BD5: 143.4 | BE5: 143.68 | BF5: 143.81 | BG5: 141.9 | BH5: 136.11 | BI5: 138.52 | BJ5: 137.91 | BK5: 134.8 | BL5: 137.82 | BM5: 138.41 | BN5: 144.16 | BO5: 146.42 | BP5: 146.24 | BQ5: 155.61 | BR5: 160.08 | BS5: 160.41 | BT5: 156.99 | BU5: 157 | BV5: 154.72 | BW5: 158.65 | BX5: 162.12 | BY5: 166.47 | BZ5: 173.66 | CA5: 177.44 | CB5: 179.51 | CC5: 176.31 | CD5: 171.7 | CE5: 176.78 | CF5: 174.31 | CG5: 163.12 | CH5: 172.4 | CI5: 172.76 | CJ5: 172.28 | CK5: 174.95 | CL5: 184.42 | CM5: 180.95 | CN5: 177.51 | CO5: 176.14 | CP5: 166.55 | CQ5: 165.2 | CR5: 163.71 | CS5: 167.76 | CT5: 163.36 | CU5: 166.62 | CV5: 167.13 | CW5: 168.58 | CX5: 162.63 | CY5: 162.32 | CZ5: 162.13 | DA5: 161.79 | DB5: 151.14 | DC5: 151.41 | DD5: 155.82 | DE5: 159.54 | DF5: 155.67 | DG5: 158.57 | DH5: 161.16 | DI5: 160.46 | DJ5: 159.16 | DK5: 157.92 | DL5: 157.39 | DM5: 159.79 | DN5: 160.9 | DO5: 160.88 | DP5: 161.27 | DQ5: 159.46 | DR5: 161.36 | DS5: 161.79 | DT5: 164.01 | DU5: 169.73 | DV5: 164.67 | DW5: 203.71 | DX5: 211.51 | DY5: 235.56 | DZ5: 232.89 | EA5: 214.9 | EB5: 216.42 | EC5: 218.09 | ED5: 238.6 | EE5: 234.56 | EF5: 233.08 | EG5: 240.56 | EH5: 238.03 | EI5: 230.23 | EJ5: 234.99 | EK5: 252.92 | EL5: 259.67 | EM5: 258.01 | EN5: 264.33 | EO5: 254.84 | EP5: 256.12 | EQ5: 259.65 | ER5: 250.05 | ES5: 256.33 | ET5: 237.7 | EU5: 233.54 | EV5: 243.98 | EW5: 237.52 | EX5: 258.89 | EY5: 247.96 | EZ5: 246.81 | FA5: 240.52 | FB5: 230.29 | FC5: 223.55 | FD5: 206.02 | FE5: 203.78 | FF5: 215.05 | FG5: 206.13 | FH5: 214.24 | FI5: 217.53 | FJ5: 219.76 | FK5: 215.24 | FL5: 217.6 | FM5: 215.98 | FN5: 217.97 | FO5: 221.11 | FP5: 221.62 | FQ5: 221.42 | FR5: 221.43 | FS5: 210.78 | FT5: 207.58 | FU5: 209.17 | FV5: 198.11 | FW5: 201.06 | FX5: 213.43 | FY5: 214.95 | FZ5: 214.9 | GA5: 215.04 | GB5: 214.99 | GC5: 215.61 | GD5: 215.34 | GE5: 214.16 | GF5: 223.47 | GG5: 221.08 | GH5: 214.35 | GI5: 210.02 | GJ5: 204.68 | GK5: 203.17 | GL5: 207.69 | GM5: 220.97 | GN5: 223.6 | GO5: 227.92 | GP5: 231.83 | GQ5: 231.92 | GR5: 249.8 | GS5: 253.73 | GT5: 259.68 | GU5: 251.31 | GV5: 252.03 | GW5: 252.74 | GX5: 252.18 | GY5: 236.73 | GZ5: 246.27 | HA5: 242.11 | HB5: 200.19 | HC5: 192.5 | HD5: 208.44 | HE5: 216 | HF5: 213.57 | HG5: 213.58 | HH5: 205.94 | HI5: 207.32 | HJ5: 203.08 | HK5: 200.12 | HL5: 203.37 | HM5: 200.15 | HN5: 196.6 | HO5: 213.84 | HP5: 210.86 | HQ5: 203.68 | HR5: 200.21 | HS5: 198.62 | HT5: 190.95 | HU5: 202.07 | HV5: 199.45 | HW5: 192.43 | HX5: 202.68 | HY5: 203.23 | HZ5: 204.83 | IA5: 197.74 | IB5: 193.39 | IC5: 196.58 | ID5: 196.31 | IE5: 199.46 | IF5: 205.27 | IG5: 201.33 | IH5: 202.68 | II5: 205.37 | IJ5: 220.27 | IK5: 203.77 | IL5: 201.99 | IM5: 196.04 | IN5: 203.43 | IO5: 210.21 | IP5: 217.5
A6: =Dashboard!B10 -> AMZN | B6: {=TRANSPOSE(_xlfn.STOCKHISTORY(A6,TODAY()-365,TODAY(),0,0,1))} -> 175.26 | C6: 170.66 | D6: 191.1 | E6: 181.22 | F6: 184.87 | G6: 182.12 | H6: 179.59 | I6: 174.33 | J6: 172.61 | K6: 167.32 | L6: 173.18 | M6: 180.6 | N6: 186.54 | O6: 188.99 | P6: 187.7 | Q6: 187.39 | R6: 184.42 | S6: 190.2 | T6: 189.98 | U6: 186.35 | V6: 185.01 | W6: 188.71 | X6: 192.08 | Y6: 193.06 | Z6: 208.64 | AA6: 211.37 | AB6: 210.25 | AC6: 205.17 | AD6: 205.59 | AE6: 206.16 | AF6: 204.07 | AG6: 201.12 | AH6: 203.1 | AI6: 200.99 | AJ6: 206.02 | AK6: 204.72 | AL6: 205.7 | AM6: 205.01 | AN6: 206.65 | AO6: 205.71 | AP6: 207.23 | AQ6: 207.91 | AR6: 213.57 | AS6: 216.98 | AT6: 217.61 | AU6: 213.2 | AV6: 213.24 | AW6: 212.1 | AX6: 216.1 | AY6: 214.82 | AZ6: 212.52 | BA6: 209.69 | BB6: 208.47 | BC6: 212.77 | BD6: 211.99 | BE6: 217.12 | BF6: 223.3 | BG6: 219.39 | BH6: 220.46 | BI6: 219.92 | BJ6: 223.41 | BK6: 223.47 | BL6: 219.36 | BM6: 222.54 | BN6: 222.26 | BO6: 225.02 | BP6: 225.69 | BQ6: 226.35 | BR6: 223.19 | BS6: 223.88 | BT6: 226.13 | BU6: 229.3 | BV6: 227.47 | BW6: 228.29 | BX6: 232.23 | BY6: 231.44 | BZ6: 232.79 | CA6: 231.01 | CB6: 230.19 | CC6: 234.11 | CD6: 214.75 | CE6: 211.65 | CF6: 213.75 | CG6: 222.31 | CH6: 223.13 | CI6: 222.69 | CJ6: 221.3 | CK6: 221.47 | CL6: 224.56 | CM6: 230.98 | CN6: 231.03 | CO6: 231.49 | CP6: 228.01 | CQ6: 223.81 | CR6: 221.95 | CS6: 228.84 | CT6: 227.94 | CU6: 228.71 | CV6: 229.12 | CW6: 231.6 | CX6: 229 | CY6: 225.34 | CZ6: 225.99 | DA6: 235.68 | DB6: 232.33 | DC6: 235.84 | DD6: 238.24 | DE6: 230.33 | DF6: 229.95 | DG6: 228.15 | DH6: 231.43 | DI6: 234.05 | DJ6: 231.62 | DK6: 231.23 | DL6: 231.48 | DM6: 227.63 | DN6: 220.71 | DO6: 220.21 | DP6: 218.15 | DQ6: 219.78 | DR6: 222.17 | DS6: 219.57 | DT6: 220.63 | DU6: 222.41 | DV6: 219.51 | DW6: 220.9 | DX6: 221.78 | DY6: 225.22 | DZ6: 227.74 | EA6: 216.37 | EB6: 220.07 | EC6: 216.39 | ED6: 215.57 | EE6: 214.47 | EF6: 213.04 | EG6: 216.48 | EH6: 222.03 | EI6: 217.95 | EJ6: 221.09 | EK6: 224.21 | EL6: 226.97 | EM6: 229.25 | EN6: 230.3 | EO6: 222.86 | EP6: 244.22 | EQ6: 254 | ER6: 249.32 | ES6: 250.2 | ET6: 243.04 | EU6: 244.41 | EV6: 248.4 | EW6: 249.1 | EX6: 244.2 | EY6: 237.58 | EZ6: 234.69 | FA6: 232.87 | FB6: 222.55 | FC6: 222.69 | FD6: 217.14 | FE6: 220.69 | FF6: 226.28 | FG6: 229.67 | FH6: 229.16 | FI6: 233.22 | FJ6: 233.88 | FK6: 234.42 | FL6: 232.38 | FM6: 229.11 | FN6: 229.53 | FO6: 226.89 | FP6: 227.92 | FQ6: 231.78 | FR6: 230.28 | FS6: 226.19 | FT6: 222.54 | FU6: 222.56 | FV6: 221.27 | FW6: 226.76 | FX6: 227.35 | FY6: 228.43 | FZ6: 232.14 | GA6: 232.38 | GB6: 232.52 | GC6: 232.07 | GD6: 232.53 | GE6: 230.82 | GF6: 226.5 | GG6: 233.06 | GH6: 240.93 | GI6: 241.56 | GJ6: 246.29 | GK6: 247.38 | GL6: 246.47 | GM6: 242.6 | GN6: 236.65 | GO6: 238.18 | GP6: 239.12 | GQ6: 231 | GR6: 231.31 | GS6: 234.34 | GT6: 239.16 | GU6: 238.42 | GV6: 244.68 | GW6: 243.01 | GX6: 241.73 | GY6: 239.3 | GZ6: 242.96 | HA6: 238.62 | HB6: 232.99 | HC6: 222.69 | HD6: 210.32 | HE6: 208.72 | HF6: 206.96 | HG6: 204.08 | HH6: 199.6 | HI6: 198.79 | HJ6: 201.15 | HK6: 204.79 | HL6: 204.86 | HM6: 210.11 | HN6: 205.27 | HO6: 208.56 | HP6: 210.64 | HQ6: 207.92 | HR6: 210 | HS6: 208.39 | HT6: 208.73 | HU6: 216.82 | HV6: 218.94 | HW6: 213.21 | HX6: 213.49 | HY6: 214.33 | HZ6: 212.65 | IA6: 209.53 | IB6: 207.67 | IC6: 211.74 | ID6: 215.2 | IE6: 209.87 | IF6: 208.76 | IG6: 205.37 | IH6: 210.14 | II6: 207.24 | IJ6: 211.71 | IK6: 207.54 | IL6: 199.34 | IM6: 200.95 | IN6: 208.27 | IO6: 210.57 | IP6: 209.77
A7: =Dashboard!B11 -> BA | B7: {=TRANSPOSE(_xlfn.STOCKHISTORY(A7,TODAY()-365,TODAY(),0,0,1))} -> 129.79 | C7: 145.99 | D7: 156.9422 | E7: 153 | F7: 156.39 | G7: 158.77 | H7: 156.6 | I7: 155.47 | J7: 163.77 | K7: 160.75 | L7: 173.0981 | M7: 177.02 | N7: 176.83 | O7: 181.12 | P7: 182.23 | Q7: 182.1767 | R7: 183.5567 | S7: 186.39 | T7: 185.85 | U7: 184.31 | V7: 183.685 | W7: 192.25 | X7: 194.37 | Y7: 198.3607 | Z7: 204.0822 | AA7: 204.8655 | AB7: 207.1 | AC7: 205.1205 | AD7: 205.0471 | AE7: 208.1 | AF7: 204.04 | AG7: 203.99 | AH7: 201.36 | AI7: #N/A | AJ7: 202.04 | AK7: 201.29 | AL7: 206.99 | AM7: 206.5376 | AN7: 208.89 | AO7: 215.43 | AP7: 212.71 | AQ7: 210.7291 | AR7: 208.7375 | AS7: 213.17 | AT7: 214.84 | AU7: 212.8993 | AV7: 203.77 | AW7: 200.24 | AX7: 203.03 | AY7: 199.29 | AZ7: 198.41 | BA7: #N/A | BB7: 199.5 | BC7: 199.19 | BD7: 200.58 | BE7: 198.73 | BF7: 202.48 | BG7: 211.53 | BH7: 210.95 | BI7: 210.55 | BJ7: 211.17 | BK7: 216.66 | BL7: #N/A | BM7: 215.9 | BN7: 216.23 | BO7: 227.4519 | BP7: 224.0802 | BQ7: 227.6872 | BR7: 229.98 | BS7: 232.135 | BT7: 229.115 | BU7: 229 | BV7: 228.4893 | BW7: 230.81 | BX7: 226.57 | BY7: 231.15 | BZ7: 233.22 | CA7: 231.51 | CB7: 235.29 | CC7: 228.2 | CD7: 226.98 | CE7: 222.81 | CF7: 219.885 | CG7: 219.41 | CH7: 225.33 | CI7: 225.22 | CJ7: 225.42 | CK7: 229.79 | CL7: 226.1235 | CM7: 231.11 | CN7: 231.35 | CO7: 232.78 | CP7: 235.4425 | CQ7: 230.5872 | CR7: 228.62 | CS7: 224.36 | CT7: 225.17 | CU7: 232.11 | CV7: 227.4685 | CW7: 234.0488 | CX7: 234.55 | CY7: 235.72 | CZ7: 234.65 | DA7: #N/A | DB7: 236.73 | DC7: 231.94 | DD7: 230.9845 | DE7: 226.47 | DF7: 229.25 | DG7: 229.65 | DH7: 226.83 | DI7: 228.75 | DJ7: 217.16 | DK7: 216.18 | DL7: 214 | DM7: 215.09 | DN7: 215.39 | DO7: 214.7029 | DP7: 212.22 | DQ7: 215.2062 | DR7: 215.48 | DS7: 213.2132 | DT7: 222.5 | DU7: 217.35 | DV7: 214.79 | DW7: 215.22 | DX7: 217.98 | DY7: 217.92 | DZ7: 218.88 | EA7: 219.6 | EB7: 225.5415 | EC7: 217.58 | ED7: 212.27 | EE7: 215.4 | EF7: 215.43 | EG7: 215.6 | EH7: 212.16 | EI7: 213.38 | EJ7: 216.96 | EK7: 216.735 | EL7: 214 | EM7: 218.725 | EN7: 221.42 | EO7: 222.53 | EP7: 223.7 | EQ7: 213.38 | ER7: 202.665 | ES7: 200.375 | ET7: 204.8857 | EU7: 198.93 | EV7: 196.75 | EW7: 196.96 | EX7: 193.4615 | EY7: 194.3058 | EZ7: 195.7113 | FA7: 195.65 | FB7: 194.65 | FC7: 194.12 | FD7: 191.745 | FE7: 190.25 | FF7: 184.2 | FG7: 179.2998 | FH7: 179.57 | FI7: 178.49 | FJ7: 182.415 | FK7: 187.518 | FL7: #N/A | FM7: 189.39 | FN7: 188.1773 | FO7: 203.85 | FP7: 199.35 | FQ7: 203.03 | FR7: 201.59 | FS7: 206.04 | FT7: 200.71 | FU7: 199.4695 | FV7: 201.24 | FW7: 204.3687 | FX7: 204.337 | FY7: 205.85 | FZ7: 207.92 | GA7: 209.95 | GB7: 215.36 | GC7: 216.02 | GD7: 216.75 | GE7: 218.4669 | GF7: 217.24 | GG7: 221.1 | GH7: 217.26 | GI7: 225.1958 | GJ7: 229.39 | GK7: 230.18 | GL7: 229.95 | GM7: 226.43 | GN7: 233.23 | GO7: 239.35 | GP7: 243.49 | GQ7: 241.83 | GR7: 248.01 | GS7: 247.55 | GT7: #N/A | GU7: 247.33 | GV7: 247.85 | GW7: 253.6115 | GX7: 252.67 | GY7: 250.19 | GZ7: 246.53 | HA7: 243.05 | HB7: 237.03 | HC7: 230.9396 | HD7: 235.63 | HE7: 230 | HF7: 232.35 | HG7: 239.08 | HH7: 243.61 | HI7: 244.2 | HJ7: 241.88 | HK7: 237.97 | HL7: 240.9 | HM7: 241.53 | HN7: #N/A | HO7: 242.41 | HP7: 240.25 | HQ7: 234.42 | HR7: 233.98 | HS7: 229.6 | HT7: 234.387 | HU7: 229.64 | HV7: 229.22 | HW7: 225 | HX7: 228.7 | HY7: 224.13 | HZ7: 227.16 | IA7: 220.81 | IB7: 219.08 | IC7: 221.29 | ID7: 220.26 | IE7: 213.86 | IF7: 204.58 | IG7: 210.2516 | IH7: 213.93 | II7: 211.05 | IJ7: 206.4 | IK7: 201.31 | IL7: 194.27 | IM7: 199.64 | IN7: 197 | IO7: 199.83 | IP7: 194.44 | IQ7: 189.43 | IR7: 189.7 | IS7: 197.86 | IT7: 207.95 | IU7: 206.34
A8: =Dashboard!B12 -> BLK | B8: {=TRANSPOSE(_xlfn.STOCKHISTORY(A8,TODAY()-365,TODAY(),0,0,1))} -> 817.5 | C8: 815.72 | D8: 897.08 | E8: 858.78 | F8: 878.78 | G8: 889.95 | H8: 888.44 | I8: 865.78 | J8: 875.78 | K8: 854 | L8: 887.22 | M8: 892.54 | N8: 916.26 | O8: 907.69 | P8: 913.74 | Q8: 920.52 | R8: 914.26 | S8: 916.14 | T8: 929.2 | U8: 920.53 | V8: 914.97 | W8: 920.36 | X8: 928.64 | Y8: 923.44 | Z8: 958.03 | AA8: 959.18 | AB8: 967.06 | AC8: 983.08 | AD8: 989.71 | AE8: 993.66 | AF8: 997.71 | AG8: 972.83 | AH8: 969.9 | AI8: 963.18 | AJ8: 981.32 | AK8: 971.28 | AL8: 976.32 | AM8: 979.89 | AN8: 978.07 | AO8: 982.13 | AP8: 988.97 | AQ8: 985.46 | AR8: 989.05 | AS8: 988.84 | AT8: 991.9 | AU8: 993.3 | AV8: 988.25 | AW8: 971.82 | AX8: 982.1 | AY8: 969.18 | AZ8: 979.52 | BA8: 974.44 | BB8: 986.3 | BC8: 1004.97 | BD8: 1018.08 | BE8: 1030.79 | BF8: 1047.82 | BG8: 1049.25 | BH8: 1054.27 | BI8: 1070.57 | BJ8: 1082.15 | BK8: 1075.97 | BL8: 1075.02 | BM8: 1088.75 | BN8: 1104.05 | BO8: 1101.64 | BP8: 1111.46 | BQ8: 1046.16 | BR8: 1082.24 | BS8: 1105.38 | BT8: 1103.59 | BU8: 1093.02 | BV8: 1100.39 | BW8: 1120.37 | BX8: 1118.37 | BY8: 1123.28 | BZ8: 1117.82 | CA8: 1121.53 | CB8: 1114.65 | CC8: 1106.01 | CD8: 1091.8 | CE8: 1116.06 | CF8: 1109.64 | CG8: 1120.54 | CH8: 1112.83 | CI8: 1124.97 | CJ8: 1127.93 | CK8: 1159.61 | CL8: 1160.03 | CM8: 1160.16 | CN8: 1135.01 | CO8: 1136.12 | CP8: 1128.47 | CQ8: 1128.46 | CR8: 1124.75 | CS8: 1148.17 | CT8: 1137.1 | CU8: 1139.8 | CV8: 1131.63 | CW8: 1130.48 | CX8: 1127.14 | CY8: 1114.77 | CZ8: 1099.49 | DA8: 1108.76 | DB8: 1099.15 | DC8: 1104.92 | DD8: 1105.67 | DE8: 1102.89 | DF8: 1134.18 | DG8: 1123.41 | DH8: 1115.11 | DI8: 1118.89 | DJ8: 1131.78 | DK8: 1137.13 | DL8: 1142.85 | DM8: 1136.21 | DN8: 1131.75 | DO8: 1127.98 | DP8: 1147.29 | DQ8: 1156.45 | DR8: 1175.56 | DS8: 1165.87 | DT8: 1141.07 | DU8: 1160.54 | DV8: 1160.69 | DW8: 1179.27 | DX8: 1166.23 | DY8: 1165 | DZ8: 1167.43 | EA8: 1132.36 | EB8: 1155.12 | EC8: 1194.26 | ED8: 1202.59 | EE8: 1171.36 | EF8: 1161.16 | EG8: 1160 | EH8: 1130 | EI8: 1129.68 | EJ8: 1125 | EK8: 1136.63 | EL8: 1131.31 | EM8: 1124.95 | EN8: 1098 | EO8: 1098.05 | EP8: 1082.81 | EQ8: 1068.83 | ER8: 1059.91 | ES8: 1073.57 | ET8: 1069.44 | EU8: 1082.2 | EV8: 1082.63 | EW8: 1085.76 | EX8: 1093.93 | EY8: 1069.65 | EZ8: 1057.94 | FA8: 1023.8 | FB8: 1019.14 | FC8: 1014.68 | FD8: 992.52 | FE8: 1014.72 | FF8: 1019.49 | FG8: 1029.77 | FH8: 1040.06 | FI8: 1047.3 | FJ8: 1039.94 | FK8: 1038.62 | FL8: 1079.87 | FM8: 1075.58 | FN8: 1072.16 | FO8: 1062.02 | FP8: 1071.31 | FQ8: 1083.36 | FR8: 1101.84 | FS8: 1089.09 | FT8: 1082.16 | FU8: 1068.14 | FV8: 1065 | FW8: 1064.99 | FX8: 1060.17 | FY8: 1088.21 | FZ8: 1086.55 | GA8: 1088.96 | GB8: 1088.11 | GC8: 1088.4 | GD8: 1083.31 | GE8: 1070.34 | GF8: 1085.06 | GG8: 1119.76 | GH8: 1112.28 | GI8: 1075.09 | GJ8: 1087.92 | GK8: 1085.1 | GL8: 1089.26 | GM8: 1089.54 | GN8: 1091.85 | GO8: 1156.65 | GP8: 1163.17 | GQ8: 1110.05 | GR8: 1127.85 | GS8: 1139.72 | GT8: 1129.91 | GU8: 1121.54 | GV8: 1106.69 | GW8: 1121.67 | GX8: 1127.78 | GY8: 1118.94 | GZ8: 1119.66 | HA8: 1070.08 | HB8: 1076.16 | HC8: 1054.8 | HD8: 1056.38 | HE8: 1079.9 | HF8: 1087.78 | HG8: 1082.88 | HH8: 1055.63 | HI8: 1071.51 | HJ8: 1072.67 | HK8: 1092.26 | HL8: 1081.28 | HM8: 1093.64 | HN8: 1071.01 | HO8: 1081.05 | HP8: 1093.78 | HQ8: 1090.27 | HR8: 1063.23 | HS8: 1068.31 | HT8: 1052.59 | HU8: 1049.23 | HV8: 1035 | HW8: 955.45 | HX8: 957.67 | HY8: 967.36 | HZ8: 951.17 | IA8: 922.9 | IB8: 924.11 | IC8: 943.26 | ID8: 971.01 | IE8: 968.31 | IF8: 969.6 | IG8: 957.91 | IH8: 974.58 | II8: 976.06 | IJ8: 981.35 | IK8: 968.46 | IL8: 933.85 | IM8: 934.06 | IN8: 961.71 | IO8: 957.4 | IP8: 966.56
A9: =Dashboard!B13 -> C | B9: {=TRANSPOSE(_xlfn.STOCKHISTORY(A9,TODAY()-365,TODAY(),0,0,1))} -> 58.85 | C9: 58.77 | D9: 64.15 | E9: 61.59 | F9: 61.64 | G9: 63.22 | H9: 64.33 | I9: 62.1 | J9: 63.25 | K9: 62.69 | L9: 64.55 | M9: 66.3 | N9: 68.16 | O9: 68.43 | P9: 68.28 | Q9: 68.88 | R9: 68.38 | S9: 68.14 | T9: 70.59 | U9: 70.24 | V9: 69.47 | W9: 70.25 | X9: 71.64 | Y9: 71.45 | Z9: 74.91 | AA9: 75.57 | AB9: 75.29 | AC9: 75.96 | AD9: 75.72 | AE9: 76.13 | AF9: 75.9 | AG9: 73.42 | AH9: 73.42 | AI9: 73.09 | AJ9: 75.47 | AK9: 75.03 | AL9: 75.53 | AM9: 75.32 | AN9: 75.8 | AO9: 76.53 | AP9: 76.4 | AQ9: 76.67 | AR9: 78.26 | AS9: 78.17 | AT9: 78.03 | AU9: 78.38 | AV9: 78.23 | AW9: 76.36 | AX9: 78.07 | AY9: 77.36 | AZ9: 78.35 | BA9: 78.45 | BB9: 79.36 | BC9: 81.14 | BD9: 82.63 | BE9: 84.37 | BF9: 84.38 | BG9: 85.12 | BH9: 86.27 | BI9: 86.76 | BJ9: 88.72 | BK9: 87.6 | BL9: 85.57 | BM9: 85.79 | BN9: 87.08 | BO9: 86.73 | BP9: 87.5 | BQ9: 90.72 | BR9: 90.02 | BS9: 93.09 | BT9: 93.45 | BU9: 92.65 | BV9: 94 | BW9: 95.99 | BX9: 95.39 | BY9: 96.07 | BZ9: 95.55 | CA9: 94.48 | CB9: 95.81 | CC9: 93.7 | CD9: 91.83 | CE9: 92.08 | CF9: 91.52 | CG9: 92.23 | CH9: 91.23 | CI9: 92.73 | CJ9: 92.31 | CK9: 95.74 | CL9: 94.65 | CM9: 95.46 | CN9: 93.69 | CO9: 94.22 | CP9: 93.74 | CQ9: 93.17 | CR9: 92.59 | CS9: 95.26 | CT9: 95 | CU9: 95.72 | CV9: 96.87 | CW9: 96.82 | CX9: 96.57 | CY9: 94.78 | CZ9: 95.03 | DA9: 97.08 | DB9: 95.4 | DC9: 95.87 | DD9: 97.34 | DE9: 97.17 | DF9: 98.82 | DG9: 99.44 | DH9: 99.79 | DI9: 100.64 | DJ9: 101.76 | DK9: 102.41 | DL9: 102.68 | DM9: 103.49 | DN9: 103 | DO9: 101.65 | DP9: 102.11 | DQ9: 103.42 | DR9: 103.16 | DS9: 101.5 | DT9: 98.71 | DU9: 97.34 | DV9: 97.74 | DW9: 98.05 | DX9: 97.8 | DY9: 96.7 | DZ9: 95.92 | EA9: 93.93 | EB9: 96.1 | EC9: 99.84 | ED9: 99.78 | EE9: 96.26 | EF9: 97.07 | EG9: 99.3 | EH9: 98.25 | EI9: 96.3 | EJ9: 96.69 | EK9: 98.78 | EL9: 100.99 | EM9: 101.39 | EN9: 99.12 | EO9: 100.22 | EP9: 101.23 | EQ9: 101.61 | ER9: 101.01 | ES9: 101.69 | ET9: 100.85 | EU9: 100.79 | EV9: 101.49 | EW9: 100.76 | EX9: 102.87 | EY9: 100.67 | EZ9: 100.3 | FA9: 98.19 | FB9: 98.32 | FC9: 99.83 | FD9: 97.63 | FE9: 98.7 | FF9: 99.69 | FG9: 101.17 | FH9: 102.5 | FI9: 103.6 | FJ9: 102.68 | FK9: 103.19 | FL9: 106.72 | FM9: 107.79 | FN9: 108.88 | FO9: 108.92 | FP9: 109.43 | FQ9: 111.09 | FR9: 111.74 | FS9: 111.8 | FT9: 112.8 | FU9: 111.28 | FV9: 111.46 | FW9: 112.83 | FX9: 114.86 | FY9: 118.09 | FZ9: 119.4 | GA9: 121.56 | GB9: 120.42 | GC9: 118.13 | GD9: 117.21 | GE9: 116.69 | GF9: 118.7 | GG9: 123.3 | GH9: 122.5 | GI9: 121.37 | GJ9: 120.6 | GK9: 121.32 | GL9: 117.7 | GM9: 116.3 | GN9: 112.41 | GO9: 117.46 | GP9: 118.04 | GQ9: 112.8 | GR9: 113.86 | GS9: 115.66 | GT9: 113.59 | GU9: 114.82 | GV9: 114.79 | GW9: 114.2 | GX9: 115.2 | GY9: 115.71 | GZ9: 116.23 | HA9: 117.71 | HB9: 117.43 | HC9: 115.74 | HD9: 122.69 | HE9: 123.77 | HF9: 122.15 | HG9: 117.39 | HH9: 111.15 | HI9: 110.86 | HJ9: 113.78 | HK9: 116.27 | HL9: 115.55 | HM9: 116 | HN9: 110.75 | HO9: 109.56 | HP9: 114.34 | HQ9: 116.19 | HR9: 110.19 | HS9: 111.45 | HT9: 110.76 | HU9: 111.32 | HV9: 108.95 | HW9: 106.53 | HX9: 106.59 | HY9: 108.97 | HZ9: 109.19 | IA9: 105.5 | IB9: 105.69 | IC9: 107.35 | ID9: 107.71 | IE9: 108.67 | IF9: 109.85 | IG9: 109.52 | IH9: 111.64 | II9: 113.74 | IJ9: 114.48 | IK9: 112.41 | IL9: 107.38 | IM9: 107.27 | IN9: 113.41 | IO9: 115.3 | IP9: 115.25
A10: =Dashboard!B14 -> CVX | B10: {=TRANSPOSE(_xlfn.STOCKHISTORY(A10,TODAY()-365,TODAY(),0,0,1))} -> 140.15 | C10: 136.93 | D10: 146.03 | E10: 134.98 | F10: 135.63 | G10: 135.32 | H10: 134.54 | I10: 135.36 | J10: 137.87 | K10: 133.73 | L10: 137.3 | M10: 136.68 | N10: 139.07 | O10: 138.73 | P10: 140.1 | Q10: 139.3 | R10: 136.06 | S10: 136.26 | T10: 138.5 | U10: 135.5 | V10: 135.6 | W10: 135.79 | X10: 137.04 | Y10: 138.49 | Z10: 141.62 | AA10: 142.35 | AB10: 141.67 | AC10: 142.26 | AD10: 142.1 | AE10: 138.49 | AF10: 137.27 | AG10: 135.56 | AH10: 135.29 | AI10: 136.54 | AJ10: 137.83 | AK10: 136.02 | AL10: 137.91 | AM10: 136.7 | AN10: 137.84 | AO10: 139.55 | AP10: 137.37 | AQ10: 136.9 | AR10: 140.21 | AS10: 140.76 | AT10: 143.35 | AU10: 144.78 | AV10: 144.97 | AW10: 145.91 | AX10: 146.03 | AY10: 148.85 | AZ10: 148.19 | BA10: 149.55 | BB10: 146.86 | BC10: 143.55 | BD10: 143.23 | BE10: 144.44 | BF10: 143.79 | BG10: 143.19 | BH10: 145.57 | BI10: 147.98 | BJ10: 148.37 | BK10: 147.4 | BL10: 153.24 | BM10: 153.02 | BN10: 154.17 | BO10: 155.31 | BP10: 151.65 | BQ10: 150.69 | BR10: 149.92 | BS10: 151.38 | BT10: 150.04 | BU10: 149.68 | BV10: 150.04 | BW10: 153.12 | BX10: 155.83 | BY10: 154.84 | BZ10: 156.28 | CA10: 157.03 | CB10: 153.56 | CC10: 151.64 | CD10: 151.4 | CE10: 151.04 | CF10: 153.04 | CG10: 152.78 | CH10: 153.16 | CI10: 155.01 | CJ10: 153.45 | CK10: 154.44 | CL10: 155.87 | CM10: 155.16 | CN10: 156.55 | CO10: 155.32 | CP10: 152 | CQ10: 153.22 | CR10: 155.55 | CS10: 158.18 | CT10: 158.2 | CU10: 157.36 | CV10: 159.24 | CW10: 159.32 | CX10: 160.6 | CY10: 161.83 | CZ10: 158.06 | DA10: 157.69 | DB10: 153.66 | DC10: 154 | DD10: 154.85 | DE10: 157.79 | DF10: 158.25 | DG10: 157.11 | DH10: 157.31 | DI10: 159.54 | DJ10: 160.09 | DK10: 158.84 | DL10: 156.21 | DM10: 156.05 | DN10: 157.42 | DO10: 159.18 | DP10: 160.72 | DQ10: 160.16 | DR10: 156.1 | DS10: 155.29 | DT10: 154.58 | DU10: 153.37 | DV10: 153.55 | DW10: 154.02 | DX10: 154.91 | DY10: 153.74 | DZ10: 151.64 | EA10: 148.9 | EB10: 151.94 | EC10: 152.39 | ED10: 152.11 | EE10: 151.71 | EF10: 153.08 | EG10: 154.48 | EH10: 153.79 | EI10: 155.57 | EJ10: 156.56 | EK10: 155.56 | EL10: 155.28 | EM10: 154.13 | EN10: 155.1 | EO10: 153.52 | EP10: 157.72 | EQ10: 154.04 | ER10: 153.39 | ES10: 152.66 | ET10: 152.94 | EU10: 155.02 | EV10: 155.65 | EW10: 156.24 | EX10: 153.32 | EY10: 155.58 | EZ10: 157.62 | FA10: 154.82 | FB10: 153.62 | FC10: 151.7 | FD10: 150.31 | FE10: 149.98 | FF10: 149.75 | FG10: 148.53 | FH10: 149.51 | FI10: 151.13 | FJ10: 152.54 | FK10: 150.25 | FL10: 151.59 | FM10: 152.26 | FN10: 150 | FO10: 148.71 | FP10: 148.49 | FQ10: 151.41 | FR10: 150.72 | FS10: 149.99 | FT10: 149.8 | FU10: 146.75 | FV10: 149.52 | FW10: 147.69 | FX10: 147.75 | FY10: 149.8 | FZ10: 150.51 | GA10: 150.5 | GB10: 150.02 | GC10: 150.99 | GD10: 152.31 | GE10: 152.41 | GF10: 155.9 | GG10: 163.85 | GH10: 156.54 | GI10: 155.2 | GJ10: 159.25 | GK10: 162.11 | GL10: 162.34 | GM10: 163.87 | GN10: 167.24 | GO10: 166.16 | GP10: 166.26 | GQ10: 165.3 | GR10: 166.73 | GS10: 166.66 | GT10: 166.72 | GU10: 167.5 | GV10: 169.05 | GW10: 169.93 | GX10: 171.19 | GY10: 176.9 | GZ10: 174.03 | HA10: 178.04 | HB10: 181.23 | HC10: 179.23 | HD10: 180.86 | HE10: 182.6 | HF10: 182.26 | HG10: 185.82 | HH10: 182.4 | HI10: 183.74 | HJ10: 180.55 | HK10: 183.87 | HL10: 184.78 | HM10: 183.93 | HN10: 184.91 | HO10: 185.34 | HP10: 184.22 | HQ10: 184.16 | HR10: 186.76 | HS10: 189.6 | HT10: 188.77 | HU10: 186.03 | HV10: 189.9 | HW10: 189.94 | HX10: 189.44 | HY10: 186.29 | HZ10: 191.79 | IA10: 196.97 | IB10: 196.82 | IC10: 196.84 | ID10: 197.97 | IE10: 198.61 | IF10: 201.44 | IG10: 201.73 | IH10: 205.21 | II10: 206.79 | IJ10: 205.15 | IK10: 207.79 | IL10: 211.15 | IM10: 210.71 | IN10: 206.9 | IO10: 197.41 | IP10: 198.97
A11: =Dashboard!B15 -> F | B11: {=TRANSPOSE(_xlfn.STOCKHISTORY(A11,TODAY()-365,TODAY(),0,0,1))} -> 9.24 | C11: 8.69 | D11: 9.5 | E11: 9.14 | F11: 9.33 | G11: 9.71 | H11: 9.45 | I11: 9.4 | J11: 9.63 | K11: 9.47 | L11: 9.65 | M11: 9.78 | N11: 10.06 | O11: 10.04 | P11: 10.02 | Q11: 10.15 | R11: 10.01 | S11: 10.18 | T11: 10.28 | U11: 10.17 | V11: 10.44 | W11: 10.28 | X11: 10.28 | Y11: 10.43 | Z11: 10.55 | AA11: 10.6 | AB11: 10.65 | AC11: 10.75 | AD11: 10.8 | AE11: 10.75 | AF11: 10.72 | AG11: 10.48 | AH11: 10.44 | AI11: 10.36 | AJ11: 10.31 | AK11: 10.17 | AL11: 10.22 | AM11: 10.38 | AN11: 9.98 | AO11: 10.19 | AP11: 10.24 | AQ11: 10.1 | AR11: 10.26 | AS11: 10.34 | AT11: 10.6 | AU11: 10.66 | AV11: 10.53 | AW11: 10.43 | AX11: 10.62 | AY11: 10.42 | AZ11: 10.43 | BA11: 10.59 | BB11: 10.75 | BC11: 10.73 | BD11: 10.48 | BE11: 10.63 | BF11: 10.8 | BG11: 10.85 | BH11: 11.35 | BI11: 11.77 | BJ11: 11.81 | BK11: 11.59 | BL11: 11.68 | BM11: 11.83 | BN11: 11.91 | BO11: 11.78 | BP11: 11.88 | BQ11: 11.57 | BR11: 11.24 | BS11: 11.15 | BT11: 11.16 | BU11: 11.31 | BV11: 11.19 | BW11: 11.38 | BX11: 11.26 | BY11: 11.47 | BZ11: 11.28 | CA11: 11.08 | CB11: 10.87 | CC11: 11.07 | CD11: 10.82 | CE11: 10.95 | CF11: 11.06 | CG11: 11.21 | CH11: 11.28 | CI11: 11.32 | CJ11: 11.14 | CK11: 11.25 | CL11: 11.44 | CM11: 11.44 | CN11: 11.44 | CO11: 11.46 | CP11: 11.58 | CQ11: 11.49 | CR11: 11.33 | CS11: 11.74 | CT11: 11.82 | CU11: 11.84 | CV11: 11.91 | CW11: 11.71 | CX11: 11.77 | CY11: 11.72 | CZ11: 11.62 | DA11: 11.68 | DB11: 11.74 | DC11: 11.69 | DD11: 11.49 | DE11: 11.42 | DF11: 11.76 | DG11: 11.68 | DH11: 11.68 | DI11: 11.61 | DJ11: 11.66 | DK11: 11.74 | DL11: 11.62 | DM11: 11.66 | DN11: 11.73 | DO11: 11.63 | DP11: 11.62 | DQ11: 12.01 | DR11: 12.09 | DS11: 11.96 | DT11: 12.27 | DU11: 12.22 | DV11: 12.67 | DW11: 12.7 | DX11: 11.92 | DY11: 11.74 | DZ11: 11.5 | EA11: 11.41 | EB11: 11.54 | EC11: 11.65 | ED11: 11.76 | EE11: 11.74 | EF11: 11.92 | EG11: 11.99 | EH11: 12.56 | EI11: 12.43 | EJ11: 12.34 | EK11: 13.84 | EL11: 13.26 | EM11: 13.13 | EN11: 13.24 | EO11: 13.06 | EP11: 13.13 | EQ11: 13.01 | ER11: 12.79 | ES11: 13.11 | ET11: 13.12 | EU11: 13.21 | EV11: 13.16 | EW11: 13.3 | EX11: 13.45 | EY11: 13.28 | EZ11: 13.19 | FA11: 12.88 | FB11: 13.02 | FC11: 12.9 | FD11: 12.41 | FE11: 12.83 | FF11: 12.96 | FG11: 13.17 | FH11: 13.19 | FI11: 13.28 | FJ11: 13.16 | FK11: 12.96 | FL11: 13.09 | FM11: 13.14 | FN11: 13.03 | FO11: 13.14 | FP11: 13.08 | FQ11: 13.41 | FR11: 13.63 | FS11: 13.76 | FT11: 13.65 | FU11: 13.67 | FV11: 13.31 | FW11: 13.32 | FX11: 13.47 | FY11: 13.46 | FZ11: 13.29 | GA11: 13.36 | GB11: 13.31 | GC11: 13.28 | GD11: 13.23 | GE11: 13.12 | GF11: 13.34 | GG11: 13.47 | GH11: 13.8 | GI11: 13.74 | GJ11: 14.4 | GK11: 14.2 | GL11: 14.03 | GM11: 13.98 | GN11: 13.84 | GO11: 13.81 | GP11: 13.6 | GQ11: 13.28 | GR11: 13.77 | GS11: 13.71 | GT11: 13.56 | GU11: 13.44 | GV11: 13.93 | GW11: 13.82 | GX11: 14 | GY11: 13.88 | GZ11: 13.81 | HA11: 13.73 | HB11: 13.82 | HC11: 13.72 | HD11: 13.8 | HE11: 13.59 | HF11: 13.57 | HG11: 13.85 | HH11: 14 | HI11: 14.12 | HJ11: 14.13 | HK11: 13.85 | HL11: 13.78 | HM11: 14.01 | HN11: 13.64 | HO11: 14.2 | HP11: 14.43 | HQ11: 14.41 | HR11: 14.09 | HS11: 13.39 | HT11: 12.7 | HU11: 12.81 | HV11: 12.34 | HW11: 12.15 | HX11: 12.19 | HY11: 12.24 | HZ11: 12.11 | IA11: 12.04 | IB11: 11.67 | IC11: 11.71 | ID11: 11.94 | IE11: 11.79 | IF11: 11.64 | IG11: 11.52 | IH11: 11.76 | II11: 11.84 | IJ11: 11.67 | IK11: 11.6 | IL11: 11.37 | IM11: 11.21 | IN11: 11.54 | IO11: 11.68 | IP11: 11.6
A12: =Dashboard!B16 -> GOOG | B12: {=TRANSPOSE(_xlfn.STOCKHISTORY(A12,TODAY()-365,TODAY(),0,0,1))} -> 149.24 | C12: 146.58 | D12: 161.06 | E12: 155.37 | F12: 159.4 | G12: 161.47 | H12: 158.68 | I12: 155.5 | J12: 153.36 | K12: 149.86 | L12: 153.9 | M12: 157.72 | N12: 161.47 | O12: 163.85 | P12: 162.42 | Q12: 162.06 | R12: 160.89 | S12: 162.79 | T12: 165.81 | U12: 166.05 | V12: 165.2 | W12: 152.8 | X12: 155.75 | Y12: 154.38 | Z12: 159.58 | AA12: 160.89 | AB12: 166.81 | AC12: 165.4 | AD12: 167.43 | AE12: 167.87 | AF12: 165.32 | AG12: 170.06 | AH12: 171.98 | AI12: 169.59 | AJ12: 173.98 | AK12: 173.38 | AL12: 172.96 | AM12: 172.85 | AN12: 170.37 | AO12: 167.71 | AP12: 169.39 | AQ12: 169.81 | AR12: 174.92 | AS12: 177.63 | AT12: 180.01 | AU12: 178.79 | AV12: 176.97 | AW12: 175.88 | AX12: 177.94 | AY12: 177.23 | AZ12: 173.98 | BA12: 167.73 | BB12: 166.01 | BC12: 167.74 | BD12: 171.49 | BE12: 174.43 | BF12: 178.27 | BG12: 177.39 | BH12: 176.91 | BI12: 179.76 | BJ12: 180.55 | BK12: 177.56 | BL12: 175.16 | BM12: 177.66 | BN12: 178.7 | BO12: 181.31 | BP12: 182.81 | BQ12: 183.1 | BR12: 183.77 | BS12: 184.7 | BT12: 185.94 | BU12: 191.15 | BV12: 192.11 | BW12: 191.51 | BX12: 193.2 | BY12: 194.08 | BZ12: 193.42 | CA12: 196.43 | CB12: 197.44 | CC12: 192.86 | CD12: 189.95 | CE12: 195.75 | CF12: 195.32 | CG12: 196.92 | CH12: 197.28 | CI12: 202.09 | CJ12: 201.63 | CK12: 204.16 | CL12: 203.03 | CM12: 203.82 | CN12: 204.91 | CO12: 204.29 | CP12: 202.49 | CQ12: 200.19 | CR12: 200.62 | CS12: 206.72 | CT12: 209.16 | CU12: 207.95 | CV12: 208.21 | CW12: 212.37 | CX12: 213.53 | CY12: 211.99 | CZ12: 231.1 | DA12: 232.66 | DB12: 235.17 | DC12: 234.16 | DD12: 239.94 | DE12: 239.56 | DF12: 240.78 | DG12: 241.38 | DH12: 251.76 | DI12: 251.42 | DJ12: 249.85 | DK12: 252.33 | DL12: 255.24 | DM12: 252.88 | DN12: 252.34 | DO12: 247.83 | DP12: 246.57 | DQ12: 247.18 | DR12: 244.36 | DS12: 243.55 | DT12: 245.54 | DU12: 246.43 | DV12: 246.45 | DW12: 251.51 | DX12: 247.13 | DY12: 245.46 | DZ12: 242.21 | EA12: 237.49 | EB12: 244.64 | EC12: 246.19 | ED12: 251.71 | EE12: 251.88 | EF12: 253.79 | EG12: 257.02 | EH12: 251.34 | EI12: 252.53 | EJ12: 253.73 | EK12: 260.51 | EL12: 269.93 | EM12: 268.43 | EN12: 275.17 | EO12: 281.9 | EP12: 281.82 | EQ12: 284.12 | ER12: 278.06 | ES12: 284.75 | ET12: 285.34 | EU12: 279.7 | EV12: 290.59 | EW12: 291.74 | EX12: 287.43 | EY12: 279.12 | EZ12: 276.98 | FA12: 285.6 | FB12: 284.96 | FC12: 292.99 | FD12: 289.98 | FE12: 299.65 | FF12: 318.47 | FG12: 323.64 | FH12: 320.28 | FI12: 320.12 | FJ12: 315.12 | FK12: 316.02 | FL12: 320.62 | FM12: 318.39 | FN12: 322.09 | FO12: 314.45 | FP12: 317.75 | FQ12: 321 | FR12: 313.7 | FS12: 310.52 | FT12: 309.32 | FU12: 307.73 | FV12: 298.06 | FW12: 303.75 | FX12: 308.61 | FY12: 311.33 | FZ12: 315.68 | GA12: 315.67 | GB12: 314.96 | GC12: 314.39 | GD12: 314.55 | GE12: 313.8 | GF12: 315.32 | GG12: 317.32 | GH12: 314.55 | GI12: 322.43 | GJ12: 326.01 | GK12: 329.14 | GL12: 332.73 | GM12: 336.43 | GN12: 336.31 | GO12: 333.16 | GP12: 330.34 | GQ12: 322.16 | GR12: 328.38 | GS12: 330.84 | GT12: 328.43 | GU12: 333.59 | GV12: 335 | GW12: 336.28 | GX12: 338.66 | GY12: 338.53 | GZ12: 344.9 | HA12: 340.7 | HB12: 333.34 | HC12: 331.33 | HD12: 323.1 | HE12: 324.4 | HF12: 318.63 | HG12: 311.33 | HH12: 309.37 | HI12: 306.02 | HJ12: 302.82 | HK12: 303.94 | HL12: 303.56 | HM12: 314.9 | HN12: 311.69 | HO12: 310.92 | HP12: 313.03 | HQ12: 307.15 | HR12: 311.43 | HS12: 306.36 | HT12: 303.56 | HU12: 303.45 | HV12: 300.91 | HW12: 298.3 | HX12: 306.01 | HY12: 306.93 | HZ12: 308.42 | IA12: 303.21 | IB12: 301.46 | IC12: 304.42 | ID12: 309.41 | IE12: 306.3 | IF12: 305.73 | IG12: 298.79 | IH12: 299.02 | II12: 289.2 | IJ12: 289.59 | IK12: 280.74 | IL12: 273.76 | IM12: 273.14 | IN12: 286.86 | IO12: 294.9 | IP12: 294.46
A13: =Dashboard!B17 -> HMC | B13: {=TRANSPOSE(_xlfn.STOCKHISTORY(A13,TODAY()-365,TODAY(),0,0,1))} -> 4.96 | C13: 4.78 | D13: 4.59 | E13: 4.94 | F13: 4.63 | G13: 4.75 | H13: 4.62 | I13: 4.53 | J13: 4.57 | K13: 4.41 | L13: 4.6 | M13: 4.67 | N13: 4.68 | O13: 4.93 | P13: 4.86 | Q13: 5.26 | R13: 5.26 | S13: 5.17 | T13: 4.87 | U13: 5.09 | V13: 5.23 | W13: 5.21 | X13: 5.38 | Y13: 5.58 | Z13: 5.64 | AA13: 5.56 | AB13: 5.73 | AC13: 5.58 | AD13: 5.7 | AE13: 5.29 | AF13: 5.26 | AG13: 5.27 | AH13: 5.06 | AI13: 5.04 | AJ13: 4.95 | AK13: 5.06 | AL13: 5.05 | AM13: 4.85 | AN13: 4.79 | AO13: 4.85 | AP13: 4.9 | AQ13: 4.82 | AR13: 4.91 | AS13: 4.83 | AT13: 4.74 | AU13: 4.67 | AV13: 4.74 | AW13: 4.77 | AX13: 4.7 | AY13: 4.78 | AZ13: 4.79 | BA13: 4.61 | BB13: 4.93 | BC13: 5.03 | BD13: 5.22 | BE13: 5.06 | BF13: 5.1 | BG13: 4.22 | BH13: 4.08 | BI13: 4.35 | BJ13: 4.37 | BK13: 4.11 | BL13: 3.89 | BM13: 3.8 | BN13: 3.9 | BO13: 3.75 | BP13: 3.72 | BQ13: 3.76 | BR13: 3.72 | BS13: 3.77 | BT13: 3.85 | BU13: 3.77 | BV13: 3.72 | BW13: 3.72 | BX13: 3.63 | BY13: 3.7 | BZ13: 3.74 | CA13: 3.6 | CB13: 3.67 | CC13: 3.59 | CD13: 3.53 | CE13: 3.57 | CF13: 3.64 | CG13: 3.61 | CH13: 3.51 | CI13: 3.57 | CJ13: 3.63 | CK13: 3.58 | CL13: 3.57 | CM13: 3.61 | CN13: 3.63 | CO13: 3.5 | CP13: 3.27 | CQ13: 3.85 | CR13: 3.79 | CS13: 3.78 | CT13: 3.91 | CU13: 3.85 | CV13: 3.85 | CW13: 3.82 | CX13: 3.85 | CY13: 3.76 | CZ13: 3.64 | DA13: 3.53 | DB13: 3.4 | DC13: 3.75 | DD13: 3.71 | DE13: 3.53 | DF13: 3.63 | DG13: 3.6 | DH13: 3.83 | DI13: 3.65 | DJ13: 3.63 | DK13: 3.52 | DL13: 3.48 | DM13: 3.43 | DN13: 3.39 | DO13: 3.33 | DP13: 3.34 | DQ13: 3.35 | DR13: 3.28 | DS13: 3.23 | DT13: 3.18 | DU13: 3.2 | DV13: 3.13 | DW13: 3.36 | DX13: 3.18 | DY13: 3.12 | DZ13: 3.1 | EA13: 3.09 | EB13: 3.07 | EC13: 3.1 | ED13: 3.37 | EE13: 3.62 | EF13: 3.41 | EG13: 3.37 | EH13: 3.16 | EI13: 3.22 | EJ13: 3.28 | EK13: 3.2 | EL13: 3.25 | EM13: 3.28 | EN13: 3.17 | EO13: 3.12 | EP13: 3.21 | EQ13: 3.1 | ER13: 3.25 | ES13: 3.24 | ET13: 3.15 | EU13: 3.12 | EV13: 3.1 | EW13: 3.15 | EX13: 3.13 | EY13: 3.05 | EZ13: 2.98 | FA13: 2.9 | FB13: 2.94 | FC13: 2.95 | FD13: 2.99 | FE13: 3.17 | FF13: 3.22 | FG13: 3.2 | FH13: 3.15 | FI13: 3.22 | FJ13: 3.55 | FK13: 3.87 | FL13: 3.6 | FM13: 3.6 | FN13: 3.4 | FO13: 3.57 | FP13: 3.59 | FQ13: 3.49 | FR13: 3.58 | FS13: 3.58 | FT13: 3.6 | FU13: 3.65 | FV13: 3.66 | FW13: 3.51 | FX13: 3.66 | FY13: 3.7 | FZ13: 3.97 | GA13: 3.78 | GB13: 3.78 | GC13: 3.96 | GD13: 3.88 | GE13: 3.96 | GF13: 3.96 | GG13: 4.03 | GH13: 3.83 | GI13: 3.81 | GJ13: 4.06 | GK13: 4.02 | GL13: 4.14 | GM13: 4.41 | GN13: 4.43 | GO13: 4.35 | GP13: 4.3 | GQ13: 4.46 | GR13: 4.39 | GS13: 4.33 | GT13: 4.05 | GU13: 4.16 | GV13: 4.32 | GW13: 4.13 | GX13: 4.17 | GY13: 4.22 | GZ13: 4.2 | HA13: 4.19 | HB13: 4.25 | HC13: 4.03 | HD13: 4.03 | HE13: 3.92 | HF13: 3.72 | HG13: 3.74 | HH13: 3.6 | HI13: 3.32 | HJ13: 3.11 | HK13: 3.13 | HL13: 3.06 | HM13: 3.15 | HN13: 3.13 | HO13: 3.06 | HP13: 2.96 | HQ13: 2.82 | HR13: 2.81 | HS13: 2.9 | HT13: 2.78 | HU13: 2.7 | HV13: 2.56 | HW13: 2.41 | HX13: 2.46 | HY13: 2.53 | HZ13: 2.42 | IA13: 2.47 | IB13: 2.42 | IC13: 2.31 | ID13: 2.35 | IE13: 2.37 | IF13: 2.34 | IG13: 2.4 | IH13: 2.33 | II13: 2.25 | IJ13: 2.26 | IK13: 2.2 | IL13: 2.33 | IM13: 2.25 | IN13: 2.27 | IO13: 2.2 | IP13: 2.34 | IQ13: 2.72 | IR13: 2.52
A14: =Dashboard!B18 -> JPM | B14: {=TRANSPOSE(_xlfn.STOCKHISTORY(A14,TODAY()-365,TODAY(),0,0,1))} -> 214.44 | C14: 216.87 | D14: 234.34 | E14: 227.11 | F14: 236.2 | G14: 234.72 | H14: 233.13 | I14: 229.61 | J14: 231.96 | K14: 228.99 | L14: 235.59 | M14: 240.88 | N14: 244.64 | O14: 243.55 | P14: 243.22 | Q14: 244.62 | R14: 244.62 | S14: 246.89 | T14: 252.51 | U14: 252.56 | V14: 249.25 | W14: 249.39 | X14: 253.47 | Y14: 253.08 | Z14: 260.05 | AA14: 263.01 | AB14: 265.64 | AC14: 267.49 | AD14: 267.56 | AE14: 264.88 | AF14: 265.68 | AG14: 261.04 | AH14: 260.67 | AI14: 260.71 | AJ14: 265.29 | AK14: 263.49 | AL14: 264.37 | AM14: 264 | AN14: 264.66 | AO14: 266.27 | AP14: 264.22 | AQ14: 261.95 | AR14: 265.73 | AS14: 266.74 | AT14: 268.6 | AU14: 268.15 | AV14: 268.24 | AW14: 264.95 | AX14: 270.36 | AY14: 269.52 | AZ14: 273.96 | BA14: 275 | BB14: 278.27 | BC14: 281.26 | BD14: 284.06 | BE14: 288.75 | BF14: 287.11 | BG14: 289.91 | BH14: 290.41 | BI14: 292 | BJ14: 296 | BK14: 291.97 | BL14: 282.78 | BM14: 283.16 | BN14: 288.19 | BO14: 286.86 | BP14: 288.7 | BQ14: 286.55 | BR14: 285.82 | BS14: 289.9 | BT14: 291.27 | BU14: 290.97 | BV14: 291.43 | BW14: 296.76 | BX14: 296.55 | BY14: 298.62 | BZ14: 298.28 | CA14: 297.04 | CB14: 299.63 | CC14: 296.24 | CD14: 289.37 | CE14: 294.26 | CF14: 291.37 | CG14: 291.35 | CH14: 286.94 | CI14: 288.76 | CJ14: 289.56 | CK14: 292.85 | CL14: 290.53 | CM14: 294.16 | CN14: 290.49 | CO14: 291.53 | CP14: 290.66 | CQ14: 292.24 | CR14: 291.47 | CS14: 296.24 | CT14: 294.9 | CU14: 298.57 | CV14: 299.28 | CW14: 301.07 | CX14: 301.42 | CY14: 299.7 | CZ14: 299.51 | DA14: 303.82 | DB14: 294.38 | DC14: 292.91 | DD14: 297.85 | DE14: 300.54 | DF14: 305.56 | DG14: 306.91 | DH14: 308.9 | DI14: 309.19 | DJ14: 311.75 | DK14: 313.23 | DL14: 314.78 | DM14: 312.44 | DN14: 312.74 | DO14: 313.42 | DP14: 313.45 | DQ14: 316.06 | DR14: 315.69 | DS14: 315.43 | DT14: 310.71 | DU14: 307.55 | DV14: 310.03 | DW14: 309.18 | DX14: 307.69 | DY14: 304.03 | DZ14: 305.53 | EA14: 300.89 | EB14: 307.97 | EC14: 302.08 | ED14: 305.69 | EE14: 298.54 | EF14: 297.56 | EG14: 302.36 | EH14: 297.09 | EI14: 294.11 | EJ14: 294.54 | EK14: 300.44 | EL14: 304.15 | EM14: 305.36 | EN14: 305.51 | EO14: 309.44 | EP14: 311.12 | EQ14: 309.35 | ER14: 309.25 | ES14: 311.68 | ET14: 313.42 | EU14: 314.21 | EV14: 316.89 | EW14: 315.62 | EX14: 320.41 | EY14: 309.48 | EZ14: 303.61 | FA14: 300.37 | FB14: 299.41 | FC14: 303.27 | FD14: 298.38 | FE14: 298.02 | FF14: 298 | FG14: 303 | FH14: 307.64 | FI14: 313.08 | FJ14: 308.92 | FK14: 307.88 | FL14: 312.13 | FM14: 316.1 | FN14: 315.04 | FO14: 315.21 | FP14: 300.51 | FQ14: 310.11 | FR14: 317.38 | FS14: 318.52 | FT14: 320.02 | FU14: 315.55 | FV14: 314.98 | FW14: 313 | FX14: 317.21 | FY14: 323.09 | FZ14: 325.93 | GA14: 329.17 | GB14: 327.91 | GC14: 323.75 | GD14: 323.42 | GE14: 322.22 | GF14: 325.48 | GG14: 334.04 | GH14: 334.61 | GI14: 326.99 | GJ14: 329.79 | GK14: 329.19 | GL14: 324.49 | GM14: 310.9 | GN14: 307.87 | GO14: 309.26 | GP14: 312.47 | GQ14: 302.74 | GR14: 302.04 | GS14: 303.63 | GT14: 297.72 | GU14: 301.04 | GV14: 300.31 | GW14: 300.77 | GX14: 306.42 | GY14: 305.89 | GZ14: 308.14 | HA14: 314.85 | HB14: 317.27 | HC14: 310.16 | HD14: 322.4 | HE14: 322.1 | HF14: 318.28 | HG14: 310.82 | HH14: 302.64 | HI14: 302.55 | HJ14: 307.13 | HK14: 308.78 | HL14: 308.05 | HM14: 310.79 | HN14: 297.67 | HO14: 297.3 | HP14: 303.3 | HQ14: 306.13 | HR14: 300.3 | HS14: 297.56 | HT14: 300.26 | HU14: 299.39 | HV14: 293.55 | HW14: 289.48 | HX14: 289.92 | HY14: 288.73 | HZ14: 287.52 | IA14: 282.89 | IB14: 283.44 | IC14: 286.16 | ID14: 286.89 | IE14: 287.74 | IF14: 287.97 | IG14: 286.56 | IH14: 289.91 | II14: 292.4 | IJ14: 295.42 | IK14: 291.66 | IL14: 282.84 | IM14: 283.77 | IN14: 294.16 | IO14: 295.38 | IP14: 294.6
A15: =Dashboard!B19 -> META | B15: {=TRANSPOSE(_xlfn.STOCKHISTORY(A15,TODAY()-365,TODAY(),0,0,1))} -> 516.25 | C15: 510.45 | D15: 585.77 | E15: 546.29 | F15: 543.57 | G15: 531.48 | H15: 521.52 | I15: 502.31 | J15: 501.48 | K15: 484.66 | L15: 500.28 | M15: 520.27 | N15: 533.15 | O15: 547.27 | P15: 549.74 | Q15: 554.44 | R15: 549 | S15: 572.21 | T15: 597.02 | U15: 599.27 | V15: 587.31 | W15: 596.81 | X15: 598.01 | Y15: 592.49 | Z15: 639.43 | AA15: 656.03 | AB15: 659.36 | AC15: 643.88 | AD15: 640.34 | AE15: 640.43 | AF15: 637.1 | AG15: 635.5 | AH15: 636.57 | AI15: 627.06 | AJ15: 642.32 | AK15: 643.58 | AL15: 645.05 | AM15: 647.49 | AN15: 670.9 | AO15: 666.85 | AP15: 687.95 | AQ15: 684.62 | AR15: 697.71 | AS15: 694.06 | AT15: 702.4 | AU15: 694.14 | AV15: 693.36 | AW15: 682.87 | AX15: 702.12 | AY15: 697.23 | AZ15: 695.77 | BA15: 682.35 | BB15: 698.53 | BC15: 712.2 | BD15: 708.68 | BE15: 726.09 | BF15: 733.63 | BG15: 738.09 | BH15: 719.22 | BI15: 713.57 | BJ15: 719.01 | BK15: 718.35 | BL15: 720.67 | BM15: 732.78 | BN15: 727.24 | BO15: 717.51 | BP15: 720.92 | BQ15: 710.39 | BR15: 702.91 | BS15: 701.41 | BT15: 704.28 | BU15: 712.965 | BV15: 704.81 | BW15: 713.58 | BX15: 714.8 | BY15: 712.68 | BZ15: 717.63 | CA15: 700 | CB15: 695.21 | CC15: 773.44 | CD15: 750.01 | CE15: 776.37 | CF15: 763.46 | CG15: 771.99 | CH15: 761.83 | CI15: 769.3 | CJ15: 765.87 | CK15: 790 | CL15: 780.08 | CM15: 782.13 | CN15: 785.23 | CO15: 767.37 | CP15: 751.48 | CQ15: 747.72 | CR15: 739.1 | CS15: 754.79 | CT15: 753.3 | CU15: 754.1 | CV15: 747.38 | CW15: 751.11 | CX15: 738.7 | CY15: 735.11 | CZ15: 737.05 | DA15: 748.65 | DB15: 752.45 | DC15: 752.3 | DD15: 765.7 | DE15: 751.98 | DF15: 750.9 | DG15: 755.59 | DH15: 764.7 | DI15: 779 | DJ15: 775.715 | DK15: 780.25 | DL15: 778.38 | DM15: 765.16 | DN15: 755.4 | DO15: 760.66 | DP15: 748.91 | DQ15: 743.75 | DR15: 743.4 | DS15: 734.38 | DT15: 717.34 | DU15: 727.05 | DV15: 710.56 | DW15: 715.66 | DX15: 713.08 | DY15: 717.84 | DZ15: 733.51 | EA15: 705.3 | EB15: 715.7 | EC15: 708.65 | ED15: 717.55 | EE15: 712.07 | EF15: 716.915 | EG15: 732.17 | EH15: 733.27 | EI15: 733.41 | EJ15: 734 | EK15: 738.36 | EL15: 750.82 | EM15: 751.44 | EN15: 751.67 | EO15: 666.47 | EP15: 648.35 | EQ15: 637.71 | ER15: 627.32 | ES15: 635.95 | ET15: 618.94 | EU15: 621.71 | EV15: 631.76 | EW15: 627.08 | EX15: 609.01 | EY15: 609.89 | EZ15: 609.46 | FA15: 602.01 | FB15: 597.69 | FC15: 590.32 | FD15: 589.15 | FE15: 594.25 | FF15: 613.05 | FG15: 636.22 | FH15: 633.61 | FI15: 647.95 | FJ15: 640.87 | FK15: 647.1 | FL15: 639.6 | FM15: 661.53 | FN15: 673.42 | FO15: 666.8 | FP15: 656.96 | FQ15: 650.13 | FR15: 652.71 | FS15: 644.23 | FT15: 647.51 | FU15: 657.15 | FV15: 649.5 | FW15: 664.45 | FX15: 658.77 | FY15: 661.5 | FZ15: 664.94 | GA15: 667.55 | GB15: 663.29 | GC15: 658.69 | GD15: 665.95 | GE15: 660.09 | GF15: 650.41 | GG15: 658.79 | GH15: 660.62 | GI15: 648.69 | GJ15: 646.06 | GK15: 653.06 | GL15: 641.97 | GM15: 631.09 | GN15: 615.52 | GO15: 620.8 | GP15: 620.25 | GQ15: 604.12 | GR15: 612.96 | GS15: 647.63 | GT15: 658.76 | GU15: 672.36 | GV15: 672.97 | GW15: 668.73 | GX15: 738.31 | GY15: 716.5 | GZ15: 706.41 | HA15: 691.7 | HB15: 668.99 | HC15: 670.21 | HD15: 661.46 | HE15: 677.22 | HF15: 670.72 | HG15: 668.69 | HH15: 649.81 | HI15: 639.77 | HJ15: 639.29 | HK15: 643.22 | HL15: 644.78 | HM15: 655.66 | HN15: 637.25 | HO15: 639.3 | HP15: 653.69 | HQ15: 657.01 | HR15: 648.18 | HS15: 653.56 | HT15: 655.08 | HU15: 667.73 | HV15: 660.57 | HW15: 644.86 | HX15: 647.39 | HY15: 654.07 | HZ15: 654.86 | IA15: 638.18 | IB15: 613.71 | IC15: 627.45 | ID15: 622.66 | IE15: 615.68 | IF15: 606.7 | IG15: 593.66 | IH15: 604.06 | II15: 592.92 | IJ15: 594.89 | IK15: 547.54 | IL15: 525.72 | IM15: 536.38 | IN15: 572.13 | IO15: 579.23 | IP15: 574.46
A16: =Dashboard!B20 -> NVDA | B16: {=IFERROR(TRANSPOSE(_xlfn.STOCKHISTORY(A16,TODAY()-365,TODAY(),0,0,1)),"")} -> 97.64 | C16: 96.3 | D16: 114.33 | E16: 107.57 | F16: 110.93 | G16: 110.71 | H16: 112.2 | I16: 104.49 | J16: 101.49 | K16: 96.91 | L16: 98.89 | M16: 102.71 | N16: 106.43 | O16: 111.01 | P16: 108.73 | Q16: 109.02 | R16: 108.92 | S16: 111.61 | T16: 114.5 | U16: 113.82 | V16: 113.54 | W16: 117.06 | X16: 117.37 | Y16: 116.65 | Z16: 123 | AA16: 129.93 | AB16: 135.34 | AC16: 134.83 | AD16: 135.4 | AE16: 135.57 | AF16: 134.38 | AG16: 131.8 | AH16: 132.83 | AI16: 131.29 | AJ16: 135.5 | AK16: 134.81 | AL16: 139.19 | AM16: 135.13 | AN16: 137.38 | AO16: 141.22 | AP16: 141.92 | AQ16: 139.99 | AR16: 141.72 | AS16: 142.63 | AT16: 143.96 | AU16: 142.83 | AV16: 145 | AW16: 141.97 | AX16: 144.69 | AY16: 144.12 | AZ16: 145.48 | BA16: 143.85 | BB16: 144.17 | BC16: 147.9 | BD16: 154.31 | BE16: 155.02 | BF16: 157.75 | BG16: 157.99 | BH16: 153.3 | BI16: 157.25 | BJ16: 159.34 | BK16: 158.24 | BL16: 160 | BM16: 162.88 | BN16: 164.1 | BO16: 164.92 | BP16: 164.07 | BQ16: 170.7 | BR16: 171.37 | BS16: 173 | BT16: 172.41 | BU16: 171.38 | BV16: 167.03 | BW16: 170.78 | BX16: 173.74 | BY16: 173.5 | BZ16: 176.75 | CA16: 175.51 | CB16: 179.27 | CC16: 177.87 | CD16: 173.72 | CE16: 180 | CF16: 178.26 | CG16: 179.42 | CH16: 180.77 | CI16: 182.7 | CJ16: 182.06 | CK16: 183.16 | CL16: 181.59 | CM16: 182.02 | CN16: 180.45 | CO16: 182.01 | CP16: 175.64 | CQ16: 175.4 | CR16: 174.98 | CS16: 177.99 | CT16: 179.81 | CU16: 181.77 | CV16: 181.6 | CW16: 180.17 | CX16: 174.18 | CY16: 170.78 | CZ16: 170.62 | DA16: 171.66 | DB16: 167.02 | DC16: 168.31 | DD16: 170.76 | DE16: 177.33 | DF16: 177.17 | DG16: 177.82 | DH16: 177.75 | DI16: 174.88 | DJ16: 170.29 | DK16: 176.24 | DL16: 176.67 | DM16: 183.61 | DN16: 178.43 | DO16: 176.97 | DP16: 177.69 | DQ16: 178.19 | DR16: 181.85 | DS16: 186.58 | DT16: 187.24 | DU16: 188.89 | DV16: 187.62 | DW16: 185.54 | DX16: 185.04 | DY16: 189.11 | DZ16: 192.57 | EA16: 183.16 | EB16: 188.32 | EC16: 180.03 | ED16: 179.83 | EE16: 181.81 | EF16: 183.22 | EG16: 182.64 | EH16: 181.16 | EI16: 180.28 | EJ16: 182.16 | EK16: 186.26 | EL16: 191.49 | EM16: 201.03 | EN16: 207.04 | EO16: 202.89 | EP16: 202.49 | EQ16: 206.88 | ER16: 198.69 | ES16: 195.21 | ET16: 188.08 | EU16: 188.15 | EV16: 199.05 | EW16: 193.16 | EX16: 193.8 | EY16: 186.86 | EZ16: 190.17 | FA16: 186.6 | FB16: 181.36 | FC16: 186.52 | FD16: 180.64 | FE16: 178.88 | FF16: 182.55 | FG16: 177.82 | FH16: 180.26 | FI16: 177 | FJ16: 179.92 | FK16: 181.46 | FL16: 179.59 | FM16: 183.38 | FN16: 182.41 | FO16: 185.55 | FP16: 184.97 | FQ16: 183.78 | FR16: 180.93 | FS16: 175.02 | FT16: 176.29 | FU16: 177.72 | FV16: 170.94 | FW16: 174.14 | FX16: 180.99 | FY16: 183.69 | FZ16: 189.21 | GA16: 188.61 | GB16: 190.53 | GC16: 188.22 | GD16: 187.54 | GE16: 186.5 | GF16: 188.85 | GG16: 188.12 | GH16: 187.24 | GI16: 189.11 | GJ16: 185.04 | GK16: 184.86 | GL16: 184.94 | GM16: 185.81 | GN16: 183.14 | GO16: 187.05 | GP16: 186.23 | GQ16: 178.07 | GR16: 183.32 | GS16: 184.84 | GT16: 187.67 | GU16: 186.47 | GV16: 188.52 | GW16: 191.52 | GX16: 192.51 | GY16: 191.13 | GZ16: 185.61 | HA16: 180.34 | HB16: 174.19 | HC16: 171.88 | HD16: 185.41 | HE16: 190.04 | HF16: 188.54 | HG16: 190.05 | HH16: 186.94 | HI16: 182.81 | HJ16: 184.97 | HK16: 187.98 | HL16: 187.9 | HM16: 189.82 | HN16: 191.55 | HO16: 192.85 | HP16: 195.56 | HQ16: 184.89 | HR16: 177.19 | HS16: 182.48 | HT16: 180.05 | HU16: 183.04 | HV16: 183.34 | HW16: 177.82 | HX16: 182.65 | HY16: 184.77 | HZ16: 186.03 | IA16: 183.14 | IB16: 180.25 | IC16: 183.22 | ID16: 181.93 | IE16: 180.4 | IF16: 178.56 | IG16: 172.7 | IH16: 175.64 | II16: 175.2 | IJ16: 178.68 | IK16: 171.24 | IL16: 167.52 | IM16: 165.17 | IN16: 174.4 | IO16: 175.75 | IP16: 177.39
A17: =Dashboard!B21 -> TM | B17: {=TRANSPOSE(_xlfn.STOCKHISTORY(A17,TODAY()-365,TODAY(),0,0,1))} -> 160.34 | C17: 159.32 | D17: 174.14 | E17: 167.22 | F17: 169.42 | G17: 172 | H17: 174.24 | I17: 175.1 | J17: 176.38 | K17: 174.52 | L17: 178.7 | M17: 181.43 | N17: 186.61 | O17: 188.21 | P17: 193.13 | Q17: 195.39 | R17: 191.22 | S17: 190.58 | T17: 192.24 | U17: 192.48 | V17: 192.43 | W17: 188.9 | X17: 187.92 | Y17: 187.53 | Z17: 192.32 | AA17: 193.97 | AB17: 187 | AC17: 183.45 | AD17: 183.19 | AE17: 185.32 | AF17: 186.36 | AG17: 184.47 | AH17: 182.82 | AI17: 182.3 | AJ17: 186.68 | AK17: 182.88 | AL17: 186.11 | AM17: 190.57 | AN17: 189.14 | AO17: 191.4 | AP17: 187.96 | AQ17: 184.4 | AR17: 185.14 | AS17: 183.94 | AT17: 185.25 | AU17: 182.61 | AV17: 181.99 | AW17: 178.75 | AX17: 177.67 | AY17: 173.95 | AZ17: 175.59 | BA17: 172.4 | BB17: 170.88 | BC17: 171.58 | BD17: 169.15 | BE17: 170.63 | BF17: 175.74 | BG17: 172.26 | BH17: 171.54 | BI17: 172.01 | BJ17: 174.89 | BK17: 167.86 | BL17: 170.2 | BM17: 170.54 | BN17: 170.39 | BO17: 170.26 | BP17: 172.14 | BQ17: 170.02 | BR17: 169.88 | BS17: 170.48 | BT17: 168.65 | BU17: 170.03 | BV17: 169.99 | BW17: 193.18 | BX17: 191.66 | BY17: 188.49 | BZ17: 187.18 | CA17: 184.27 | CB17: 182.75 | CC17: 178.97 | CD17: 179.69 | CE17: 182.31 | CF17: 181.5 | CG17: 183.99 | CH17: 181.49 | CI17: 188.64 | CJ17: 189.13 | CK17: 193.97 | CL17: 194.4 | CM17: 192.48 | CN17: 193.66 | CO17: 197.83 | CP17: 198.6 | CQ17: 199.19 | CR17: 197.27 | CS17: 201.37 | CT17: 198.37 | CU17: 197.35 | CV17: 196.74 | CW17: 198.25 | CX17: 194.57 | CY17: 193.57 | CZ17: 193.01 | DA17: 197.64 | DB17: 199.62 | DC17: 202.79 | DD17: 200.8 | DE17: 197.38 | DF17: 197.63 | DG17: 196.13 | DH17: 197.28 | DI17: 198.78 | DJ17: 201.38 | DK17: 200.47 | DL17: 198.95 | DM17: 200.68 | DN17: 200.66 | DO17: 198.09 | DP17: 197.28 | DQ17: 198.1 | DR17: 196.44 | DS17: 191.09 | DT17: 191.83 | DU17: 190.52 | DV17: 194.59 | DW17: 199.18 | DX17: 199.89 | DY17: 198.21 | DZ17: 192.33 | EA17: 185.22 | EB17: 187.88 | EC17: 191.74 | ED17: 194.33 | EE17: 195.41 | EF17: 197.83 | EG17: 200.11 | EH17: 201.95 | EI17: 203.51 | EJ17: 204.06 | EK17: 205.37 | EL17: 209.22 | EM17: 211.24 | EN17: 207.09 | EO17: 207.21 | EP17: 204.19 | EQ17: 205.72 | ER17: 203.89 | ES17: 199.15 | ET17: 202.94 | EU17: 201.98 | EV17: 203.94 | EW17: 205.99 | EX17: 207.29 | EY17: 203.26 | EZ17: 204.08 | FA17: 199 | FB17: 195.96 | FC17: 196.78 | FD17: 191.25 | FE17: 197.62 | FF17: 199.06 | FG17: 200.26 | FH17: 202.44 | FI17: 201.87 | FJ17: 199.22 | FK17: 196.99 | FL17: 195.44 | FM17: 198.27 | FN17: 196.56 | FO17: 195.21 | FP17: 196.34 | FQ17: 200.78 | FR17: 203.56 | FS17: 208.12 | FT17: 214.81 | FU17: 214.42 | FV17: 214.24 | FW17: 216.08 | FX17: 219.38 | FY17: 219.51 | FZ17: 219.24 | GA17: 216.73 | GB17: 216.62 | GC17: 216.44 | GD17: 214.85 | GE17: 214.06 | GF17: 217.87 | GG17: 218.86 | GH17: 215.27 | GI17: 213.33 | GJ17: 214.73 | GK17: 221.52 | GL17: 222.59 | GM17: 229.03 | GN17: 227.3 | GO17: 232.33 | GP17: 231.42 | GQ17: 220.47 | GR17: 227.74 | GS17: 227.04 | GT17: 226.28 | GU17: 225.62 | GV17: 224.12 | GW17: 218.89 | GX17: 227.07 | GY17: 226.86 | GZ17: 231.58 | HA17: 231.42 | HB17: 241.39 | HC17: 237.19 | HD17: 244.22 | HE17: 242.39 | HF17: 238.24 | HG17: 242.81 | HH17: 241.64 | HI17: 248.29 | HJ17: 245.51 | HK17: 243.2 | HL17: 241.65 | HM17: 239.6 | HN17: 238.03 | HO17: 238.64 | HP17: 241.73 | HQ17: 242.62 | HR17: 242.38 | HS17: 243.66 | HT17: 232.17 | HU17: 232.81 | HV17: 221.48 | HW17: 219.14 | HX17: 219.53 | HY17: 221.01 | HZ17: 220.77 | IA17: 216.59 | IB17: 210.84 | IC17: 213.23 | ID17: 213.07 | IE17: 209.11 | IF17: 208.93 | IG17: 205.02 | IH17: 210.64 | II17: 209.78 | IJ17: 210.93 | IK17: 209.93 | IL17: 206.73 | IM17: 202.94 | IN17: 206.09 | IO17: 209.67 | IP17: 207.01
A18: =Dashboard!B22 -> WMT | B18: {=TRANSPOSE(_xlfn.STOCKHISTORY(A18,TODAY()-365,TODAY(),0,0,1))} -> 83.83 | C18: 81.79 | D18: 89.6 | E18: 90.61 | F18: 92.8 | G18: 94.73 | H18: 93.97 | I18: 91.19 | J18: 93.22 | K18: 92.41 | L18: 94.85 | M18: 94.96 | N18: 95.84 | O18: 95.09 | P18: 95.22 | Q18: 96.04 | R18: 97.25 | S18: 97.41 | T18: 98.75 | U18: 99.33 | V18: 98.55 | W18: 98.83 | X18: 97.43 | Y18: 96.72 | Z18: 96.75 | AA18: 95.88 | AB18: 96.83 | AC18: 96.35 | AD18: 98.24 | AE18: 98.12 | AF18: 97.8 | AG18: 96.43 | AH18: 95.93 | AI18: 96.34 | AJ18: 97.58 | AK18: 97.24 | AL18: 97.1 | AM18: 98.72 | AN18: 99.77 | AO18: 99.98 | AP18: 99.35 | AQ18: 97.96 | AR18: 97.47 | AS18: 97.45 | AT18: 97.32 | AU18: 95.8 | AV18: 94.83 | AW18: 94.44 | AX18: 94.29 | AY18: 94.25 | AZ18: 95.09 | BA18: 96.12 | BB18: 97.87 | BC18: 98 | BD18: 97.26 | BE18: 96.02 | BF18: 97.27 | BG18: 97.78 | BH18: 98.24 | BI18: 97.61 | BJ18: 98.36 | BK18: 99.35 | BL18: 97.09 | BM18: 96.81 | BN18: 94.86 | BO18: 94.4 | BP18: 95.78 | BQ18: 95.39 | BR18: 95.15 | BS18: 95.09 | BT18: 95.05 | BU18: 95.67 | BV18: 95.85 | BW18: 95.68 | BX18: 96.6 | BY18: 97.47 | BZ18: 97.61 | CA18: 98.33 | CB18: 97.59 | CC18: 97.98 | CD18: 98.49 | CE18: 99.59 | CF18: 99.31 | CG18: 103.36 | CH18: 103.12 | CI18: 103.73 | CJ18: 103.93 | CK18: 103.62 | CL18: 100.99 | CM18: 100.85 | CN18: 100 | CO18: 100.7 | CP18: 101.29 | CQ18: 102.57 | CR18: 97.96 | CS18: 96.83 | CT18: 96.07 | CU18: 96.05 | CV18: 96.08 | CW18: 96.11 | CX18: 96.98 | CY18: 97.85 | CZ18: 99.44 | DA18: 100.93 | DB18: 100.51 | DC18: 102.28 | DD18: 102.29 | DE18: 100.41 | DF18: 102.65 | DG18: 103.49 | DH18: 103.69 | DI18: 103.42 | DJ18: 104.27 | DK18: 103.6 | DL18: 102.33 | DM18: 102.82 | DN18: 102.52 | DO18: 102.73 | DP18: 103.05 | DQ18: 103.16 | DR18: 103.08 | DS18: 103.06 | DT18: 101.96 | DU18: 101.7 | DV18: 102.07 | DW18: 102.7 | DX18: 103.24 | DY18: 102.9 | DZ18: 101.77 | EA18: 101.84 | EB18: 102.12 | EC18: 107.21 | ED18: 109.03 | EE18: 106.47 | EF18: 107.73 | EG18: 107.05 | EH18: 106.22 | EI18: 107.14 | EJ18: 106.86 | EK18: 106.17 | EL18: 104.47 | EM18: 103.17 | EN18: 102.46 | EO18: 102.23 | EP18: 101.18 | EQ18: 101.59 | ER18: 102.27 | ES18: 101.47 | ET18: 101.68 | EU18: 102.59 | EV18: 102.42 | EW18: 103.44 | EX18: 103.44 | EY18: 102.54 | EZ18: 102.48 | FA18: 102.95 | FB18: 101.39 | FC18: 100.61 | FD18: 107.11 | FE18: 105.32 | FF18: 104.06 | FG18: 107 | FH18: 109.1 | FI18: 110.51 | FJ18: 111.53 | FK18: 112.41 | FL18: 114.41 | FM18: 114.84 | FN18: 115.11 | FO18: 113.56 | FP18: 115.06 | FQ18: 113.18 | FR18: 115.52 | FS18: 116.7 | FT18: 116.79 | FU18: 115.42 | FV18: 115.66 | FW18: 114.83 | FX18: 114.36 | FY18: 112.6 | FZ18: 110.9 | GA18: 111.61 | GB18: 111.74 | GC18: 112.53 | GD18: 111.92 | GE18: 111.41 | GF18: 112.76 | GG18: 112.71 | GH18: 114.34 | GI18: 112.72 | GJ18: 113.07 | GK18: 114.53 | GL18: 117.97 | GM18: 120.36 | GN18: 120.04 | GO18: 119.2 | GP18: 119.7 | GQ18: 118.71 | GR18: 119.36 | GS18: 117.83 | GT18: 117.73 | GU18: 117.64 | GV18: 116.94 | GW18: 116.57 | GX18: 117.41 | GY18: 119.14 | GZ18: 124.06 | HA18: 127.71 | HB18: 128 | HC18: 126.94 | HD18: 131.18 | HE18: 129.02 | HF18: 126.7 | HG18: 128.77 | HH18: 133.64 | HI18: 133.89 | HJ18: 128.85 | HK18: 126.62 | HL18: 124.87 | HM18: 122.99 | HN18: 125.81 | HO18: 126.75 | HP18: 125.75 | HQ18: 124.42 | HR18: 127.95 | HS18: 127.1 | HT18: 127.91 | HU18: 127.81 | HV18: 123.31 | HW18: 123.8 | HX18: 124.34 | HY18: 125.12 | HZ18: 123.49 | IA18: 125.33 | IB18: 126.52 | IC18: 125.99 | ID18: 125.08 | IE18: 121.98 | IF18: 121.09 | IG18: 119.02 | IH18: 120.72 | II18: 122.05 | IJ18: 123.06 | IK18: 122.18 | IL18: 122.89 | IM18: 123.5 | IN18: 124.28 | IO18: 124.74 | IP18: 125.79

Sheet Ledger
A1: TRANSACTION LEDGER
B2: Date | C2: Stock | D2: Transaction Type | E2: Price | F2: Units | G2: Transaction Amount | H2: Ticker | I2: Holding Days | J2: Tax Status
B3: 43466 | C3: #VALUE! | D3: Buy | E3: 19.15 | F3: 29.24 | G3: =E3*F3 -> 559.946 | H3: {=_FV(Ledger[[#This Row],[Stock]],"Ticker symbol",TRUE)} -> AMD | I3: =IF(D3="Sell",B3-_xlfn.MAXIFS(B$3:B$114,H$3:H$114,H3,D$3:D$114,"Buy",B$3:B$114,"<"&B3),TODAY()-B3) -> 2652 | J3: =IF(I3>365,"LT GAIN","ST GAIN · HIGH TAX") -> LT GAIN
B4: 43831 | C4: #VALUE! | D4: Buy | E4: 30.98 | F4: 18.07 | G4: =E4*F4 -> 559.8086 | H4: {=_FV(Ledger[[#This Row],[Stock]],"Ticker symbol",TRUE)} -> AMD | I4: =IF(D4="Sell",B4-_xlfn.MAXIFS(B$3:B$114,H$3:H$114,H4,D$3:D$114,"Buy",B$3:B$114,"<"&B4),TODAY()-B4) -> 2287 | J4: =IF(I4>365,"LT GAIN","ST GAIN · HIGH TAX") -> LT GAIN
B5: 44197 | C5: #VALUE! | D5: Buy | E5: 89.33 | F5: 6.27 | G5: =E5*F5 -> 560.0991 | H5: {=_FV(Ledger[[#This Row],[Stock]],"Ticker symbol",TRUE)} -> AMD | I5: =IF(D5="Sell",B5-_xlfn.MAXIFS(B$3:B$114,H$3:H$114,H5,D$3:D$114,"Buy",B$3:B$114,"<"&B5),TODAY()-B5) -> 1921 | J5: =IF(I5>365,"LT GAIN","ST GAIN · HIGH TAX") -> LT GAIN
B6: 44562 | C6: #VALUE! | D6: Sell | E6: 110.93 | F6: 5.05 | G6: =E6*F6 -> 560.1965 | H6: {=_FV(Ledger[[#This Row],[Stock]],"Ticker symbol",TRUE)} -> AMD | I6: =IF(D6="Sell",B6-_xlfn.MAXIFS(B$3:B$114,H$3:H$114,H6,D$3:D$114,"Buy",B$3:B$114,"<"&B6),TODAY()-B6) -> 365 | J6: =IF(I6>365,"LT GAIN","ST GAIN · HIGH TAX") -> ST GAIN · HIGH TAX
B7: 44927 | C7: #VALUE! | D7: Buy | E7: 66.09 | F7: 8.47 | G7: =E7*F7 -> 559.7823 | H7: {=_FV(Ledger[[#This Row],[Stock]],"Ticker symbol",TRUE)} -> AMD | I7: =IF(D7="Sell",B7-_xlfn.MAXIFS(B$3:B$114,H$3:H$114,H7,D$3:D$114,"Buy",B$3:B$114,"<"&B7),TODAY()-B7) -> 1191 | J7: =IF(I7>365,"LT GAIN","ST GAIN · HIGH TAX") -> LT GAIN
B8: 45292 | C8: #VALUE! | D8: Buy | E8: 104.7 | F8: 21.4 | G8: =E8*F8 -> 2240.58 | H8: {=_FV(Ledger[[#This Row],[Stock]],"Ticker symbol",TRUE)} -> AMD | I8: =IF(D8="Sell",B8-_xlfn.MAXIFS(B$3:B$114,H$3:H$114,H8,D$3:D$114,"Buy",B$3:B$114,"<"&B8),TODAY()-B8) -> 826 | J8: =IF(I8>365,"LT GAIN","ST GAIN · HIGH TAX") -> LT GAIN
B9: 45658 | C9: #VALUE! | D9: Sell | E9: 126.16 | F9: 18.66 | G9: =E9*F9 -> 2354.1456 | H9: {=_FV(Ledger[[#This Row],[Stock]],"Ticker symbol",TRUE)} -> AMD | I9: =IF(D9="Sell",B9-_xlfn.MAXIFS(B$3:B$114,H$3:H$114,H9,D$3:D$114,"Buy",B$3:B$114,"<"&B9),TODAY()-B9) -> 366 | J9: =IF(I9>365,"LT GAIN","ST GAIN · HIGH TAX") -> LT GAIN
B10: 43466 | C10: #VALUE! | D10: Buy | E10: 97.62 | F10: 7.32 | G10: =E10*F10 -> 714.5784 | H10: {=_FV(Ledger[[#This Row],[Stock]],"Ticker symbol",TRUE)} -> JPM | I10: =IF(D10="Sell",B10-_xlfn.MAXIFS(B$3:B$114,H$3:H$114,H10,D$3:D$114,"Buy",B$3:B$114,"<"&B10),TODAY()-B10) -> 2652 | J10: =IF(I10>365,"LT GAIN","ST GAIN · HIGH TAX") -> LT GAIN
B11: 43831 | C11: #VALUE! | D11: Buy | E11: 139.4 | F11: 5.12 | G11: =E11*F11 -> 713.728 | H11: {=_FV(Ledger[[#This Row],[Stock]],"Ticker symbol",TRUE)} -> JPM | I11: =IF(D11="Sell",B11-_xlfn.MAXIFS(B$3:B$114,H$3:H$114,H11,D$3:D$114,"Buy",B$3:B$114,"<"&B11),TODAY()-B11) -> 2287 | J11: =IF(I11>365,"LT GAIN","ST GAIN · HIGH TAX") -> LT GAIN
B12: 44197 | C12: #VALUE! | D12: Buy | E12: 127.07 | F12: 5.62 | G12: =E12*F12 -> 714.1334 | H12: {=_FV(Ledger[[#This Row],[Stock]],"Ticker symbol",TRUE)} -> JPM | I12: =IF(D12="Sell",B12-_xlfn.MAXIFS(B$3:B$114,H$3:H$114,H12,D$3:D$114,"Buy",B$3:B$114,"<"&B12),TODAY()-B12) -> 1921 | J12: =IF(I12>365,"LT GAIN","ST GAIN · HIGH TAX") -> LT GAIN
B13: 44562 | C13: #VALUE! | D13: Sell | E13: 167.89 | F13: 4.26 | G13: =E13*F13 -> 715.2114 | H13: {=_FV(Ledger[[#This Row],[Stock]],"Ticker symbol",TRUE)} -> JPM | I13: =IF(D13="Sell",B13-_xlfn.MAXIFS(B$3:B$114,H$3:H$114,H13,D$3:D$114,"Buy",B$3:B$114,"<"&B13),TODAY()-B13) -> 365 | J13: =IF(I13>365,"LT GAIN","ST GAIN · HIGH TAX") -> ST GAIN · HIGH TAX
B14: 44927 | C14: #VALUE! | D14: Buy | E14: 134.12 | F14: 5.32 | G14: =E14*F14 -> 713.5184 | H14: {=_FV(Ledger[[#This Row],[Stock]],"Ticker symbol",TRUE)} -> JPM | I14: =IF(D14="Sell",B14-_xlfn.MAXIFS(B$3:B$114,H$3:H$114,H14,D$3:D$114,"Buy",B$3:B$114,"<"&B14),TODAY()-B14) -> 1191 | J14: =IF(I14>365,"LT GAIN","ST GAIN · HIGH TAX") -> LT GAIN
... B114: 45658 | C114: #VALUE! | D114: Sell | E114: 170.54 | F114: 12.59 | G114: =E114*F114 -> 2147.0986 | H114: {=_FV(Ledger[[#This Row],[Stock]],"Ticker symbol",TRUE)} -> TM | I114: =IF(D114="Sell",B114-_xlfn.MAXIFS(B$3:B$114,H$3:H$114,H114,D$3:D$114,"Buy",B$3:B$114,"<"&B114),TODAY()-B114) -> 366 | J114: =IF(I114>365,"LT GAIN","ST GAIN · HIGH TAX") -> LT GAIN

Sheet AMD
A1: Stock | B1: #VALUE!
A3: Exchange abbreviation | B3: Ticker symbol
A4: XNAS | B4: AMD | C4: {=TRANSPOSE(_xlfn.STOCKHISTORY(A4&":"&B4,TODAY()-365,TODAY(),0,0,1))} -> 83.64 | D4: 78.21 | E4: 96.84 | F4: 88.7 | G4: 93.4 | H4: 94.5 | I4: 95.29 | J4: 88.29 | K4: 87.5 | L4: 85.56 | M4: 86.26 | N4: 90.39 | O4: 94.47 | P4: 96.645 | Q4: 96.39 | R4: 96.06 | S4: 97.35 | T4: 96.65 | U4: 98.8 | V4: 100.59 | W4: 98.62 | X4: 100.36 | Y4: 101.7 | Z4: 102.84 | AA4: 108.12 | AB4: 112.46 | AC4: 117.72 | AD4: 114.99 | AE4: 117.17 | AF4: 114.74 | AG4: 113.51 | AH4: 112.06 | AI4: 110.71 | AJ4: 110.31 | AK4: 114.56 | AL4: 112.86 | AM4: 113.03 | AN4: 110.73 | AO4: 114.63 | AP4: 117.31 | AQ4: 118.58 | AR4: 115.69 | AS4: 116.19 | AT4: 121.73 | AU4: 123.24 | AV4: 121.14 | AW4: 118.5 | AX4: 116.16 | AY4: 126.39 | AZ4: 127.1 | BA4: 126.79 | BB4: 128.24 | BC4: 129.58 | BD4: 138.43 | BE4: 143.4 | BF4: 143.68 | BG4: 143.81 | BH4: 141.9 | BI4: 136.11 | BJ4: 138.52 | BK4: 137.91 | BL4: 134.8 | BM4: 137.82 | BN4: 138.41 | BO4: 144.16 | BP4: 146.42 | BQ4: 146.24 | BR4: 155.61 | BS4: 160.08 | BT4: 160.41 | BU4: 156.99 | BV4: 157 | BW4: 154.72 | BX4: 158.65 | BY4: 162.12 | BZ4: 166.47 | CA4: 173.66 | CB4: 177.44 | CC4: 179.51 | CD4: 176.31 | CE4: 171.7 | CF4: 176.78 | CG4: 174.31 | CH4: 163.12 | CI4: 172.4 | CJ4: 172.76 | CK4: 172.28 | CL4: 174.95 | CM4: 184.42 | CN4: 180.95 | CO4: 177.51 | CP4: 176.14 | CQ4: 166.55 | CR4: 165.2 | CS4: 163.71 | CT4: 167.76 | CU4: 163.36 | CV4: 166.62 | CW4: 167.13 | CX4: 168.58 | CY4: 162.63 | CZ4: 162.32 | DA4: 162.13 | DB4: 161.79 | DC4: 151.14 | DD4: 151.41 | DE4: 155.82 | DF4: 159.54 | DG4: 155.67 | DH4: 158.57 | DI4: 161.16 | DJ4: 160.46 | DK4: 159.16 | DL4: 157.92 | DM4: 157.39 | DN4: 159.79 | DO4: 160.9 | DP4: 160.88 | DQ4: 161.27 | DR4: 159.46 | DS4: 161.36 | DT4: 161.79 | DU4: 164.01 | DV4: 169.73 | DW4: 164.67 | DX4: 203.71 | DY4: 211.51 | DZ4: 235.56 | EA4: 232.89 | EB4: 214.9 | EC4: 216.42 | ED4: 218.09 | EE4: 238.6 | EF4: 234.56 | EG4: 233.08 | EH4: 240.56 | EI4: 238.03 | EJ4: 230.23 | EK4: 234.99 | EL4: 252.92 | EM4: 259.67 | EN4: 258.01 | EO4: 264.33 | EP4: 254.84 | EQ4: 256.12 | ER4: 259.65 | ES4: 250.05 | ET4: 256.33 | EU4: 237.7 | EV4: 233.54 | EW4: 243.98 | EX4: 237.52 | EY4: 258.89 | EZ4: 247.96 | FA4: 246.81 | FB4: 240.52 | FC4: 230.29 | FD4: 223.55 | FE4: 206.02 | FF4: 203.78 | FG4: 215.05 | FH4: 206.13 | FI4: 214.24 | FJ4: 217.53 | FK4: 219.76 | FL4: 215.24 | FM4: 217.6 | FN4: 215.98 | FO4: 217.97 | FP4: 221.11 | FQ4: 221.62 | FR4: 221.42 | FS4: 221.43 | FT4: 210.78 | FU4: 207.58 | FV4: 209.17 | FW4: 198.11 | FX4: 201.06 | FY4: 213.43 | FZ4: 214.95 | GA4: 214.9 | GB4: 215.04 | GC4: 214.99 | GD4: 215.61 | GE4: 215.34 | GF4: 214.16 | GG4: 223.47 | GH4: 221.08 | GI4: 214.35 | GJ4: 210.02 | GK4: 204.68 | GL4: 203.17 | GM4: 207.69 | GN4: 220.97 | GO4: 223.6 | GP4: 227.92 | GQ4: 231.83 | GR4: 231.92 | GS4: 249.8 | GT4: 253.73 | GU4: 259.68 | GV4: 251.31 | GW4: 252.03 | GX4: 252.74 | GY4: 252.18 | GZ4: 236.73 | HA4: 246.27 | HB4: 242.11 | HC4: 200.19 | HD4: 192.5 | HE4: 208.44 | HF4: 216 | HG4: 213.57 | HH4: 213.58 | HI4: 205.94 | HJ4: 207.32 | HK4: 203.08 | HL4: 200.12 | HM4: 203.37 | HN4: 200.15 | HO4: 196.6 | HP4: 213.84 | HQ4: 210.86 | HR4: 203.68 | HS4: 200.21 | HT4: 198.62 | HU4: 190.95 | HV4: 202.07 | HW4: 199.45 | HX4: 192.43 | HY4: 202.68 | HZ4: 203.23 | IA4: 204.83 | IB4: 197.74 | IC4: 193.39 | ID4: 196.58 | IE4: 196.31 | IF4: 199.46 | IG4: 205.27 | IH4: 201.33 | II4: 202.68 | IJ4: 205.37 | IK4: 220.27 | IL4: 203.77 | IM4: 201.99 | IN4: 196.04 | IO4: 203.43 | IP4: 210.21 | IQ4: 217.5
A6: {=_xlfn.STOCKHISTORY(A4&":"&B4,TODAY()-30,TODAY(),0,1,0,5,2,3,4,1)} -> Date | B6: Volume | C6: Open | D6: High | E6: Low | F6: Close
A7: 46090 | B7: 38877220 | C7: 189.36 | D7: 202.97 | E7: 189.02 | F7: 202.68
A8: 46091 | B8: 29139162 | C8: 202.51 | D8: 206.59 | E8: 202.2 | F8: 203.23
A9: 46092 | B9: 23076366 | C9: 205.11 | D9: 209.21 | E9: 203.63 | F9: 204.83
A10: 46093 | B10: 28886913 | C10: 202.825 | D10: 203.62 | E10: 196.67 | F10: 197.74
A11: 46094 | B11: 27561888 | C11: 198.11 | D11: 199.68 | E11: 192.27 | F11: 193.39
A12: 46097 | B12: 30285170 | C12: 194.975 | D12: 200.17 | E12: 194.8 | F12: 196.58
A13: 46098 | B13: 22779675 | C13: 196.68 | D13: 199.21 | E13: 195.26 | F13: 196.31
A14: 46099 | B14: 28569135 | C14: 196 | D14: 202.86 | E14: 195.75 | F14: 199.46
A15: 46100 | B15: 32245329 | C15: 195.032 | D15: 205.88 | E15: 192.83 | F15: 205.27
A16: 46101 | B16: 37265103 | C16: 204.885 | D16: 206.3 | E16: 198.26 | F16: 201.33
A17: 46104 | B17: 31857752 | C17: 206.395 | D17: 209.109 | E17: 201.71 | F17: 202.68
A18: 46105 | B18: 27258849 | C18: 201.39 | D18: 206.43 | E18: 200.13 | F18: 205.37
... A25: 46114 | B25: 38463484 | C25: 204.05 | D25: 217.78 | E25: 200.62 | F25: 217.5

Sheet BABA
A1: Stock | B1: #VALUE!
A3: Exchange abbreviation | B3: Ticker symbol
A4: XNYS | B4: BABA | C4: {=TRANSPOSE(_xlfn.STOCKHISTORY(A4&":"&B4,TODAY()-365,TODAY(),0,0,1))} -> 105.1438 | D4: 98.586 | E4: 103.9533 | F4: 103.358 | G4: 106.88 | H4: 113.0708 | I4: 111.3941 | J4: 105.9077 | K4: 108.011 | L4: 109.2809 | M4: 114.9657 | N4: 118.0313 | O4: 118.3488 | P4: 119.331 | Q4: 117.4361 | R4: 117.942 | S4: 118.4877 | T4: 119.579 | U4: 124.7678 | V4: 125.5714 | W4: 126.6528 | X4: 122.2577 | Y4: 124.7975 | Z4: 124.3411 | AA4: 131.5042 | AB4: 130.6113 | AC4: 132.9923 | AD4: 122.9224 | AE4: 122.4859 | AF4: 121.9898 | AG4: 124.1725 | AH4: 122.6149 | AI4: 120.5215 | AJ4: 119.7774 | AK4: 118.577 | AL4: 115.8189 | AM4: 116.2554 | AN4: 112.9418 | AO4: 113.8446 | AP4: 114.0629 | AQ4: 118.5075 | AR4: 119.0135 | AS4: 118.4381 | AT4: 120.5215 | AU4: 120.9184 | AV4: 119.3806 | AW4: 116.62 | AX4: 112.87 | AY4: 115.96 | AZ4: 115.03 | BA4: 113.49 | BB4: 113.01 | BC4: 113.09 | BD4: 117.01 | BE4: 114.55 | BF4: 113.93 | BG4: 114.08 | BH4: 113.41 | BI4: 113.97 | BJ4: 110.71 | BK4: 108.7 | BL4: 106.27 | BM4: 107.99 | BN4: 103.83 | BO4: 106.64 | BP4: 106.72 | BQ4: 108.22 | BR4: 116.97 | BS4: 115.73 | BT4: 117.3 | BU4: 120.23 | BV4: 120.27 | BW4: 120.71 | BX4: 122.58 | BY4: 121.15 | BZ4: 120.03 | CA4: 122.15 | CB4: 119.36 | CC4: 117.38 | CD4: 120.63 | CE4: 117.07 | CF4: 117.5 | CG4: 117.04 | CH4: 120.86 | CI4: 120.96 | CJ4: 120.36 | CK4: 118.64 | CL4: 122.42 | CM4: 126.86 | CN4: 122.28 | CO4: 121.26 | CP4: 121.4 | CQ4: 119.99 | CR4: 119.49 | CS4: 118.09 | CT4: 122.94 | CU4: 124.35 | CV4: 124.19 | CW4: 122.23 | CX4: 119.57 | CY4: 135 | CZ4: 138.55 | DA4: 136.45 | DB4: 130.92 | DC4: 135.58 | DD4: 141.2 | DE4: 147.1 | DF4: 143.93 | DG4: 155.44 | DH4: 155.06 | DI4: 158.04 | DJ4: 162.21 | DK4: 166.17 | DL4: 162.48 | DM4: 162.81 | DN4: 164.25 | DO4: 163.08 | DP4: 176.44 | DQ4: 175.47 | DR4: 171.91 | DS4: 179.9 | DT4: 178.73 | DU4: 182.78 | DV4: 189.34 | DW4: 188.03 | DX4: 187.22 | DY4: 181.33 | DZ4: 181.12 | EA4: 173.68 | EB4: 159.01 | EC4: 166.81 | ED4: 162.86 | EE4: 165.91 | EF4: 165.09 | EG4: 167.05 | EH4: 173.47 | EI4: 166.67 | EJ4: 165.86 | EK4: 171.9 | EL4: 174.7 | EM4: 179.45 | EN4: 176.72 | EO4: 179.97 | EP4: 173.93 | EQ4: 170.43 | ER4: 167.69 | ES4: 164.3 | ET4: 164.82 | EU4: 167.61 | EV4: 166.34 | EW4: 165.89 | EX4: 160.8 | EY4: 157.91 | EZ4: 159.84 | FA4: 153.8 | FB4: 157.71 | FC4: 159.72 | FD4: 158.89 | FE4: 153.28 | FF4: 152.93 | FG4: 160.73 | FH4: 157.01 | FI4: 157.6 | FJ4: 157.3 | FK4: 164.26 | FL4: 161.13 | FM4: 158.08 | FN4: 157.44 | FO4: 158.32 | FP4: 158.13 | FQ4: 155.96 | FR4: 158.82 | FS4: 156.9 | FT4: 155.68 | FU4: 150.09 | FV4: 149.29 | FW4: 147.09 | FX4: 147.32 | FY4: 149.79 | FZ4: 150.96 | GA4: 151.23 | GB4: 150.06 | GC4: 152.24 | GD4: 148.49 | GE4: 147.36 | GF4: 146.58 | GG4: 155.74 | GH4: 156.26 | GI4: 150.9 | GJ4: 146.75 | GK4: 154.47 | GL4: 150.96 | GM4: 166.31 | GN4: 167.01 | GO4: 169.9 | GP4: 170.93 | GQ4: 165.4 | GR4: 162.39 | GS4: 168.67 | GT4: 177.18 | GU4: 173.23 | GV4: 171.37 | GW4: 172.72 | GX4: 175.66 | GY4: 174.25 | GZ4: 169.56 | HA4: 168.39 | HB4: 163.65 | HC4: 159.14 | HD4: 157.76 | HE4: 162.51 | HF4: 163 | HG4: 166.51 | HH4: 164.32 | HI4: 158.73 | HJ4: 155.73 | HK4: 155.43 | HL4: 155.77 | HM4: 154.27 | HN4: 154.45 | HO4: 152.78 | HP4: 153.11 | HQ4: 152.28 | HR4: 148.05 | HS4: 144.11 | HT4: 142.56 | HU4: 135.59 | HV4: 133.27 | HW4: 130.35 | HX4: 130.79 | HY4: 132.64 | HZ4: 136.85 | IA4: 136.29 | IB4: 134.2 | IC4: 135.21 | ID4: 136.71 | IE4: 136.57 | IF4: 134.43 | IG4: 124.9 | IH4: 122.41 | II4: 126.06 | IJ4: 125.48 | IK4: 129.87 | IL4: 125.41 | IM4: 122.69 | IN4: 121.98 | IO4: 125.46 | IP4: 123.73 | IQ4: 122.05
A6: {=_xlfn.STOCKHISTORY(A4&":"&B4,TODAY()-30,TODAY(),0,1,0,5,2,3,4,1)} -> Date | B6: Volume | C6: Open | D6: High | E6: Low | F6: Close
A7: 46090 | B7: 10072449 | C7: 130.24 | D7: 132.91 | E7: 128.55 | F7: 132.64
A8: 46091 | B8: 15264286 | C8: 135.71 | D8: 139.22 | E8: 134.56 | F8: 136.85
A9: 46092 | B9: 6685065 | C9: 135.57 | D9: 136.74 | E9: 134.82 | F9: 136.29
A10: 46093 | B10: 7591786 | C10: 135.38 | D10: 136 | E10: 133.45 | F10: 134.2
A11: 46094 | B11: 6438401 | C11: 136.07 | D11: 137.2 | E11: 134.7 | F11: 135.21
A12: 46097 | B12: 9972344 | C12: 138.8 | D12: 138.8 | E12: 136.5 | F12: 136.71
A13: 46098 | B13: 10005699 | C13: 137.875 | D13: 138.22 | E13: 135.97 | F13: 136.57
A14: 46099 | B14: 17158597 | C14: 138.445 | D14: 139.16 | E14: 134.37 | F14: 134.43
A15: 46100 | B15: 33440469 | C15: 123.02 | D15: 126.92 | E15: 121.16 | F15: 124.9
A16: 46101 | B16: 15479264 | C16: 125.715 | D16: 126.48 | E16: 122.09 | F16: 122.41
A17: 46104 | B17: 15583917 | C17: 123.24 | D17: 127.27 | E17: 123.1 | F17: 126.06
A18: 46105 | B18: 8516233 | C18: 124.36 | D18: 125.75 | E18: 123.92 | F18: 125.48
... A25: 46114 | B25: 8830234 | C25: 120.27 | D25: 122.8479 | E25: 120.14 | F25: 122.05

Sheet BAC
A1: Stock | B1: #VALUE!
A3: Exchange abbreviation | B3: Ticker symbol
A4: XNYS | B4: BAC | C4: {=TRANSPOSE(_xlfn.STOCKHISTORY(A4&":"&B4,TODAY()-365,TODAY(),0,0,1))} -> 35.58 | D4: 35.03 | E4: 37.15 | F4: 35.85 | G4: 35.95 | H4: 36.67 | I4: 37.99 | J4: 37.33 | K4: 37.41 | L4: 36.92 | M4: 38.32 | N4: 38.75 | O4: 39.58 | P4: 39.69 | Q4: 39.78 | R4: 39.99 | S4: 39.88 | T4: 40.17 | U4: 41.07 | V4: 41.12 | W4: 40.84 | X4: 40.93 | Y4: 41.6 | Z4: 41.79 | AA4: 43.36 | AB4: 44.28 | AC4: 44.74 | AD4: 44.38 | AE4: 44.69 | AF4: 44.77 | AG4: 44.69 | AH4: 43.25 | AI4: 43.31 | AJ4: 43.2 | AK4: 44.22 | AL4: 44.06 | AM4: 44.24 | AN4: 44.13 | AO4: 44.08 | AP4: 44.65 | AQ4: 44.36 | AR4: 44.38 | AS4: 44.97 | AT4: 44.87 | AU4: 45.09 | AV4: 44.73 | AW4: 44.62 | AX4: 44.09 | AY4: 44.41 | AZ4: 44.23 | BA4: 45.06 | BB4: 45.5 | BC4: 46.3 | BD4: 46.66 | BE4: 46.85 | BF4: 47.46 | BG4: 47.12 | BH4: 47.32 | BI4: 48.15 | BJ4: 48.71 | BK4: 48.93 | BL4: 48.66 | BM4: 47.15 | BN4: 46.84 | BO4: 46.97 | BP4: 46.73 | BQ4: 47.07 | BR4: 46.15 | BS4: 46.03 | BT4: 47.02 | BU4: 47.32 | BV4: 47.48 | BW4: 47.77 | BX4: 48.14 | BY4: 48.39 | BZ4: 48.45 | CA4: 48.23 | CB4: 47.95 | CC4: 47.96 | CD4: 47.27 | CE4: 45.66 | CF4: 45.85 | CG4: 45.56 | CH4: 45.42 | CI4: 44.92 | CJ4: 46.01 | CK4: 46.16 | CL4: 47.5 | CM4: 47.24 | CN4: 47.71 | CO4: 46.94 | CP4: 47.92 | CQ4: 48.08 | CR4: 48.35 | CS4: 48.26 | CT4: 49.48 | CU4: 49.48 | CV4: 50.25 | CW4: 50.38 | CX4: 50.49 | CY4: 50.74 | CZ4: 50.42 | DA4: 50.06 | DB4: 50.62 | DC4: 49.77 | DD4: 49.46 | DE4: 50.29 | DF4: 50.13 | DG4: 50.75 | DH4: 50.58 | DI4: 50.59 | DJ4: 50.66 | DK4: 51.4 | DL4: 52.13 | DM4: 52.25 | DN4: 51.92 | DO4: 51.7 | DP4: 51.7 | DQ4: 51.85 | DR4: 52.21 | DS4: 52.42 | DT4: 51.59 | DU4: 50.68 | DV4: 50.48 | DW4: 50.64 | DX4: 50.39 | DY4: 50.29 | DZ4: 49.84 | EA4: 49.79 | EB4: 48.65 | EC4: 48.86 | ED4: 50.09 | EE4: 52.28 | EF4: 50.44 | EG4: 51.28 | EH4: 52.04 | EI4: 51.52 | EJ4: 51.1 | EK4: 51.76 | EL4: 52.57 | EM4: 53.02 | EN4: 52.87 | EO4: 52.58 | EP4: 53.03 | EQ4: 53.45 | ER4: 53.56 | ES4: 53.54 | ET4: 52.45 | EU4: 53.29 | EV4: 53.2 | EW4: 53.42 | EX4: 53.63 | EY4: 54.11 | EZ4: 52.87 | FA4: 52.61 | FB4: 51.48 | FC4: 51.64 | FD4: 52.02 | FE4: 51 | FF4: 51.56 | FG4: 51.93 | FH4: 52.48 | FI4: 52.99 | FJ4: 53.65 | FK4: 53.24 | FL4: 53.19 | FM4: 54.09 | FN4: 54.16 | FO4: 53.95 | FP4: 53.9 | FQ4: 53.54 | FR4: 54.08 | FS4: 54.56 | FT4: 55.14 | FU4: 55.33 | FV4: 54.81 | FW4: 54.55 | FX4: 54.26 | FY4: 55.27 | FZ4: 55.88 | GA4: 55.97 | GB4: 56.25 | GC4: 56.17 | GD4: 55.35 | GE4: 55.28 | GF4: 55 | GG4: 55.95 | GH4: 56.89 | GI4: 57.25 | GJ4: 55.64 | GK4: 56.18 | GL4: 55.85 | GM4: 55.19 | GN4: 54.54 | GO4: 52.48 | GP4: 52.59 | GQ4: 52.97 | GR4: 52.1 | GS4: 52.07 | GT4: 52.45 | GU4: 51.72 | GV4: 52.02 | GW4: 52.17 | GX4: 51.81 | GY4: 53.08 | GZ4: 53.2 | HA4: 54.03 | HB4: 54.45 | HC4: 55.38 | HD4: 54.94 | HE4: 56.53 | HF4: 56.41 | HG4: 55.39 | HH4: 53.85 | HI4: 52.52 | HJ4: 52.55 | HK4: 52.74 | HL4: 53.36 | HM4: 52.77 | HN4: 53.06 | HO4: 51.07 | HP4: 50.41 | HQ4: 51.69 | HR4: 52.3 | HS4: 49.83 | HT4: 49.81 | HU4: 49.97 | HV4: 50.3 | HW4: 49.81 | HX4: 48.64 | HY4: 47.9 | HZ4: 48.56 | IA4: 48.52 | IB4: 47.13 | IC4: 46.72 | ID4: 47.06 | IE4: 47.28 | IF4: 46.83 | IG4: 47.01 | IH4: 47.16 | II4: 47.52 | IJ4: 48.14 | IK4: 48.75 | IL4: 48.24 | IM4: 46.97 | IN4: 47.23 | IO4: 48.75 | IP4: 49.27 | IQ4: 49.38
A6: {=_xlfn.STOCKHISTORY(A4&":"&B4,TODAY()-30,TODAY(),0,1,0,5,2,3,4,1)} -> Date | B6: Volume | C6: Open | D6: High | E6: Low | F6: Close
A7: 46090 | B7: 62752798 | C7: 47.94 | D7: 48.15 | E7: 46.77 | F7: 47.9
A8: 46091 | B8: 50271136 | C8: 48.28 | D8: 49.15 | E8: 47.595 | F8: 48.56
A9: 46092 | B9: 42185812 | C9: 48.36 | D9: 48.65 | E9: 47.78 | F9: 48.52
A10: 46093 | B10: 58354534 | C10: 47.7 | D10: 47.7824 | E10: 46.79 | F10: 47.13
A11: 46094 | B11: 45473073 | C11: 47.52 | D11: 47.8201 | E11: 46.655 | F11: 46.72
A12: 46097 | B12: 38055608 | C12: 47.12 | D12: 47.68 | E12: 46.9001 | F12: 47.06
A13: 46098 | B13: 33427815 | C13: 47.66 | D13: 48.08 | E13: 47.2 | F13: 47.28
A14: 46099 | B14: 40251811 | C14: 47.22 | D14: 47.88 | E14: 46.69 | F14: 46.83
A15: 46100 | B15: 38601377 | C15: 46.42 | D15: 47.19 | E15: 46.115 | F15: 47.01
A16: 46101 | B16: 78060881 | C16: 47.13 | D16: 47.46 | E16: 46.685 | F16: 47.16
A17: 46104 | B17: 42333241 | C17: 48.34 | D17: 48.39 | E17: 47.48 | F17: 47.52
A18: 46105 | B18: 39804103 | C18: 47.05 | D18: 48.46 | E18: 47.02 | F18: 48.14
... A25: 46114 | B25: 27548242 | C25: 48.75 | D25: 49.565 | E25: 48.16 | F25: 49.38

Sheet COST
A1: Stock | B1: #VALUE!
A3: Exchange abbreviation | B3: Ticker symbol
A4: XNAS | B4: COST | C4: {=TRANSPOSE(_xlfn.STOCKHISTORY(A4&":"&B4,TODAY()-365,TODAY(),0,0,1))} -> 908.13 | D4: 908.75 | E4: 965.19 | F4: 964.31 | G4: 963.41 | H4: 979.32 | I4: 976.92 | J4: 967.75 | K4: 994.5 | L4: 957.77 | M4: 979.23 | N4: 975.84 | O4: 975.48 | P4: 977.16 | Q4: 978.54 | R4: 991.7 | S4: 994.5 | T4: 999.04 | U4: 1008.3 | V4: 1014.89 | W4: 1010.5 | X4: 1007.15 | Y4: 1007.71 | Z4: 1008.09 | AA4: 1016.15 | AB4: 999.03 | AC4: 991.54 | AD4: 1010.47 | AE4: 1025.83 | AF4: 1034.34 | AG4: 1036.82 | AH4: 1025.3 | AI4: 1018.13 | AJ4: 1008.5 | AK4: 1017.79 | AL4: 1013.14 | AM4: 1008.74 | AN4: 1040.18 | AO4: 1056.85 | AP4: 1055.59 | AQ4: 1051.69 | AR4: 1010.81 | AS4: 1014.94 | AT4: 1006.18 | AU4: 1007.27 | AV4: 996.78 | AW4: 1002.71 | AX4: 990.21 | AY4: 984.36 | AZ4: 977.72 | BA4: 974.9 | BB4: 980.29 | BC4: 1004.48 | BD4: 1001.92 | BE4: 986.54 | BF4: 982.91 | BG4: 985.14 | BH4: 989.94 | BI4: 985.96 | BJ4: 982.36 | BK4: 987.02 | BL4: 992.18 | BM4: 985.84 | BN4: 982.09 | BO4: 970.17 | BP4: 970.33 | BQ4: 980.91 | BR4: 967.68 | BS4: 951.37 | BT4: 953.91 | BU4: 950.95 | BV4: 947.56 | BW4: 941.61 | BX4: 941.19 | BY4: 933.8 | BZ4: 935.48 | CA4: 933.99 | CB4: 934.57 | CC4: 927.51 | CD4: 939.64 | CE4: 952.52 | CF4: 955.37 | CG4: 943.63 | CH4: 968.56 | CI4: 977.45 | CJ4: 980.98 | CK4: 988.74 | CL4: 991.25 | CM4: 978.85 | CN4: 975.39 | CO4: 972.04 | CP4: 979.35 | CQ4: 980.85 | CR4: 994.57 | CS4: 969.68 | CT4: 958.54 | CU4: 941.58 | CV4: 941.34 | CW4: 949.52 | CX4: 944.96 | CY4: 943.32 | CZ4: 938.82 | DA4: 949.78 | DB4: 955.9 | DC4: 963.48 | DD4: 971.85 | DE4: 979.25 | DF4: 956.29 | DG4: 964.32 | DH4: 967.9 | DI4: 960.1 | DJ4: 952.07 | DK4: 963.03 | DL4: 952.36 | DM4: 951.16 | DN4: 943.26 | DO4: 943.6 | DP4: 945.27 | DQ4: 943.31 | DR4: 915.95 | DS4: 916.87 | DT4: 925.63 | DU4: 917.34 | DV4: 916.77 | DW4: 915.38 | DX4: 910.94 | DY4: 914.8 | DZ4: 914.8 | EA4: 942.89 | EB4: 930.01 | EC4: 935.56 | ED4: 946.51 | EE4: 954.99 | EF4: 925.62 | EG4: 936.33 | EH4: 936.11 | EI4: 937.5 | EJ4: 944.68 | EK4: 942.05 | EL4: 932.14 | EM4: 929.85 | EN4: 924.16 | EO4: 912.42 | EP4: 920.18 | EQ4: 911.45 | ER4: 928.04 | ES4: 940.74 | ET4: 935.03 | EU4: 923.58 | EV4: 922.74 | EW4: 915.56 | EX4: 913.86 | EY4: 914 | EZ4: 925.08 | FA4: 922.98 | FB4: 912.59 | FC4: 895.08 | FD4: 890.6 | FE4: 893.29 | FF4: 899.01 | FG4: 886.12 | FH4: 894.33 | FI4: 908.26 | FJ4: 913.59 | FK4: 911.96 | FL4: 922.03 | FM4: 922.26 | FN4: 895.855 | FO4: 894.68 | FP4: 887.52 | FQ4: 888.44 | FR4: 874.41 | FS4: 884.48 | FT4: 884.47 | FU4: 860.56 | FV4: 860.39 | FW4: 862.65 | FX4: 857.59 | FY4: 855.62 | FZ4: 850 | GA4: 854.79 | GB4: 871.86 | GC4: 873.35 | GD4: 867.84 | GE4: 865.65 | GF4: 862.34 | GG4: 854.5 | GH4: 875.74 | GI4: 889.1 | GJ4: 882.58 | GK4: 915.31 | GL4: 924.88 | GM4: 943.08 | GN4: 941.93 | GO4: 950.98 | GP4: 956.75 | GQ4: 963.61 | GR4: 964.26 | GS4: 982.86 | GT4: 976.17 | GU4: 983.25 | GV4: 977.67 | GW4: 970.28 | GX4: 960.78 | GY4: 952.89 | GZ4: 940.25 | HA4: 968.36 | HB4: 977.92 | HC4: 978.35 | HD4: 989.29 | HE4: 1001.16 | HF4: 997.59 | HG4: 971.23 | HH4: 978.14 | HI4: 998.86 | HJ4: 1018.48 | HK4: 1012.05 | HL4: 996.08 | HM4: 987.82 | HN4: 985.27 | HO4: 986.02 | HP4: 998.43 | HQ4: 994.76 | HR4: 986.74 | HS4: 1010.79 | HT4: 1002.77 | HU4: 1007.77 | HV4: 1006.74 | HW4: 982.57 | HX4: 998.1 | HY4: 1005.3 | HZ4: 997.36 | IA4: 992.23 | IB4: 1003.32 | IC4: 1008.43 | ID4: 1001.74 | IE4: 996.16 | IF4: 979.92 | IG4: 974.78 | IH4: 972.33 | II4: 965.73 | IJ4: 973.82 | IK4: 974.86 | IL4: 979.65 | IM4: 983.86 | IN4: 996.58 | IO4: 996.43 | IP4: 996.56 | IQ4: 1014.96
A6: {=_xlfn.STOCKHISTORY(A4&":"&B4,TODAY()-30,TODAY(),0,1,0,5,2,3,4,1)} -> Date | B6: Volume | C6: Open | D6: High | E6: Low | F6: Close
A7: 46090 | B7: 2348212 | C7: 999.63 | D7: 1007.41 | E7: 987.99 | F7: 1005.3
A8: 46091 | B8: 1613381 | C8: 1000.5 | D8: 1010.1 | E8: 996 | F8: 997.36
A9: 46092 | B9: 1262006 | C9: 996.32 | D9: 997.39 | E9: 987.89 | F9: 992.23
A10: 46093 | B10: 1669248 | C10: 988.61 | D10: 1006.21 | E10: 984 | F10: 1003.32
A11: 46094 | B11: 1469672 | C11: 1005.9 | D11: 1012.83 | E11: 1002 | F11: 1008.43
A12: 46097 | B12: 1243752 | C12: 1010.5 | D12: 1012.65 | E12: 995.4301 | F12: 1001.74
A13: 46098 | B13: 1210414 | C13: 1006.49 | D13: 1008.095 | E13: 994.75 | F13: 996.16
A14: 46099 | B14: 1434421 | C14: 990.37 | D14: 993.9819 | E14: 978.14 | F14: 979.92
A15: 46100 | B15: 1340173 | C15: 985.84 | D15: 988.79 | E15: 970.41 | F15: 974.78
A16: 46101 | B16: 2621555 | C16: 975.08 | D16: 980.76 | E16: 970.54 | F16: 972.33
A17: 46104 | B17: 1779094 | C17: 985.665 | D17: 986.64 | E17: 964.53 | F17: 965.73
A18: 46105 | B18: 1259325 | C18: 962.06 | D18: 981.28 | E18: 961 | F18: 973.82
... A25: 46114 | B25: 1828612 | C25: 1008 | D25: 1016 | E25: 999.21 | F25: 1014.96

Sheet DELL
A1: Stock | B1: #VALUE!
A3: Exchange abbreviation | B3: Ticker symbol
A4: XNYS | B4: DELL | C4: {=TRANSPOSE(_xlfn.STOCKHISTORY(A4&":"&B4,TODAY()-365,TODAY(),0,0,1))} -> 75 | D4: 72.59 | E4: 84.19 | F4: 78.94 | G4: 81.93 | H4: 85.19 | I4: 85.49 | J4: 83.36 | K4: 84.8 | L4: 82.39 | M4: 84.08 | N4: 89.16 | O4: 94.4 | P4: 94.89 | Q4: 94.47 | R4: 93.78 | S4: 91.76 | T4: 91.95 | U4: 94.59 | V4: 94.36 | W4: 93.95 | X4: 95.79 | Y4: 96.22 | Z4: 95.91 | AA4: 103.42 | AB4: 107.85 | AC4: 111.02 | AD4: 110.87 | AE4: 114.19 | AF4: 114.28 | AG4: 114.23 | AH4: 111.93 | AI4: 111.95 | AJ4: 112.11 | AK4: 113.99 | AL4: 113.77 | AM4: 113.63 | AN4: 111.27 | AO4: 108.08 | AP4: 111.9 | AQ4: 112.7 | AR4: 111.82 | AS4: 113.75 | AT4: 114.22 | AU4: 113.25 | AV4: 111.24 | AW4: 113.4 | AX4: 109.56 | AY4: 113.74 | AZ4: 115.93 | BA4: 116.56 | BB4: 119.37 | BC4: 118.02 | BD4: 120.59 | BE4: 120.46 | BF4: 125.98 | BG4: 123.99 | BH4: 122.6 | BI4: 121.73 | BJ4: 123.48 | BK4: 125.22 | BL4: 124.77 | BM4: 124.39 | BN4: 126.63 | BO4: 127.91 | BP4: 126.83 | BQ4: 125.67 | BR4: 125.69 | BS4: 123.57 | BT4: 123.88 | BU4: 131.24 | BV4: 128.96 | BW4: 124.33 | BX4: 127.22 | BY4: 128.35 | BZ4: 131.22 | CA4: 133.86 | CB4: 133.51 | CC4: 133.54 | CD4: 132.69 | CE4: 127.32 | CF4: 130.23 | CG4: 130.48 | CH4: 128.14 | CI4: 133.93 | CJ4: 137.61 | CK4: 138.32 | CL4: 141.64 | CM4: 139.14 | CN4: 138.86 | CO4: 138.28 | CP4: 138.13 | CQ4: 135.2 | CR4: 128.48 | CS4: 127.83 | CT4: 130.84 | CU4: 131.01 | CV4: 130.99 | CW4: 132.5 | CX4: 134.05 | CY4: 122.15 | CZ4: 120.96 | DA4: 124.02 | DB4: 126.67 | DC4: 124.83 | DD4: 123 | DE4: 121.29 | DF4: 124.45 | DG4: 125.37 | DH4: 125.04 | DI4: 126.8 | DJ4: 127.68 | DK4: 130.34 | DL4: 132.11 | DM4: 131.94 | DN4: 135.69 | DO4: 134.34 | DP4: 132.09 | DQ4: 130.96 | DR4: 130.76 | DS4: 133.9 | DT4: 141.77 | DU4: 149.68 | DV4: 147.37 | DW4: 140.74 | DX4: 145.76 | DY4: 150.87 | DZ4: 164.53 | EA4: 155.95 | EB4: 150.57 | EC4: 153.4 | ED4: 148.77 | EE4: 153.7 | EF4: 151.31 | EG4: 149.59 | EH4: 147.87 | EI4: 149.43 | EJ4: 150.13 | EK4: 154.23 | EL4: 158.64 | EM4: 162.19 | EN4: 164.88 | EO4: 163.6 | EP4: 161.01 | EQ4: 162.01 | ER4: 160.11 | ES4: 154.64 | ET4: 152.41 | EU4: 149.18 | EV4: 146.7 | EW4: 142.69 | EX4: 138.76 | EY4: 140.71 | EZ4: 133.94 | FA4: 133.76 | FB4: 122.48 | FC4: 122.69 | FD4: 119.38 | FE4: 117.4 | FF4: 122.51 | FG4: 127.22 | FH4: 125.92 | FI4: 133.26 | FJ4: 133.35 | FK4: 132.09 | FL4: 135.95 | FM4: 133.63 | FN4: 138.99 | FO4: 138.91 | FP4: 140.41 | FQ4: 138.22 | FR4: 140.63 | FS4: 138.6 | FT4: 129.98 | FU4: 130.51 | FV4: 133.75 | FW4: 127.89 | FX4: 122.94 | FY4: 126.42 | FZ4: 126.61 | GA4: 127.62 | GB4: 128.38 | GC4: 129.24 | GD4: 127.46 | GE4: 127.92 | GF4: 125.88 | GG4: 127.8 | GH4: 124.01 | GI4: 123.93 | GJ4: 120.07 | GK4: 118.5 | GL4: 120.62 | GM4: 120.47 | GN4: 119.66 | GO4: 118.69 | GP4: 119.66 | GQ4: 120.53 | GR4: 111.07 | GS4: 113.26 | GT4: 117.17 | GU4: 115.43 | GV4: 115.93 | GW4: 114.66 | GX4: 117.32 | GY4: 118.49 | GZ4: 114.44 | HA4: 119.16 | HB4: 117.15 | HC4: 122.04 | HD4: 115.39 | HE4: 121.05 | HF4: 120.91 | HG4: 126.01 | HH4: 124.16 | HI4: 112.82 | HJ4: 117.49 | HK4: 116.09 | HL4: 116.78 | HM4: 119.06 | HN4: 122.27 | HO4: 119.14 | HP4: 119.78 | HQ4: 123.48 | HR4: 121.45 | HS4: 148.08 | HT4: 153.55 | HU4: 145.18 | HV4: 147.1 | HW4: 146.52 | HX4: 146.48 | HY4: 146.51 | HZ4: 143.8 | IA4: 147.37 | IB4: 149.91 | IC4: 151.62 | ID4: 156.54 | IE4: 153.01 | IF4: 149.21 | IG4: 156.76 | IH4: 157.67 | II4: 164.59 | IJ4: 176.91 | IK4: 184.01 | IL4: 175.82 | IM4: 171.81 | IN4: 164.66 | IO4: 164.13 | IP4: 169.38 | IQ4: 174.37
A6: {=_xlfn.STOCKHISTORY(A4&":"&B4,TODAY()-30,TODAY(),0,1,0,5,2,3,4,1)} -> Date | B6: Volume | C6: Open | D6: High | E6: Low | F6: Close
A7: 46090 | B7: 7400609 | C7: 144.6 | D7: 146.7 | E7: 141.36 | F7: 146.51
A8: 46091 | B8: 7518682 | C8: 146.285 | D8: 146.89 | E8: 137.495 | F8: 143.8
A9: 46092 | B9: 5405664 | C9: 145.66 | D9: 149.4699 | E9: 145.15 | F9: 147.37
A10: 46093 | B10: 7340868 | C10: 147.15 | D10: 151.85 | E10: 147.085 | F10: 149.91
A11: 46094 | B11: 6441089 | C11: 151 | D11: 152.95 | E11: 146.82 | F11: 151.62
A12: 46097 | B12: 7923360 | C12: 153.05 | D12: 157.8 | E12: 152.68 | F12: 156.54
A13: 46098 | B13: 6675798 | C13: 154.75 | D13: 155.02 | E13: 151.8 | F13: 153.01
A14: 46099 | B14: 5460722 | C14: 152.71 | D14: 155.02 | E14: 148.93 | F14: 149.21
A15: 46100 | B15: 7715340 | C15: 146.585 | D15: 157.07 | E15: 146.57 | F15: 156.76
A16: 46101 | B16: 23135869 | C16: 163.5 | D16: 169.9 | E16: 157.67 | F16: 157.67
A17: 46104 | B17: 10721325 | C17: 159.24 | D17: 165.42 | E17: 158.63 | F17: 164.59
A18: 46105 | B18: 15886495 | C18: 163.62 | D18: 178.31 | E18: 163.37 | F18: 176.91
... A25: 46114 | B25: 5217126 | C25: 166.99 | D25: 174.37 | E25: 166.495 | F25: 174.37

Sheet XOM
